Testbenches/MyCIC/integrator/hdl/integrator.v
module integrator(
    input wire              i_clk,
    input wire              i_reset,
    input wire              i_ce,
    input wire signed [IW-1:0] i_data,
    output reg signed [OW-1:0] o_data,
    output reg              o_aux
);

parameter IW = 5, OW = 8;

reg signed [OW-1:0] accumulator = {OW{1'b0}};

always @(posedge i_clk or posedge i_reset) begin
    if (i_reset) begin
        accumulator <= {OW{1'b0}};
        o_data <= {OW{1'b0}};
        o_aux <= 1'b0;
    end else if (i_ce) begin
        accumulator <= accumulator + {{(OW-IW){i_data[IW-1]}}, i_data};  // Sign extend and accumulate
        o_data <= accumulator;
        o_aux <= 1'b1;
    end else begin
        o_aux <= 1'b0;  // Maintain previous output data unless reset or clock enabled
    end
end

//----------------------------- 
// For simulation only
//----------------------------- 
initial begin
    $dumpfile("integrator_waves.vcd");
    $dumpvars(0, integrator);
end

endmodule

Testbenches/MyCIC/integrator/integrator_waves.vcd
$date
	Fri Apr 19 10:50:43 2024
$end
$version
	Icarus Verilog
$end
$timescale
	1ps
$end
$scope module integrator $end
$var wire 1 ! i_ce $end
$var wire 1 " i_clk $end
$var wire 5 # i_data [4:0] $end
$var wire 1 $ i_reset $end
$var parameter 32 % IW $end
$var parameter 32 & OW $end
$var reg 8 ' accumulator [7:0] $end
$var reg 1 ( o_aux $end
$var reg 8 ) o_data [7:0] $end
$upscope $end
$enddefinitions $end
$comment Show the parameter values. $end
$dumpall
b1000 &
b101 %
$end
#0
$dumpvars
bx )
x(
b0 '
z$
bz #
z"
z!
$end
#5000
0(
b0 )
1"
0$
1!
b0 #
#11250
0"
#17500
b11100 #
1(
1"
#23750
0"
#30000
b10 #
b11111100 '
1"
#36250
0"
#42500
b11111 #
b11111100 )
b11111110 '
1"
#48750
0"
#55000
b11110 #
b11111110 )
b11111101 '
1"
#61250
0"
#67500
b10 #
b11111101 )
b11111011 '
1"
#73750
0"
#80000
b10101 #
b11111011 )
b11111101 '
1"
#86250
0"
#92500
b10 #
b11111101 )
b11110010 '
1"
#98750
0"
#105000
b11 #
b11110010 )
b11110100 '
1"
#111250
0"
#117500
b10101 #
b11110100 )
b11110111 '
1"
#123750
0"
#130000
b100 #
b11110111 )
b11101100 '
1"
#136250
0"
#142500
b110 #
b11101100 )
b11110000 '
1"
#148750
0"
#155000
b1 #
b11110000 )
b11110110 '
1"
#161250
0"
#167500
b11110 #
b11110110 )
b11110111 '
1"
#173750
0"
#180000
b10 #
b11110111 )
b11110101 '
1"
#186250
0"
#192500
b100 #
b11110101 )
b11110111 '
1"
#198750
0"
#205000
b1101 #
b11110111 )
b11111011 '
1"
#211250
0"
#217500
b1011 #
b11111011 )
b1000 '
1"
#223750
0"
#230000
b101 #
b1000 )
b10011 '
1"
#236250
0"
#242500
b10111 #
b10011 )
b11000 '
1"
#248750
0"
#255000
b10101 #
b11000 )
b1111 '
1"
#261250
0"
#267500
b1010 #
b1111 )
b100 '
1"
#273750
0"
#280000
b11110 #
b100 )
b1110 '
1"
#286250
0"
#292500
b110 #
b1110 )
b1100 '
1"
#298750
0"
#305000
b10110 #
b1100 )
b10010 '
1"
#311250
0"
#317500
b10000 #
b10010 )
b1000 '
1"
#323750
0"
#330000
b1110 #
b1000 )
b11111000 '
1"
#336250
0"
#342500
b10100 #
b11111000 )
b110 '
1"
#348750
0"
#355000
b110 #
b110 )
b11111010 '
1"
#361250
0"
#367500
b10011 #
b11111010 )
b0 '
1"
#373750
0"
#380000
b0 #
b0 )
b11110011 '
1"
#386250
0"
#392500
b10011 #
b11110011 )
1"
#398750
0"
#405000
b11010 #
b11100110 '
1"
#411250
0"
#417500
b10011 #
b11100110 )
b11100000 '
1"
#423750
0"
#430000
b111 #
b11100000 )
b11010011 '
1"
#436250
0"
#442500
b11011 #
b11010011 )
b11011010 '
1"
#448750
0"
#455000
b0 #
b11011010 )
b11010101 '
1"
#461250
0"
#467500
b11011 #
b11010101 )
1"
#473750
0"
#480000
b10101 #
b11010000 '
1"
#486250
0"
#492500
b1110 #
b11010000 )
b11000101 '
1"
#498750
0"
#505000
b10 #
b11000101 )
b11010011 '
1"
#511250
0"
#517500
b11000 #
b11010011 )
b11010101 '
1"
#523750
0"
#530000
b10010 #
b11010101 )
b11001101 '
1"
#536250
0"
#542500
b11001101 )
b10111111 '
1"
#548750
0"
#555000
b10 #
b10111111 )
b10110001 '
1"
#561250
0"
#567500
b10100 #
b10110001 )
b10110011 '
1"
#573750
0"
#580000
b11110 #
b10110011 )
b10100111 '
1"
#586250
0"
#592500
b10010 #
b10100111 )
b10100101 '
1"
#598750
0"
#605000
b10111 #
b10100101 )
b10010111 '
1"
#611250
0"
#617500
b11010 #
b10010111 )
b10001110 '
1"
#623750
0"
#630000
b1011 #
b10001110 )
b10001000 '
1"
#636250
0"
#642500
b1111 #
b10001000 )
b10010011 '
1"
#648750
0"
#655000
b11010 #
b10010011 )
b10100010 '
1"
#661250
0"
#667500
b10011 #
b10100010 )
b10011100 '
1"
#673750
0"
#680000
b1000 #
b10011100 )
b10001111 '
1"
#686250
0"
#692500
b1011 #
b10001111 )
b10010111 '
1"
#698750
0"
#705000
b11100 #
b10010111 )
b10100010 '
1"
#711250
0"
#717500
b1101 #
b10100010 )
b10011110 '
1"
#723750
0"
#730000
b10110 #
b10011110 )
b10101011 '
1"
#736250
0"
#742500
b1101 #
b10101011 )
b10100001 '
1"
#748750
0"
#755000
b10100001 )
b10101110 '
1"
#761250
0"
#767500
b0 #
b10101110 )
b10111011 '
1"
#773750
0"
#780000
b10101 #
b10111011 )
1"
#786250
0"
#792500
b1 #
b10110000 '
1"
#798750
0"
#805000
b1100 #
b10110000 )
b10110001 '
1"
#811250
0"
#817500
b1110 #
b10110001 )
b10111101 '
1"
#823750
0"
#830000
b110 #
b10111101 )
b11001011 '
1"
#836250
0"
#842500
b10111 #
b11001011 )
b11010001 '
1"
#848750
0"
#855000
b100 #
b11010001 )
b11001000 '
1"
#861250
0"
#867500
b11111 #
b11001000 )
b11001100 '
1"
#873750
0"
#880000
b1110 #
b11001100 )
b11001011 '
1"
#886250
0"
#892500
b11100 #
b11001011 )
b11011001 '
1"
#898750
0"
#905000
b1111 #
b11011001 )
b11010101 '
1"
#911250
0"
#917500
b10000 #
b11010101 )
b11100100 '
1"
#923750
0"
#930000
b10101 #
b11100100 )
b11010100 '
1"
#936250
0"
#942500
b10100 #
b11010100 )
b11001001 '
1"
#948750
0"
#955000
b1111 #
b11001001 )
b10111101 '
1"
#961250
0"
#967500
b1000 #
b10111101 )
b11001100 '
1"
#973750
0"
#980000
b10001 #
b11001100 )
b11010100 '
1"
#986250
0"
#992500
b10010 #
b11010100 )
b11000101 '
1"
#998750
0"
#1005000
b11110 #
b11000101 )
b10110111 '
1"
#1011250
0"
#1017500
b11111 #
b10110111 )
b10110101 '
1"
#1023750
0"
#1030000
b101 #
b10110101 )
b10110100 '
1"
#1036250
0"
#1042500
b1001 #
b10110100 )
b10111001 '
1"
#1048750
0"
#1055000
b101 #
b10111001 )
b11000010 '
1"
#1061250
0"
#1067500
b1011 #
b11000010 )
b11000111 '
1"
#1073750
0"
#1080000
b11101 #
b11000111 )
b11010010 '
1"
#1086250
0"
#1092500
b1011 #
b11010010 )
b11001111 '
1"
#1098750
0"
#1105000
b100 #
b11001111 )
b11011010 '
1"
#1111250
0"
#1117500
b1100 #
b11011010 )
b11011110 '
1"
#1123750
0"
#1130000
b10100 #
b11011110 )
b11101010 '
1"
#1136250
0"
#1142500
b101 #
b11101010 )
b11011110 '
1"
#1148750
0"
#1155000
b10000 #
b11011110 )
b11100011 '
1"
#1161250
0"
#1167500
b11001 #
b11100011 )
b11010011 '
1"
#1173750
0"
#1180000
b10110 #
b11010011 )
b11001100 '
1"
#1186250
0"
#1192500
b11110 #
b11001100 )
b11000010 '
1"
#1198750
0"
#1205000
b11100 #
b11000010 )
b11000000 '
1"
#1211250
0"
#1217500
b11101 #
b11000000 )
b10111100 '
1"
#1223750
0"
#1230000
b10010 #
b10111100 )
b10111001 '
1"
#1236250
0"
#1242500
b1111 #
b10111001 )
b10101011 '
1"
#1248750
0"
#1255000
b11110 #
b10101011 )
b10111010 '
1"
#1261250
0"
#1267500
b10111010 )
b10111000 '
1"
