1bitSDRLattice/Testbenches/Mixer/hdl/Mixer.v
/*
Module Description:
This module performs mixing of an RF signal with sine and cosine waves to produce two output signals: MixerOutSin and MixerOutCos. The mixing process is a fundamental operation in signal processing, used to shift the frequency of the input signal.

Inputs:
- clk: Clock signal.
- RFIn: Radio Frequency input signal.
- sin_in: Signed 12-bit input signal representing the sine component.
- cos_in: Signed 12-bit input signal representing the cosine component.

Outputs:
- RFOut: Output signal directly from RF input, delayed by one clock cycle.
- MixerOutSin: Signed 12-bit output signal representing the mixed signal with the sine component.
- MixerOutCos: Signed 12-bit output signal representing the mixed signal with the cosine component.
*/

module Mixer#
(  parameter WIDTH = 12
)(
   input clk,
   input signed [WIDTH-1:0] sin_in,
   input signed [WIDTH-1:0] cos_in,
   input RFIn,
   output RFOut,
   output reg signed [WIDTH-1:0] MixerOutSin,
   output reg signed [WIDTH-1:0] MixerOutCos
  );

  // Internal registers to hold delayed RFIn signal
  reg RFInR1 = 1'b1;
  reg RFInR = 1'b1;

  // Delay the RFIn signal by two clock cycles
  always @(posedge clk) begin 
    RFInR1 <= RFIn;
    RFInR <= RFInR1;	
  end

  // Assign the delayed RFIn signal to RFOut
  assign RFOut = RFInR1;

  // Mixing process: multiply RF input with sine and cosine inputs
  always @(posedge clk) begin
    if (RFInR == 1'b 0) begin
      MixerOutSin <= sin_in;
      MixerOutCos <= cos_in;
    end else begin
      MixerOutSin <= -sin_in;
      MixerOutCos <= -cos_in;				
    end
  end

  //----------------------------- 
  // For simulation only
  //----------------------------- 
  initial begin
    $dumpfile("mixer_waves.vcd");
    $dumpvars;
  end
endmodule

/*
-----------------------------------------------------------------------------
Version History:
-----------------------------------------------------------------------------
 2024/4/18 TH: initial creation    
 2024/5/26 TH: revision
*/

1bitSDRLattice/Testbenches/Mixer/mixer_waves.vcd
$date
	Sun May 26 19:49:56 2024
$end
$version
	Icarus Verilog
$end
$timescale
	1ps
$end
$scope module Mixer $end
$var wire 1 ! RFIn $end
$var wire 1 " RFOut $end
$var wire 1 # clk $end
$var wire 12 $ cos_in [11:0] $end
$var wire 12 % sin_in [11:0] $end
$var parameter 32 & WIDTH $end
$var reg 12 ' MixerOutCos [11:0] $end
$var reg 12 ( MixerOutSin [11:0] $end
$var reg 1 ) RFInR $end
$var reg 1 * RFInR1 $end
$upscope $end
$enddefinitions $end
$comment Show the parameter values. $end
$dumpall
b1100 &
$end
#0
$dumpvars
z*
1)
bx (
bx '
b0 %
b0 $
1#
z"
1!
$end
#6250
0#
#12500
b0 '
b0 (
z)
1"
1*
1#
#18750
0#
#25000
1)
1#
#31250
0#
#37500
0!
b1101110 $
b110111001101 %
1#
#43750
0#
#50000
0"
0*
b111110010010 '
b1000110011 (
1#
#56250
0#
#62500
b110111000101 $
b111010110100 %
0)
1#
#68750
0#
#75000
b110111000101 '
b111010110100 (
1#
#81250
0#
#87500
b111100000110 $
b101011010011 %
1#
#93750
0#
#100000
b111100000110 '
b101011010011 (
1#
#106250
0#
#112500
1!
b10110111010 $
b111110010010 %
1#
#118750
0#
#125000
1"
1*
b10110111010 '
b111110010010 (
1#
#131250
0#
#137500
b100110010 $
b110000111101 %
1)
1#
#143750
0#
#150000
b111011001110 '
b1111000011 (
1#
#156250
0#
#162500
0!
b111111010101 $
b101110000 %
1#
#168750
0#
#175000
0"
0*
b101011 '
b111010010000 (
1#
#181250
0#
#187500
1!
b1001001101 $
b11100110011 %
0)
1#
#193750
0#
#200000
1"
1*
b1001001101 '
b11100110011 (
1#
#206250
0#
#212500
0!
b110011011101 $
b11110100001 %
1)
1#
#218750
0#
#225000
0"
0*
b1100100011 '
b100001011111 (
1#
#231250
0#
#237500
b10101111101 $
b11010111001 %
0)
1#
#243750
0#
#250000
b10101111101 '
b11010111001 (
1#
#256250
0#
#262500
1!
b1000000000 $
b11010110110 %
1#
#268750
0#
#275000
1"
1*
b1000000000 '
b11010110110 (
1#
#281250
0#
#287500
0!
b111100100 $
b111110010111 %
1)
1#
#293750
0#
#300000
0"
0*
b111000011100 '
b1101001 (
1#
#306250
0#
#312500
b100100111000 $
b100100101011 %
0)
1#
#318750
0#
#325000
b100100111000 '
b100100101011 (
1#
#331250
0#
#337500
b100100101011 $
b110011010001 %
1#
#343750
0#
#350000
b100100101011 '
b110011010001 (
1#
#356250
0#
#362500
1!
b101001110001 $
b100111011110 %
1#
#368750
0#
#375000
1"
1*
b101001110001 '
b100111011110 (
1#
#381250
0#
#387500
0!
b10100110111 $
b11110111010 %
1)
1#
#393750
0#
#400000
0"
0*
b101011001001 '
b100001000110 (
1#
#406250
0#
#412500
1!
b111010011001 $
b110001001011 %
0)
1#
#418750
0#
#425000
1"
1*
b111010011001 '
b110001001011 (
1#
#431250
0#
#437500
0!
b111101111010 $
b110010100000 %
1)
1#
#443750
0#
#450000
0"
0*
b10000110 '
b1101100000 (
1#
#456250
0#
#462500
1!
b110100111010 $
b11100010100 %
0)
1#
#468750
0#
#475000
1"
1*
b110100111010 '
b11100010100 (
1#
#481250
0#
#487500
b1100000111 $
b111000001000 %
1)
1#
#493750
0#
#500000
b110011111001 '
b111111000 (
1#
#506250
0#
#512500
b1101101101 $
b111000001001 %
1#
#518750
0#
#525000
b110010010011 '
b111110111 (
1#
#531250
0#
#537500
0!
b11100111101 $
b11010111 %
1#
#543750
0#
#550000
0"
0*
b100011000011 '
b111100101001 (
1#
#556250
0#
#562500
b111001011111 $
b101010100101 %
0)
1#
#568750
0#
#575000
b111001011111 '
b101010100101 (
1#
#581250
0#
#587500
1!
b101001010011 $
b110101101101 %
1#
#593750
0#
#600000
1"
1*
b101001010011 '
b110101101101 (
1#
#606250
0#
#612500
0!
b10111010001 $
b1101100 %
1)
1#
#618750
0#
#625000
0"
0*
b101000101111 '
b111110010100 (
1#
#631250
0#
#637500
b111010110000 $
b110111000001 %
0)
1#
#643750
0#
#650000
b111010110000 '
b110111000001 (
1#
#656250
0#
#662500
1!
b101111001101 $
b111001001011 %
1#
#668750
0#
#675000
1"
1*
b101111001101 '
b111001001011 (
1#
#681250
0#
#687500
b1110011010 $
b1000011 %
1)
1#
#693750
0#
#700000
b110001100110 '
b111110111101 (
1#
#706250
0#
#712500
0!
b100100111111 $
b100100000011 %
1#
#718750
0#
#725000
0"
0*
b11011000001 '
b11011111101 (
1#
#731250
0#
#737500
1!
b101011011110 $
b100000111101 %
0)
1#
#743750
0#
#750000
1"
1*
b101011011110 '
b100000111101 (
1#
#756250
0#
#762500
0!
b1111000110 $
b11010010110 %
1)
1#
#768750
0#
#775000
0"
0*
b110000111010 '
b100101101010 (
1#
#781250
0#
#787500
b10000011111 $
b1001010001 %
0)
1#
#793750
0#
#800000
b10000011111 '
b1001010001 (
1#
#806250
0#
#812500
1!
b111110110001 $
b10010011010 %
1#
#818750
0#
#825000
1"
1*
b111110110001 '
b10010011010 (
1#
#831250
0#
#837500
0!
b110001100101 $
b11010010101 %
1)
1#
#843750
0#
#850000
0"
0*
b1110011011 '
b100101101011 (
1#
#856250
0#
#862500
1!
b1011101101 $
b111011111100 %
0)
1#
#868750
0#
#875000
1"
1*
b1011101101 '
b111011111100 (
1#
#881250
0#
#887500
b110010100110 $
b1110110000 %
1)
1#
#893750
0#
#900000
b1101011010 '
b110001010000 (
1#
#906250
0#
#912500
b11110100000 $
b110001000100 %
1#
#918750
0#
#925000
b100001100000 '
b1110111100 (
1#
#931250
0#
#937500
b101110 $
b11011111111 %
1#
#943750
0#
#950000
b111111010010 '
b100100000001 (
1#
#956250
0#
#962500
0!
b111100010111 $
b101100100100 %
1#
#968750
0#
#975000
0"
0*
b11101001 '
b10011011100 (
1#
#981250
0#
#987500
1!
b1001110110 $
b10010101111 %
0)
1#
#993750
0#
#1000000
1"
1*
b1001110110 '
b10010101111 (
1#
#1006250
0#
#1012500
0!
b11001000011 $
b100011110000 %
1)
1#
#1018750
0#
#1025000
0"
0*
b100110111101 '
b11100010000 (
1#
#1031250
0#
#1037500
b101111110010 $
b100111010011 %
0)
1#
#1043750
0#
#1050000
b101111110010 '
b100111010011 (
1#
#1056250
0#
#1062500
b111110110 $
b101110100110 %
1#
#1068750
0#
#1075000
b111110110 '
b101110100110 (
1#
#1081250
0#
#1087500
b10011100001 $
b111101111001 %
1#
#1093750
0#
#1100000
b10011100001 '
b111101111001 (
1#
#1106250
0#
#1112500
b101010101101 $
b111001001100 %
1#
#1118750
0#
#1125000
b101010101101 '
b111001001100 (
1#
#1131250
0#
#1137500
1!
b1000001011 $
b1000011111 %
1#
#1143750
0#
#1150000
1"
1*
b1000001011 '
b1000011111 (
1#
#1156250
0#
#1162500
b11111000011 $
b1100010111 %
1)
1#
#1168750
0#
#1175000
b100000111101 '
b110011101001 (
1#
#1181250
0#
#1187500
0!
b101000100110 $
b100011001010 %
1#
#1193750
0#
#1200000
0"
0*
b10111011010 '
b11100110110 (
1#
#1206250
0#
#1212500
b11010010 $
b111110010110 %
0)
1#
#1218750
0#
#1225000
b11010010 '
b111110010110 (
1#
#1231250
0#
#1237500
b10011100001 $
b110001000011 %
1#
#1243750
0#
#1250000
b10011100001 '
b110001000011 (
1#
#1256250
0#
#1262500
b101010101010 $
b110000001011 %
1#
#1268750
0#
#1275000
b101010101010 '
b110000001011 (
1#
#1281250
0#
#1287500
1!
b100001101100 $
b111011001 %
1#
#1293750
0#
#1300000
1"
1*
b100001101100 '
b111011001 (
1#
#1306250
0#
#1312500
0!
b1100000100 $
b101001100 %
1)
1#
#1318750
0#
#1325000
0"
0*
b110011111100 '
b111010110100 (
1#
#1331250
0#
#1337500
b100101110001 $
b100011111001 %
0)
1#
#1343750
0#
#1350000
b100101110001 '
b100011111001 (
1#
#1356250
0#
#1362500
1!
b101111000100 $
b11101110111 %
1#
#1368750
0#
#1375000
1"
1*
b101111000100 '
b11101110111 (
1#
#1381250
0#
#1387500
b110000111110 $
b101110101011 %
1)
1#
#1393750
0#
#1400000
b1111000010 '
b10001010101 (
1#
#1406250
0#
#1412500
0!
b100100000110 $
b100010101111 %
1#
#1418750
0#
#1425000
0"
0*
b11011111010 '
b11101010001 (
1#
#1431250
0#
#1437500
b100010101100 $
b101001101 %
0)
1#
#1443750
0#
#1450000
b100010101100 '
b101001101 (
1#
#1456250
0#
#1462500
b101111000010 $
b111011101001 %
1#
#1468750
0#
#1475000
b101111000010 '
b111011101001 (
1#
#1481250
0#
#1487500
1!
b111010010 $
b111011101110 %
1#
#1493750
0#
#1500000
1"
1*
b111010010 '
b111011101110 (
1#
#1506250
0#
#1512500
0!
b101100001010 $
b110101110110 %
1)
1#
#1518750
0#
#1525000
0"
0*
b10011110110 '
b1010001010 (
1#
#1531250
0#
#1537500
b11000111100 $
b10001110100 %
0)
1#
#1543750
0#
#1550000
b11000111100 '
b10001110100 (
1#
#1556250
0#
#1562500
1!
b110011011110 $
b11110111001 %
1#
#1568750
0#
#1575000
1"
1*
b110011011110 '
b11110111001 (
1#
#1581250
0#
#1587500
b101110011010 $
b101011100001 %
1)
1#
#1593750
0#
#1600000
b10001100110 '
b10100011111 (
1#
#1606250
0#
#1612500
b1111000011 $
b1010010010 %
1#
#1618750
0#
#1625000
b110000111101 '
b110101101110 (
1#
#1631250
0#
#1637500
0!
b110000101011 $
b100000110101 %
1#
#1643750
0#
#1650000
0"
0*
b1111010101 '
b11111001011 (
1#
#1656250
0#
#1662500
b11010010100 $
b1001011010 %
0)
1#
#1668750
0#
#1675000
b11010010100 '
b1001011010 (
1#
#1681250
0#
#1687500
1!
b10100000100 $
b11100011101 %
1#
#1693750
0#
#1700000
1"
1*
b10100000100 '
b11100011101 (
1#
#1706250
0#
#1712500
b1100000 $
b1001100111 %
1)
1#
#1718750
0#
#1725000
b111110100000 '
b110110011001 (
1#
#1731250
0#
#1737500
b11101101111 $
b111010100011 %
1#
#1743750
0#
#1750000
b100010010001 '
b101011101 (
1#
#1756250
0#
#1762500
0!
b11000 $
b111100011001 %
1#
#1768750
0#
#1775000
0"
0*
b111111101000 '
b11100111 (
1#
#1781250
0#
#1787500
b100001010010 $
b101110110011 %
0)
1#
#1793750
0#
#1800000
b100001010010 '
b101110110011 (
1#
#1806250
0#
#1812500
1!
b101110111110 $
b1110101000 %
1#
#1818750
0#
#1825000
1"
1*
b101110111110 '
b1110101000 (
1#
#1831250
0#
#1837500
b101110100100 $
b110100101 %
1)
1#
#1843750
0#
#1850000
b10001011100 '
b111001011011 (
1#
#1856250
0#
#1862500
0!
b11100000011 $
b1110111001 %
1#
#1868750
0#
#1875000
0"
0*
b100011111101 '
b110001000111 (
1#
#1881250
0#
#1887500
b100111111011 $
b111001010 %
0)
1#
#1893750
0#
#1900000
b100111111011 '
b111001010 (
1#
#1906250
0#
#1912500
b110011110111 $
b101110001111 %
1#
#1918750
0#
#1925000
b110011110111 '
b101110001111 (
1#
#1931250
0#
#1937500
1!
b100010 $
b100111011100 %
1#
#1943750
0#
#1950000
1"
1*
b100010 '
b100111011100 (
1#
#1956250
0#
#1962500
0!
b101010010100 $
b110010000001 %
1)
1#
#1968750
0#
#1975000
0"
0*
b10101101100 '
b1101111111 (
1#
#1981250
0#
#1987500
1!
b110101110000 $
b111000011000 %
0)
1#
#1993750
0#
#2000000
1"
1*
b110101110000 '
b111000011000 (
1#
#2006250
0#
#2012500
b11000001101 $
b101111101011 %
1)
1#
#2018750
0#
#2025000
b100111110011 '
b10000010101 (
1#
#2031250
0#
#2037500
0!
b101101100 $
b111010001010 %
1#
#2043750
0#
#2050000
0"
0*
b111010010100 '
b101110110 (
1#
#2056250
0#
#2062500
b100010001001 $
b110110000010 %
0)
1#
#2068750
0#
#2075000
b100010001001 '
b110110000010 (
1#
#2081250
0#
#2087500
1!
b110000110101 $
b111101100100 %
1#
#2093750
0#
#2100000
1"
1*
b110000110101 '
b111101100100 (
1#
#2106250
0#
#2112500
b1100100000 $
b101111111010 %
1)
1#
#2118750
0#
#2125000
b110011100000 '
b10000000110 (
1#
#2131250
0#
#2137500
b1011100000 $
b110011101111 %
1#
#2143750
0#
#2150000
b110100100000 '
b1100010001 (
1#
#2156250
0#
#2162500
0!
b1110000 $
b110100010100 %
1#
#2168750
0#
#2175000
0"
0*
b111110010000 '
b1011101100 (
1#
#2181250
0#
#2187500
1!
b110111001011 $
b10111101110 %
0)
1#
#2193750
0#
#2200000
1"
1*
b110111001011 '
b10111101110 (
1#
#2206250
0#
#2212500
0!
b10111100001 $
b10001001101 %
1)
1#
#2218750
0#
#2225000
0"
0*
b101000011111 '
b101110110011 (
1#
#2231250
0#
#2237500
b101001110100 $
b10001100010 %
0)
1#
#2243750
0#
#2250000
b101001110100 '
b10001100010 (
1#
#2256250
0#
#2262500
b111011011 $
b1100111 %
1#
#2268750
0#
#2275000
b111011011 '
b1100111 (
1#
#2281250
0#
#2287500
b10010101000 $
b110001100101 %
1#
#2293750
0#
#2300000
b10010101000 '
b110001100101 (
1#
#2306250
0#
#2312500
b111000011010 $
b11111011100 %
1#
#2318750
0#
#2325000
b111000011010 '
b11111011100 (
1#
#2331250
0#
#2337500
1!
b101111000100 $
b100001011011 %
1#
#2343750
0#
#2350000
1"
1*
b101111000100 '
b100001011011 (
1#
#2356250
0#
#2362500
b1101100110 $
b101101011001 %
1)
1#
#2368750
0#
#2375000
b110010011010 '
b10010100111 (
1#
#2381250
0#
#2387500
b100001101011 $
b100110001011 %
1#
#2393750
0#
#2400000
b11110010101 '
b11001110101 (
1#
#2406250
0#
#2412500
b110111000110 $
b101011101101 %
1#
#2418750
0#
#2425000
b1000111010 '
b10100010011 (
1#
#2431250
0#
#2437500
0!
b101111110000 $
b111100110110 %
1#
#2443750
0#
#2450000
0"
0*
b10000010000 '
b11001010 (
1#
#2456250
0#
#2462500
b10100110100 $
b110111001110 %
0)
1#
#2468750
0#
#2475000
b10100110100 '
b110111001110 (
1#
#2481250
0#
#2487500
1!
b1101100101 $
b1010111111 %
1#
#2493750
0#
#2500000
1"
1*
b1101100101 '
b1010111111 (
1#
#2506250
0#
#2512500
0!
b100001000100 $
b11001101111 %
1)
1#
#2518750
0#
#2525000
0"
0*
b11110111100 '
b100110010001 (
1#
#2531250
0#
#2537500
0)
1#
