Testbenches/AMDemod/AMDemod.v

/* Performs AM Demodulation. sqrt( I^2 + Q^2) 
Square root code is taken from https://verilogcodes.blogspot.com/2017/11/a-verilog-function-for-finding-square-root.html

TODO: use only one multiplier with TDM
TODO: minimize rounding errors of sqrt, get fractional result by scaling input
*/
module AMDemodulator
  (
    clk,
    I_in ,
    Q_in ,
    d_out); 
  //	   PUR PUR_INST(.PUR (1'b1));


  input clk;  
  input signed [11:0] I_in;
  input signed [11:0] Q_in;
  reg signed [15:0] d_out_d;
  output reg [11:0] d_out;
  reg [1:0] state;
  reg NewSample;
  reg [31:0] ISquare;
  reg [15:0] QSquare;
  reg [15:0] SquareSum;

  reg signed [11:0] MultDataA;
  reg signed [11:0] MultDataB;
  reg signed [23:0] MultResult1;


  reg signed [11:0] MultDataC;
  reg signed [11:0] MultDataD;
  reg signed [23:0] MultResult2;

  function [15:0] sqrt;
    input [31:0] num;  //declare input
    //intermediate signals.
    reg [31:0] a;
    reg [15:0] q;
    reg [17:0] left,right,r;    
    integer i;
    begin
      //initialize all the variables.
      a = num;
      q = 0;
      i = 0;
      left = 0;   //input to adder/sub
      right = 0;  //input to adder/sub
      r = 0;  //remainder
      //run the calculations for 16 iterations.
      for(i=0;i<16;i=i+1) begin 
        right = {q,r[17],1'b1};
        left = {r[15:0],a[31:30]};
        a = {a[29:0],2'b00};    //left shift by 2 bits.
        if (r[17] == 1) //add if r is negative
          r = left + right;
        else    //subtract if r is positive
          r = left - right;
        q = {q[14:0],!r[17]};       
      end
      sqrt = q;   //final assignment of output.
    end
  endfunction //end of Function


  always@(posedge clk) begin

    MultDataA <= I_in;
    MultDataB <= I_in;
    MultDataC <= Q_in;
    MultDataD <= Q_in;

    MultResult1 <= MultDataA*MultDataB;
    MultResult2 <= MultDataC*MultDataD;

    ISquare <= MultResult1 + MultResult2;
    d_out_d <= sqrt(ISquare);
    d_out <= d_out_d[11:0];
  end


initial begin
	$dumpfile("AMDemod_waves.vcd");
	$dumpvars;
end

endmodule

Testbenches/AMDemod/AMDemod_waves.vcd
$date
	Sat Mar 30 02:10:21 2024
$end
$version
	Icarus Verilog
$end
$timescale
	1ps
$end
$scope module AMDemodulator $end
$var wire 12 ! I_in [11:0] $end
$var wire 12 " Q_in [11:0] $end
$var wire 1 # clk $end
$var reg 32 $ ISquare [31:0] $end
$var reg 12 % MultDataA [11:0] $end
$var reg 12 & MultDataB [11:0] $end
$var reg 12 ' MultDataC [11:0] $end
$var reg 12 ( MultDataD [11:0] $end
$var reg 24 ) MultResult1 [23:0] $end
$var reg 24 * MultResult2 [23:0] $end
$var reg 12 + d_out [11:0] $end
$var reg 16 , d_out_d [15:0] $end
$scope function sqrt $end
$var reg 32 - a [31:0] $end
$var reg 18 . left [17:0] $end
$var reg 32 / num [31:0] $end
$var reg 16 0 q [15:0] $end
$var reg 18 1 r [17:0] $end
$var reg 18 2 right [17:0] $end
$var integer 32 3 i [31:0] $end
$upscope $end
$upscope $end
$enddefinitions $end
$comment Show the parameter values. $end
$dumpall
$end
#0
$dumpvars
b10000 3
b0xxxxxxxxxxxxxxxx1 2
bx 1
bx 0
bx /
bx .
b0 -
bx ,
bx +
bx *
bx )
b0 (
b0 '
b0 &
b0 %
bx $
1#
b0 "
b0 !
$end
#2500
0#
#5000
b0 *
b0 )
bx 1
b0xxxxxxxxxxxxxxxx1 2
bx .
b10000 3
bx 0
b0 -
1#
#7500
0#
#10000
b0 $
bx 1
b0xxxxxxxxxxxxxxxx1 2
bx .
b10000 3
bx 0
b0 -
1#
#12500
0#
#15000
b0 ,
b111111111111111111 1
b11 2
b111111111111111100 .
b10000 3
b0 0
b0 /
1#
#17500
0#
#20000
b0 +
b111111111111111111 1
b11 2
b111111111111111100 .
b10000 3
1#
#22500
0#
#25000
b111111111111111111 1
b11 2
b111111111111111100 .
b10000 3
1#
#27500
0#
#30000
b11111111111 "
b11111111111 !
b111111111111111111 1
b11 2
b111111111111111100 .
b10000 3
1#
#32500
0#
#35000
b11111111111 (
b11111111111 '
b11111111111 &
b11111111111 %
b111111111111111111 1
b11 2
b111111111111111100 .
b10000 3
1#
#37500
0#
#40000
b1111111111000000000001 *
b1111111111000000000001 )
b111111111111111111 1
b11 2
b111111111111111100 .
b10000 3
1#
#42500
0#
#45000
b11111111110000000000010 $
b111111111111111111 1
b11 2
b111111111111111100 .
b10000 3
1#
#47500
0#
#50000
b101101001110 ,
b101101001110 0
b111111110110100001 1
b1011010011101 2
b1010000111110 .
b10000 3
b0 -
b11111111110000000000010 /
1#
#52500
0#
#55000
b101101001110 +
b111111110110100001 1
b1011010011101 2
b1010000111110 .
b10000 3
b101101001110 0
b0 -
1#
#57500
0#
#60000
b100000000000 "
b100000000000 !
b111111110110100001 1
b1011010011101 2
b1010000111110 .
b10000 3
b101101001110 0
b0 -
1#
#62500
0#
#65000
b100000000000 (
b100000000000 '
b100000000000 &
b100000000000 %
b111111110110100001 1
b1011010011101 2
b1010000111110 .
b10000 3
b101101001110 0
b0 -
1#
#67500
0#
#70000
b10000000000000000000000 *
b10000000000000000000000 )
b111111110110100001 1
b1011010011101 2
b1010000111110 .
b10000 3
b101101001110 0
b0 -
1#
#72500
0#
#75000
b100000000000000000000000 $
b111111110110100001 1
b1011010011101 2
b1010000111110 .
b10000 3
b101101001110 0
b0 -
1#
#77500
0#
#80000
b101101010000 ,
b111111000001011111 1
b1011010100011 2
b111101100110111100 .
b10000 3
b101101010000 0
b0 -
b100000000000000000000000 /
1#
#82500
0#
#85000
b101101010000 +
b111111000001011111 1
b1011010100011 2
b111101100110111100 .
b10000 3
b101101010000 0
b0 -
1#
#87500
0#
#90000
b11111111111 !
b111111000001011111 1
b1011010100011 2
b111101100110111100 .
b10000 3
b101101010000 0
b0 -
1#
#92500
0#
#95000
b11111111111 &
b11111111111 %
b111111000001011111 1
b1011010100011 2
b111101100110111100 .
b10000 3
b101101010000 0
b0 -
1#
#97500
0#
#100000
b1111111111000000000001 )
b111111000001011111 1
b1011010100011 2
b111101100110111100 .
b10000 3
b101101010000 0
b0 -
1#
#102500
0#
#105000
b11111111111000000000001 $
b111111000001011111 1
b1011010100011 2
b111101100110111100 .
b10000 3
b101101010000 0
b0 -
1#
#107500
0#
#110000
b101101001111 ,
b110110100000 1
b1011010011101 2
b10010000111101 .
b10000 3
b101101001111 0
b0 -
b11111111111000000000001 /
1#
#112500
0#
#115000
b101101001111 +
b110110100000 1
b1011010011101 2
b10010000111101 .
b10000 3
b101101001111 0
b0 -
1#
#117500
0#
#120000
b11111111111 "
b100000000000 !
b110110100000 1
b1011010011101 2
b10010000111101 .
b10000 3
b101101001111 0
b0 -
1#
#122500
0#
#125000
b11111111111 (
b11111111111 '
b100000000000 &
b100000000000 %
b110110100000 1
b1011010011101 2
b10010000111101 .
b10000 3
b101101001111 0
b0 -
1#
#127500
0#
#130000
b1111111111000000000001 *
b10000000000000000000000 )
b110110100000 1
b1011010011101 2
b10010000111101 .
b10000 3
b101101001111 0
b0 -
1#
#132500
0#
#135000
b110110100000 1
b1011010011101 2
b10010000111101 .
b10000 3
b101101001111 0
b0 -
1#
#137500
0#
#140000
b110110100000 1
b1011010011101 2
b10010000111101 .
b10000 3
b101101001111 0
b0 -
1#
#142500
0#
#145000
b110110100000 1
b1011010011101 2
b10010000111101 .
b10000 3
b101101001111 0
b0 -
1#
#147500
0#
#150000
b110000001001 "
b100010001 !
b110110100000 1
b1011010011101 2
b10010000111101 .
b10000 3
b101101001111 0
b0 -
1#
#152500
0#
#155000
b110000001001 (
b110000001001 '
b100010001 &
b100010001 %
b110110100000 1
b1011010011101 2
b10010000111101 .
b10000 3
b101101001111 0
b0 -
1#
#157500
0#
#160000
b11111011100001010001 *
b10010001100100001 )
b110110100000 1
b1011010011101 2
b10010000111101 .
b10000 3
b101101001111 0
b0 -
1#
#162500
0#
#165000
b100001101101101110010 $
b110110100000 1
b1011010011101 2
b10010000111101 .
b10000 3
b101101001111 0
b0 -
1#
#167500
0#
#170000
b10000011011 ,
b10011001 1
b100000110101 2
b100011001110 .
b10000 3
b10000011011 0
b0 -
b100001101101101110010 /
1#
#172500
0#
#175000
b10000011011 +
b10011001 1
b100000110101 2
b100011001110 .
b10000 3
b10000011011 0
b0 -
1#
#177500
0#
#180000
b101010111000 "
b101001011010 !
b10011001 1
b100000110101 2
b100011001110 .
b10000 3
b10000011011 0
b0 -
1#
#182500
0#
#185000
b101010111000 (
b101010111000 '
b101001011010 &
b101001011010 %
b10011001 1
b100000110101 2
b100011001110 .
b10000 3
b10000011011 0
b0 -
1#
#187500
0#
#190000
b110111110010001000000 *
b111111110011110100100 )
b10011001 1
b100000110101 2
b100011001110 .
b10000 3
b10000011011 0
b0 -
1#
#192500
0#
#195000
b1110111100101111100100 $
b10011001 1
b100000110101 2
b100011001110 .
b10000 3
b10000011011 0
b0 -
1#
#197500
0#
#200000
b11110111011 ,
b100101001011 1
b111101110101 2
b1100011000000 .
b10000 3
b11110111011 0
b0 -
b1110111100101111100100 /
1#
#202500
0#
#205000
b11110111011 +
b100101001011 1
b111101110101 2
b1100011000000 .
b10000 3
b11110111011 0
b0 -
1#
#207500
0#
#210000
b1010011100 "
b10110101101 !
b100101001011 1
b111101110101 2
b1100011000000 .
b10000 3
b11110111011 0
b0 -
1#
#212500
0#
#215000
b1010011100 (
b1010011100 '
b10110101101 &
b10110101101 %
b100101001011 1
b111101110101 2
b1100011000000 .
b10000 3
b11110111011 0
b0 -
1#
#217500
0#
#220000
b1101100111100010000 *
b1000000011011011101001 )
b100101001011 1
b111101110101 2
b1100011000000 .
b10000 3
b11110111011 0
b0 -
1#
#222500
0#
#225000
b1001110000010111111001 $
b100101001011 1
b111101110101 2
b1100011000000 .
b10000 3
b11110111011 0
b0 -
1#
#227500
0#
#230000
b11000111111 ,
b1001111000 1
b110001111101 2
b111011110101 .
b10000 3
b11000111111 0
b0 -
b1001110000010111111001 /
1#
#232500
0#
#235000
b11000111111 +
b1001111000 1
b110001111101 2
b111011110101 .
b10000 3
b11000111111 0
b0 -
1#
#237500
0#
#240000
b1110100011 "
b11100000111 !
b1001111000 1
b110001111101 2
b111011110101 .
b10000 3
b11000111111 0
b0 -
1#
#242500
0#
#245000
b1110100011 (
b1110100011 '
b11100000111 &
b11100000111 %
b1001111000 1
b110001111101 2
b111011110101 .
b10000 3
b11000111111 0
b0 -
1#
#247500
0#
#250000
b11010011100111001001 *
b1100010110001000110001 )
b1001111000 1
b110001111101 2
b111011110101 .
b10000 3
b11000111111 0
b0 -
1#
#252500
0#
#255000
b1111101001101111111010 $
b1001111000 1
b110001111101 2
b111011110101 .
b10000 3
b11000111111 0
b0 -
1#
#257500
0#
#260000
b11111101001 ,
b100111101001 1
b111111010011 2
b111111101000010110 .
b10000 3
b11111101001 0
b0 -
b1111101001101111111010 /
1#
#262500
0#
#265000
b11111101001 +
b100111101001 1
b111111010011 2
b111111101000010110 .
b10000 3
b11111101001 0
b0 -
1#
#267500
0#
#270000
b111011010011 "
b1100111110 !
b100111101001 1
b111111010011 2
b111111101000010110 .
b10000 3
b11111101001 0
b0 -
1#
#272500
0#
#275000
b111011010011 (
b111011010011 '
b1100111110 &
b1100111110 %
b100111101001 1
b111111010011 2
b111111101000010110 .
b10000 3
b11111101001 0
b0 -
1#
#277500
0#
#280000
b10110000111101001 *
b10101000001100000100 )
b100111101001 1
b111111010011 2
b111111101000010110 .
b10000 3
b11111101001 0
b0 -
1#
#282500
0#
#285000
b10111110010011101101 $
b100111101001 1
b111111010011 2
b111111101000010110 .
b10000 3
b11111101001 0
b0 -
1#
#287500
0#
#290000
b1101110010 ,
b111111111101000100 1
b11011100101 2
b11000101001 .
b10000 3
b1101110010 0
b0 -
b10111110010011101101 /
1#
#292500
0#
#295000
b1101110010 +
b111111111101000100 1
b11011100101 2
b11000101001 .
b10000 3
b1101110010 0
b0 -
1#
#297500
0#
#300000
b1001101010 "
b111111101001 !
b111111111101000100 1
b11011100101 2
b11000101001 .
b10000 3
b1101110010 0
b0 -
1#
#302500
0#
#305000
b1001101010 (
b1001101010 '
b111111101001 &
b111111101001 %
b111111111101000100 1
b11011100101 2
b11000101001 .
b10000 3
b1101110010 0
b0 -
1#
#307500
0#
#310000
b1011101001111100100 *
b1000010001 )
b111111111101000100 1
b11011100101 2
b11000101001 .
b10000 3
b1101110010 0
b0 -
1#
#312500
0#
#315000
b1011101010111110101 $
b111111111101000100 1
b11011100101 2
b11000101001 .
b10000 3
b1101110010 0
b0 -
1#
#317500
0#
#320000
b1001101010 ,
b111111110100111100 1
b10011010101 2
b1000010001 .
b10000 3
b1001101010 0
b0 -
b1011101010111110101 /
1#
#322500
0#
#325000
b1001101010 +
b111111110100111100 1
b10011010101 2
b1000010001 .
b10000 3
b1001101010 0
b0 -
1#
#327500
0#
#330000
b11100110010 "
b10100101100 !
b111111110100111100 1
b10011010101 2
b1000010001 .
b10000 3
b1001101010 0
b0 -
1#
#332500
0#
#335000
b11100110010 (
b11100110010 '
b10100101100 &
b10100101100 %
b111111110100111100 1
b10011010101 2
b1000010001 .
b10000 3
b1001101010 0
b0 -
1#
#337500
0#
#340000
b1100111100010111000100 *
b110101011111110010000 )
b111111110100111100 1
b10011010101 2
b1000010001 .
b10000 3
b1001101010 0
b0 -
1#
#342500
0#
#345000
b10011101000010101010100 $
b111111110100111100 1
b10011010101 2
b1000010001 .
b10000 3
b1001101010 0
b0 -
1#
#347500
0#
#350000
b100011011100 ,
b111111011010001011 1
b1000110111011 2
b111110010011010000 .
b10000 3
b100011011100 0
b0 -
b10011101000010101010100 /
1#
#352500
0#
#355000
b100011011100 +
b111111011010001011 1
b1000110111011 2
b111110010011010000 .
b10000 3
b100011011100 0
b0 -
1#
#357500
0#
#360000
b110001010001 "
b100001000 !
b111111011010001011 1
b1000110111011 2
b111110010011010000 .
b10000 3
b100011011100 0
b0 -
1#
#362500
0#
#365000
b110001010001 (
b110001010001 '
b100001000 &
b100001000 %
b111111011010001011 1
b1000110111011 2
b111110010011010000 .
b10000 3
b100011011100 0
b0 -
1#
#367500
0#
#370000
b11011001000110100001 *
b10001000001000000 )
b111111011010001011 1
b1000110111011 2
b111110010011010000 .
b10000 3
b100011011100 0
b0 -
1#
#372500
0#
#375000
b11101010000111100001 $
b111111011010001011 1
b1000110111011 2
b111110010011010000 .
b10000 3
b100011011100 0
b0 -
1#
#377500
0#
#380000
b1111010011 ,
b111111000 1
b11110100101 2
b100110011101 .
b10000 3
b1111010011 0
b0 -
b11101010000111100001 /
1#
#382500
0#
#385000
b1111010011 +
b111111000 1
b11110100101 2
b100110011101 .
b10000 3
b1111010011 0
b0 -
1#
#387500
0#
#390000
b10000010 "
b1001101010 !
b111111000 1
b11110100101 2
b100110011101 .
b10000 3
b1111010011 0
b0 -
1#
#392500
0#
#395000
b10000010 (
b10000010 '
b1001101010 &
b1001101010 %
b111111000 1
b11110100101 2
b100110011101 .
b10000 3
b1111010011 0
b0 -
1#
#397500
0#
#400000
b100001000000100 *
b1011101001111100100 )
b111111000 1
b11110100101 2
b100110011101 .
b10000 3
b1111010011 0
b0 -
1#
#402500
0#
#405000
b1100001010111101000 $
b111111000 1
b11110100101 2
b100110011101 .
b10000 3
b1111010011 0
b0 -
1#
#407500
0#
#410000
b1001110111 ,
b1010010111 1
b10011101101 2
b11110000100 .
b10000 3
b1001110111 0
b0 -
b1100001010111101000 /
1#
#412500
0#
#415000
b1001110111 +
b1010010111 1
b10011101101 2
b11110000100 .
b10000 3
b1001110111 0
b0 -
1#
#417500
0#
#420000
b10000010000 "
b10111101001 !
b1010010111 1
b10011101101 2
b11110000100 .
b10000 3
b1001110111 0
b0 -
1#
#422500
0#
#425000
b10000010000 (
b10000010000 '
b10111101001 &
b10111101001 %
b1010010111 1
b10011101101 2
b11110000100 .
b10000 3
b1001110111 0
b0 -
1#
#427500
0#
#430000
b100001000000100000000 *
b1000101110111000010001 )
b1010010111 1
b10011101101 2
b11110000100 .
b10000 3
b1001110111 0
b0 -
1#
#432500
0#
#435000
b1100110110111100010001 $
b1010010111 1
b10011101101 2
b11110000100 .
b10000 3
b1001110111 0
b0 -
1#
#437500
0#
#440000
b11100101011 ,
b110111011000 1
b111001010101 2
b1110000101101 .
b10000 3
b11100101011 0
b0 -
b1100110110111100010001 /
1#
#442500
0#
#445000
b11100101011 +
b110111011000 1
b111001010101 2
b1110000101101 .
b10000 3
b11100101011 0
b0 -
1#
#447500
0#
#450000
b11100111011 "
b1111010011 !
b110111011000 1
b111001010101 2
b1110000101101 .
b10000 3
b11100101011 0
b0 -
1#
#452500
0#
#455000
b11100111011 (
b11100111011 '
b1111010011 &
b1111010011 %
b110111011000 1
b111001010101 2
b1110000101101 .
b10000 3
b11100101011 0
b0 -
1#
#457500
0#
#460000
b1101000100011110011001 *
b11101001111111101001 )
b110111011000 1
b111001010101 2
b1110000101101 .
b10000 3
b11100101011 0
b0 -
1#
#462500
0#
#465000
b10000101110011110000010 $
b110111011000 1
b111001010101 2
b1110000101101 .
b10000 3
b11100101011 0
b0 -
1#
#467500
0#
#470000
b100000101101 ,
b111110011001 1
b1000001011011 2
b111111111100111110 .
b10000 3
b100000101101 0
b0 -
b10000101110011110000010 /
1#
#472500
0#
#475000
b100000101101 +
b111110011001 1
b1000001011011 2
b111111111100111110 .
b10000 3
b100000101101 0
b0 -
1#
#477500
0#
#480000
b11101110100 "
b101111110011 !
b111110011001 1
b1000001011011 2
b111111111100111110 .
b10000 3
b100000101101 0
b0 -
1#
#482500
0#
#485000
b11101110100 (
b11101110100 '
b101111110011 &
b101111110011 %
b111110011001 1
b1000001011011 2
b111111111100111110 .
b10000 3
b100000101101 0
b0 -
1#
#487500
0#
#490000
b1101111000110010010000 *
b100000110100010101001 )
b111110011001 1
b1000001011011 2
b111111111100111110 .
b10000 3
b100000101101 0
b0 -
1#
#492500
0#
#495000
b10001111111010100111001 $
b111110011001 1
b1000001011011 2
b111111111100111110 .
b10000 3
b100000101101 0
b0 -
1#
#497500
0#
#500000
b100001111011 ,
b101000100000 1
b1000011110101 2
b1101100010101 .
b10000 3
b100001111011 0
b0 -
b10001111111010100111001 /
1#
#502500
0#
#505000
b100001111011 +
b101000100000 1
b1000011110101 2
b1101100010101 .
b10000 3
b100001111011 0
b0 -
1#
#507500
0#
#510000
b101100010101 "
b111011110110 !
b101000100000 1
b1000011110101 2
b1101100010101 .
b10000 3
b100001111011 0
b0 -
1#
#512500
0#
#515000
b101100010101 (
b101100010101 '
b111011110110 &
b111011110110 %
b101000100000 1
b1000011110101 2
b1101100010101 .
b10000 3
b100001111011 0
b0 -
1#
#517500
0#
#520000
b110000010111110111001 *
b10001010001100100 )
b101000100000 1
b1000011110101 2
b1101100010101 .
b10000 3
b100001111011 0
b0 -
1#
#522500
0#
#525000
b110010100010000011101 $
b101000100000 1
b1000011110101 2
b1101100010101 .
b10000 3
b100001111011 0
b0 -
1#
#527500
0#
#530000
b10100000110 ,
b111111110111101100 1
b101000001101 2
b11111111001 .
b10000 3
b10100000110 0
b0 -
b110010100010000011101 /
1#
#532500
0#
#535000
b10100000110 +
b111111110111101100 1
b101000001101 2
b11111111001 .
b10000 3
b10100000110 0
b0 -
1#
#537500
0#
#540000
b1001101100 "
b10011101101 !
b111111110111101100 1
b101000001101 2
b11111111001 .
b10000 3
b10100000110 0
b0 -
1#
#542500
0#
#545000
b1001101100 (
b1001101100 '
b10011101101 &
b10011101101 %
b111111110111101100 1
b101000001101 2
b11111111001 .
b10000 3
b10100000110 0
b0 -
1#
#547500
0#
#550000
b1011101110110010000 *
b110000100001101101001 )
b111111110111101100 1
b101000001101 2
b11111111001 .
b10000 3
b10100000110 0
b0 -
1#
#552500
0#
#555000
b111100010000011111001 $
b111111110111101100 1
b101000001101 2
b11111111001 .
b10000 3
b10100000110 0
b0 -
1#
#557500
0#
#560000
b10101111101 ,
b111110000 1
b101011111011 2
b111111011011110101 .
b10000 3
b10101111101 0
b0 -
b111100010000011111001 /
1#
#562500
0#
#565000
b10101111101 +
b111110000 1
b101011111011 2
b111111011011110101 .
b10000 3
b10101111101 0
b0 -
1#
#567500
0#
#570000
b100010001000 "
b10001011101 !
b111110000 1
b101011111011 2
b111111011011110101 .
b10000 3
b10101111101 0
b0 -
1#
#572500
0#
#575000
b100010001000 (
b100010001000 '
b10001011101 &
b10001011101 %
b111110000 1
b101011111011 2
b111111011011110101 .
b10000 3
b10101111101 0
b0 -
1#
#577500
0#
#580000
b1101111100100001000000 *
b100110000100111001001 )
b111110000 1
b101011111011 2
b111111011011110101 .
b10000 3
b10101111101 0
b0 -
1#
#582500
0#
#585000
b10010101101001000001001 $
b111110000 1
b101011111011 2
b111111011011110101 .
b10000 3
b10101111101 0
b0 -
1#
#587500
0#
#590000
b100010100110 ,
b111111010100011000 1
b1000101001101 2
b11001100101 .
b10000 3
b100010100110 0
b0 -
b10010101101001000001001 /
1#
#592500
0#
#595000
b100010100110 +
b111111010100011000 1
b1000101001101 2
b11001100101 .
b10000 3
b100010100110 0
b0 -
1#
#597500
0#
#600000
b11111011101 "
b101111101110 !
b111111010100011000 1
b1000101001101 2
b11001100101 .
b10000 3
b100010100110 0
b0 -
1#
#602500
0#
#605000
b11111011101 (
b11111011101 '
b101111101110 &
b101111101110 %
b111111010100011000 1
b1000101001101 2
b11001100101 .
b10000 3
b100010100110 0
b0 -
1#
#607500
0#
#610000
b1111011101010011001001 *
b100001001000101000100 )
b111111010100011000 1
b1000101001101 2
b11001100101 .
b10000 3
b100010100110 0
b0 -
1#
#612500
0#
#615000
b10011100110011000001101 $
b111111010100011000 1
b1000101001101 2
b11001100101 .
b10000 3
b100010100110 0
b0 -
1#
#617500
0#
#620000
b100011011010 ,
b111111101010110100 1
b1000110110101 2
b110001101001 .
b10000 3
b100011011010 0
b0 -
b10011100110011000001101 /
1#
#622500
0#
#625000
b100011011010 +
b111111101010110100 1
b1000110110101 2
b110001101001 .
b10000 3
b100011011010 0
b0 -
1#
#627500
0#
#630000
b110111101000 "
b101111001011 !
b111111101010110100 1
b1000110110101 2
b110001101001 .
b10000 3
b100011011010 0
b0 -
1#
#632500
0#
#635000
b110111101000 (
b110111101000 '
b101111001011 &
b101111001011 %
b111111101010110100 1
b1000110110101 2
b110001101001 .
b10000 3
b100011011010 0
b0 -
1#
#637500
0#
#640000
b1000110001001000000 *
b100011011001011111001 )
b111111101010110100 1
b1000110110101 2
b110001101001 .
b10000 3
b100011011010 0
b0 -
1#
#642500
0#
#645000
b101100001010100111001 $
b111111101010110100 1
b1000110110101 2
b110001101001 .
b10000 3
b100011011010 0
b0 -
1#
#647500
0#
#650000
b10010110011 ,
b10000 1
b100101100101 2
b100101110101 .
b10000 3
b10010110011 0
b0 -
b101100001010100111001 /
1#
#652500
0#
#655000
b10010110011 +
b10000 1
b100101100101 2
b100101110101 .
b10000 3
b10010110011 0
b0 -
1#
#657500
0#
#660000
b111001101 "
b11011101 !
b10000 1
b100101100101 2
b100101110101 .
b10000 3
b10010110011 0
b0 -
1#
#662500
0#
#665000
b111001101 (
b111001101 '
b11011101 &
b11011101 %
b10000 1
b100101100101 2
b100101110101 .
b10000 3
b10010110011 0
b0 -
1#
#667500
0#
#670000
b110011111000101001 *
b1011111011001001 )
b10000 1
b100101100101 2
b100101110101 .
b10000 3
b10010110011 0
b0 -
1#
#672500
0#
#675000
b111111110011110010 $
b10000 1
b100101100101 2
b100101110101 .
b10000 3
b10010110011 0
b0 -
1#
#677500
0#
#680000
b111111111 ,
b11110001 1
b1111111101 2
b10011101110 .
b10000 3
b111111111 0
b0 -
b111111110011110010 /
1#
#682500
0#
#685000
b111111111 +
b11110001 1
b1111111101 2
b10011101110 .
b10000 3
b111111111 0
b0 -
1#
#687500
0#
#690000
b10000001 "
b100111010010 !
b11110001 1
b1111111101 2
b10011101110 .
b10000 3
b111111111 0
b0 -
1#
#692500
0#
#695000
b10000001 (
b10000001 '
b100111010010 &
b100111010010 %
b11110001 1
b1111111101 2
b10011101110 .
b10000 3
b111111111 0
b0 -
1#
#697500
0#
#700000
b100000100000001 *
b1001100011000001000100 )
b11110001 1
b1111111101 2
b10011101110 .
b10000 3
b111111111 0
b0 -
1#
#702500
0#
#705000
b1001100111000101000101 $
b11110001 1
b1111111101 2
b10011101110 .
b10000 3
b111111111 0
b0 -
1#
#707500
0#
#710000
b11000110011 ,
b1100011100 1
b110001100101 2
b111110000001 .
b10000 3
b11000110011 0
b0 -
b1001100111000101000101 /
1#
#712500
0#
#715000
b11000110011 +
b1100011100 1
b110001100101 2
b111110000001 .
b10000 3
b11000110011 0
b0 -
1#
#717500
0#
#720000
b100000110100 "
b110111100110 !
b1100011100 1
b110001100101 2
b111110000001 .
b10000 3
b11000110011 0
b0 -
1#
#722500
0#
#725000
b100000110100 (
b100000110100 '
b110111100110 &
b110111100110 %
b1100011100 1
b110001100101 2
b111110000001 .
b10000 3
b11000110011 0
b0 -
1#
#727500
0#
#730000
b1111001100101010010000 *
b1000110101010100100 )
b1100011100 1
b110001100101 2
b111110000001 .
b10000 3
b11000110011 0
b0 -
1#
#732500
0#
#735000
b10000010011010100110100 $
b1100011100 1
b110001100101 2
b111110000001 .
b10000 3
b11000110011 0
b0 -
1#
#737500
0#
#740000
b100000010011 ,
b1111001011 1
b1000000100101 2
b1001111110000 .
b10000 3
b100000010011 0
b0 -
b10000010011010100110100 /
1#
#742500
0#
#745000
b100000010011 +
b1111001011 1
b1000000100101 2
b1001111110000 .
b10000 3
b100000010011 0
b0 -
1#
#747500
0#
#750000
b110010100110 "
b11000001000 !
b1111001011 1
b1000000100101 2
b1001111110000 .
b10000 3
b100000010011 0
b0 -
1#
#752500
0#
#755000
b110010100110 (
b110010100110 '
b11000001000 &
b11000001000 %
b1111001011 1
b1000000100101 2
b1001111110000 .
b10000 3
b100000010011 0
b0 -
1#
#757500
0#
#760000
b10110011101110100100 *
b1001000110000001000000 )
b1111001011 1
b1000000100101 2
b1001111110000 .
b10000 3
b100000010011 0
b0 -
1#
#762500
0#
#765000
b1011111001101111100100 $
b1111001011 1
b1000000100101 2
b1001111110000 .
b10000 3
b100000010011 0
b0 -
1#
#767500
0#
#770000
b11011100110 ,
b111111011101110011 1
b110111001101 2
b10101000000 .
b10000 3
b11011100110 0
b0 -
b1011111001101111100100 /
1#
#772500
0#
#775000
b11011100110 +
b111111011101110011 1
b110111001101 2
b10101000000 .
b10000 3
b11011100110 0
b0 -
1#
#777500
0#
#780000
b10100111110 "
b1001111001 !
b111111011101110011 1
b110111001101 2
b10101000000 .
b10000 3
b11011100110 0
b0 -
1#
#782500
0#
#785000
b10100111110 (
b10100111110 '
b1001111001 &
b1001111001 %
b111111011101110011 1
b110111001101 2
b10101000000 .
b10000 3
b11011100110 0
b0 -
1#
#787500
0#
#790000
b110110111101100000100 *
b1100001110100110001 )
b111111011101110011 1
b110111001101 2
b10101000000 .
b10000 3
b11011100110 0
b0 -
1#
#792500
0#
#795000
b1000011001100000110101 $
b111111011101110011 1
b110111001101 2
b10101000000 .
b10000 3
b11011100110 0
b0 -
1#
#797500
0#
#800000
b10111001011 ,
b100100111100 1
b101110010101 2
b1010011010001 .
b10000 3
b10111001011 0
b0 -
b1000011001100000110101 /
1#
#802500
0#
#805000
b10111001011 +
b100100111100 1
b101110010101 2
b1010011010001 .
b10000 3
b10111001011 0
b0 -
1#
#807500
0#
#810000
b111100010000 "
b100000000011 !
b100100111100 1
b101110010101 2
b1010011010001 .
b10000 3
b10111001011 0
b0 -
1#
#812500
0#
#815000
b111100010000 (
b111100010000 '
b100000000011 &
b100000000011 %
b100100111100 1
b101110010101 2
b1010011010001 .
b10000 3
b10111001011 0
b0 -
1#
#817500
0#
#820000
b1110000100000000 *
b1111111101000000001001 )
b100100111100 1
b101110010101 2
b1010011010001 .
b10000 3
b10111001011 0
b0 -
1#
#822500
0#
#825000
b10000001011000100001001 $
b100100111100 1
b101110010101 2
b1010011010001 .
b10000 3
b10111001011 0
b0 -
1#
#827500
0#
#830000
b100000001011 ,
b10010000 1
b1000000010101 2
b1000010100101 .
b10000 3
b100000001011 0
b0 -
b10000001011000100001001 /
1#
#832500
0#
#835000
b100000001011 +
b10010000 1
b1000000010101 2
b1000010100101 .
b10000 3
b100000001011 0
b0 -
1#
#837500
0#
#840000
b110010110011 "
b10111010101 !
b10010000 1
b1000000010101 2
b1000010100101 .
b10000 3
b100000001011 0
b0 -
1#
#842500
0#
#845000
b110010110011 (
b110010110011 '
b10111010101 &
b10111010101 %
b10010000 1
b1000000010101 2
b1000010100101 .
b10000 3
b100000001011 0
b0 -
1#
#847500
0#
#850000
b10101110010100101001 *
b1000100000001100111001 )
b10010000 1
b1000000010101 2
b1000010100101 .
b10000 3
b100000001011 0
b0 -
1#
#852500
0#
#855000
b1011001110100001100010 $
b10010000 1
b1000000010101 2
b1000010100101 .
b10000 3
b100000001011 0
b0 -
1#
#857500
0#
#860000
b11010110011 ,
b11100111001 1
b110101100101 2
b1010010011110 .
b10000 3
b11010110011 0
b0 -
b1011001110100001100010 /
1#
#862500
0#
#865000
b11010110011 +
b11100111001 1
b110101100101 2
b1010010011110 .
b10000 3
b11010110011 0
b0 -
1#
#867500
0#
#870000
b100000000 "
b111101011110 !
b11100111001 1
b110101100101 2
b1010010011110 .
b10000 3
b11010110011 0
b0 -
1#
#872500
0#
#875000
b100000000 (
b100000000 '
b111101011110 &
b111101011110 %
b11100111001 1
b110101100101 2
b1010010011110 .
b10000 3
b11010110011 0
b0 -
1#
#877500
0#
#880000
b10000000000000000 *
b110011010000100 )
b11100111001 1
b110101100101 2
b1010010011110 .
b10000 3
b11010110011 0
b0 -
1#
#882500
0#
