Testbenches/AMDemod/AMDemod.v

/* Performs AM Demodulation. sqrt( I^2 + Q^2) 
Square root code is taken from https://verilogcodes.blogspot.com/2017/11/a-verilog-function-for-finding-square-root.html

TODO: use only one multiplier with TDM
TODO: minimize rounding errors of sqrt, get fractional result by scaling input
*/
module AMDemodulator
  (
    clk,
    I_in ,
    Q_in ,
    d_out); 
  //	   PUR PUR_INST(.PUR (1'b1));


  input clk;  
  input signed [11:0] I_in;
  input signed [11:0] Q_in;
  reg signed [15:0] d_out_d;
  output reg [11:0] d_out;
  reg [1:0] state;
  reg NewSample;
  reg [31:0] ISquare;
  reg [15:0] QSquare;
  reg [15:0] SquareSum;

  reg signed [11:0] MultDataA;
  reg signed [11:0] MultDataB;
  reg signed [23:0] MultResult1;


  reg signed [11:0] MultDataC;
  reg signed [11:0] MultDataD;
  reg signed [23:0] MultResult2;

  function [15:0] sqrt;
    input [31:0] num;  //declare input
    //intermediate signals.
    reg [31:0] a;
    reg [15:0] q;
    reg [17:0] left,right,r;    
    integer i;
    begin
      //initialize all the variables.
      a = num;
      q = 0;
      i = 0;
      left = 0;   //input to adder/sub
      right = 0;  //input to adder/sub
      r = 0;  //remainder
      //run the calculations for 16 iterations.
      for(i=0;i<16;i=i+1) begin 
        right = {q,r[17],1'b1};
        left = {r[15:0],a[31:30]};
        a = {a[29:0],2'b00};    //left shift by 2 bits.
        if (r[17] == 1) //add if r is negative
          r = left + right;
        else    //subtract if r is positive
          r = left - right;
        q = {q[14:0],!r[17]};       
      end
      sqrt = q;   //final assignment of output.
    end
  endfunction //end of Function


  always@(posedge clk) begin

    MultDataA <= I_in;
    MultDataB <= I_in;
    MultDataC <= Q_in;
    MultDataD <= Q_in;

    MultResult1 <= MultDataA*MultDataB;
    MultResult2 <= MultDataC*MultDataD;

    ISquare <= MultResult1 + MultResult2;
    d_out_d <= sqrt(ISquare);
    d_out <= d_out_d[11:0];
  end


initial begin
	$dumpfile("AMDemod_waves.vcd");
	$dumpvars;
end

endmodule

Testbenches/AMDemod/AMDemod_waves.vcd
$date
	Wed May  8 13:55:14 2024
$end
$version
	Icarus Verilog
$end
$timescale
	1ps
$end
$scope module AMDemodulator $end
$var wire 12 ! I_in [11:0] $end
$var wire 12 " Q_in [11:0] $end
$var wire 1 # clk $end
$var reg 32 $ ISquare [31:0] $end
$var reg 12 % MultDataA [11:0] $end
$var reg 12 & MultDataB [11:0] $end
$var reg 12 ' MultDataC [11:0] $end
$var reg 12 ( MultDataD [11:0] $end
$var reg 24 ) MultResult1 [23:0] $end
$var reg 24 * MultResult2 [23:0] $end
$var reg 12 + d_out [11:0] $end
$var reg 16 , d_out_d [15:0] $end
$scope function sqrt $end
$var reg 32 - a [31:0] $end
$var reg 18 . left [17:0] $end
$var reg 32 / num [31:0] $end
$var reg 16 0 q [15:0] $end
$var reg 18 1 r [17:0] $end
$var reg 18 2 right [17:0] $end
$var integer 32 3 i [31:0] $end
$upscope $end
$upscope $end
$enddefinitions $end
$comment Show the parameter values. $end
$dumpall
$end
#0
$dumpvars
b10000 3
b0xxxxxxxxxxxxxxxx1 2
bx 1
bx 0
bx /
bx .
b0 -
bx ,
bx +
bx *
bx )
b0 (
b0 '
b0 &
b0 %
bx $
1#
b0 "
b0 !
$end
#6250
0#
#12500
b0 *
b0 )
bx 1
b0xxxxxxxxxxxxxxxx1 2
bx .
b10000 3
bx 0
b0 -
1#
#18750
0#
#25000
b0 $
bx 1
b0xxxxxxxxxxxxxxxx1 2
bx .
b10000 3
bx 0
b0 -
1#
#31250
0#
#37500
b0 ,
b111111111111111111 1
b11 2
b111111111111111100 .
b10000 3
b0 0
b0 /
1#
#43750
0#
#50000
b0 +
b111111111111111111 1
b11 2
b111111111111111100 .
b10000 3
1#
#56250
0#
#62500
b111111111111111111 1
b11 2
b111111111111111100 .
b10000 3
1#
#68750
0#
#75000
b11111111111 "
b11111111111 !
b111111111111111111 1
b11 2
b111111111111111100 .
b10000 3
1#
#81250
0#
#87500
b11111111111 (
b11111111111 '
b11111111111 &
b11111111111 %
b111111111111111111 1
b11 2
b111111111111111100 .
b10000 3
1#
#93750
0#
#100000
b1111111111000000000001 *
b1111111111000000000001 )
b111111111111111111 1
b11 2
b111111111111111100 .
b10000 3
1#
#106250
0#
#112500
b11111111110000000000010 $
b111111111111111111 1
b11 2
b111111111111111100 .
b10000 3
1#
#118750
0#
#125000
b101101001110 ,
b101101001110 0
b111111110110100001 1
b1011010011101 2
b1010000111110 .
b10000 3
b0 -
b11111111110000000000010 /
1#
#131250
0#
#137500
b101101001110 +
b111111110110100001 1
b1011010011101 2
b1010000111110 .
b10000 3
b101101001110 0
b0 -
1#
#143750
0#
#150000
b100000000000 "
b100000000000 !
b111111110110100001 1
b1011010011101 2
b1010000111110 .
b10000 3
b101101001110 0
b0 -
1#
#156250
0#
#162500
b100000000000 (
b100000000000 '
b100000000000 &
b100000000000 %
b111111110110100001 1
b1011010011101 2
b1010000111110 .
b10000 3
b101101001110 0
b0 -
1#
#168750
0#
#175000
b10000000000000000000000 *
b10000000000000000000000 )
b111111110110100001 1
b1011010011101 2
b1010000111110 .
b10000 3
b101101001110 0
b0 -
1#
#181250
0#
#187500
b100000000000000000000000 $
b111111110110100001 1
b1011010011101 2
b1010000111110 .
b10000 3
b101101001110 0
b0 -
1#
#193750
0#
#200000
b101101010000 ,
b111111000001011111 1
b1011010100011 2
b111101100110111100 .
b10000 3
b101101010000 0
b0 -
b100000000000000000000000 /
1#
#206250
0#
#212500
b101101010000 +
b111111000001011111 1
b1011010100011 2
b111101100110111100 .
b10000 3
b101101010000 0
b0 -
1#
#218750
0#
#225000
b10101 !
b111111000001011111 1
b1011010100011 2
b111101100110111100 .
b10000 3
b101101010000 0
b0 -
1#
#231250
0#
#237500
b10101 &
b10101 %
b111111000001011111 1
b1011010100011 2
b111101100110111100 .
b10000 3
b101101010000 0
b0 -
1#
#243750
0#
#250000
b110111001 )
b111111000001011111 1
b1011010100011 2
b111101100110111100 .
b10000 3
b101101010000 0
b0 -
1#
#256250
0#
#262500
b10000000000000110111001 $
b111111000001011111 1
b1011010100011 2
b111101100110111100 .
b10000 3
b101101010000 0
b0 -
1#
#268750
0#
#275000
b100000000000 ,
b111111000110111000 1
b1000000000011 2
b111110000110110101 .
b10000 3
b100000000000 0
b0 -
b10000000000000110111001 /
1#
#281250
0#
#287500
b100000000000 +
b111111000110111000 1
b1000000000011 2
b111110000110110101 .
b10000 3
b100000000000 0
b0 -
1#
#293750
0#
#300000
b11111111111 "
b100000000000 !
b111111000110111000 1
b1000000000011 2
b111110000110110101 .
b10000 3
b100000000000 0
b0 -
1#
#306250
0#
#312500
b11111111111 (
b11111111111 '
b100000000000 &
b100000000000 %
b111111000110111000 1
b1000000000011 2
b111110000110110101 .
b10000 3
b100000000000 0
b0 -
1#
#318750
0#
#325000
b1111111111000000000001 *
b10000000000000000000000 )
b111111000110111000 1
b1000000000011 2
b111110000110110101 .
b10000 3
b100000000000 0
b0 -
1#
#331250
0#
#337500
b11111111111000000000001 $
b111111000110111000 1
b1000000000011 2
b111110000110110101 .
b10000 3
b100000000000 0
b0 -
1#
#343750
0#
#350000
b101101001111 ,
b110110100000 1
b1011010011101 2
b10010000111101 .
b10000 3
b101101001111 0
b0 -
b11111111111000000000001 /
1#
#356250
0#
#362500
b101101001111 +
b110110100000 1
b1011010011101 2
b10010000111101 .
b10000 3
b101101001111 0
b0 -
1#
#368750
0#
#375000
b10001111110 "
b10101010111 !
b110110100000 1
b1011010011101 2
b10010000111101 .
b10000 3
b101101001111 0
b0 -
1#
#381250
0#
#387500
b10001111110 (
b10001111110 '
b10101010111 &
b10101010111 %
b110110100000 1
b1011010011101 2
b10010000111101 .
b10000 3
b101101001111 0
b0 -
1#
#393750
0#
#400000
b101000010111000000100 *
b111001000001110010001 )
b110110100000 1
b1011010011101 2
b10010000111101 .
b10000 3
b101101001111 0
b0 -
1#
#406250
0#
#412500
b1100001011000110010101 $
b110110100000 1
b1011010011101 2
b10010000111101 .
b10000 3
b101101001111 0
b0 -
1#
#418750
0#
#425000
b11011111010 ,
b111111011101111100 1
b110111110101 2
b10101110001 .
b10000 3
b11011111010 0
b0 -
b1100001011000110010101 /
1#
#431250
0#
#437500
b11011111010 +
b111111011101111100 1
b110111110101 2
b10101110001 .
b10000 3
b11011111010 0
b0 -
1#
#443750
0#
#450000
b10111111110 "
b100010111000 !
b111111011101111100 1
b110111110101 2
b10101110001 .
b10000 3
b11011111010 0
b0 -
1#
#456250
0#
#462500
b10111111110 (
b10111111110 '
b100010111000 &
b100010111000 %
b111111011101111100 1
b110111110101 2
b10101110001 .
b10000 3
b11011111010 0
b0 -
1#
#468750
0#
#475000
b1000111110100000000100 *
b1101010000010001000000 )
b111111011101111100 1
b110111110101 2
b10101110001 .
b10000 3
b11011111010 0
b0 -
1#
#481250
0#
#487500
b10110001110110001000100 $
b111111011101111100 1
b110111110101 2
b10101110001 .
b10000 3
b11011111010 0
b0 -
1#
#493750
0#
#500000
b100101101110 ,
b111110111000100011 1
b1001011011101 2
b100000000 .
b10000 3
b100101101110 0
b0 -
b10110001110110001000100 /
1#
#506250
0#
#512500
b100101101110 +
b111110111000100011 1
b1001011011101 2
b100000000 .
b10000 3
b100101101110 0
b0 -
1#
#518750
0#
#525000
b1010100001 "
b110110111 !
b111110111000100011 1
b1001011011101 2
b100000000 .
b10000 3
b100101101110 0
b0 -
1#
#531250
0#
#537500
b1010100001 (
b1010100001 '
b110110111 &
b110110111 %
b111110111000100011 1
b1001011011101 2
b100000000 .
b10000 3
b100101101110 0
b0 -
1#
#543750
0#
#550000
b1101110100101000001 *
b101111000011010001 )
b111110111000100011 1
b1001011011101 2
b100000000 .
b10000 3
b100101101110 0
b0 -
1#
#556250
0#
#562500
b10011101101000010010 $
b111110111000100011 1
b1001011011101 2
b100000000 .
b10000 3
b100101101110 0
b0 -
1#
#568750
0#
#575000
b1100100011 ,
b1101001001 1
b11001000101 2
b100110001110 .
b10000 3
b1100100011 0
b0 -
b10011101101000010010 /
1#
#581250
0#
#587500
b1100100011 +
b1101001001 1
b11001000101 2
b100110001110 .
b10000 3
b1100100011 0
b0 -
1#
#593750
0#
#600000
b100100101110 "
b11110111111 !
b1101001001 1
b11001000101 2
b100110001110 .
b10000 3
b1100100011 0
b0 -
1#
#606250
0#
#612500
b100100101110 (
b100100101110 '
b11110111111 &
b11110111111 %
b1101001001 1
b11001000101 2
b100110001110 .
b10000 3
b1100100011 0
b0 -
1#
#618750
0#
#625000
b1011101000010001000100 *
b1111000000000010000001 )
b1101001001 1
b11001000101 2
b100110001110 .
b10000 3
b1100100011 0
b0 -
1#
#631250
0#
#637500
b11010101000010011000101 $
b1101001001 1
b11001000101 2
b100110001110 .
b10000 3
b1100100011 0
b0 -
1#
#643750
0#
#650000
b101001010010 ,
b111110110111011100 1
b1010010100101 2
b1010000001 .
b10000 3
b101001010010 0
b0 -
b11010101000010011000101 /
1#
#656250
0#
#662500
b101001010010 +
b111110110111011100 1
b1010010100101 2
b1010000001 .
b10000 3
b101001010010 0
b0 -
1#
#668750
0#
#675000
b1111111011 "
b10111010110 !
b111110110111011100 1
b1010010100101 2
b1010000001 .
b10000 3
b101001010010 0
b0 -
1#
#681250
0#
#687500
b1111111011 (
b1111111011 '
b10111010110 &
b10111010110 %
b111110110111011100 1
b1010010100101 2
b1010000001 .
b10000 3
b101001010010 0
b0 -
1#
#693750
0#
#700000
b11111101100000011001 *
b1000100000111011100100 )
b111110110111011100 1
b1010010100101 2
b1010000001 .
b10000 3
b101001010010 0
b0 -
1#
#706250
0#
#712500
b1100011110011011111101 $
b111110110111011100 1
b1010010100101 2
b1010000001 .
b10000 3
b101001010010 0
b0 -
1#
#718750
0#
#725000
b11100010000 ,
b111111011111011100 1
b111000100011 2
b111110100110111001 .
b10000 3
b11100010000 0
b0 -
b1100011110011011111101 /
1#
#731250
0#
#737500
b11100010000 +
b111111011111011100 1
b111000100011 2
b111110100110111001 .
b10000 3
b11100010000 0
b0 -
1#
#743750
0#
#750000
b110110110100 "
b111001110011 !
b111111011111011100 1
b111000100011 2
b111110100110111001 .
b10000 3
b11100010000 0
b0 -
1#
#756250
0#
#762500
b110110110100 (
b110110110100 '
b111001110011 &
b111001110011 %
b111111011111011100 1
b111000100011 2
b111110100110111001 .
b10000 3
b11100010000 0
b0 -
1#
#768750
0#
#775000
b1010100011010010000 *
b100110011110101001 )
b111111011111011100 1
b111000100011 2
b111110100110111001 .
b10000 3
b11100010000 0
b0 -
1#
#781250
0#
#787500
b1111010111000111001 $
b111111011111011100 1
b111000100011 2
b111110100110111001 .
b10000 3
b11100010000 0
b0 -
1#
#793750
0#
#800000
b1011000101 ,
b1010100000 1
b10110001011 2
b111111110100010101 .
b10000 3
b1011000101 0
b0 -
b1111010111000111001 /
1#
#806250
0#
#812500
b1011000101 +
b1010100000 1
b10110001011 2
b111111110100010101 .
b10000 3
b1011000101 0
b0 -
1#
#818750
0#
#825000
b101001101010 "
b101100011 !
b1010100000 1
b10110001011 2
b111111110100010101 .
b10000 3
b1011000101 0
b0 -
1#
#831250
0#
#837500
b101001101010 (
b101001101010 '
b101100011 &
b101100011 %
b1010100000 1
b10110001011 2
b111111110100010101 .
b10000 3
b1011000101 0
b0 -
1#
#843750
0#
#850000
b111110011001111100100 *
b11110110001001001 )
b1010100000 1
b10110001011 2
b111111110100010101 .
b10000 3
b1011000101 0
b0 -
1#
#856250
0#
#862500
b1000010010000000101101 $
b1010100000 1
b10110001011 2
b111111110100010101 .
b10000 3
b1011000101 0
b0 -
1#
#868750
0#
#875000
b10111000001 ,
b10010101100 1
b101110000011 2
b111111100100101001 .
b10000 3
b10111000001 0
b0 -
b1000010010000000101101 /
1#
#881250
0#
#887500
b10111000001 +
b10010101100 1
b101110000011 2
b111111100100101001 .
b10000 3
b10111000001 0
b0 -
1#
#893750
0#
#900000
b100011100011 "
b100100111100 !
b10010101100 1
b101110000011 2
b111111100100101001 .
b10000 3
b10111000001 0
b0 -
1#
#906250
0#
#912500
b100011100011 (
b100011100011 '
b100100111100 &
b100100111100 %
b10010101100 1
b101110000011 2
b111111100100101001 .
b10000 3
b10111000001 0
b0 -
1#
#918750
0#
#925000
b1100101001100101001001 *
b1011011100011000010000 )
b10010101100 1
b101110000011 2
b111111100100101001 .
b10000 3
b10111000001 0
b0 -
1#
#931250
0#
#937500
b11000000101111101011001 $
b10010101100 1
b101110000011 2
b111111100100101001 .
b10000 3
b10111000001 0
b0 -
1#
#943750
0#
#950000
b100111010001 ,
b1010111000 1
b1001110100011 2
b111110111100010101 .
b10000 3
b100111010001 0
b0 -
b11000000101111101011001 /
1#
#956250
0#
#962500
b100111010001 +
b1010111000 1
b1001110100011 2
b111110111100010101 .
b10000 3
b100111010001 0
b0 -
1#
#968750
0#
#975000
b110111101100 "
b100010011101 !
b1010111000 1
b1001110100011 2
b111110111100010101 .
b10000 3
b100111010001 0
b0 -
1#
#981250
0#
#987500
b110111101100 (
b110111101100 '
b100010011101 &
b100010011101 %
b1010111000 1
b1001110100011 2
b111110111100010101 .
b10000 3
b100111010001 0
b0 -
1#
#993750
0#
#1000000
b1000101000110010000 *
b1101101001000001001001 )
b1010111000 1
b1001110100011 2
b111110111100010101 .
b10000 3
b100111010001 0
b0 -
1#
#1006250
0#
#1012500
b1110101110000111011001 $
b1010111000 1
b1001110100011 2
b111110111100010101 .
b10000 3
b100111010001 0
b0 -
1#
#1018750
0#
#1025000
b11110101100 ,
b111111011011110000 1
b111101011011 2
b111110011110010101 .
b10000 3
b11110101100 0
b0 -
b1110101110000111011001 /
1#
#1031250
0#
#1037500
b11110101100 +
b111111011011110000 1
b111101011011 2
b111110011110010101 .
b10000 3
b11110101100 0
b0 -
1#
#1043750
0#
#1050000
b100001111001 "
b110000100101 !
b111111011011110000 1
b111101011011 2
b111110011110010101 .
b10000 3
b11110101100 0
b0 -
1#
#1056250
0#
#1062500
b100001111001 (
b100001111001 '
b110000100101 &
b110000100101 %
b111111011011110000 1
b111101011011 2
b111110011110010101 .
b10000 3
b11110101100 0
b0 -
1#
#1068750
0#
#1075000
b1110001010100100110001 *
b11101101110101011001 )
b111111011011110000 1
b111101011011 2
b111110011110010101 .
b10000 3
b11110101100 0
b0 -
1#
#1081250
0#
#1087500
b10001111000011010001010 $
b111111011011110000 1
b111101011011 2
b111110011110010101 .
b10000 3
b11110101100 0
b0 -
1#
#1093750
0#
#1100000
b100001110101 ,
b100010001 1
b1000011101011 2
b111111000000100110 .
b10000 3
b100001110101 0
b0 -
b10001111000011010001010 /
1#
#1106250
0#
#1112500
b100001110101 +
b100010001 1
b1000011101011 2
b111111000000100110 .
b10000 3
b100001110101 0
b0 -
1#
#1118750
0#
#1125000
b11000101010 "
b11001010010 !
b100010001 1
b1000011101011 2
b111111000000100110 .
b10000 3
b100001110101 0
b0 -
1#
#1131250
0#
#1137500
b11000101010 (
b11000101010 '
b11001010010 &
b11001010010 %
b100010001 1
b1000011101011 2
b111111000000100110 .
b10000 3
b100001110101 0
b0 -
1#
#1143750
0#
#1150000
b1001011111111011100100 *
b1001111111001001000100 )
b100010001 1
b1000011101011 2
b111111000000100110 .
b10000 3
b100001110101 0
b0 -
1#
#1156250
0#
#1162500
b10011011111000100101000 $
b100010001 1
b1000011101011 2
b111111000000100110 .
b10000 3
b100001110101 0
b0 -
1#
#1168750
0#
#1175000
b100011010100 ,
b111110111111101111 1
b1000110101011 2
b111101111001000100 .
b10000 3
b100011010100 0
b0 -
b10011011111000100101000 /
1#
#1181250
0#
#1187500
b100011010100 +
b111110111111101111 1
b1000110101011 2
b111101111001000100 .
b10000 3
b100011010100 0
b0 -
1#
#1193750
0#
#1200000
b1011001 "
b110111001011 !
b111110111111101111 1
b1000110101011 2
b111101111001000100 .
b10000 3
b100011010100 0
b0 -
1#
#1206250
0#
#1212500
b1011001 (
b1011001 '
b110111001011 &
b110111001011 %
b111110111111101111 1
b1000110101011 2
b111101111001000100 .
b10000 3
b100011010100 0
b0 -
1#
#1218750
0#
#1225000
b1111011110001 *
b1001101111011111001 )
b111110111111101111 1
b1000110101011 2
b111101111001000100 .
b10000 3
b100011010100 0
b0 -
1#
#1231250
0#
#1237500
b1001111110111101010 $
b111110111111101111 1
b1000110101011 2
b111101111001000100 .
b10000 3
b100011010100 0
b0 -
1#
#1243750
0#
#1250000
b1000111011 ,
b10001010001 1
b10001110101 2
b100011000110 .
b10000 3
b1000111011 0
b0 -
b1001111110111101010 /
1#
#1256250
0#
#1262500
b1000111011 +
b10001010001 1
b10001110101 2
b100011000110 .
b10000 3
b1000111011 0
b0 -
1#
#1268750
0#
#1275000
b1110101000 "
b101101001101 !
b10001010001 1
b10001110101 2
b100011000110 .
b10000 3
b1000111011 0
b0 -
1#
#1281250
0#
#1287500
b1110101000 (
b1110101000 '
b101101001101 &
b101101001101 %
b10001010001 1
b10001110101 2
b100011000110 .
b10000 3
b1000111011 0
b0 -
1#
#1293750
0#
#1300000
b11010101111001000000 *
b101100001010100101001 )
b10001010001 1
b10001110101 2
b100011000110 .
b10000 3
b1000111011 0
b0 -
1#
#1306250
0#
#1312500
b1000110111001101101001 $
b10001010001 1
b10001110101 2
b100011000110 .
b10000 3
b1000111011 0
b0 -
1#
#1318750
0#
#1325000
b10111110100 ,
b111111011011110000 1
b101111101011 2
b111110101100000101 .
b10000 3
b10111110100 0
b0 -
b1000110111001101101001 /
1#
#1331250
0#
#1337500
b10111110100 +
b111111011011110000 1
b101111101011 2
b111110101100000101 .
b10000 3
b10111110100 0
b0 -
1#
#1343750
0#
#1350000
b1111011010 "
b11111001000 !
b111111011011110000 1
b101111101011 2
b111110101100000101 .
b10000 3
b10111110100 0
b0 -
1#
#1356250
0#
#1362500
b1111011010 (
b1111011010 '
b11111001000 &
b11111001000 %
b111111011011110000 1
b101111101011 2
b111110101100000101 .
b10000 3
b10111110100 0
b0 -
1#
#1368750
0#
#1375000
b11101101010110100100 *
b1111001000110001000000 )
b111111011011110000 1
b101111101011 2
b111110101100000101 .
b10000 3
b10111110100 0
b0 -
1#
#1381250
0#
#1387500
b10010110110000111100100 $
b111111011011110000 1
b101111101011 2
b111110101100000101 .
b10000 3
b10111110100 0
b0 -
1#
#1393750
0#
#1400000
b100010101110 ,
b111111101001000011 1
b1000101011101 2
b101110100000 .
b10000 3
b100010101110 0
b0 -
b10010110110000111100100 /
1#
#1406250
0#
#1412500
b100010101110 +
b111111101001000011 1
b1000101011101 2
b101110100000 .
b10000 3
b100010101110 0
b0 -
1#
#1418750
0#
#1425000
b100000110000 "
b100000000110 !
b111111101001000011 1
b1000101011101 2
b101110100000 .
b10000 3
b100010101110 0
b0 -
1#
#1431250
0#
#1437500
b100000110000 (
b100000110000 '
b100000000110 &
b100000000110 %
b111111101001000011 1
b1000101011101 2
b101110100000 .
b10000 3
b100010101110 0
b0 -
1#
#1443750
0#
#1450000
b1111010000100100000000 *
b1111111010000000100100 )
b111111101001000011 1
b1000101011101 2
b101110100000 .
b10000 3
b100010101110 0
b0 -
1#
#1456250
0#
#1462500
b11111001010100100100100 $
b111111101001000011 1
b1000101011101 2
b101110100000 .
b10000 3
b100010101110 0
b0 -
1#
#1468750
0#
#1475000
b101100101010 ,
b111110111111101011 1
b1011001010101 2
b11001000000 .
b10000 3
b101100101010 0
b0 -
b11111001010100100100100 /
1#
#1481250
0#
#1487500
b101100101010 +
b111110111111101011 1
b1011001010101 2
b11001000000 .
b10000 3
b101100101010 0
b0 -
1#
#1493750
0#
#1500000
b10111001100 "
b11010110 !
b111110111111101011 1
b1011001010101 2
b11001000000 .
b10000 3
b101100101010 0
b0 -
1#
#1506250
0#
#1512500
b10111001100 (
b10111001100 '
b11010110 &
b11010110 %
b111110111111101011 1
b1011001010101 2
b11001000000 .
b10000 3
b101100101010 0
b0 -
1#
#1518750
0#
#1525000
b1000011001101010010000 *
b1011001011100100 )
b111110111111101011 1
b1011001010101 2
b11001000000 .
b10000 3
b101100101010 0
b0 -
1#
#1531250
0#
#1537500
b1000100100110101110100 $
b111110111111101011 1
b1011001010101 2
b11001000000 .
b10000 3
b101100101010 0
b0 -
1#
#1543750
0#
#1550000
b10111011011 ,
b10000011011 1
b101110110101 2
b111111010000 .
b10000 3
b10111011011 0
b0 -
b1000100100110101110100 /
1#
#1556250
0#
#1562500
b10111011011 +
b10000011011 1
b101110110101 2
b111111010000 .
b10000 3
b10111011011 0
b0 -
1#
#1568750
0#
#1575000
b111010011000 "
b100001101001 !
b10000011011 1
b101110110101 2
b111111010000 .
b10000 3
b10111011011 0
b0 -
1#
#1581250
0#
#1587500
b111010011000 (
b111010011000 '
b100001101001 &
b100001101001 %
b10000011011 1
b101110110101 2
b111111010000 .
b10000 3
b10111011011 0
b0 -
1#
#1593750
0#
#1600000
b11111101001000000 *
b1110011001101100010001 )
b10000011011 1
b101110110101 2
b111111010000 .
b10000 3
b10111011011 0
b0 -
1#
#1606250
0#
#1612500
b1110111001010101010001 $
b10000011011 1
b101110110101 2
b111111010000 .
b10000 3
b10111011011 0
b0 -
1#
#1618750
0#
#1625000
b11110111000 ,
b111111000110100000 1
b111101110011 2
b111110001000101101 .
b10000 3
b11110111000 0
b0 -
b1110111001010101010001 /
1#
#1631250
0#
#1637500
b11110111000 +
b111111000110100000 1
b111101110011 2
b111110001000101101 .
b10000 3
b11110111000 0
b0 -
1#
#1643750
0#
#1650000
b100010100110 "
b10111101000 !
b111111000110100000 1
b111101110011 2
b111110001000101101 .
b10000 3
b11110111000 0
b0 -
1#
#1656250
0#
#1662500
b100010100110 (
b100010100110 '
b10111101000 &
b10111101000 %
b111111000110100000 1
b111101110011 2
b111110001000101101 .
b10000 3
b11110111000 0
b0 -
1#
#1668750
0#
#1675000
b1101100000101110100100 *
b1000101110001001000000 )
b111111000110100000 1
b111101110011 2
b111110001000101101 .
b10000 3
b11110111000 0
b0 -
1#
#1681250
0#
#1687500
b10110001110110111100100 $
b111111000110100000 1
b111101110011 2
b111110001000101101 .
b10000 3
b11110111000 0
b0 -
1#
#1693750
0#
#1700000
b100101101110 ,
b111110111111000011 1
b1001011011101 2
b1010100000 .
b10000 3
b100101101110 0
b0 -
b10110001110110111100100 /
1#
#1706250
0#
#1712500
b100101101110 +
b111110111111000011 1
b1001011011101 2
b1010100000 .
b10000 3
b100101101110 0
b0 -
1#
#1718750
0#
#1725000
b11100010100 "
b10010000001 !
b111110111111000011 1
b1001011011101 2
b1010100000 .
b10000 3
b100101101110 0
b0 -
1#
#1731250
0#
#1737500
b11100010100 (
b11100010100 '
b10010000001 &
b10010000001 %
b111110111111000011 1
b1001011011101 2
b1010100000 .
b10000 3
b100101101110 0
b0 -
1#
#1743750
0#
#1750000
b1100100001100110010000 *
b101000100100100000001 )
b111110111111000011 1
b1001011011101 2
b1010100000 .
b10000 3
b100101101110 0
b0 -
1#
#1756250
0#
#1762500
b10001100110001010010001 $
b111110111111000011 1
b1001011011101 2
b1010100000 .
b10000 3
b100101101110 0
b0 -
1#
#1768750
0#
#1775000
b100001100011 ,
b110001001000 1
b1000011000101 2
b1110100001101 .
b10000 3
b100001100011 0
b0 -
b10001100110001010010001 /
1#
#1781250
0#
#1787500
b100001100011 +
b110001001000 1
b1000011000101 2
b1110100001101 .
b10000 3
b100001100011 0
b0 -
1#
#1793750
0#
#1800000
b1011110001 "
b100001110000 !
b110001001000 1
b1000011000101 2
b1110100001101 .
b10000 3
b100001100011 0
b0 -
1#
#1806250
0#
#1812500
b1011110001 (
b1011110001 '
b100001110000 &
b100001110000 %
b110001001000 1
b1000011000101 2
b1110100001101 .
b10000 3
b100001100011 0
b0 -
1#
#1818750
0#
#1825000
b10001010011011100001 *
b1110010011000100000000 )
b110001001000 1
b1000011000101 2
b1110100001101 .
b10000 3
b100001100011 0
b0 -
1#
#1831250
0#
#1837500
b10000011101011111100001 $
b110001001000 1
b1000011000101 2
b1110100001101 .
b10000 3
b100001100011 0
b0 -
1#
#1843750
0#
#1850000
b100000011101 ,
b10010011000 1
b1000000111011 2
b111111010001011101 .
b10000 3
b100000011101 0
b0 -
b10000011101011111100001 /
1#
#1856250
0#
#1862500
b100000011101 +
b10010011000 1
b1000000111011 2
b111111010001011101 .
b10000 3
b100000011101 0
b0 -
1#
#1868750
0#
#1875000
b111100011111 "
b101111110011 !
b10010011000 1
b1000000111011 2
b111111010001011101 .
b10000 3
b100000011101 0
b0 -
1#
#1881250
0#
#1887500
b111100011111 (
b111100011111 '
b101111110011 &
b101111110011 %
b10010011000 1
b1000000111011 2
b111111010001011101 .
b10000 3
b100000011101 0
b0 -
1#
#1893750
0#
#1900000
b1100010111000001 *
b100000110100010101001 )
b10010011000 1
b1000000111011 2
b111111010001011101 .
b10000 3
b100000011101 0
b0 -
1#
#1906250
0#
#1912500
b100010010111001101010 $
b10010011000 1
b1000000111011 2
b111111010001011101 .
b10000 3
b100000011101 0
b0 -
1#
#1918750
0#
#1925000
b10000100101 ,
b100010001 1
b100001001011 2
b111111100011000110 .
b10000 3
b10000100101 0
b0 -
b100010010111001101010 /
1#
#1931250
0#
#1937500
b10000100101 +
b100010001 1
b100001001011 2
b111111100011000110 .
b10000 3
b10000100101 0
b0 -
1#
#1943750
0#
#1950000
b100011100001 "
b10100010101 !
b100010001 1
b100001001011 2
b111111100011000110 .
b10000 3
b10000100101 0
b0 -
1#
#1956250
0#
#1962500
b100011100001 (
b100011100001 '
b10100010101 &
b10100010101 %
b100010001 1
b100001001011 2
b111111100011000110 .
b10000 3
b10000100101 0
b0 -
1#
#1968750
0#
#1975000
b1100101011010111000001 *
b110011101001110111001 )
b100010001 1
b100001001011 2
b111111100011000110 .
b10000 3
b10000100101 0
b0 -
1#
#1981250
0#
#1987500
b10011001000100101111010 $
b100010001 1
b100001001011 2
b111111100011000110 .
b10000 3
b10000100101 0
b0 -
1#
#1993750
0#
#2000000
b100010111111 ,
b101011111001 1
b1000101111101 2
b1110001110110 .
b10000 3
b100010111111 0
b0 -
b10011001000100101111010 /
1#
#2006250
0#
#2012500
b100010111111 +
b101011111001 1
b1000101111101 2
b1110001110110 .
b10000 3
b100010111111 0
b0 -
1#
#2018750
0#
#2025000
b1000000001 "
b11010101111 !
b101011111001 1
b1000101111101 2
b1110001110110 .
b10000 3
b100010111111 0
b0 -
1#
#2031250
0#
#2037500
b1000000001 (
b1000000001 '
b11010101111 &
b11010101111 %
b101011111001 1
b1000101111101 2
b1110001110110 .
b10000 3
b100010111111 0
b0 -
1#
#2043750
0#
#2050000
b1000000010000000001 *
b1011001010101110100001 )
b101011111001 1
b1000101111101 2
b1110001110110 .
b10000 3
b100010111111 0
b0 -
1#
#2056250
0#
#2062500
b1100001010111110100010 $
b101011111001 1
b1000101111101 2
b1110001110110 .
b10000 3
b100010111111 0
b0 -
1#
#2068750
0#
#2075000
b11011111010 ,
b111111010110001001 1
b110111110101 2
b1101111110 .
b10000 3
b11011111010 0
b0 -
b1100001010111110100010 /
1#
#2081250
0#
#2087500
b11011111010 +
b111111010110001001 1
b110111110101 2
b1101111110 .
b10000 3
b11011111010 0
b0 -
1#
#2093750
0#
#2100000
b100011100 "
b111011000011 !
b111111010110001001 1
b110111110101 2
b1101111110 .
b10000 3
b11011111010 0
b0 -
1#
#2106250
0#
#2112500
b100011100 (
b100011100 '
b111011000011 &
b111011000011 %
b111111010110001001 1
b110111110101 2
b1101111110 .
b10000 3
b11011111010 0
b0 -
1#
#2118750
0#
#2125000
b10011101100010000 *
b11000100010001001 )
b111111010110001001 1
b110111110101 2
b1101111110 .
b10000 3
b11011111010 0
b0 -
1#
#2131250
0#
