Testbenches/AMDemod/AMDemod.v

/* Performs AM Demodulation. sqrt( I^2 + Q^2) 
Square root code is taken from https://verilogcodes.blogspot.com/2017/11/a-verilog-function-for-finding-square-root.html

TODO: use only one multiplier with TDM
TODO: minimize rounding errors of sqrt, get fractional result by scaling input
*/
module AMDemodulator
  (
    clk,
    I_in ,
    Q_in ,
    d_out); 
  //	   PUR PUR_INST(.PUR (1'b1));


  input clk;  
  input signed [11:0] I_in;
  input signed [11:0] Q_in;
  reg signed [15:0] d_out_d;
  output reg [11:0] d_out;
  reg [1:0] state;
  reg NewSample;
  reg [31:0] ISquare;
  reg [15:0] QSquare;
  reg [15:0] SquareSum;

  reg signed [11:0] MultDataA;
  reg signed [11:0] MultDataB;
  reg signed [23:0] MultResult1;


  reg signed [11:0] MultDataC;
  reg signed [11:0] MultDataD;
  reg signed [23:0] MultResult2;

  function [15:0] sqrt;
    input [31:0] num;  //declare input
    //intermediate signals.
    reg [31:0] a;
    reg [15:0] q;
    reg [17:0] left,right,r;    
    integer i;
    begin
      //initialize all the variables.
      a = num;
      q = 0;
      i = 0;
      left = 0;   //input to adder/sub
      right = 0;  //input to adder/sub
      r = 0;  //remainder
      //run the calculations for 16 iterations.
      for(i=0;i<16;i=i+1) begin 
        right = {q,r[17],1'b1};
        left = {r[15:0],a[31:30]};
        a = {a[29:0],2'b00};    //left shift by 2 bits.
        if (r[17] == 1) //add if r is negative
          r = left + right;
        else    //subtract if r is positive
          r = left - right;
        q = {q[14:0],!r[17]};       
      end
      sqrt = q;   //final assignment of output.
    end
  endfunction //end of Function


  always@(posedge clk) begin

    MultDataA <= I_in;
    MultDataB <= I_in;
    MultDataC <= Q_in;
    MultDataD <= Q_in;

    MultResult1 <= MultDataA*MultDataB;
    MultResult2 <= MultDataC*MultDataD;

    ISquare <= MultResult1 + MultResult2;
    d_out_d <= sqrt(ISquare);
    d_out <= d_out_d[11:0];
  end


initial begin
	$dumpfile("AMDemod_waves.vcd");
	$dumpvars;
end

endmodule

Testbenches/AMDemod/AMDemod_waves.vcd
$date
	Thu Apr 18 14:51:13 2024
$end
$version
	Icarus Verilog
$end
$timescale
	1ps
$end
$scope module AMDemodulator $end
$var wire 12 ! I_in [11:0] $end
$var wire 12 " Q_in [11:0] $end
$var wire 1 # clk $end
$var reg 32 $ ISquare [31:0] $end
$var reg 12 % MultDataA [11:0] $end
$var reg 12 & MultDataB [11:0] $end
$var reg 12 ' MultDataC [11:0] $end
$var reg 12 ( MultDataD [11:0] $end
$var reg 24 ) MultResult1 [23:0] $end
$var reg 24 * MultResult2 [23:0] $end
$var reg 12 + d_out [11:0] $end
$var reg 16 , d_out_d [15:0] $end
$scope function sqrt $end
$var reg 32 - a [31:0] $end
$var reg 18 . left [17:0] $end
$var reg 32 / num [31:0] $end
$var reg 16 0 q [15:0] $end
$var reg 18 1 r [17:0] $end
$var reg 18 2 right [17:0] $end
$var integer 32 3 i [31:0] $end
$upscope $end
$upscope $end
$enddefinitions $end
$comment Show the parameter values. $end
$dumpall
$end
#0
$dumpvars
b10000 3
b0xxxxxxxxxxxxxxxx1 2
bx 1
bx 0
bx /
bx .
b0 -
bx ,
bx +
bx *
bx )
b0 (
b0 '
b0 &
b0 %
bx $
1#
b0 "
b0 !
$end
#6250
0#
#12500
b0 *
b0 )
bx 1
b0xxxxxxxxxxxxxxxx1 2
bx .
b10000 3
bx 0
b0 -
1#
#18750
0#
#25000
b0 $
bx 1
b0xxxxxxxxxxxxxxxx1 2
bx .
b10000 3
bx 0
b0 -
1#
#31250
0#
#37500
b0 ,
b111111111111111111 1
b11 2
b111111111111111100 .
b10000 3
b0 0
b0 /
1#
#43750
0#
#50000
b0 +
b111111111111111111 1
b11 2
b111111111111111100 .
b10000 3
1#
#56250
0#
#62500
b111111111111111111 1
b11 2
b111111111111111100 .
b10000 3
1#
#68750
0#
#75000
b11111111111 "
b11111111111 !
b111111111111111111 1
b11 2
b111111111111111100 .
b10000 3
1#
#81250
0#
#87500
b11111111111 (
b11111111111 '
b11111111111 &
b11111111111 %
b111111111111111111 1
b11 2
b111111111111111100 .
b10000 3
1#
#93750
0#
#100000
b1111111111000000000001 *
b1111111111000000000001 )
b111111111111111111 1
b11 2
b111111111111111100 .
b10000 3
1#
#106250
0#
#112500
b11111111110000000000010 $
b111111111111111111 1
b11 2
b111111111111111100 .
b10000 3
1#
#118750
0#
#125000
b101101001110 ,
b101101001110 0
b111111110110100001 1
b1011010011101 2
b1010000111110 .
b10000 3
b0 -
b11111111110000000000010 /
1#
#131250
0#
#137500
b101101001110 +
b111111110110100001 1
b1011010011101 2
b1010000111110 .
b10000 3
b101101001110 0
b0 -
1#
#143750
0#
#150000
b100000000000 "
b100000000000 !
b111111110110100001 1
b1011010011101 2
b1010000111110 .
b10000 3
b101101001110 0
b0 -
1#
#156250
0#
#162500
b100000000000 (
b100000000000 '
b100000000000 &
b100000000000 %
b111111110110100001 1
b1011010011101 2
b1010000111110 .
b10000 3
b101101001110 0
b0 -
1#
#168750
0#
#175000
b10000000000000000000000 *
b10000000000000000000000 )
b111111110110100001 1
b1011010011101 2
b1010000111110 .
b10000 3
b101101001110 0
b0 -
1#
#181250
0#
#187500
b100000000000000000000000 $
b111111110110100001 1
b1011010011101 2
b1010000111110 .
b10000 3
b101101001110 0
b0 -
1#
#193750
0#
#200000
b101101010000 ,
b111111000001011111 1
b1011010100011 2
b111101100110111100 .
b10000 3
b101101010000 0
b0 -
b100000000000000000000000 /
1#
#206250
0#
#212500
b101101010000 +
b111111000001011111 1
b1011010100011 2
b111101100110111100 .
b10000 3
b101101010000 0
b0 -
1#
#218750
0#
#225000
b10101 !
b111111000001011111 1
b1011010100011 2
b111101100110111100 .
b10000 3
b101101010000 0
b0 -
1#
#231250
0#
#237500
b10101 &
b10101 %
b111111000001011111 1
b1011010100011 2
b111101100110111100 .
b10000 3
b101101010000 0
b0 -
1#
#243750
0#
#250000
b110111001 )
b111111000001011111 1
b1011010100011 2
b111101100110111100 .
b10000 3
b101101010000 0
b0 -
1#
#256250
0#
#262500
b10000000000000110111001 $
b111111000001011111 1
b1011010100011 2
b111101100110111100 .
b10000 3
b101101010000 0
b0 -
1#
#268750
0#
#275000
b100000000000 ,
b111111000110111000 1
b1000000000011 2
b111110000110110101 .
b10000 3
b100000000000 0
b0 -
b10000000000000110111001 /
1#
#281250
0#
#287500
b100000000000 +
b111111000110111000 1
b1000000000011 2
b111110000110110101 .
b10000 3
b100000000000 0
b0 -
1#
#293750
0#
#300000
b11111111111 "
b100000000000 !
b111111000110111000 1
b1000000000011 2
b111110000110110101 .
b10000 3
b100000000000 0
b0 -
1#
#306250
0#
#312500
b11111111111 (
b11111111111 '
b100000000000 &
b100000000000 %
b111111000110111000 1
b1000000000011 2
b111110000110110101 .
b10000 3
b100000000000 0
b0 -
1#
#318750
0#
#325000
b1111111111000000000001 *
b10000000000000000000000 )
b111111000110111000 1
b1000000000011 2
b111110000110110101 .
b10000 3
b100000000000 0
b0 -
1#
#331250
0#
#337500
b11111111111000000000001 $
b111111000110111000 1
b1000000000011 2
b111110000110110101 .
b10000 3
b100000000000 0
b0 -
1#
#343750
0#
#350000
b101101001111 ,
b110110100000 1
b1011010011101 2
b10010000111101 .
b10000 3
b101101001111 0
b0 -
b11111111111000000000001 /
1#
#356250
0#
#362500
b101101001111 +
b110110100000 1
b1011010011101 2
b10010000111101 .
b10000 3
b101101001111 0
b0 -
1#
#368750
0#
#375000
b100011000011 "
b110011111 !
b110110100000 1
b1011010011101 2
b10010000111101 .
b10000 3
b101101001111 0
b0 -
1#
#381250
0#
#387500
b100011000011 (
b100011000011 '
b110011111 &
b110011111 %
b110110100000 1
b1011010011101 2
b10010000111101 .
b10000 3
b101101001111 0
b0 -
1#
#393750
0#
#400000
b1101000110010010001001 *
b101010000011000001 )
b110110100000 1
b1011010011101 2
b10010000111101 .
b10000 3
b101101001111 0
b0 -
1#
#406250
0#
#412500
b1101110000010101001010 $
b110110100000 1
b1011010011101 2
b10010000111101 .
b10000 3
b101101001111 0
b0 -
1#
#418750
0#
#425000
b11101101010 ,
b111111111010010001 1
b111011010101 2
b110101100110 .
b10000 3
b11101101010 0
b0 -
b1101110000010101001010 /
1#
#431250
0#
#437500
b11101101010 +
b111111111010010001 1
b111011010101 2
b110101100110 .
b10000 3
b11101101010 0
b0 -
1#
#443750
0#
#450000
b10000001111 "
b11010110000 !
b111111111010010001 1
b111011010101 2
b110101100110 .
b10000 3
b11101101010 0
b0 -
1#
#456250
0#
#462500
b10000001111 (
b10000001111 '
b11010110000 &
b11010110000 %
b111111111010010001 1
b111011010101 2
b110101100110 .
b10000 3
b11101101010 0
b0 -
1#
#468750
0#
#475000
b100000111100011100001 *
b1011001011100100000000 )
b111111111010010001 1
b111011010101 2
b110101100110 .
b10000 3
b11101101010 0
b0 -
1#
#481250
0#
#487500
b1111010011000111100001 $
b111111111010010001 1
b111011010101 2
b110101100110 .
b10000 3
b11101101010 0
b0 -
1#
#493750
0#
#500000
b11111010010 ,
b111111100111111000 1
b111110100101 2
b100110011101 .
b10000 3
b11111010010 0
b0 -
b1111010011000111100001 /
1#
#506250
0#
#512500
b11111010010 +
b111111100111111000 1
b111110100101 2
b100110011101 .
b10000 3
b11111010010 0
b0 -
1#
#518750
0#
#525000
b11101011000 "
b111000001101 !
b111111100111111000 1
b111110100101 2
b100110011101 .
b10000 3
b11111010010 0
b0 -
1#
#531250
0#
#537500
b11101011000 (
b11101011000 '
b111000001101 &
b111000001101 %
b111111100111111000 1
b111110100101 2
b100110011101 .
b10000 3
b11111010010 0
b0 -
1#
#543750
0#
#550000
b1101011110111001000000 *
b111100110010101001 )
b111111100111111000 1
b111110100101 2
b100110011101 .
b10000 3
b11111010010 0
b0 -
1#
#556250
0#
#562500
b1110011011101011101001 $
b111111100111111000 1
b111110100101 2
b100110011101 .
b10000 3
b11111010010 0
b0 -
1#
#568750
0#
#575000
b11110011001 ,
b101111000 1
b111100110011 2
b111111001001000101 .
b10000 3
b11110011001 0
b0 -
b1110011011101011101001 /
1#
#581250
0#
#587500
b11110011001 +
b101111000 1
b111100110011 2
b111111001001000101 .
b10000 3
b11110011001 0
b0 -
1#
#593750
0#
#600000
b11001110110 "
b100010111010 !
b101111000 1
b111100110011 2
b111111001001000101 .
b10000 3
b11110011001 0
b0 -
1#
#606250
0#
#612500
b11001110110 (
b11001110110 '
b100010111010 &
b100010111010 %
b101111000 1
b111100110011 2
b111111001001000101 .
b10000 3
b11110011001 0
b0 -
1#
#618750
0#
#625000
b1010011011111001100100 *
b1101001110011100100100 )
b101111000 1
b111100110011 2
b111111001001000101 .
b10000 3
b11110011001 0
b0 -
1#
#631250
0#
#637500
b10111101010010110001000 $
b101111000 1
b111100110011 2
b111111001001000101 .
b10000 3
b11110011001 0
b0 -
1#
#643750
0#
#650000
b100110111010 ,
b111111011011101111 1
b1001101110101 2
b101001100100 .
b10000 3
b100110111010 0
b0 -
b10111101010010110001000 /
1#
#656250
0#
#662500
b100110111010 +
b111111011011101111 1
b1001101110101 2
b101001100100 .
b10000 3
b100110111010 0
b0 -
1#
#668750
0#
#675000
b101000110011 "
b11000011 !
b111111011011101111 1
b1001101110101 2
b101001100100 .
b10000 3
b100110111010 0
b0 -
1#
#681250
0#
#687500
b101000110011 (
b101000110011 '
b11000011 &
b11000011 %
b111111011011101111 1
b1001101110101 2
b101001100100 .
b10000 3
b100110111010 0
b0 -
1#
#693750
0#
#700000
b1000011010011000101001 *
b1001010010001001 )
b111111011011101111 1
b1001101110101 2
b101001100100 .
b10000 3
b100110111010 0
b0 -
1#
#706250
0#
#712500
b1000100011101010110010 $
b111111011011101111 1
b1001101110101 2
b101001100100 .
b10000 3
b100110111010 0
b0 -
1#
#718750
0#
#725000
b10111011001 ,
b100011000001 1
b101110110011 2
b111111110100001110 .
b10000 3
b10111011001 0
b0 -
b1000100011101010110010 /
1#
#731250
0#
#737500
b10111011001 +
b100011000001 1
b101110110011 2
b111111110100001110 .
b10000 3
b10111011001 0
b0 -
1#
#743750
0#
#750000
b110111001101 "
b11011101100 !
b100011000001 1
b101110110011 2
b111111110100001110 .
b10000 3
b10111011001 0
b0 -
1#
#756250
0#
#762500
b110111001101 (
b110111001101 '
b11011101100 &
b11011101100 %
b100011000001 1
b101110110011 2
b111111110100001110 .
b10000 3
b10111011001 0
b0 -
1#
#768750
0#
#775000
b1001101011000101001 *
b1011111110100110010000 )
b100011000001 1
b101110110011 2
b111111110100001110 .
b10000 3
b10111011001 0
b0 -
1#
#781250
0#
#787500
b1101001011111110111001 $
b100011000001 1
b101110110011 2
b111111110100001110 .
b10000 3
b10111011001 0
b0 -
1#
#793750
0#
#800000
b11101000011 ,
b10000110000 1
b111010000101 2
b1001010110101 .
b10000 3
b11101000011 0
b0 -
b1101001011111110111001 /
1#
#806250
0#
#812500
b11101000011 +
b10000110000 1
b111010000101 2
b1001010110101 .
b10000 3
b11101000011 0
b0 -
1#
#818750
0#
#825000
b1000000111 "
b111111110110 !
b10000110000 1
b111010000101 2
b1001010110101 .
b10000 3
b11101000011 0
b0 -
1#
#831250
0#
#837500
b1000000111 (
b1000000111 '
b111111110110 &
b111111110110 %
b10000110000 1
b111010000101 2
b1001010110101 .
b10000 3
b11101000011 0
b0 -
1#
#843750
0#
#850000
b1000001110000110001 *
b1100100 )
b10000110000 1
b111010000101 2
b1001010110101 .
b10000 3
b11101000011 0
b0 -
1#
#856250
0#
#862500
b1000001110010010101 $
b10000110000 1
b111010000101 2
b1001010110101 .
b10000 3
b11101000011 0
b0 -
1#
#868750
0#
#875000
b1000000111 ,
b1100100 1
b10000001101 2
b10001110001 .
b10000 3
b1000000111 0
b0 -
b1000001110010010101 /
1#
#881250
0#
#887500
b1000000111 +
b1100100 1
b10000001101 2
b10001110001 .
b10000 3
b1000000111 0
b0 -
1#
#893750
0#
#900000
b111101000 "
b110001001100 !
b1100100 1
b10000001101 2
b10001110001 .
b10000 3
b1000000111 0
b0 -
1#
#906250
0#
#912500
b111101000 (
b111101000 '
b110001001100 &
b110001001100 %
b1100100 1
b10000001101 2
b10001110001 .
b10000 3
b1000000111 0
b0 -
1#
#918750
0#
#925000
b111010001001000000 *
b11011011011010010000 )
b1100100 1
b10000001101 2
b10001110001 .
b10000 3
b1000000111 0
b0 -
1#
#931250
0#
#937500
b100010101100011010000 $
b1100100 1
b10000001101 2
b10001110001 .
b10000 3
b1000000111 0
b0 -
1#
#943750
0#
#950000
b10000101010 ,
b111111100110010111 1
b100001010101 2
b111101100 .
b10000 3
b10000101010 0
b0 -
b100010101100011010000 /
1#
#956250
0#
#962500
b10000101010 +
b111111100110010111 1
b100001010101 2
b111101100 .
b10000 3
b10000101010 0
b0 -
1#
#968750
0#
#975000
b101001000111 "
b101101110101 !
b111111100110010111 1
b100001010101 2
b111101100 .
b10000 3
b10000101010 0
b0 -
1#
#981250
0#
#987500
b101001000111 (
b101001000111 '
b101101110101 &
b101101110101 %
b111111100110010111 1
b100001010101 2
b111101100 .
b10000 3
b10000101010 0
b0 -
1#
#993750
0#
#1000000
b1000001011111110110001 *
b101001010001101111001 )
b111111100110010111 1
b100001010101 2
b111101100 .
b10000 3
b10000101010 0
b0 -
1#
#1006250
0#
#1012500
b1101010110001100101010 $
b111111100110010111 1
b100001010101 2
b111101100 .
b10000 3
b10000101010 0
b0 -
1#
#1018750
0#
#1025000
b11101001110 ,
b111111100011001001 1
b111010011101 2
b11101100110 .
b10000 3
b11101001110 0
b0 -
b1101010110001100101010 /
1#
#1031250
0#
#1037500
b11101001110 +
b111111100011001001 1
b111010011101 2
b11101100110 .
b10000 3
b11101001110 0
b0 -
1#
#1043750
0#
#1050000
b100010111110 "
b100001001 !
b111111100011001001 1
b111010011101 2
b11101100110 .
b10000 3
b11101001110 0
b0 -
1#
#1056250
0#
#1062500
b100010111110 (
b100010111110 '
b100001001 &
b100001001 %
b111111100011001001 1
b111010011101 2
b11101100110 .
b10000 3
b11101001110 0
b0 -
1#
#1068750
0#
#1075000
b1101001010110100000100 *
b10001001001010001 )
b111111100011001001 1
b111010011101 2
b11101100110 .
b10000 3
b11101001110 0
b0 -
1#
#1081250
0#
#1087500
b1101011011111101010101 $
b111111100011001001 1
b111010011101 2
b11101100110 .
b10000 3
b11101001110 0
b0 -
1#
#1093750
0#
#1100000
b11101010100 ,
b111111110100011100 1
b111010101011 2
b111110111001110001 .
b10000 3
b11101010100 0
b0 -
b1101011011111101010101 /
1#
#1106250
0#
#1112500
b11101010100 +
b111111110100011100 1
b111010101011 2
b111110111001110001 .
b10000 3
b11101010100 0
b0 -
1#
#1118750
0#
#1125000
b10111010111 "
b100111011000 !
b111111110100011100 1
b111010101011 2
b111110111001110001 .
b10000 3
b11101010100 0
b0 -
1#
#1131250
0#
#1137500
b10111010111 (
b10111010111 '
b100111011000 &
b100111011000 %
b111111110100011100 1
b111010101011 2
b111110111001110001 .
b10000 3
b11101010100 0
b0 -
1#
#1143750
0#
#1150000
b1000100001101010010001 *
b1001011110011001000000 )
b111111110100011100 1
b111010101011 2
b111110111001110001 .
b10000 3
b11101010100 0
b0 -
1#
#1156250
0#
#1162500
b10010000000000011010001 $
b111111110100011100 1
b111010101011 2
b111110111001110001 .
b10000 3
b11101010100 0
b0 -
1#
#1168750
0#
#1175000
b100001111100 ,
b111111001111001000 1
b1000011111011 2
b111110001011001101 .
b10000 3
b100001111100 0
b0 -
b10010000000000011010001 /
1#
#1181250
0#
#1187500
b100001111100 +
b111111001111001000 1
b1000011111011 2
b111110001011001101 .
b10000 3
b100001111100 0
b0 -
1#
#1193750
0#
#1200000
b111111011100 "
b1000110110 !
b111111001111001000 1
b1000011111011 2
b111110001011001101 .
b10000 3
b100001111100 0
b0 -
1#
#1206250
0#
#1212500
b111111011100 (
b111111011100 '
b1000110110 &
b1000110110 %
b111111001111001000 1
b1000011111011 2
b111110001011001101 .
b10000 3
b100001111100 0
b0 -
1#
#1218750
0#
#1225000
b10100010000 *
b1001110001101100100 )
b111111001111001000 1
b1000011111011 2
b111110001011001101 .
b10000 3
b100001111100 0
b0 -
1#
#1231250
0#
#1237500
b1001110100001110100 $
b111111001111001000 1
b1000011111011 2
b111110001011001101 .
b10000 3
b100001111100 0
b0 -
1#
#1243750
0#
#1250000
b1000110111 ,
b10100011 1
b10001101101 2
b10100010000 .
b10000 3
b1000110111 0
b0 -
b1001110100001110100 /
1#
#1256250
0#
#1262500
b1000110111 +
b10100011 1
b10001101101 2
b10100010000 .
b10000 3
b1000110111 0
b0 -
1#
#1268750
0#
#1275000
b101111110101 "
b111100001011 !
b10100011 1
b10001101101 2
b10100010000 .
b10000 3
b1000110111 0
b0 -
1#
#1281250
0#
#1287500
b101111110101 (
b101111110101 '
b111100001011 &
b111100001011 %
b10100011 1
b10001101101 2
b10100010000 .
b10000 3
b1000110111 0
b0 -
1#
#1293750
0#
#1300000
b100000101100001111001 *
b1110101001111001 )
b10100011 1
b10001101101 2
b10100010000 .
b10000 3
b1000110111 0
b0 -
1#
#1306250
0#
#1312500
b100010100001011110010 $
b10100011 1
b10001101101 2
b10100010000 .
b10000 3
b1000110111 0
b0 -
1#
#1318750
0#
#1325000
b10000100111 ,
b10100000001 1
b100001001101 2
b110101001110 .
b10000 3
b10000100111 0
b0 -
b100010100001011110010 /
1#
#1331250
0#
#1337500
b10000100111 +
b10100000001 1
b100001001101 2
b110101001110 .
b10000 3
b10000100111 0
b0 -
1#
#1343750
0#
#1350000
b11010101001 "
b1111010101 !
b10100000001 1
b100001001101 2
b110101001110 .
b10000 3
b10000100111 0
b0 -
1#
#1356250
0#
#1362500
b11010101001 (
b11010101001 '
b1111010101 &
b1111010101 %
b10100000001 1
b100001001101 2
b110101001110 .
b10000 3
b10000100111 0
b0 -
1#
#1368750
0#
#1375000
b1011000101101110010001 *
b11101010111100111001 )
b10100000001 1
b100001001101 2
b110101001110 .
b10000 3
b10000100111 0
b0 -
1#
#1381250
0#
#1387500
b1110110000101011001010 $
b10100000001 1
b100001001101 2
b110101001110 .
b10000 3
b10000100111 0
b0 -
1#
#1393750
0#
#1400000
b11110101111 ,
b100101001 1
b111101011101 2
b1000010000110 .
b10000 3
b11110101111 0
b0 -
b1110110000101011001010 /
1#
#1406250
0#
#1412500
b11110101111 +
b100101001 1
b111101011101 2
b1000010000110 .
b10000 3
b11110101111 0
b0 -
1#
#1418750
0#
#1425000
b10111111100 "
b1111001 !
b100101001 1
b111101011101 2
b1000010000110 .
b10000 3
b11110101111 0
b0 -
1#
#1431250
0#
#1437500
b10111111100 (
b10111111100 '
b1111001 &
b1111001 %
b100101001 1
b111101011101 2
b1000010000110 .
b10000 3
b11110101111 0
b0 -
1#
#1443750
0#
#1450000
b1000111101000000010000 *
b11100100110001 )
b100101001 1
b111101011101 2
b1000010000110 .
b10000 3
b11110101111 0
b0 -
1#
#1456250
0#
#1462500
b1001000000100101000001 $
b100101001 1
b111101011101 2
b1000010000110 .
b10000 3
b11110101111 0
b0 -
1#
#1468750
0#
#1475000
b11000000000 ,
b111111110101000000 1
b110000000011 2
b111111000100111101 .
b10000 3
b11000000000 0
b0 -
b1001000000100101000001 /
1#
#1481250
0#
#1487500
b11000000000 +
b111111110101000000 1
b110000000011 2
b111111000100111101 .
b10000 3
b11000000000 0
b0 -
1#
#1493750
0#
#1500000
b100100101010 "
b10000001101 !
b111111110101000000 1
b110000000011 2
b111111000100111101 .
b10000 3
b11000000000 0
b0 -
1#
#1506250
0#
#1512500
b100100101010 (
b100100101010 '
b10000001101 &
b10000001101 %
b111111110101000000 1
b110000000011 2
b111111000100111101 .
b10000 3
b11000000000 0
b0 -
1#
#1518750
0#
#1525000
b1011101011101011100100 *
b100000110100010101001 )
b111111110101000000 1
b110000000011 2
b111111000100111101 .
b10000 3
b11000000000 0
b0 -
1#
#1531250
0#
#1537500
b1111110010001110001101 $
b111111110101000000 1
b110000000011 2
b111111000100111101 .
b10000 3
b11000000000 0
b0 -
1#
#1543750
0#
#1550000
b11111110010 ,
b111111001011100100 1
b111111100101 2
b1011001001 .
b10000 3
b11111110010 0
b0 -
b1111110010001110001101 /
1#
#1556250
0#
#1562500
b11111110010 +
b111111001011100100 1
b111111100101 2
b1011001001 .
b10000 3
b11111110010 0
b0 -
1#
#1568750
0#
#1575000
b110101100110 "
b11001101001 !
b111111001011100100 1
b111111100101 2
b1011001001 .
b10000 3
b11111110010 0
b0 -
1#
#1581250
0#
#1587500
b110101100110 (
b110101100110 '
b11001101001 &
b11001101001 %
b111111001011100100 1
b111111100101 2
b1011001001 .
b10000 3
b11111110010 0
b0 -
1#
#1593750
0#
#1600000
b1101100010010100100 *
b1010010001011100010001 )
b111111001011100100 1
b111111100101 2
b1011001001 .
b10000 3
b11111110010 0
b0 -
1#
#1606250
0#
#1612500
b1011111101101110110101 $
b111111001011100100 1
b111111100101 2
b1011001001 .
b10000 3
b11111110010 0
b0 -
1#
#1618750
0#
#1625000
b11011101010 ,
b111111111111111100 1
b110111010101 2
b110111010001 .
b10000 3
b11011101010 0
b0 -
b1011111101101110110101 /
1#
#1631250
0#
#1637500
b11011101010 +
b111111111111111100 1
b110111010101 2
b110111010001 .
b10000 3
b11011101010 0
b0 -
1#
#1643750
0#
#1650000
b111010000001 "
b111111010100 !
b111111111111111100 1
b110111010101 2
b110111010001 .
b10000 3
b11011101010 0
b0 -
1#
#1656250
0#
#1662500
b111010000001 (
b111010000001 '
b111111010100 &
b111111010100 %
b111111111111111100 1
b110111010101 2
b110111010001 .
b10000 3
b11011101010 0
b0 -
1#
#1668750
0#
#1675000
b100011110100000001 *
b11110010000 )
b111111111111111100 1
b110111010101 2
b110111010001 .
b10000 3
b11011101010 0
b0 -
1#
#1681250
0#
#1687500
b100100010010010001 $
b111111111111111100 1
b110111010101 2
b110111010001 .
b10000 3
b11011101010 0
b0 -
1#
#1693750
0#
#1700000
b110000001 ,
b110010000 1
b1100000011 2
b111111111010001101 .
b10000 3
b110000001 0
b0 -
b100100010010010001 /
1#
#1706250
0#
#1712500
b110000001 +
b110010000 1
b1100000011 2
b111111111010001101 .
b10000 3
b110000001 0
b0 -
1#
#1718750
0#
#1725000
b1011000010 "
b111010000010 !
b110010000 1
b1100000011 2
b111111111010001101 .
b10000 3
b110000001 0
b0 -
1#
#1731250
0#
#1737500
b1011000010 (
b1011000010 '
b111010000010 &
b111010000010 %
b110010000 1
b1100000011 2
b111111111010001101 .
b10000 3
b110000001 0
b0 -
1#
#1743750
0#
#1750000
b1111001101100000100 *
b100011101000000100 )
b110010000 1
b1100000011 2
b111111111010001101 .
b10000 3
b110000001 0
b0 -
1#
#1756250
0#
#1762500
b10011101010100001000 $
b110010000 1
b1100000011 2
b111111111010001101 .
b10000 3
b110000001 0
b0 -
1#
#1768750
0#
#1775000
b1100100010 ,
b111111111000111111 1
b11001000101 2
b10010000100 .
b10000 3
b1100100010 0
b0 -
b10011101010100001000 /
1#
#1781250
0#
#1787500
b1100100010 +
b111111111000111111 1
b11001000101 2
b10010000100 .
b10000 3
b1100100010 0
b0 -
1#
#1793750
0#
#1800000
b101111011100 "
b10001001011 !
b111111111000111111 1
b11001000101 2
b10010000100 .
b10000 3
b1100100010 0
b0 -
1#
#1806250
0#
#1812500
b101111011100 (
b101111011100 '
b10001001011 &
b10001001011 %
b111111111000111111 1
b11001000101 2
b10010000100 .
b10000 3
b1100100010 0
b0 -
1#
#1818750
0#
#1825000
b100010010010100010000 *
b100100110110111111001 )
b111111111000111111 1
b11001000101 2
b10010000100 .
b10000 3
b1100100010 0
b0 -
1#
#1831250
0#
#1837500
b1000111001001100001001 $
b111111111000111111 1
b11001000101 2
b10010000100 .
b10000 3
b1100100010 0
b0 -
1#
#1843750
0#
#1850000
b10111110110 ,
b111111111010111000 1
b101111101101 2
b101010100101 .
b10000 3
b10111110110 0
b0 -
b1000111001001100001001 /
1#
#1856250
0#
#1862500
b10111110110 +
b111111111010111000 1
b101111101101 2
b101010100101 .
b10000 3
b10111110110 0
b0 -
1#
#1868750
0#
#1875000
b10001101100 "
b111001110100 !
b111111111010111000 1
b101111101101 2
b101010100101 .
b10000 3
b10111110110 0
b0 -
1#
#1881250
0#
#1887500
b10001101100 (
b10001101100 '
b111001110100 &
b111001110100 %
b111111111010111000 1
b101111101101 2
b101010100101 .
b10000 3
b10111110110 0
b0 -
1#
#1893750
0#
#1900000
b100111000110110010000 *
b100110010010010000 )
b111111111010111000 1
b101111101101 2
b101010100101 .
b10000 3
b10111110110 0
b0 -
1#
#1906250
0#
#1912500
b101011111001000100000 $
b111111111010111000 1
b101111101101 2
b101010100101 .
b10000 3
b10111110110 0
b0 -
1#
#1918750
0#
#1925000
b10010101111 ,
b1001111111 1
b100101011101 2
b101111011100 .
b10000 3
b10010101111 0
b0 -
b101011111001000100000 /
1#
#1931250
0#
#1937500
b10010101111 +
b1001111111 1
b100101011101 2
b101111011100 .
b10000 3
b10010101111 0
b0 -
1#
#1943750
0#
#1950000
b1001010 "
b1011011100 !
b1001111111 1
b100101011101 2
b101111011100 .
b10000 3
b10010101111 0
b0 -
1#
#1956250
0#
#1962500
b1001010 (
b1001010 '
b1011011100 &
b1011011100 %
b1001111111 1
b100101011101 2
b101111011100 .
b10000 3
b10010101111 0
b0 -
1#
#1968750
0#
#1975000
b1010101100100 *
b10000010110100010000 )
b1001111111 1
b100101011101 2
b101111011100 .
b10000 3
b10010101111 0
b0 -
1#
#1981250
0#
#1987500
b10000100001001110100 $
b1001111111 1
b100101011101 2
b101111011100 .
b10000 3
b10010101111 0
b0 -
1#
#1993750
0#
#2000000
b1011011111 ,
b10000110011 1
b10110111101 2
b100111110000 .
b10000 3
b1011011111 0
b0 -
b10000100001001110100 /
1#
#2006250
0#
#2012500
b1011011111 +
b10000110011 1
b10110111101 2
b100111110000 .
b10000 3
b1011011111 0
b0 -
1#
#2018750
0#
#2025000
b1110010001 "
b110100111100 !
b10000110011 1
b10110111101 2
b100111110000 .
b10000 3
b1011011111 0
b0 -
1#
#2031250
0#
#2037500
b1110010001 (
b1110010001 '
b110100111100 &
b110100111100 %
b10000110011 1
b10110111101 2
b100111110000 .
b10000 3
b1011011111 0
b0 -
1#
#2043750
0#
#2050000
b11001011100000100001 *
b1111010011000010000 )
b10000110011 1
b10110111101 2
b100111110000 .
b10000 3
b1011011111 0
b0 -
1#
#2056250
0#
#2062500
b101000101111000110001 $
b10000110011 1
b10110111101 2
b100111110000 .
b10000 3
b1011011111 0
b0 -
1#
#2068750
0#
#2075000
b10010000011 ,
b1100101000 1
b100100000101 2
b110000101101 .
b10000 3
b10010000011 0
b0 -
b101000101111000110001 /
1#
#2081250
0#
#2087500
b10010000011 +
b1100101000 1
b100100000101 2
b110000101101 .
b10000 3
b10010000011 0
b0 -
1#
#2093750
0#
#2100000
b101101010011 "
b11101110000 !
b1100101000 1
b100100000101 2
b110000101101 .
b10000 3
b10010000011 0
b0 -
1#
#2106250
0#
#2112500
b101101010011 (
b101101010011 '
b11101110000 &
b11101110000 %
b1100101000 1
b100100000101 2
b110000101101 .
b10000 3
b10010000011 0
b0 -
1#
#2118750
0#
#2125000
b101011101110011101001 *
b1101110101000100000000 )
b1100101000 1
b100100000101 2
b110000101101 .
b10000 3
b10010000011 0
b0 -
1#
#2131250
0#
#2137500
b10011010010110111101001 $
b1100101000 1
b100100000101 2
b110000101101 .
b10000 3
b10010000011 0
b0 -
1#
#2143750
0#
#2150000
b100011001001 ,
b11000 1
b1000110010011 2
b111110111010000101 .
b10000 3
b100011001001 0
b0 -
b10011010010110111101001 /
1#
#2156250
0#
#2162500
b100011001001 +
b11000 1
b1000110010011 2
b111110111010000101 .
b10000 3
b100011001001 0
b0 -
1#
#2168750
0#
