5.NewModules/SineGenerator/quartertable_lut_module/1.hw/quarterwave_table.v

module quarterwave_table #(
    parameter QLUT_DEPTH = 8,
    parameter DATA_WIDTH = 12
)(
    input  reg        [QLUT_DEPTH-3:0] address, // 6-bit address signal for 64 values
    output reg signed [DATA_WIDTH-1:0] value    // 12-bit output signal
);

    always_comb begin
        unique case(address)
            6'd0: value = 12'h19;
            6'd1: value = 12'h4B;
            6'd2: value = 12'h7D;
            6'd3: value = 12'hAF;
            6'd4: value = 12'hE1;
            6'd5: value = 12'h113;
            6'd6: value = 12'h145;
            6'd7: value = 12'h176;
            6'd8: value = 12'h1A7;
            6'd9: value = 12'h1D8;
            6'd10: value = 12'h209;
            6'd11: value = 12'h23A;
            6'd12: value = 12'h26A;
            6'd13: value = 12'h299;
            6'd14: value = 12'h2C9;
            6'd15: value = 12'h2F8;
            6'd16: value = 12'h326;
            6'd17: value = 12'h354;
            6'd18: value = 12'h381;
            6'd19: value = 12'h3AE;
            6'd20: value = 12'h3DB;
            6'd21: value = 12'h406;
            6'd22: value = 12'h431;
            6'd23: value = 12'h45C;
            6'd24: value = 12'h486;
            6'd25: value = 12'h4AF;
            6'd26: value = 12'h4D7;
            6'd27: value = 12'h4FF;
            6'd28: value = 12'h525;
            6'd29: value = 12'h54B;
            6'd30: value = 12'h571;
            6'd31: value = 12'h595;
            6'd32: value = 12'h5B9;
            6'd33: value = 12'h5DB;
            6'd34: value = 12'h5FD;
            6'd35: value = 12'h61E;
            6'd36: value = 12'h63E;
            6'd37: value = 12'h65D;
            6'd38: value = 12'h67B;
            6'd39: value = 12'h697;
            6'd40: value = 12'h6B3;
            6'd41: value = 12'h6CE;
            6'd42: value = 12'h6E8;
            6'd43: value = 12'h701;
            6'd44: value = 12'h718;
            6'd45: value = 12'h72F;
            6'd46: value = 12'h745;
            6'd47: value = 12'h759;
            6'd48: value = 12'h76C;
            6'd49: value = 12'h77E;
            6'd50: value = 12'h78F;
            6'd51: value = 12'h79F;
            6'd52: value = 12'h7AE;
            6'd53: value = 12'h7BB;
            6'd54: value = 12'h7C7;
            6'd55: value = 12'h7D2;
            6'd56: value = 12'h7DC;
            6'd57: value = 12'h7E5;
            6'd58: value = 12'h7EC;
            6'd59: value = 12'h7F2;
            6'd60: value = 12'h7F7;
            6'd61: value = 12'h7FB;
            6'd62: value = 12'h7FD;
            6'd63: value = 12'h7FE;

            default: value = 12'd0;
        endcase
    end

endmodule

5.NewModules/SineGenerator/quartertable_lut_module/1.hw/quarterwave_generator.sv

module quarterwave_generator #(
    parameter DATA_WIDTH  = 16,
              QLUT_DEPTH  = 11,
              PHASE_WIDTH = 64
) (
    input  logic                             clk,
    input  logic                             arst,
    input  logic                             sample_clk_ce,
    input  logic         [PHASE_WIDTH-1:0]   phase_increment,
    output logic  signed [DATA_WIDTH -1:0]   sinewave,
    output logic  signed [DATA_WIDTH -1:0]   cosinewave
);

  logic         [           1:0] sine_negate;
  logic         [QLUT_DEPTH-3:0] sine_index;
  logic signed  [DATA_WIDTH-1:0] sine_table_value;

  logic         [           1:0] cosine_negate;
  logic         [QLUT_DEPTH-3:0] cosine_index;
  logic signed  [DATA_WIDTH-1:0] cosine_table_value;

  logic         [PHASE_WIDTH-1:0] phase_accumulator;

  // Instantiate quarterwave_table for sine and cosine
  quarterwave_table #( .QLUT_DEPTH(QLUT_DEPTH), .DATA_WIDTH(DATA_WIDTH) ) sinewave_inst (
      .address(sine_index),
      .value  (sine_table_value)
  );

  quarterwave_table #( .QLUT_DEPTH(QLUT_DEPTH), .DATA_WIDTH(DATA_WIDTH) ) cosinewave_inst (
      .address(cosine_index),
      .value  (cosine_table_value)
  );

  always_ff @(posedge clk or posedge arst) begin
    if      (arst == 1'b1)          phase_accumulator <= '0;
    else if (sample_clk_ce == 1'b1) phase_accumulator <= PHASE_WIDTH'(phase_accumulator + phase_increment);
  end

  always_ff @(posedge clk or posedge arst) begin
    if (arst == 1'b1) begin
      sine_negate        <= 2'b00;
      sine_index         <= '0;
      sinewave           <= '0;

      cosine_negate      <= 2'b00;
      cosine_index       <= '0;
      cosinewave         <= '0;
    end else if (sample_clk_ce == 1'b1) begin
      // Clock #1
      sine_negate[0]     <= phase_accumulator[PHASE_WIDTH-1];
      cosine_negate [0]  <= phase_accumulator[PHASE_WIDTH-1] ^ phase_accumulator[PHASE_WIDTH-2];

      if (phase_accumulator[(PHASE_WIDTH-2)]) begin
         sine_index      <= ~phase_accumulator[PHASE_WIDTH-3:(PHASE_WIDTH-QLUT_DEPTH)];
         cosine_index    <=  phase_accumulator[PHASE_WIDTH-3:(PHASE_WIDTH-QLUT_DEPTH)];
      end else begin
         sine_index      <=  phase_accumulator[PHASE_WIDTH-3:(PHASE_WIDTH-QLUT_DEPTH)];
         cosine_index    <= ~phase_accumulator[PHASE_WIDTH-3:(PHASE_WIDTH-QLUT_DEPTH)];
      end
      // Clock #2
      sine_negate  [1]   <= sine_negate  [0];
      cosine_negate[1]   <= cosine_negate[0];
      // Output Clock
      sinewave           <= sine_negate  [1] ? -sine_table_value   : sine_table_value;
      cosinewave         <= cosine_negate[1] ? -cosine_table_value : cosine_table_value;
    end
  end

  initial begin
    $dumpfile("quarterwave.vcd");
    $dumpvars;
  end
endmodule

5.NewModules/SineGenerator/quartertable_lut_module/2.sim/quarterwave.vcd
$date
	Tue Aug 27 19:22:47 2024
$end
$version
	Icarus Verilog
$end
$timescale
	1ps
$end
$scope module quarterwave_generator $end
$var wire 1 ! arst $end
$var wire 1 " clk $end
$var wire 64 # phase_increment [63:0] $end
$var wire 1 $ sample_clk_ce $end
$var wire 16 % sine_table_value [15:0] $end
$var wire 16 & cosine_table_value [15:0] $end
$var parameter 32 ' DATA_WIDTH $end
$var parameter 32 ( PHASE_WIDTH $end
$var parameter 32 ) QLUT_DEPTH $end
$var reg 9 * cosine_index [8:0] $end
$var reg 2 + cosine_negate [1:0] $end
$var reg 16 , cosinewave [15:0] $end
$var reg 64 - phase_accumulator [63:0] $end
$var reg 9 . sine_index [8:0] $end
$var reg 2 / sine_negate [1:0] $end
$var reg 16 0 sinewave [15:0] $end
$scope module cosinewave_inst $end
$var wire 9 1 address [8:0] $end
$var parameter 32 2 DATA_WIDTH $end
$var parameter 32 3 QLUT_DEPTH $end
$var reg 16 4 value [15:0] $end
$upscope $end
$scope module sinewave_inst $end
$var wire 9 5 address [8:0] $end
$var parameter 32 6 DATA_WIDTH $end
$var parameter 32 7 QLUT_DEPTH $end
$var reg 16 8 value [15:0] $end
$upscope $end
$upscope $end
$enddefinitions $end
$comment Show the parameter values. $end
$dumpall
b1011 7
b10000 6
b1011 3
b10000 2
b1011 )
b1000000 (
b10000 '
$end
#0
$dumpvars
b110010 8
b0 5
b110010 4
b0 1
b0 0
b0 /
b0 .
b0 -
b0 ,
b0 +
b0 *
b110010 &
b110010 %
1$
b10000000000000000000000000000000000000000000000000000000000 #
1"
1!
$end
#6250
0"
#12500
1"
#18750
0"
#25000
0!
1"
#31250
0"
#37500
b111111111111110 &
b111111111111110 4
b110010 ,
b110010 0
b111111111 *
b111111111 1
b10000000000000000000000000000000000000000000000000000000000 -
1"
#43750
0"
#50000
b111111101011100 &
b111111101011100 4
b110010111101 %
b110010111101 8
b100000000000000000000000000000000000000000000000000000000000 -
b111111111111110 ,
b111011111 *
b111011111 1
b100000 .
b100000 5
1"
#56250
0"
#62500
b111110101111111 &
b111110101111111 4
b1100100101001 %
b1100100101001 8
b111111101011100 ,
b110010111101 0
b110111111 *
b110111111 1
b1000000 .
b1000000 5
b110000000000000000000000000000000000000000000000000000000000 -
1"
#68750
0"
#75000
b111101001101101 &
b111101001101101 4
b10010101010111 %
b10010101010111 8
b1000000000000000000000000000000000000000000000000000000000000 -
b111110101111111 ,
b1100100101001 0
b110011111 *
b110011111 1
b1100000 .
b1100000 5
1"
#81250
0"
#87500
b111011000101101 &
b111011000101101 4
b11000100101001 %
b11000100101001 8
b111101001101101 ,
b10010101010111 0
b101111111 *
b101111111 1
b10000000 .
b10000000 5
b1010000000000000000000000000000000000000000000000000000000000 -
1"
#93750
0"
#100000
b111000011001010 &
b111000011001010 4
b11110010000010 %
b11110010000010 8
b1100000000000000000000000000000000000000000000000000000000000 -
b111011000101101 ,
b11000100101001 0
b101011111 *
b101011111 1
b10100000 .
b10100000 5
1"
#106250
0"
#112500
b110101001010000 &
b110101001010000 4
b100011101000110 %
b100011101000110 8
b111000011001010 ,
b11110010000010 0
b100111111 *
b100111111 1
b11000000 .
b11000000 5
b1110000000000000000000000000000000000000000000000000000000000 -
1"
#118750
0"
#125000
b110001011010001 &
b110001011010001 4
b101000101011001 %
b101000101011001 8
b10000000000000000000000000000000000000000000000000000000000000 -
b110101001010000 ,
b100011101000110 0
b100011111 *
b100011111 1
b11100000 .
b11100000 5
1"
#131250
0"
#137500
b101101001011110 &
b101101001011110 4
b101101010100101 %
b101101010100101 8
b110001011010001 ,
b101000101011001 0
b11111111 *
b11111111 1
b100000000 .
b100000000 5
b10010000000000000000000000000000000000000000000000000000000000 -
1"
#143750
0"
#150000
b101000100001100 &
b101000100001100 4
b110001100010001 %
b110001100010001 8
b10100000000000000000000000000000000000000000000000000000000000 -
b101101001011110 ,
b101101010100101 0
b11011111 *
b11011111 1
b100100000 .
b100100000 5
1"
#156250
0"
#162500
b100011011110010 &
b100011011110010 4
b110101010001000 %
b110101010001000 8
b101000100001100 ,
b110001100010001 0
b10111111 *
b10111111 1
b101000000 .
b101000000 5
b10110000000000000000000000000000000000000000000000000000000000 -
1"
#168750
0"
#175000
b11110000101001 &
b11110000101001 4
b111000011111001 %
b111000011111001 8
b11000000000000000000000000000000000000000000000000000000000000 -
b100011011110010 ,
b110101010001000 0
b10011111 *
b10011111 1
b101100000 .
b101100000 5
1"
#181250
0"
#187500
b11000011001100 &
b11000011001100 4
b111011001010011 %
b111011001010011 8
b11110000101001 ,
b111000011111001 0
b1111111 *
b1111111 1
b110000000 .
b110000000 5
b11010000000000000000000000000000000000000000000000000000000000 -
1"
#193750
0"
#200000
b10010011110111 &
b10010011110111 4
b111101010001010 %
b111101010001010 8
b11100000000000000000000000000000000000000000000000000000000000 -
b11000011001100 ,
b111011001010011 0
b1011111 *
b1011111 1
b110100000 .
b110100000 5
1"
#206250
0"
#212500
b1100011000111 &
b1100011000111 4
b111110110010011 %
b111110110010011 8
b10010011110111 ,
b111101010001010 0
b111111 *
b111111 1
b111000000 .
b111000000 5
b11110000000000000000000000000000000000000000000000000000000000 -
1"
#218750
0"
#225000
b110001011001 &
b110001011001 4
b111111101100110 %
b111111101100110 8
b100000000000000000000000000000000000000000000000000000000000000 -
b1100011000111 ,
b111110110010011 0
b11111 *
b11111 1
b111100000 .
b111100000 5
1"
#231250
0"
#237500
b110010 &
b110010 4
b111111111111110 %
b111111111111110 8
b110001011001 ,
b111111101100110 0
b0 *
b0 1
b111111111 .
b111111111 5
b1 +
b100010000000000000000000000000000000000000000000000000000000000 -
1"
#243750
0"
#250000
b110010111101 &
b110010111101 4
b111111101011100 %
b111111101011100 8
b100100000000000000000000000000000000000000000000000000000000000 -
b110010 ,
b111111111111110 0
b11 +
b100000 *
b100000 1
b111011111 .
b111011111 5
1"
#256250
0"
#262500
b1100100101001 &
b1100100101001 4
b111110101111111 %
b111110101111111 8
b1111001101000011 ,
b111111101011100 0
b1000000 *
b1000000 1
b110111111 .
b110111111 5
b100110000000000000000000000000000000000000000000000000000000000 -
1"
#268750
0"
#275000
b10010101010111 &
b10010101010111 4
b111101001101101 %
b111101001101101 8
b101000000000000000000000000000000000000000000000000000000000000 -
b1110011011010111 ,
b111110101111111 0
b1100000 *
b1100000 1
b110011111 .
b110011111 5
1"
#281250
0"
#287500
b11000100101001 &
b11000100101001 4
b111011000101101 %
b111011000101101 8
b1101101010101001 ,
b111101001101101 0
b10000000 *
b10000000 1
b101111111 .
b101111111 5
b101010000000000000000000000000000000000000000000000000000000000 -
1"
#293750
0"
#300000
b11110010000010 &
b11110010000010 4
b111000011001010 %
b111000011001010 8
b101100000000000000000000000000000000000000000000000000000000000 -
b1100111011010111 ,
b111011000101101 0
b10100000 *
b10100000 1
b101011111 .
b101011111 5
1"
#306250
0"
#312500
b100011101000110 &
b100011101000110 4
b110101001010000 %
b110101001010000 8
b1100001101111110 ,
b111000011001010 0
b11000000 *
b11000000 1
b100111111 .
b100111111 5
b101110000000000000000000000000000000000000000000000000000000000 -
1"
#318750
0"
#325000
b101000101011001 &
b101000101011001 4
b110001011010001 %
b110001011010001 8
b110000000000000000000000000000000000000000000000000000000000000 -
b1011100010111010 ,
b110101001010000 0
b11100000 *
b11100000 1
b100011111 .
b100011111 5
1"
#331250
0"
#337500
b101101010100101 &
b101101010100101 4
b101101001011110 %
b101101001011110 8
b1010111010100111 ,
b110001011010001 0
b100000000 *
b100000000 1
b11111111 .
b11111111 5
b110010000000000000000000000000000000000000000000000000000000000 -
1"
#343750
0"
#350000
b110001100010001 &
b110001100010001 4
b101000100001100 %
b101000100001100 8
b110100000000000000000000000000000000000000000000000000000000000 -
b1010010101011011 ,
b101101001011110 0
b100100000 *
b100100000 1
b11011111 .
b11011111 5
1"
#356250
0"
#362500
b110101010001000 &
b110101010001000 4
b100011011110010 %
b100011011110010 8
b1001110011101111 ,
b101000100001100 0
b101000000 *
b101000000 1
b10111111 .
b10111111 5
b110110000000000000000000000000000000000000000000000000000000000 -
1"
#368750
0"
#375000
b111000011111001 &
b111000011111001 4
b11110000101001 %
b11110000101001 8
b111000000000000000000000000000000000000000000000000000000000000 -
b1001010101111000 ,
b100011011110010 0
b101100000 *
b101100000 1
b10011111 .
b10011111 5
1"
#381250
0"
#387500
b111011001010011 &
b111011001010011 4
b11000011001100 %
b11000011001100 8
b1000111100000111 ,
b11110000101001 0
b110000000 *
b110000000 1
b1111111 .
b1111111 5
b111010000000000000000000000000000000000000000000000000000000000 -
1"
#393750
0"
#400000
b111101010001010 &
b111101010001010 4
b10010011110111 %
b10010011110111 8
b111100000000000000000000000000000000000000000000000000000000000 -
b1000100110101101 ,
b11000011001100 0
b110100000 *
b110100000 1
b1011111 .
b1011111 5
1"
#406250
0"
#412500
b111110110010011 &
b111110110010011 4
b1100011000111 %
b1100011000111 8
b1000010101110110 ,
b10010011110111 0
b111000000 *
b111000000 1
b111111 .
b111111 5
b111110000000000000000000000000000000000000000000000000000000000 -
1"
#418750
0"
#425000
b111111101100110 &
b111111101100110 4
b110001011001 %
b110001011001 8
b1000000000000000000000000000000000000000000000000000000000000000 -
b1000001001101101 ,
b1100011000111 0
b111100000 *
b111100000 1
b11111 .
b11111 5
1"
#431250
0"
#437500
b111111111111110 &
b111111111111110 4
b110010 %
b110010 8
b1000000010011010 ,
b110001011001 0
b111111111 *
b111111111 1
b0 .
b0 5
b1 /
b1000010000000000000000000000000000000000000000000000000000000000 -
1"
#443750
0"
#450000
b111111101011100 &
b111111101011100 4
b110010111101 %
b110010111101 8
b1000100000000000000000000000000000000000000000000000000000000000 -
b1000000000000010 ,
b110010 0
b11 /
b111011111 *
b111011111 1
b100000 .
b100000 5
1"
#456250
0"
#462500
b111110101111111 &
b111110101111111 4
b1100100101001 %
b1100100101001 8
b1000000010100100 ,
b1111001101000011 0
b110111111 *
b110111111 1
b1000000 .
b1000000 5
b1000110000000000000000000000000000000000000000000000000000000000 -
1"
#468750
0"
#475000
b111101001101101 &
b111101001101101 4
b10010101010111 %
b10010101010111 8
b1001000000000000000000000000000000000000000000000000000000000000 -
b1000001010000001 ,
b1110011011010111 0
b110011111 *
b110011111 1
b1100000 .
b1100000 5
1"
#481250
0"
#487500
b111011000101101 &
b111011000101101 4
b11000100101001 %
b11000100101001 8
b1000010110010011 ,
b1101101010101001 0
b101111111 *
b101111111 1
b10000000 .
b10000000 5
b1001010000000000000000000000000000000000000000000000000000000000 -
1"
#493750
0"
#500000
b111000011001010 &
b111000011001010 4
b11110010000010 %
b11110010000010 8
b1001100000000000000000000000000000000000000000000000000000000000 -
b1000100111010011 ,
b1100111011010111 0
b101011111 *
b101011111 1
b10100000 .
b10100000 5
1"
#506250
0"
#512500
b110101001010000 &
b110101001010000 4
b100011101000110 %
b100011101000110 8
b1000111100110110 ,
b1100001101111110 0
b100111111 *
b100111111 1
b11000000 .
b11000000 5
b1001110000000000000000000000000000000000000000000000000000000000 -
1"
#518750
0"
#525000
b110001011010001 &
b110001011010001 4
b101000101011001 %
b101000101011001 8
b1010000000000000000000000000000000000000000000000000000000000000 -
b1001010110110000 ,
b1011100010111010 0
b100011111 *
b100011111 1
b11100000 .
b11100000 5
1"
#531250
0"
#537500
b101101001011110 &
b101101001011110 4
b101101010100101 %
b101101010100101 8
b1001110100101111 ,
b1010111010100111 0
b11111111 *
b11111111 1
b100000000 .
b100000000 5
b1010010000000000000000000000000000000000000000000000000000000000 -
1"
#543750
0"
#550000
b101000100001100 &
b101000100001100 4
b110001100010001 %
b110001100010001 8
b1010100000000000000000000000000000000000000000000000000000000000 -
b1010010110100010 ,
b1010010101011011 0
b11011111 *
b11011111 1
b100100000 .
b100100000 5
1"
#556250
0"
#562500
b100011011110010 &
b100011011110010 4
b110101010001000 %
b110101010001000 8
b1010111011110100 ,
b1001110011101111 0
b10111111 *
b10111111 1
b101000000 .
b101000000 5
b1010110000000000000000000000000000000000000000000000000000000000 -
1"
#568750
0"
#575000
b11110000101001 &
b11110000101001 4
b111000011111001 %
b111000011111001 8
b1011000000000000000000000000000000000000000000000000000000000000 -
b1011100100001110 ,
b1001010101111000 0
b10011111 *
b10011111 1
b101100000 .
b101100000 5
1"
#581250
0"
#587500
b11000011001100 &
b11000011001100 4
b111011001010011 %
b111011001010011 8
b1100001111010111 ,
b1000111100000111 0
b1111111 *
b1111111 1
b110000000 .
b110000000 5
b1011010000000000000000000000000000000000000000000000000000000000 -
1"
#593750
0"
#600000
b10010011110111 &
b10010011110111 4
b111101010001010 %
b111101010001010 8
b1011100000000000000000000000000000000000000000000000000000000000 -
b1100111100110100 ,
b1000100110101101 0
b1011111 *
b1011111 1
b110100000 .
b110100000 5
1"
#606250
0"
#612500
b1100011000111 &
b1100011000111 4
b111110110010011 %
b111110110010011 8
b1101101100001001 ,
b1000010101110110 0
b111111 *
b111111 1
b111000000 .
b111000000 5
b1011110000000000000000000000000000000000000000000000000000000000 -
1"
#618750
0"
#625000
b110001011001 &
b110001011001 4
b111111101100110 %
b111111101100110 8
b1100000000000000000000000000000000000000000000000000000000000000 -
b1110011100111001 ,
b1000001001101101 0
b11111 *
b11111 1
b111100000 .
b111100000 5
1"
#631250
0"
#637500
b110010 &
b110010 4
b111111111111110 %
b111111111111110 8
b1111001110100111 ,
b1000000010011010 0
b0 *
b0 1
b111111111 .
b111111111 5
b10 +
b1100010000000000000000000000000000000000000000000000000000000000 -
1"
#643750
0"
#650000
b110010111101 &
b110010111101 4
b111111101011100 %
b111111101011100 8
b1100100000000000000000000000000000000000000000000000000000000000 -
b1111111111001110 ,
b1000000000000010 0
b0 +
b100000 *
b100000 1
b111011111 .
b111011111 5
1"
#656250
0"
#662500
b1100100101001 &
b1100100101001 4
b111110101111111 %
b111110101111111 8
b110010111101 ,
b1000000010100100 0
b1000000 *
b1000000 1
b110111111 .
b110111111 5
b1100110000000000000000000000000000000000000000000000000000000000 -
1"
#668750
0"
#675000
b10010101010111 &
b10010101010111 4
b111101001101101 %
b111101001101101 8
b1101000000000000000000000000000000000000000000000000000000000000 -
b1100100101001 ,
b1000001010000001 0
b1100000 *
b1100000 1
b110011111 .
b110011111 5
1"
#681250
0"
#687500
b11000100101001 &
b11000100101001 4
b111011000101101 %
b111011000101101 8
b10010101010111 ,
b1000010110010011 0
b10000000 *
b10000000 1
b101111111 .
b101111111 5
b1101010000000000000000000000000000000000000000000000000000000000 -
1"
#693750
0"
#700000
b11110010000010 &
b11110010000010 4
b111000011001010 %
b111000011001010 8
b1101100000000000000000000000000000000000000000000000000000000000 -
b11000100101001 ,
b1000100111010011 0
b10100000 *
b10100000 1
b101011111 .
b101011111 5
1"
#706250
0"
#712500
b100011101000110 &
b100011101000110 4
b110101001010000 %
b110101001010000 8
b11110010000010 ,
b1000111100110110 0
b11000000 *
b11000000 1
b100111111 .
b100111111 5
b1101110000000000000000000000000000000000000000000000000000000000 -
1"
#718750
0"
#725000
b101000101011001 &
b101000101011001 4
b110001011010001 %
b110001011010001 8
b1110000000000000000000000000000000000000000000000000000000000000 -
b100011101000110 ,
b1001010110110000 0
b11100000 *
b11100000 1
b100011111 .
b100011111 5
1"
#731250
0"
#737500
b101101010100101 &
b101101010100101 4
b101101001011110 %
b101101001011110 8
b101000101011001 ,
b1001110100101111 0
b100000000 *
b100000000 1
b11111111 .
b11111111 5
b1110010000000000000000000000000000000000000000000000000000000000 -
1"
#743750
0"
#750000
b110001100010001 &
b110001100010001 4
b101000100001100 %
b101000100001100 8
b1110100000000000000000000000000000000000000000000000000000000000 -
b101101010100101 ,
b1010010110100010 0
b100100000 *
b100100000 1
b11011111 .
b11011111 5
1"
#756250
0"
#762500
b110101010001000 &
b110101010001000 4
b100011011110010 %
b100011011110010 8
b110001100010001 ,
b1010111011110100 0
b101000000 *
b101000000 1
b10111111 .
b10111111 5
b1110110000000000000000000000000000000000000000000000000000000000 -
1"
#768750
0"
#775000
b111000011111001 &
b111000011111001 4
b11110000101001 %
b11110000101001 8
b1111000000000000000000000000000000000000000000000000000000000000 -
b110101010001000 ,
b1011100100001110 0
b101100000 *
b101100000 1
b10011111 .
b10011111 5
1"
#781250
0"
#787500
b111011001010011 &
b111011001010011 4
b11000011001100 %
b11000011001100 8
b111000011111001 ,
b1100001111010111 0
b110000000 *
b110000000 1
b1111111 .
b1111111 5
b1111010000000000000000000000000000000000000000000000000000000000 -
1"
#793750
0"
#800000
b111101010001010 &
b111101010001010 4
b10010011110111 %
b10010011110111 8
b1111100000000000000000000000000000000000000000000000000000000000 -
b111011001010011 ,
b1100111100110100 0
b110100000 *
b110100000 1
b1011111 .
b1011111 5
1"
#806250
0"
#812500
b111110110010011 &
b111110110010011 4
b1100011000111 %
b1100011000111 8
b111101010001010 ,
b1101101100001001 0
b111000000 *
b111000000 1
b111111 .
b111111 5
b1111110000000000000000000000000000000000000000000000000000000000 -
1"
#818750
0"
#825000
b111111101100110 &
b111111101100110 4
b110001011001 %
b110001011001 8
b0 -
b111110110010011 ,
b1110011100111001 0
b111100000 *
b111100000 1
b11111 .
b11111 5
1"
#831250
0"
#837500
b111111111111110 &
b111111111111110 4
b110010 %
b110010 8
b111111101100110 ,
b1111001110100111 0
b111111111 *
b111111111 1
b0 .
b0 5
b10 /
b10000000000000000000000000000000000000000000000000000000000 -
1"
#843750
0"
#850000
b111111101011100 &
b111111101011100 4
b110010111101 %
b110010111101 8
b100000000000000000000000000000000000000000000000000000000000 -
b111111111111110 ,
b1111111111001110 0
b0 /
b111011111 *
b111011111 1
b100000 .
b100000 5
1"
#856250
0"
#862500
b111110101111111 &
b111110101111111 4
b1100100101001 %
b1100100101001 8
b111111101011100 ,
b110010111101 0
b110111111 *
b110111111 1
b1000000 .
b1000000 5
b110000000000000000000000000000000000000000000000000000000000 -
1"
#868750
0"
#875000
b111101001101101 &
b111101001101101 4
b10010101010111 %
b10010101010111 8
b1000000000000000000000000000000000000000000000000000000000000 -
b111110101111111 ,
b1100100101001 0
b110011111 *
b110011111 1
b1100000 .
b1100000 5
1"
#881250
0"
#887500
b111011000101101 &
b111011000101101 4
b11000100101001 %
b11000100101001 8
b111101001101101 ,
b10010101010111 0
b101111111 *
b101111111 1
b10000000 .
b10000000 5
b1010000000000000000000000000000000000000000000000000000000000 -
1"
#893750
0"
#900000
b111000011001010 &
b111000011001010 4
b11110010000010 %
b11110010000010 8
b1100000000000000000000000000000000000000000000000000000000000 -
b111011000101101 ,
b11000100101001 0
b101011111 *
b101011111 1
b10100000 .
b10100000 5
1"
#906250
0"
#912500
b110101001010000 &
b110101001010000 4
b100011101000110 %
b100011101000110 8
b111000011001010 ,
b11110010000010 0
b100111111 *
b100111111 1
b11000000 .
b11000000 5
b1110000000000000000000000000000000000000000000000000000000000 -
1"
#918750
0"
#925000
b110001011010001 &
b110001011010001 4
b101000101011001 %
b101000101011001 8
b10000000000000000000000000000000000000000000000000000000000000 -
b110101001010000 ,
b100011101000110 0
b100011111 *
b100011111 1
b11100000 .
b11100000 5
1"
#931250
0"
#937500
b101101001011110 &
b101101001011110 4
b101101010100101 %
b101101010100101 8
b110001011010001 ,
b101000101011001 0
b11111111 *
b11111111 1
b100000000 .
b100000000 5
b10010000000000000000000000000000000000000000000000000000000000 -
1"
#943750
0"
#950000
b101000100001100 &
b101000100001100 4
b110001100010001 %
b110001100010001 8
b10100000000000000000000000000000000000000000000000000000000000 -
b101101001011110 ,
b101101010100101 0
b11011111 *
b11011111 1
b100100000 .
b100100000 5
1"
#956250
0"
#962500
b100011011110010 &
b100011011110010 4
b110101010001000 %
b110101010001000 8
b101000100001100 ,
b110001100010001 0
b10111111 *
b10111111 1
b101000000 .
b101000000 5
b10110000000000000000000000000000000000000000000000000000000000 -
1"
#968750
0"
#975000
b11110000101001 &
b11110000101001 4
b111000011111001 %
b111000011111001 8
b11000000000000000000000000000000000000000000000000000000000000 -
b100011011110010 ,
b110101010001000 0
b10011111 *
b10011111 1
b101100000 .
b101100000 5
1"
#981250
0"
#987500
b11000011001100 &
b11000011001100 4
b111011001010011 %
b111011001010011 8
b11110000101001 ,
b111000011111001 0
b1111111 *
b1111111 1
b110000000 .
b110000000 5
b11010000000000000000000000000000000000000000000000000000000000 -
1"
#993750
0"
#1000000
b10010011110111 &
b10010011110111 4
b111101010001010 %
b111101010001010 8
b11100000000000000000000000000000000000000000000000000000000000 -
b11000011001100 ,
b111011001010011 0
b1011111 *
b1011111 1
b110100000 .
b110100000 5
1"
#1006250
0"
#1012500
b1100011000111 &
b1100011000111 4
b111110110010011 %
b111110110010011 8
b10010011110111 ,
b111101010001010 0
b111111 *
b111111 1
b111000000 .
b111000000 5
b11110000000000000000000000000000000000000000000000000000000000 -
1"
#1018750
0"
#1025000
b110001011001 &
b110001011001 4
b111111101100110 %
b111111101100110 8
b100000000000000000000000000000000000000000000000000000000000000 -
b1100011000111 ,
b111110110010011 0
b11111 *
b11111 1
b111100000 .
b111100000 5
1"
#1031250
0"
#1037500
b110010 &
b110010 4
b111111111111110 %
b111111111111110 8
b110001011001 ,
b111111101100110 0
b0 *
b0 1
b111111111 .
b111111111 5
b1 +
b100010000000000000000000000000000000000000000000000000000000000 -
1"
#1043750
0"
#1050000
b110010111101 &
b110010111101 4
b111111101011100 %
b111111101011100 8
b100100000000000000000000000000000000000000000000000000000000000 -
b110010 ,
b111111111111110 0
b11 +
b100000 *
b100000 1
b111011111 .
b111011111 5
1"
#1056250
0"
#1062500
b1100100101001 &
b1100100101001 4
b111110101111111 %
b111110101111111 8
b1111001101000011 ,
b111111101011100 0
b1000000 *
b1000000 1
b110111111 .
b110111111 5
b100110000000000000000000000000000000000000000000000000000000000 -
1"
#1068750
0"
#1075000
b10010101010111 &
b10010101010111 4
b111101001101101 %
b111101001101101 8
b101000000000000000000000000000000000000000000000000000000000000 -
b1110011011010111 ,
b111110101111111 0
b1100000 *
b1100000 1
b110011111 .
b110011111 5
1"
#1081250
0"
#1087500
b11000100101001 &
b11000100101001 4
b111011000101101 %
b111011000101101 8
b1101101010101001 ,
b111101001101101 0
b10000000 *
b10000000 1
b101111111 .
b101111111 5
b101010000000000000000000000000000000000000000000000000000000000 -
1"
#1093750
0"
#1100000
b11110010000010 &
b11110010000010 4
b111000011001010 %
b111000011001010 8
b101100000000000000000000000000000000000000000000000000000000000 -
b1100111011010111 ,
b111011000101101 0
b10100000 *
b10100000 1
b101011111 .
b101011111 5
1"
#1106250
0"
#1112500
b100011101000110 &
b100011101000110 4
b110101001010000 %
b110101001010000 8
b1100001101111110 ,
b111000011001010 0
b11000000 *
b11000000 1
b100111111 .
b100111111 5
b101110000000000000000000000000000000000000000000000000000000000 -
1"
#1118750
0"
#1125000
b101000101011001 &
b101000101011001 4
b110001011010001 %
b110001011010001 8
b110000000000000000000000000000000000000000000000000000000000000 -
b1011100010111010 ,
b110101001010000 0
b11100000 *
b11100000 1
b100011111 .
b100011111 5
1"
#1131250
0"
#1137500
b101101010100101 &
b101101010100101 4
b101101001011110 %
b101101001011110 8
b1010111010100111 ,
b110001011010001 0
b100000000 *
b100000000 1
b11111111 .
b11111111 5
b110010000000000000000000000000000000000000000000000000000000000 -
1"
#1143750
0"
#1150000
b110001100010001 &
b110001100010001 4
b101000100001100 %
b101000100001100 8
b110100000000000000000000000000000000000000000000000000000000000 -
b1010010101011011 ,
b101101001011110 0
b100100000 *
b100100000 1
b11011111 .
b11011111 5
1"
#1156250
0"
#1162500
b110101010001000 &
b110101010001000 4
b100011011110010 %
b100011011110010 8
b1001110011101111 ,
b101000100001100 0
b101000000 *
b101000000 1
b10111111 .
b10111111 5
b110110000000000000000000000000000000000000000000000000000000000 -
1"
#1168750
0"
#1175000
b111000011111001 &
b111000011111001 4
b11110000101001 %
b11110000101001 8
b111000000000000000000000000000000000000000000000000000000000000 -
b1001010101111000 ,
b100011011110010 0
b101100000 *
b101100000 1
b10011111 .
b10011111 5
1"
#1181250
0"
#1187500
b111011001010011 &
b111011001010011 4
b11000011001100 %
b11000011001100 8
b1000111100000111 ,
b11110000101001 0
b110000000 *
b110000000 1
b1111111 .
b1111111 5
b111010000000000000000000000000000000000000000000000000000000000 -
1"
#1193750
0"
#1200000
b111101010001010 &
b111101010001010 4
b10010011110111 %
b10010011110111 8
b111100000000000000000000000000000000000000000000000000000000000 -
b1000100110101101 ,
b11000011001100 0
b110100000 *
b110100000 1
b1011111 .
b1011111 5
1"
#1206250
0"
