1bitSDRLattice/Testbenches/CIC/hdl/CIC.v
/*
-----------------------------------------------------------------------------
Module: CIC
Description:
This module implements a Cascaded Integrator-Comb (CIC) filter, which is commonly used for decimation (reducing the sampling rate) and interpolation (increasing the sampling rate) in digital signal processing.

Inputs:
- clk: Clock signal.
- Gain: 8-bit gain control signal.
- d_in: 12-bit signed input data signal.

Outputs:
- d_out: 12-bit signed output data signal.
- d_clk: Output clock signal for the decimated data.

Parameters:
- width: Bit width for internal registers (default is 64).
- decimation_ratio: Decimation factor (default is 16).

Bit Width Calculation to Avoid Overflow:
For a Q-stage CIC decimation-by-D filter (diff delay = 1), overflow errors are avoided if the number of integrator and comb register bit widths is at least:

    register bit widths = number of bits in x(n) + {Q * log2(D)}

Where:
- x(n) is the input to the CIC filter.
- {k} means rounding up to the next larger integer if k is not an integer.

For example, if a 3-stage CIC decimation filter accepts one-bit binary input words from a sigma-delta A/D converter and the decimation factor is D = 64, binary overflow errors are avoided if the three integrator and three comb registers' bit widths are no less than:

    register bit widths = 1 + {3 * log2(64)} = 1 + 18 = 19 bits.

For a 5-stage CIC decimation filter with a decimation factor of 16384 (14 bits):

    register bit widths = 1 + 5 * 14 = 71 bits.

-----------------------------------------------------------------------------
*/

module CIC #(
    parameter int width = 64,
    parameter int decimation_ratio = 16
)(
    input wire clk,
    input wire [7:0] Gain,
    input wire signed [11:0] d_in,
    output reg signed [11:0] d_out,
    output reg d_clk
);

    // Internal registers
    reg signed [width-1:0] d_tmp, d_d_tmp;
    reg signed [width-1:0] d1, d2, d3, d4, d5;
    reg signed [width-1:0] d6, d_d6, d7, d_d7, d8, d_d8, d9, d_d9, d10;
    reg signed [width-1:0] d_scaled;
    reg [15:0] count;
    reg v_comb;  // Valid signal for comb section running at output rate
    reg d_clk_tmp;

    // Integrator section
    always @(posedge clk) begin
        d1 <= d_in + d1;
        d2 <= d1 + d2;
        d3 <= d2 + d3;
        d4 <= d3 + d4;
        d5 <= d4 + d5;

        // Decimation
        if (count == decimation_ratio - 1) begin
            count <= 16'b0;
            d_tmp <= d5;
            d_clk_tmp <= 1'b1;
            v_comb <= 1'b1;
        end else if (count == decimation_ratio >> 1) begin
            d_clk_tmp <= 1'b0;
            count <= count + 16'd1;
            v_comb <= 1'b0;
        end else begin
            count <= count + 16'd1;
            v_comb <= 1'b0;
        end
    end

    // Comb section running at output rate
    always @(posedge clk) begin
        d_clk <= d_clk_tmp;

        if (v_comb) begin
            // Comb section
            d_d_tmp <= d_tmp;
            d6 <= d_tmp - d_d_tmp;
            d_d6 <= d6;
            d7 <= d6 - d_d6;
            d_d7 <= d7;
            d8 <= d7 - d_d7;
            d_d8 <= d8;
            d9 <= d8 - d_d8;
            d_d9 <= d9;
            d10 <= d9 - d_d9;

            d_scaled <= d10;
            d_out <= d10 >>> (width - 12 - Gain);
        end
    end

    //----------------------------- 
    // For simulation only
    //----------------------------- 
    initial begin
        $dumpfile("CIC_waves.vcd");
        $dumpvars;
    end
endmodule

/*
-----------------------------------------------------------------------------
Version History:
-----------------------------------------------------------------------------
 2024/5/26 TH: initial creation    
 2024/5/26 TH: revision
*/

1bitSDRLattice/Testbenches/CIC/CIC_waves.vcd
$date
	Wed Jun 12 16:06:08 2024
$end
$version
	Icarus Verilog
$end
$timescale
	1ps
$end
$scope module CIC $end
$var wire 8 ! Gain [7:0] $end
$var wire 1 " clk $end
$var wire 12 # d_in [11:0] $end
$var parameter 32 $ decimation_ratio $end
$var parameter 32 % width $end
$var reg 16 & count [15:0] $end
$var reg 64 ' d1 [63:0] $end
$var reg 64 ( d10 [63:0] $end
$var reg 64 ) d2 [63:0] $end
$var reg 64 * d3 [63:0] $end
$var reg 64 + d4 [63:0] $end
$var reg 64 , d5 [63:0] $end
$var reg 64 - d6 [63:0] $end
$var reg 64 . d7 [63:0] $end
$var reg 64 / d8 [63:0] $end
$var reg 64 0 d9 [63:0] $end
$var reg 1 1 d_clk $end
$var reg 1 2 d_clk_tmp $end
$var reg 64 3 d_d6 [63:0] $end
$var reg 64 4 d_d7 [63:0] $end
$var reg 64 5 d_d8 [63:0] $end
$var reg 64 6 d_d9 [63:0] $end
$var reg 64 7 d_d_tmp [63:0] $end
$var reg 12 8 d_out [11:0] $end
$var reg 64 9 d_scaled [63:0] $end
$var reg 64 : d_tmp [63:0] $end
$var reg 1 ; v_comb $end
$upscope $end
$enddefinitions $end
$comment Show the parameter values. $end
$dumpall
b1000000 %
b10000 $
$end
#0
$dumpvars
0;
b0 :
b0 9
b0 8
b0 7
b0 6
b0 5
b0 4
b0 3
02
01
b0 0
b0 /
b0 .
b0 -
b0 ,
b0 +
b0 *
b0 )
b0 (
b1111101000 '
b1 &
b1111101000 #
1"
b1 !
$end
#6250
0"
#12500
b10 &
b1111101000 )
b11111010000 '
1"
#18750
0"
#25000
b11 &
b1111101000 *
b101110111000 )
b101110111000 '
1"
#31250
0"
#37500
b100 &
b1111101000 +
b111110100000 *
b1011101110000 )
b111110100000 '
1"
#43750
0"
#50000
b101 &
b1111101000 ,
b1001110001000 +
b10011100010000 *
b10011100010000 )
b1001110001000 '
1"
#56250
0"
#62500
b110 &
b1011101110000 ,
b11101010011000 +
b100111000100000 *
b11101010011000 )
b1011101110000 '
1"
#68750
0"
#75000
b111 &
b101001000001000 ,
b1000100010111000 +
b1000100010111000 *
b101001000001000 )
b1101101011000 '
1"
#81250
0"
#87500
b1000 &
b1101101011000000 ,
b10001000101110000 +
b1101101011000000 *
b110110101100000 )
b1111101000000 '
1"
#93750
0"
#100000
b1001 &
b11110110000110000 ,
b11110110000110000 +
b10100100000100000 *
b1000110010100000 )
b10001100101000 '
1"
#106250
0"
#112500
b1010 &
b111101100001100000 ,
b110011010001010000 +
b11101010011000000 *
b1010111111001000 )
b10011100010000 '
1"
#118750
0"
#125000
b1011 &
b1110000110010110000 ,
b1010000100100010000 +
b101000010010001000 *
b1101011011011000 )
b10101011111000 '
1"
#131250
0"
#137500
b1100 &
b11000001010111000000 ,
b1111000110110011000 +
b110101101101100000 *
b10000000111010000 )
b10111011100000 '
1"
#143750
0"
#150000
b1101 &
b100111010001101011000 ,
b10101110100011111000 +
b1000101110100110000 *
b10011000010110000 )
b11001011001000 '
1"
#156250
0"
#162500
b1110 &
b111101000110001010000 ,
b11110100011000101000 +
b1011000110111100000 *
b10110001101111000 )
b11011010110000 '
1"
#168750
0"
#175000
b1111 &
b1011011101001001111000 ,
b101001101010000001000 +
b1101111000101011000 *
b11001101000101000 )
b11101010011000 '
1"
#181250
0"
#187500
1;
12
b1011011101001001111000 :
b0 &
b10000101010011010000000 ,
b110111100010101100000 +
b10001000101110000000 *
b11101010011000000 )
b11111010000000 '
1"
#193750
0"
#200000
0;
b1 &
b10111100110101111100000 ,
b1001000101000011100000 +
b10100110000001000000 *
b100001001101000000 )
b100001001101000 '
b1011011101001001111000 -
b1011011101001001111000 7
11
1"
#206250
0"
#212500
b10 &
b100000101011110011000000 ,
b1011101011000100100000 +
b11000111001110000000 *
b100101010110101000 )
b100011001010000 '
1"
#218750
0"
#225000
b11 &
b101100010110110111100000 ,
b1110110010010010100000 +
b11101100100100101000 *
b101001101111111000 )
b100101000111000 '
1"
#231250
0"
#237500
b100 &
b111011001001001010000000 ,
b10010011110110111001000 +
b100010110010100100000 *
b101110011000110000 )
b100111000100000 '
1"
#243750
0"
#250000
b101 &
b1001101101000000001001000 ,
b10110110101001011101000 +
b101000100101101010000 *
b110011010001010000 )
b101001000001000 '
1"
#256250
0"
#262500
b110 &
b1100100011101001100110000 ,
b11011111001111000111000 +
b101110111111110100000 *
b111000011001011000 )
b101010111110000 '
1"
#268750
0"
#275000
b111 &
b10000000010111000101101000 ,
b100001110001110111011000 +
b110110000010111111000 *
b111101110001001000 )
b101100111011000 '
1"
#281250
0"
#287500
b1000 &
b10100010001000111101000000 ,
b101000100010001111010000 +
b111101110001001000000 *
b1000011011000100000 )
b101110111000000 '
1"
#293750
0"
#300000
b1001 &
02
b11001010101011001100010000 ,
b110000010000011000010000 +
b1000110001100001100000 *
b1001001001111100000 )
b110000110101000 '
1"
#306250
0"
#312500
01
b1010 &
b11111010111011100100100000 ,
b111001000001111001110000 +
b1001111010110001000000 *
b1001111010110001000 )
b110010110010000 '
1"
#318750
0"
#325000
b1011 &
b100110011111101011110010000 ,
b1000010111100101010110000 +
b1011001010000111001000 *
b1010101101100011000 )
b110100101111000 '
1"
#331250
0"
#337500
b1100 &
b101110110111010001001000000 ,
b1001110000110110001111000 +
b1100011111110011100000 *
b1011100010010010000 )
b110110101100000 '
1"
#343750
0"
#350000
b1101 &
b111000101000000111010111000 ,
b1011010100110100101011000 +
b1101111100000101110000 *
b1100011000111110000 )
b111000101001000 '
1"
#356250
0"
#362500
b1110 &
b1000011111100111100000010000 ,
b1101000100010101011001000 +
b1111011111001101100000 *
b1101010001100111000 )
b111010100110000 '
1"
#368750
0"
#375000
b1111 &
b1010001000001010001011011000 ,
b1111000000001111000101000 +
b10001001001011010011000 *
b1110001100001101000 )
b111100100011000 '
1"
#381250
0"
#387500
1;
12
b1010001000001010001011011000 :
b0 &
b1100000000001100000100000000 ,
b10001001001011010011000000 +
b10010111010111100000000 *
b1111001000110000000 )
b111110100000000 '
1"
#393750
0"
#400000
0;
b1 &
b1110001001010111010111000000 ,
b10011100000110001111000000 +
b10100110100000010000000 *
b10000000111010000000 )
b1000000011101000 '
b1011011101001001111000 .
b1011011101001001111000 3
b1001111100101101000001100000 -
b1010001000001010001011011000 7
11
1"
#406250
0"
#412500
b10 &
b10000100101011101100110000000 ,
b10110000111010010001000000 +
b10110110100111100000000 *
b10001000111101101000 )
b1000010011010000 '
1"
#418750
0"
#425000
b11 &
b10011010110010111110111000000 ,
b11000111101111001101000000 +
b11000111101111001101000 *
b10010001010000111000 )
b1000100010111000 '
1"
#431250
0"
#437500
b100 &
b10110011110000111000100000000 ,
b11100000101101000110101000 +
b11011001111001010100000 *
b10011001110011110000 )
b1000110010100000 '
1"
#443750
0"
#450000
b101 &
b11001111110110100001010101000 ,
b11111011111100010001001000 +
b11101101000111110010000 *
b10100010100110010000 )
b1001000010001000 '
1"
#456250
0"
#462500
b110 &
b11101111010110000011011110000 ,
b100011001100101001111011000 +
b100000001011100100100000 *
b10101011101000011000 )
b1001010001110000 '
1"
#468750
0"
#475000
b111 &
b100010010100010101101011001000 ,
b100111001110000110011111000 +
b100010110111001100111000 *
b10110100111010001000 )
b1001100001011000 '
1"
#481250
0"
#487500
b1000 &
b100111001110000110011111000000 ,
b101011100101000000000110000 +
b100101101100000111000000 *
b10111110011011100000 )
b1001110001000000 '
1"
#493750
0"
#500000
b1001 &
02
b101100101010101110011111110000 ,
b110000010010100000111110000 +
b101000101010100010100000 *
b11001000001100100000 )
b1010000000101000 '
1"
#506250
0"
#512500
01
b1010 &
b110010101101000010100111100000 ,
b110101010111110101010010000 +
b101011110010101111000000 *
b11010010001101001000 )
b1010010000010000 '
1"
#518750
0"
#525000
b1011 &
b111001011000000001010001110000 ,
b111010110110001011001010000 +
b101111000100111100001000 *
b11011100011101011000 )
b1010011111111000 '
1"
#531250
0"
#537500
b1100 &
b1000000101110110010101011000000 ,
b1000000101110110010101011000 +
b110010100001011001100000 *
b11100110111101010000 )
b1010101111100000 '
1"
#543750
0"
#550000
b1101 &
b1001000110100101001000000011000 ,
b1000111000010111101110111000 +
b110110001000010110110000 *
b11110001101100110000 )
b1010111111001000 '
1"
#556250
0"
#562500
b1110 &
b1010001101101000000101111010000 ,
b1001101110100000000101101000 +
b111001111010000011100000 *
b11111100101011111000 )
b1011001110110000 '
1"
#568750
0"
#575000
b1111 &
b1011011011011100000110100111000 ,
b1010101000011010001001001000 +
b111101110110101111011000 *
b100000111111010101000 )
b1011011110011000 '
1"
#581250
0"
#587500
1;
12
b1011011011011100000110100111000 :
b0 &
b1100110000011111010111110000000 ,
b1011100110010000111000100000 +
b1000001111110101010000000 *
b100010011011001000000 )
b1011101110000000 '
1"
#593750
0"
#600000
0;
b1 &
b1110001101010001011110110100000 ,
b1100101000001111100010100000 +
b1000110010010000011000000 *
b100011111000111000000 )
b1011111101101000 '
b1011011101001001111000 /
b1011011101001001111000 4
b1001110001001111110111101000 .
b1001111100101101000001100000 3
b1010001010011010110101001100000 -
b1011011011011100000110100111000 7
11
1"
#606250
0"
#612500
b10 &
b1111110010010011011011001000000 ,
b1101101110100001100101100000 +
b1001010110001001010000000 *
b100101011000100101000 )
b1100001101010000 '
1"
