New Modules/CORDIC/CORDIC-Comb2/cordic.sv
//==========================================================================
// Copyright (C) 2024 Chili.CHIPS*ba
//--------------------------------------------------------------------------
//                      PROPRIETARY INFORMATION
//
// The information contained in this file is the property of CHILI CHIPS LLC.
// Except as specifically authorized in writing by CHILI CHIPS LLC, the holder
// of this file: (1) shall keep all information contained herein confidential;
// and (2) shall protect the same in whole or in part from disclosure and
// dissemination to all third parties; and (3) shall use the same for operation
// and maintenance purposes only.
//--------------------------------------------------------------------------
// Description: 
//   Test code for Tarik's MSEE, based on:
//      https://zipcpu.com/dsp/2017/08/30/cordic.html
//==========================================================================

module cordic #(
   parameter int IW = 13, // Width of Input Word
   parameter int OW = 13, // Width of Output Word
   parameter int WW = 16, // Width of Word of data
   parameter int PW = 20  // Width of Phase
)(

 //inputs
   input  logic                 i_clk,  
   input  logic                 i_reset,
   input  logic signed [IW-1:0] i_xval, 
   input  logic signed [IW-1:0] i_yval, 
   input  logic        [PW-1:0] i_phase,

 //outputs
   output logic signed [OW-1:0] o_xval, 
   output logic signed [OW-1:0] o_yval, 
   output logic        [PW-1:0] o_phval 
);
   
   localparam int NSTAGES = 16; // Number of Stages

   // Declare variables for all of the separate stages
   logic signed [WW-1:0] e_xval, e_yval; 

   logic signed [WW-1:0] xv [NSTAGES+1];
   logic signed [WW-1:0] yv [NSTAGES+1];
   logic        [PW-1:0] ph [NSTAGES+1];
   logic        [PW-1:0] cordic_angle[NSTAGES];

   logic        [WW-1:0] pre_xval, pre_yval;

   always_comb begin: _cordic_comb

      //--Step1: Sign extend our inputs
      e_xval = { i_xval[IW-1], i_xval, {(WW-IW-1){1'b0}} };
      e_yval = { i_yval[IW-1], i_yval, {(WW-IW-1){1'b0}} };


      //--Step2: Pre-CORDIC rotation
      unique case(i_phase[PW-1 -: 3])
         3'd0: begin     // 0 .. 45, No change
              xv[0] = e_xval;
              yv[0] = e_yval;
              ph[0] = i_phase;
         end
         3'd1: begin     // 45 .. 90
              xv[0] = -e_yval;
              yv[0] = e_xval;
              ph[0] = i_phase - 20'h40000;
         end
         3'd2: begin     // 90 .. 135
              xv[0] = -e_yval;
              yv[0] = e_xval;
              ph[0] = i_phase - 20'h40000;
         end
         3'd3: begin     // 135 .. 180
              xv[0] = -e_xval;
              yv[0] = -e_yval;
              ph[0] = i_phase - 20'h80000;
         end
         3'd4: begin     // 180 .. 225
              xv[0] = -e_xval;
              yv[0] = -e_yval;
              ph[0] = i_phase - 20'h80000;
         end
         3'd5: begin     // 225 .. 270
              xv[0] = e_yval;
              yv[0] = -e_xval;
              ph[0] = i_phase - 20'hc0000;
         end
         3'd6: begin    // 270 .. 315
              xv[0] = e_yval;
              yv[0] = -e_xval;
              ph[0] = i_phase - 20'hc0000;
         end
         default: begin  // 315 .. 360, No change
              xv[0] = e_xval;
              yv[0] = e_yval;
              ph[0] = i_phase;
           end
      endcase


   //--Step3: CORDIC rotations
      cordic_angle[ 0] = 20'h1_2e40; // 26.565051 deg
      cordic_angle[ 1] = 20'h0_9fb3; // 14.036243 deg
      cordic_angle[ 2] = 20'h0_5111; //  7.125016 deg
      cordic_angle[ 3] = 20'h0_28b0; //  3.576334 deg
      cordic_angle[ 4] = 20'h0_145d; //  1.789911 deg
      cordic_angle[ 5] = 20'h0_0a2f; //  0.895174 deg
      cordic_angle[ 6] = 20'h0_0517; //  0.447614 deg
      cordic_angle[ 7] = 20'h0_028b; //  0.223811 deg
      cordic_angle[ 8] = 20'h0_0145; //  0.111906 deg
      cordic_angle[ 9] = 20'h0_00a2; //  0.055953 deg
      cordic_angle[10] = 20'h0_0051; //  0.027976 deg
      cordic_angle[11] = 20'h0_0028; //  0.013988 deg
      cordic_angle[12] = 20'h0_0014; //  0.006994 deg
      cordic_angle[13] = 20'h0_000a; //  0.003497 deg
      cordic_angle[14] = 20'h0_0005; //  0.001749 deg
      cordic_angle[15] = 20'h0_0002; //  0.000874 deg

      for (int i=0; i<NSTAGES; i++) begin

         // Do nothing but move our outputs forward one stage
         if (cordic_angle[i] == 0 || i > WW) begin
            xv[i+1] = xv[i];
            yv[i+1] = yv[i];
            ph[i+1] = ph[i];
         end

         // if phase is negative, rotate clockwise
         if (ph[i][PW-1] == 1'b1) begin
            xv[i+1] = xv[i] + (yv[i] >>> (i+1));
            yv[i+1] = yv[i] - (xv[i] >>> (i+1));
            ph[i+1] = ph[i] + cordic_angle[i];
         end
          
         // if phase is positive, rotate counter-clockwise
         else begin   
            xv[i+1] = xv[i] - (yv[i] >>> (i+1));
            yv[i+1] = yv[i] + (xv[i] >>> (i+1));
            ph[i+1] = ph[i] - cordic_angle[i];
         end
      end // for (int i=0; i<NSTAGES; i++)


      //--Step4: Round our result towards even
      pre_xval = xv[NSTAGES] 
               + $signed({ 
                   {OW{1'b0}},
                    xv[NSTAGES][WW-OW],
                    {WW-OW-1{~xv[NSTAGES][WW-OW]}} 
                 });

      pre_yval = yv[NSTAGES] 
               + $signed({ 
                   {OW{1'b0}},
                    yv[NSTAGES][WW-OW],
                   {WW-OW-1{~yv[NSTAGES][WW-OW]}} 
                 });

   end: _cordic_comb


  //--Step5: Output registers
   always_ff @(posedge i_clk) begin: _cordic_ff
      if (i_reset) begin
         o_xval <= '0;
         o_yval <= '0;
      end 
      else begin
         o_xval <= pre_xval[(WW-1):(WW-OW)];
	 o_yval <= pre_yval[(WW-1):(WW-OW)];
      end
   end: _cordic_ff


  //----------------------------- 
  // For sim only
  //----------------------------- 
   initial begin
      $dumpfile("cordic_waves.vcd");
      $dumpvars;
   end
   
endmodule: cordic

/*
-----------------------------------------------------------------------------
Version History:
-----------------------------------------------------------------------------
 2024/4/14 TH: initial creation    
 2024/4/15 TH: added rest of CORDIC structure
*/

New Modules/CORDIC/CORDIC-Comb2/cordic_waves.vcd
$date
	Thu Apr 18 21:13:43 2024
$end
$version
	Icarus Verilog
$end
$timescale
	1ps
$end
$scope module cordic $end
$var wire 1 ! i_clk $end
$var wire 20 " i_phase [19:0] $end
$var wire 1 # i_reset $end
$var wire 13 $ i_xval [12:0] $end
$var wire 13 % i_yval [12:0] $end
$var parameter 32 & IW $end
$var parameter 32 ' NSTAGES $end
$var parameter 32 ( OW $end
$var parameter 32 ) PW $end
$var parameter 32 * WW $end
$var reg 16 + e_xval [15:0] $end
$var reg 16 , e_yval [15:0] $end
$var reg 20 - o_phval [19:0] $end
$var reg 13 . o_xval [12:0] $end
$var reg 13 / o_yval [12:0] $end
$var reg 16 0 pre_xval [15:0] $end
$var reg 16 1 pre_yval [15:0] $end
$scope begin _cordic_comb $end
$scope begin $ivl_for_loop0 $end
$var integer 32 2 i [31:0] $end
$upscope $end
$upscope $end
$scope begin _cordic_ff $end
$upscope $end
$upscope $end
$enddefinitions $end
$comment Show the parameter values. $end
$dumpall
b10000 *
b10100 )
b1101 (
b10000 '
b1101 &
$end
#0
$dumpvars
b10000 2
bx 1
bx 0
b0 /
b0 .
bx -
bz00 ,
bz00 +
bz %
bz $
0#
bz "
1!
$end
#6250
0!
#12500
b11 1
b100101010001000 0
b10000 2
b0 ,
b11111111111100 +
b0 "
b0 %
b111111111111 $
bx /
bx .
1!
#18750
0!
#25000
b0 /
b100101010001 .
1!
#31250
0!
#37500
b100011000110 1
b100100111111110 0
b10000 2
b100110011001101 "
1!
#43750
0!
#50000
b1000101101000 1
b100100001110011 0
b10000 2
b1001100110011010 "
b100011000 /
b100100111111 .
1!
#56250
0!
#62500
b1100111001101 1
b100010111101001 0
b10000 2
b1110011001100111 "
b1000101101 /
b100100001110 .
1!
#68750
0!
#75000
b10000111011010 1
b100001001100100 0
b10000 2
b10011001100110100 "
b1100111001 /
b100010111101 .
1!
#81250
0!
#87500
b10100101100111 1
b11110111110111 0
b10000 2
b11000000000000001 "
b10000111011 /
b100001001100 .
1!
#93750
0!
#100000
b11000001100100 1
b11100010101110 0
b10000 2
b11100110011001110 "
b10100101100 /
b11110111110 .
1!
#106250
0!
#112500
b11011010111100 1
b11001010010101 0
b10000 2
b100001100110011011 "
b11000001100 /
b11100010101 .
1!
#118750
0!
#125000
b11110001001001 1
b10101111001111 0
b10000 2
b100110011001101000 "
b11011010111 /
b11001010010 .
1!
#131250
0!
#137500
b100000100000011 1
b10010001101100 0
b10000 2
b101011001100110101 "
b11110001001 /
b10101111001 .
1!
#143750
0!
#150000
b100010011011100 1
b1110010000101 0
b10000 2
b110000000000000010 "
b100000100000 /
b10010001101 .
1!
#156250
0!
#162500
b100011110110110 1
b1010000111100 0
b10000 2
b110100110011001111 "
b100010011011 /
b1110010000 .
1!
#168750
0!
#175000
b100100110010101 1
b101110101110 0
b10000 2
b111001100110011100 "
b100011110110 /
b1010000111 .
1!
#181250
0!
#187500
b100101001110100 1
b1011110010 0
b10000 2
b111110011001101001 "
b100100110010 /
b101110101 .
1!
#193750
0!
#200000
b100101001000111 1
b1111101000101100 0
b10000 2
b1000011001100110110 "
b100101001110 /
b1011110 .
1!
#206250
0!
#212500
b100100100010111 1
b1111000101111010 0
b10000 2
b1001000000000000011 "
b100101001000 /
b1111101000101 .
1!
#218750
0!
#225000
b100011011100010 1
b1110100011111100 0
b10000 2
b1001100110011010000 "
b100100100010 /
b1111000101111 .
1!
#231250
0!
#237500
b100001110101101 1
b1110000011010101 0
b10000 2
b1010001100110011101 "
b100011011100 /
b1110100011111 .
1!
#243750
0!
#250000
b11111110001010 1
b1101100100010011 0
b10000 2
b1010110011001101010 "
b100001110101 /
b1110000011010 .
1!
#256250
0!
#262500
b11101010000100 1
b1101000111100100 0
b10000 2
b1011011001100110111 "
b11111110001 /
b1101100100010 .
1!
#268750
0!
#275000
b11010010110011 1
b1100101101010011 0
b10000 2
b1100000000000000100 "
b11101010000 /
b1101000111100 .
1!
#281250
0!
#287500
b10111000100011 1
b1100010110000000 0
b10000 2
b1100100110011010001 "
b11010010110 /
b1100101101010 .
1!
#293750
0!
#300000
b10011011110001 1
b1100000001111110 0
b10000 2
b1101001100110011110 "
b10111000100 /
b1100010110000 .
1!
#306250
0!
#312500
b1111100110100 1
b1011110001010110 0
b10000 2
b1101110011001101011 "
b10011011110 /
b1100000001111 .
1!
#318750
0!
#325000
b1011100000111 1
b1011100100101000 0
b10000 2
b1110011001100111000 "
b1111100110 /
b1011110001010 .
1!
#331250
0!
#337500
b111010001010 1
b1011011011110001 0
b10000 2
b1111000000000000101 "
b1011100000 /
b1011100100101 .
1!
#343750
0!
#350000
b10111011110 1
b1011010110111100 0
b10000 2
b1111100110011010010 "
b111010001 /
b1011011011110 .
1!
#356250
0!
#362500
b1111110100010101 1
b1011010110010010 0
b10000 2
b10000001100110011111 "
b10111011 /
b1011010110111 .
1!
#368750
0!
#375000
b1111010001011110 1
b1011011001101001 0
b10000 2
b10000110011001101100 "
b1111110100010 /
b1011010110010 .
1!
#381250
0!
#387500
b1110101111001001 1
b1011100001010000 0
b10000 2
b10001011001100111001 "
b1111010001011 /
b1011011001101 .
1!
#393750
0!
#400000
b1110001101111100 1
b1011101100110001 0
b10000 2
b10010000000000000110 "
b1110101111001 /
b1011100001010 .
1!
#406250
0!
#412500
b1101101110011100 1
b1011111100000011 0
b10000 2
b10010100110011010011 "
b1110001101111 /
b1011101100110 .
1!
#418750
0!
#425000
b1101010000110110 1
b1100001111000001 0
b10000 2
b10011001100110100000 "
b1101101110011 /
b1011111100000 .
1!
#431250
0!
#437500
b1100110101110010 1
b1100100101001101 0
b10000 2
b10011110011001101101 "
b1101010000110 /
b1100001111000 .
1!
#443750
0!
#450000
b1100011101100001 1
b1100111110011101 0
b10000 2
b10100011001100111010 "
b1100110101110 /
b1100100101001 .
1!
#456250
0!
#462500
b1100001000001111 1
b1101011010100010 0
b10000 2
b10101000000000000111 "
b1100011101100 /
b1100111110011 .
1!
#468750
0!
#475000
b1011110110011110 1
b1101111000110100 0
b10000 2
b10101100110011010100 "
b1100001000001 /
b1101011010100 .
1!
#481250
0!
#487500
b1011101000011101 1
b1110011000111010 0
b10000 2
b10110001100110100001 "
b1011110110011 /
b1101111000110 .
1!
#493750
0!
#500000
b1011011110010011 1
b1110111010100001 0
b10000 2
b10110110011001101110 "
b1011101000011 /
b1110011000111 .
1!
#506250
0!
#512500
b1011011000000010 1
b1111011101000110 0
b10000 2
b10111011001100111011 "
b1011011110010 /
b1110111010100 .
1!
#518750
0!
#525000
b1011010110000001 1
b101 0
b10000 2
b11000000000000001000 "
b1011011000000 /
b1111011101000 .
1!
#531250
0!
#537500
b1011011000001000 1
b100011000100 0
b10000 2
b11000100110011010101 "
b1011010110000 /
b0 .
1!
#543750
0!
#550000
b1011011110010011 1
b1000101101000 0
b10000 2
b11001001100110100010 "
b1011011000001 /
b100011000 .
1!
#556250
0!
#562500
b1011101000011110 1
b1100111001111 0
b10000 2
b11001110011001101111 "
b1011011110010 /
b1000101101 .
1!
#568750
0!
#575000
b1011110110100011 1
b10000111010100 0
b10000 2
b11010011001100111100 "
b1011101000011 /
b1100111001 .
1!
#581250
0!
#587500
b1100001000010011 1
b10100101100101 0
b10000 2
b11011000000000001001 "
b1011110110100 /
b10000111010 .
1!
#593750
0!
#600000
b1100011101011001 1
b11000001101010 0
b10000 2
b11011100110011010110 "
b1100001000010 /
b10100101100 .
1!
#606250
0!
#612500
b1100110101110010 1
b11011010111000 0
b10000 2
b11100001100110100011 "
b1100011101011 /
b11000001101 .
1!
#618750
0!
#625000
b1101010000111000 1
b11110001001000 0
b10000 2
b11100110011001110000 "
b1100110101110 /
b11011010111 .
1!
#631250
0!
#637500
b1101101110011100 1
b100000100000101 0
b10000 2
b11101011001100111101 "
b1101010000111 /
b11110001001 .
1!
#643750
0!
#650000
b1110001110000010 1
b100010011011010 0
b10000 2
b11110000000000001010 "
b1101101110011 /
b100000100000 .
1!
#656250
0!
#662500
b1110101111001100 1
b100011110111001 0
b10000 2
b11110100110011010111 "
b1110001110000 /
b100010011011 .
1!
#668750
0!
#675000
b1111010001011001 1
b100100110100000 0
b10000 2
b11111001100110100100 "
b1110101111001 /
b100011110111 .
1!
#681250
0!
#687500
b1111110100010111 1
b100101001110011 0
b10000 2
b11111110011001110001 "
b1111010001011 /
b100100110100 .
1!
#693750
0!
#700000
b10111011100 1
b100101001001100 0
b10000 2
b11001100111110 "
b1111110100010 /
b100101001110 .
1!
#706250
0!
#712500
b111010001111 1
b100100100010101 0
b10000 2
b1000000000001011 "
b10111011 /
b100101001001 .
1!
#718750
0!
#725000
b1011100001100 1
b100011011011111 0
b10000 2
b1100110011011000 "
b111010001 /
b100100100010 .
1!
#731250
0!
#737500
b1111100110100 1
b100001110110001 0
b10000 2
b10001100110100101 "
b1011100001 /
b100011011011 .
1!
#743750
0!
#750000
b10011011110011 1
b11111110001001 0
b10000 2
b10110011001110010 "
b1111100110 /
b100001110110 .
1!
#756250
0!
#762500
b10111000100011 1
b11101010000111 0
b10000 2
b11011001100111111 "
b10011011110 /
b11111110001 .
1!
#768750
0!
#775000
b11010010110100 1
b11010010110010 0
b10000 2
b100000000000001100 "
b10111000100 /
b11101010000 .
1!
#781250
0!
#787500
b11101010000111 1
b10111000100011 0
b10000 2
b100100110011011001 "
b11010010110 /
b11010010110 .
1!
#793750
0!
#800000
b11111110001001 1
b10011011110011 0
b10000 2
b101001100110100110 "
b11101010000 /
b10111000100 .
1!
#806250
0!
#812500
b100001110110001 1
b1111100110001 0
b10000 2
b101110011001110011 "
b11111110001 /
b10011011110 .
1!
#818750
0!
#825000
b100011011011111 1
b1011100001001 0
b10000 2
b110011001101000000 "
b100001110110 /
b1111100110 .
1!
#831250
0!
#837500
b100100100010101 1
b111010001010 0
b10000 2
b111000000000001101 "
b100011011011 /
b1011100001 .
1!
#843750
0!
#850000
b100101001001100 1
b10111011001 0
b10000 2
b111100110011011010 "
b100100100010 /
b111010001 .
1!
#856250
0!
#862500
b100101001110110 1
b1111110100010011 0
b10000 2
b1000001100110100111 "
b100101001001 /
b10111011 .
1!
#868750
0!
#875000
b100100110011100 1
b1111010001010111 0
b10000 2
b1000110011001110100 "
b100101001110 /
b1111110100010 .
1!
#881250
0!
#887500
b100011110110101 1
b1110101111001001 0
b10000 2
b1001011001101000001 "
b100100110011 /
b1111010001010 .
1!
#893750
0!
#900000
b100010011011010 1
b1110001110000000 0
b10000 2
b1010000000000001110 "
b100011110110 /
b1110101111001 .
1!
#906250
0!
#912500
b100000100000011 1
b1101101110011001 0
b10000 2
b1010100110011011011 "
b100010011011 /
b1110001110000 .
1!
#918750
0!
#925000
b11110001001000 1
b1101010000110110 0
b10000 2
b1011001100110101000 "
b100000100000 /
b1101101110011 .
1!
#931250
0!
#937500
b11011010111000 1
b1100110101101110 0
b10000 2
b1011110011001110101 "
b11110001001 /
b1101010000110 .
1!
#943750
0!
#950000
b11000001101000 1
b1100011101011001 0
b10000 2
b1100011001101000010 "
b11011010111 /
b1100110101101 .
1!
#956250
0!
#962500
b10100101100101 1
b1100001000010000 0
b10000 2
b1101000000000001111 "
b11000001101 /
b1100011101011 .
1!
#968750
0!
#975000
b10000111010001 1
b1011110110100011 0
b10000 2
b1101100110011011100 "
b10100101100 /
b1100001000010 .
1!
#981250
0!
#987500
b1100111001010 1
b1011101000011110 0
b10000 2
b1110001100110101001 "
b10000111010 /
b1011110110100 .
1!
#993750
0!
#1000000
b1000101100100 1
b1011011110010011 0
b10000 2
b1110110011001110110 "
b1100111001 /
b1011101000011 .
1!
#1006250
0!
#1012500
b100010111111 1
b1011011000001000 0
b10000 2
b1111011001101000011 "
b1000101100 /
b1011011110010 .
1!
#1018750
0!
#1025000
b0 1
b1011010110000010 0
b10000 2
b10000000000000010000 "
b100010111 /
b1011011000001 .
1!
#1031250
0!
#1037500
b1111011101000001 1
b1011011000000101 0
b10000 2
b10000100110011011101 "
b0 /
b1011010110000 .
1!
#1043750
0!
#1050000
b1110111010100011 1
b1011011110001101 0
b10000 2
b10001001100110101010 "
b1111011101000 /
b1011011000000 .
1!
#1056250
0!
#1062500
b1110011000111000 1
b1011101000011101 0
b10000 2
b10001110011001110111 "
b1110111010100 /
b1011011110001 .
1!
#1068750
0!
#1075000
b1101111000110011 1
b1011110110011110 0
b10000 2
b10010011001101000100 "
b1110011000111 /
b1011101000011 .
1!
#1081250
0!
#1087500
b1101011010100000 1
b1100001000001111 0
b10000 2
b10011000000000010001 "
b1101111000110 /
b1011110110011 .
1!
#1093750
0!
#1100000
b1100111110011101 1
b1100011101100001 0
b10000 2
b10011100110011011110 "
b1101011010100 /
b1100001000001 .
1!
#1106250
0!
#1112500
b1100100101001111 1
b1100110101110000 0
b10000 2
b10100001100110101011 "
b1100111110011 /
b1100011101100 .
1!
#1118750
0!
#1125000
b1100001110111101 1
b1101010000111010 0
b10000 2
b10100110011001111000 "
b1100100101001 /
b1100110101110 .
1!
#1131250
0!
#1137500
b1011111100000000 1
b1101101110100010 0
b10000 2
b10101011001101000101 "
b1100001110111 /
b1101010000111 .
1!
#1143750
0!
#1150000
b1011101100101101 1
b1110001110000010 0
b10000 2
b10110000000000010010 "
b1011111100000 /
b1101101110100 .
1!
#1156250
0!
#1162500
b1011100001001100 1
b1110101111010000 0
b10000 2
b10110100110011011111 "
b1011101100101 /
b1110001110000 .
1!
#1168750
0!
#1175000
b1011011001101100 1
b1111010001100000 0
b10000 2
b10111001100110101100 "
b1011100001001 /
b1110101111010 .
1!
#1181250
0!
#1187500
b1011010110010010 1
b1111110100010111 0
b10000 2
b10111110011001111001 "
b1011011001101 /
b1111010001100 .
1!
#1193750
0!
#1200000
b1011010110111100 1
b10111100011 0
b10000 2
b11000011001101000110 "
b1011010110010 /
b1111110100010 .
1!
#1206250
0!
#1212500
b1011011011110001 1
b111010001111 0
b10000 2
b11001000000000010011 "
b1011010110111 /
b10111100 .
1!
#1218750
0!
#1225000
b1011100100101000 1
b1011100001110 0
b10000 2
b11001100110011100000 "
b1011011011110 /
b111010001 .
1!
#1231250
0!
#1237500
b1011110001010110 1
b1111100111000 0
b10000 2
b11010001100110101101 "
b1011100100101 /
b1011100001 .
1!
#1243750
0!
#1250000
b1100000001111110 1
b10011011110100 0
b10000 2
b11010110011001111010 "
b1011110001010 /
b1111100111 .
1!
#1256250
0!
#1262500
b1100010110000010 1
b10111000100110 0
b10000 2
b11011011001101000111 "
b1100000001111 /
b10011011110 .
1!
#1268750
0!
#1275000
b1100101101010101 1
b11010010110011 0
b10000 2
b11100000000000010100 "
b1100010110000 /
b10111000100 .
1!
#1281250
0!
#1287500
b1101000111100100 1
b11101010000110 0
b10000 2
b11100100110011100001 "
b1100101101010 /
b11010010110 .
1!
#1293750
0!
#1300000
b1101100100010111 1
b11111110001000 0
b10000 2
b11101001100110101110 "
b1101000111100 /
b11101010000 .
1!
#1306250
0!
#1312500
b1110000011010111 1
b100001110101111 0
b10000 2
b11101110011001111011 "
b1101100100010 /
b11111110001 .
1!
#1318750
0!
#1325000
b1110100100000000 1
b100011011100000 0
b10000 2
b11110011001101001000 "
b1110000011010 /
b100001110101 .
1!
#1331250
0!
#1337500
b1111000101111101 1
b100100100010111 0
b10000 2
b11111000000000010101 "
b1110100100000 /
b100011011100 .
1!
#1343750
0!
#1350000
b1111101000101110 1
b100101001000111 0
b10000 2
b11111100110011100010 "
b1111000101111 /
b100100100010 .
1!
#1356250
0!
#1362500
b1011110011 1
b100101001110100 0
b10000 2
b1100110101111 "
b1111101000101 /
b100101001000 .
1!
#1368750
0!
#1375000
b101110110000 1
b100100110010101 0
b10000 2
b110011001111100 "
b1011110 /
b100101001110 .
1!
#1381250
0!
#1387500
b1010001000000 1
b100011110110110 0
b10000 2
b1011001101001001 "
b101110110 /
b100100110010 .
1!
#1393750
0!
#1400000
b1110010000111 1
b100010011010111 0
b10000 2
b10000000000010110 "
b1010001000 /
b100011110110 .
1!
#1406250
0!
#1412500
b10010001110000 1
b100000100000001 0
b10000 2
b10100110011100011 "
b1110010000 /
b100010011010 .
1!
#1418750
0!
#1425000
b10101111010001 1
b11110001000111 0
b10000 2
b11001100110110000 "
b10010001110 /
b100000100000 .
1!
#1431250
0!
#1437500
b11001010011001 1
b11011010110111 0
b10000 2
b11110011001111101 "
b10101111010 /
b11110001000 .
1!
#1443750
0!
#1450000
b11100010101110 1
b11000001100100 0
b10000 2
b100011001101001010 "
b11001010011 /
b11011010110 .
1!
#1456250
0!
#1462500
b11110111110111 1
b10100101100111 0
b10000 2
b101000000000010111 "
b11100010101 /
b11000001100 .
1!
#1468750
0!
#1475000
b100001001100100 1
b10000111011000 0
b10000 2
b101100110011100100 "
b11110111110 /
b10100101100 .
1!
#1481250
0!
#1487500
b100010111101001 1
b1100111001010 0
b10000 2
b110001100110110001 "
b100001001100 /
b10000111011 .
1!
#1493750
0!
#1500000
b100100001110011 1
b1000101100110 0
b10000 2
b110110011001111110 "
b100010111101 /
b1100111001 .
1!
#1506250
0!
#1512500
b100101000000000 1
b100011000010 0
b10000 2
b111011001101001011 "
b100100001110 /
b1000101100 .
1!
#1518750
0!
#1525000
b100101010000100 1
b10 0
b10000 2
b1000000000000011000 "
b100101000000 /
b100011000 .
1!
#1531250
0!
#1537500
b100101000000101 1
b1111011100111101 0
b10000 2
b1000100110011100101 "
b100101010000 /
b0 .
1!
#1543750
0!
#1550000
b100100001111000 1
b1110111010011010 0
b10000 2
b1001001100110110010 "
b100101000000 /
b1111011100111 .
1!
#1556250
0!
#1562500
b100010111101010 1
b1110011000110110 0
b10000 2
b1001110011001111111 "
b100100001111 /
b1110111010011 .
1!
#1568750
0!
#1575000
b100001001100111 1
b1101111000101010 0
b10000 2
b1010011001101001100 "
b100010111101 /
b1110011000110 .
1!
#1581250
0!
#1587500
b11110111110110 1
b1101011010011010 0
b10000 2
b1011000000000011001 "
b100001001100 /
b1101111000101 .
1!
#1593750
0!
#1600000
b11100010100100 1
b1100111110100001 0
b10000 2
b1011100110011100110 "
b11110111110 /
b1101011010011 .
1!
#1606250
0!
#1612500
b11001010010101 1
b1100100101001100 0
b10000 2
b1100001100110110011 "
b11100010100 /
b1100111110100 .
1!
#1618750
0!
#1625000
b10101111001010 1
b1100001110111110 0
b10000 2
b1100110011010000000 "
b11001010010 /
b1100100101001 .
1!
#1631250
0!
#1637500
b10010001100101 1
b1011111100000011 0
b10000 2
b1101011001101001101 "
b10101111001 /
b1100001110111 .
1!
#1643750
0!
#1650000
b1110010000101 1
b1011101100101100 0
b10000 2
b1110000000000011010 "
b10010001100 /
b1011111100000 .
1!
#1656250
0!
#1662500
b1010000111110 1
b1011100001001101 0
b10000 2
b1110100110011100111 "
b1110010000 /
b1011101100101 .
1!
#1668750
0!
#1675000
b101110100101 1
b1011011001110001 0
b10000 2
b1111001100110110100 "
b1010000111 /
b1011100001001 .
1!
#1681250
0!
#1687500
b1011101110 1
b1011010110010011 0
b10000 2
b1111110011010000001 "
b101110100 /
b1011011001110 .
1!
#1693750
0!
#1700000
b1111101000100011 1
b1011010111000001 0
b10000 2
b10000011001101001110 "
b1011101 /
b1011010110010 .
1!
#1706250
0!
#1712500
b1111000101110110 1
b1011011011110010 0
b10000 2
b10001000000000011011 "
b1111101000100 /
b1011010111000 .
1!
#1718750
0!
#1725000
b1110100011111110 1
b1011100100100101 0
b10000 2
b10001100110011101000 "
b1111000101110 /
b1011011011110 .
1!
#1731250
0!
#1737500
b1110000011001110 1
b1011110001011100 0
b10000 2
b10010001100110110101 "
b1110100011111 /
b1011100100100 .
1!
#1743750
0!
#1750000
b1101100100010011 1
b1100000010000001 0
b10000 2
b10010110011010000010 "
b1110000011001 /
b1011110001011 .
1!
#1756250
0!
#1762500
b1101000111011111 1
b1100010110000100 0
b10000 2
b10011011001101001111 "
b1101100100010 /
b1100000010000 .
1!
#1768750
0!
#1775000
b1100101101010011 1
b1100101101010101 0
b10000 2
b10100000000000011100 "
b1101000111011 /
b1100010110000 .
1!
#1781250
0!
#1787500
b1100010110000001 1
b1101000111100100 0
b10000 2
b10100100110011101001 "
b1100101101010 /
b1100101101010 .
1!
#1793750
0!
#1800000
b1100000001111101 1
b1101100100011000 0
b10000 2
b10101001100110110110 "
b1100010110000 /
b1101000111100 .
1!
#1806250
0!
#1812500
b1011110001010101 1
b1110000011010111 0
b10000 2
b10101110011010000011 "
b1100000001111 /
b1101100100011 .
1!
#1818750
0!
#1825000
b1011100100100101 1
b1110100100000010 0
b10000 2
b10110011001101010000 "
b1011110001010 /
b1110000011010 .
1!
#1831250
0!
#1837500
b1011011011101110 1
b1111000101111111 0
b10000 2
b10111000000000011101 "
b1011100100100 /
b1110100100000 .
1!
#1843750
0!
#1850000
b1011010110111111 1
b1111101000101100 0
b10000 2
b10111100110011101010 "
b1011011011101 /
b1111000101111 .
1!
#1856250
0!
#1862500
b1011010110010011 1
b1011110101 0
b10000 2
b11000001100110110111 "
b1011010110111 /
b1111101000101 .
1!
#1868750
0!
#1875000
b1011011001110001 1
b101110101001 0
b10000 2
b11000110011010000100 "
b1011010110010 /
b1011110 .
1!
#1881250
0!
#1887500
b1011100001010001 1
b1010001000000 0
b10000 2
b11001011001101010001 "
b1011011001110 /
b101110101 .
1!
#1893750
0!
#1900000
b1011101100110000 1
b1110010001001 0
b10000 2
b11010000000000011110 "
b1011100001010 /
b1010001000 .
1!
#1906250
0!
#1912500
b1011111100000110 1
b10010001101100 0
b10000 2
b11010100110011101011 "
b1011101100110 /
b1110010001 .
1!
#1918750
0!
#1925000
b1100001111000000 1
b10101111010001 0
b10000 2
b11011001100110111000 "
b1011111100000 /
b10010001101 .
1!
#1931250
0!
#1937500
b1100100101010000 1
b11001010011001 0
b10000 2
b11011110011010000101 "
b1100001111000 /
b10101111010 .
1!
#1943750
0!
#1950000
b1100111110100110 1
b11100010101010 0
b10000 2
b11100011001101010010 "
b1100100101010 /
b11001010011 .
1!
#1956250
0!
#1962500
b1101011010100001 1
b11110111111101 0
b10000 2
b11101000000000011111 "
b1100111110100 /
b11100010101 .
1!
#1968750
0!
#1975000
b1101111000110011 1
b100001001100011 0
b10000 2
b11101100110011101100 "
b1101011010100 /
b11110111111 .
1!
#1981250
0!
#1987500
b1110011000111101 1
b100010111101111 0
b10000 2
b11110001100110111001 "
b1101111000110 /
b100001001100 .
1!
#1993750
0!
#2000000
b1110111010100011 1
b100100001110110 0
b10000 2
b11110110011010000110 "
b1110011000111 /
b100010111101 .
1!
#2006250
0!
#2012500
b1111011101000101 1
b100100111111110 0
b10000 2
b11111011001101010011 "
b1110111010100 /
b100100001110 .
1!
#2018750
0!
#2025000
b111 1
b100101010000111 0
b10000 2
b100000 "
b1111011101000 /
b100100111111 .
1!
#2031250
0!
#2037500
b100011001010 1
b100100111111110 0
b10000 2
b100110011101101 "
b0 /
b100101010000 .
1!
#2043750
0!
#2050000
b1000101101101 1
b100100001110010 0
b10000 2
b1001100110111010 "
b100011001 /
b100100111111 .
1!
#2056250
0!
#2062500
b1100111010001 1
b100010111101001 0
b10000 2
b1110011010000111 "
b1000101101 /
b100100001110 .
1!
#2068750
0!
#2075000
b10000111011101 1
b100001001100011 0
b10000 2
b10011001101010100 "
b1100111010 /
b100010111101 .
1!
#2081250
0!
#2087500
b10100101101110 1
b11110111110011 0
b10000 2
b11000000000100001 "
b10000111011 /
b100001001100 .
1!
#2093750
0!
#2100000
b11000001100110 1
b11100010101100 0
b10000 2
b11100110011101110 "
b10100101101 /
b11110111110 .
1!
#2106250
0!
#2112500
b11011010111100 1
b11001010010101 0
b10000 2
b100001100110111011 "
b11000001100 /
b11100010101 .
1!
#2118750
0!
#2125000
b11110001001110 1
b10101111001000 0
b10000 2
b100110011010001000 "
b11011010111 /
b11001010010 .
1!
#2131250
0!
#2137500
b100000100000100 1
b10010001101001 0
b10000 2
b101011001101010101 "
b11110001001 /
b10101111001 .
1!
#2143750
0!
