New Modules/CORDIC/CORDIC-Comb2/cordic.sv
//==========================================================================
// Copyright (C) 2024 Chili.CHIPS*ba
//--------------------------------------------------------------------------
//                      PROPRIETARY INFORMATION
//
// The information contained in this file is the property of CHILI CHIPS LLC.
// Except as specifically authorized in writing by CHILI CHIPS LLC, the holder
// of this file: (1) shall keep all information contained herein confidential;
// and (2) shall protect the same in whole or in part from disclosure and
// dissemination to all third parties; and (3) shall use the same for operation
// and maintenance purposes only.
//--------------------------------------------------------------------------
// Description: 
//   Test code for Tarik's MSEE, based on:
//      https://zipcpu.com/dsp/2017/08/30/cordic.html
//==========================================================================

module cordic #(
   parameter int IW = 13, // Width of Input Word
   parameter int OW = 13, // Width of Output Word
   parameter int WW = 16, // Width of Word of data
   parameter int PW = 20  // Width of Phase
)(

 //inputs
   input  logic                 i_clk,  
   input  logic                 i_reset,
   input  logic signed [IW-1:0] i_xval, 
   input  logic signed [IW-1:0] i_yval, 
   input  logic        [PW-1:0] i_phase,

 //outputs
   output logic signed [OW-1:0] o_xval, 
   output logic signed [OW-1:0] o_yval, 
   output logic        [PW-1:0] o_phval 
);
   
   localparam int NSTAGES = 16; // Number of Stages

   // Declare variables for all of the separate stages
   logic signed [WW-1:0] e_xval, e_yval; 

   logic signed [WW-1:0] xv [NSTAGES+1];
   logic signed [WW-1:0] yv [NSTAGES+1];
   logic        [PW-1:0] ph [NSTAGES+1];
   logic        [PW-1:0] cordic_angle[NSTAGES];

   logic        [WW-1:0] pre_xval, pre_yval;

   always_comb begin: _cordic_comb

      //--Step1: Sign extend our inputs
      e_xval = { i_xval[IW-1], i_xval, {(WW-IW-1){1'b0}} };
      e_yval = { i_yval[IW-1], i_yval, {(WW-IW-1){1'b0}} };


      //--Step2: Pre-CORDIC rotation
      unique case(i_phase[PW-1 -: 3])
         3'd0: begin     // 0 .. 45, No change
              xv[0] = e_xval;
              yv[0] = e_yval;
              ph[0] = i_phase;
         end
         3'd1: begin     // 45 .. 90
              xv[0] = -e_yval;
              yv[0] = e_xval;
              ph[0] = i_phase - 20'h40000;
         end
         3'd2: begin     // 90 .. 135
              xv[0] = -e_yval;
              yv[0] = e_xval;
              ph[0] = i_phase - 20'h40000;
         end
         3'd3: begin     // 135 .. 180
              xv[0] = -e_xval;
              yv[0] = -e_yval;
              ph[0] = i_phase - 20'h80000;
         end
         3'd4: begin     // 180 .. 225
              xv[0] = -e_xval;
              yv[0] = -e_yval;
              ph[0] = i_phase - 20'h80000;
         end
         3'd5: begin     // 225 .. 270
              xv[0] = e_yval;
              yv[0] = -e_xval;
              ph[0] = i_phase - 20'hc0000;
         end
         3'd6: begin    // 270 .. 315
              xv[0] = e_yval;
              yv[0] = -e_xval;
              ph[0] = i_phase - 20'hc0000;
         end
         default: begin  // 315 .. 360, No change
              xv[0] = e_xval;
              yv[0] = e_yval;
              ph[0] = i_phase;
           end
      endcase


   //--Step3: CORDIC rotations
      cordic_angle[ 0] = 20'h1_2e40; // 26.565051 deg
      cordic_angle[ 1] = 20'h0_9fb3; // 14.036243 deg
      cordic_angle[ 2] = 20'h0_5111; //  7.125016 deg
      cordic_angle[ 3] = 20'h0_28b0; //  3.576334 deg
      cordic_angle[ 4] = 20'h0_145d; //  1.789911 deg
      cordic_angle[ 5] = 20'h0_0a2f; //  0.895174 deg
      cordic_angle[ 6] = 20'h0_0517; //  0.447614 deg
      cordic_angle[ 7] = 20'h0_028b; //  0.223811 deg
      cordic_angle[ 8] = 20'h0_0145; //  0.111906 deg
      cordic_angle[ 9] = 20'h0_00a2; //  0.055953 deg
      cordic_angle[10] = 20'h0_0051; //  0.027976 deg
      cordic_angle[11] = 20'h0_0028; //  0.013988 deg
      cordic_angle[12] = 20'h0_0014; //  0.006994 deg
      cordic_angle[13] = 20'h0_000a; //  0.003497 deg
      cordic_angle[14] = 20'h0_0005; //  0.001749 deg
      cordic_angle[15] = 20'h0_0002; //  0.000874 deg

      for (int i=0; i<NSTAGES; i++) begin

         // Do nothing but move our outputs forward one stage
         if (cordic_angle[i] == 0 || i > WW) begin
            xv[i+1] = xv[i];
            yv[i+1] = yv[i];
            ph[i+1] = ph[i];
         end

         // if phase is negative, rotate clockwise
         if (ph[i][PW-1] == 1'b1) begin
            xv[i+1] = xv[i] + (yv[i] >>> (i+1));
            yv[i+1] = yv[i] - (xv[i] >>> (i+1));
            ph[i+1] = ph[i] + cordic_angle[i];
         end
          
         // if phase is positive, rotate counter-clockwise
         else begin   
            xv[i+1] = xv[i] - (yv[i] >>> (i+1));
            yv[i+1] = yv[i] + (xv[i] >>> (i+1));
            ph[i+1] = ph[i] - cordic_angle[i];
         end
      end // for (int i=0; i<NSTAGES; i++)


      //--Step4: Round our result towards even
      pre_xval = xv[NSTAGES] 
               + $signed({ 
                   {OW{1'b0}},
                    xv[NSTAGES][WW-OW],
                    {WW-OW-1{~xv[NSTAGES][WW-OW]}} 
                 });

      pre_yval = yv[NSTAGES] 
               + $signed({ 
                   {OW{1'b0}},
                    yv[NSTAGES][WW-OW],
                   {WW-OW-1{~yv[NSTAGES][WW-OW]}} 
                 });

   end: _cordic_comb


  //--Step5: Output registers
   always_ff @(posedge i_clk) begin: _cordic_ff
      if (i_reset) begin
         o_xval <= '0;
         o_yval <= '0;
      end 
      else begin
         o_xval <= pre_xval[(WW-1):(WW-OW)];
	 o_yval <= pre_yval[(WW-1):(WW-OW)];
      end
   end: _cordic_ff


  //----------------------------- 
  // For sim only
  //----------------------------- 
   initial begin
      $dumpfile("cordic_waves.vcd");
      $dumpvars;
   end
   
endmodule: cordic

/*
-----------------------------------------------------------------------------
Version History:
-----------------------------------------------------------------------------
 2024/4/14 TH: initial creation    
 2024/4/15 TH: added rest of CORDIC structure
*/

New Modules/CORDIC/CORDIC-Comb2/cordic_waves.vcd
$date
	Mon Apr 15 21:56:54 2024
$end
$version
	Icarus Verilog
$end
$timescale
	1ps
$end
$scope module cordic $end
$var wire 1 ! i_clk $end
$var wire 20 " i_phase [19:0] $end
$var wire 1 # i_reset $end
$var wire 13 $ i_xval [12:0] $end
$var wire 13 % i_yval [12:0] $end
$var parameter 32 & IW $end
$var parameter 32 ' NSTAGES $end
$var parameter 32 ( OW $end
$var parameter 32 ) PW $end
$var parameter 32 * WW $end
$var reg 16 + e_xval [15:0] $end
$var reg 16 , e_yval [15:0] $end
$var reg 20 - o_phval [19:0] $end
$var reg 13 . o_xval [12:0] $end
$var reg 13 / o_yval [12:0] $end
$var reg 16 0 pre_xval [15:0] $end
$var reg 16 1 pre_yval [15:0] $end
$scope begin _cordic_comb $end
$scope begin $ivl_for_loop0 $end
$var integer 32 2 i [31:0] $end
$upscope $end
$upscope $end
$scope begin _cordic_ff $end
$upscope $end
$upscope $end
$enddefinitions $end
$comment Show the parameter values. $end
$dumpall
b10000 *
b10100 )
b1101 (
b10000 '
b1101 &
$end
#0
$dumpvars
b10000 2
bx 1
bx 0
b0 /
b0 .
bx -
bz00 ,
bz00 +
bz %
bz $
0#
bz "
1!
$end
#6250
0!
#12500
b11 1
b100101010001000 0
b10000 2
b0 ,
b11111111111100 +
b0 "
b0 %
b111111111111 $
bx /
bx .
1!
#18750
0!
#25000
b0 /
b100101010001 .
1!
#31250
0!
#37500
b11101010100 1
b100101000100011 0
b10000 2
b100000000000000 "
1!
#43750
0!
#50000
b111010001101 1
b100100100010101 0
b10000 2
b1000000000000000 "
b11101010 /
b100101000100 .
1!
#56250
0!
#62500
b1010110100101 1
b100011101010000 0
b10000 2
b1100000000000000 "
b111010001 /
b100100100010 .
1!
#68750
0!
#75000
b1110010000101 1
b100010011011100 0
b10000 2
b10000000000000000 "
b1010110100 /
b100011101010 .
1!
#81250
0!
#87500
b10001100100100 1
b100000110110101 0
b10000 2
b10100000000000000 "
b1110010000 /
b100010011011 .
1!
#93750
0!
#100000
b10100101100111 1
b11110111110111 0
b10000 2
b11000000000000000 "
b10001100100 /
b100000110110 .
1!
#106250
0!
#112500
b10111101001001 1
b11100110011101 0
b10000 2
b11100000000000000 "
b10100101100 /
b11110111110 .
1!
#118750
0!
#125000
b11010010110100 1
b11010010110010 0
b10000 2
b100000000000000000 "
b10111101001 /
b11100110011 .
1!
#131250
0!
#137500
b11100110011101 1
b10111101001001 0
b10000 2
b100100000000000000 "
b11010010110 /
b11010010110 .
1!
#143750
0!
#150000
b11110111110111 1
b10100101100111 0
b10000 2
b101000000000000000 "
b11100110011 /
b10111101001 .
1!
#156250
0!
#162500
b100000110110101 1
b10001100100100 0
b10000 2
b101100000000000000 "
b11110111110 /
b10100101100 .
1!
#168750
0!
#175000
b100010011011100 1
b1110010000101 0
b10000 2
b110000000000000000 "
b100000110110 /
b10001100100 .
1!
#181250
0!
#187500
b100011101010000 1
b1010110100101 0
b10000 2
b110100000000000000 "
b100010011011 /
b1110010000 .
1!
#193750
0!
#200000
b100100100010101 1
b111010001101 0
b10000 2
b111000000000000000 "
b100011101010 /
b1010110100 .
1!
#206250
0!
#212500
b100101000100011 1
b11101010100 0
b10000 2
b111100000000000000 "
b100100100010 /
b111010001 .
1!
#218750
0!
#225000
b100101010001000 1
b11 0
b10000 2
b1000000000000000000 "
b100101000100 /
b11101010 .
1!
#231250
0!
#237500
b100101000110000 1
b1111100010110011 0
b10000 2
b1000100000000000000 "
b100101010001 /
b0 .
1!
#243750
0!
#250000
b100100100011001 1
b1111000101111010 0
b10000 2
b1001000000000000000 "
b100101000110 /
b1111100010110 .
1!
#256250
0!
#262500
b100011101010011 1
b1110101001100010 0
b10000 2
b1001100000000000000 "
b100100100011 /
b1111000101111 .
1!
#268750
0!
#275000
b100010011011000 1
b1110001110000010 0
b10000 2
b1010000000000000000 "
b100011101010 /
b1110101001100 .
1!
#281250
0!
#287500
b100000110111010 1
b1101110011100011 0
b10000 2
b1010100000000000000 "
b100010011011 /
b1110001110000 .
1!
#293750
0!
#300000
b11110111111000 1
b1101011010100001 0
b10000 2
b1011000000000000000 "
b100000110111 /
b1101110011100 .
1!
#306250
0!
#312500
b11100110011110 1
b1101000010111110 0
b10000 2
b1011100000000000000 "
b11110111111 /
b1101011010100 .
1!
#318750
0!
#325000
b11010010110011 1
b1100101101010011 0
b10000 2
b1100000000000000000 "
b11100110011 /
b1101000010111 .
1!
#331250
0!
#337500
b10111101000111 1
b1100011001101010 0
b10000 2
b1100100000000000000 "
b11010010110 /
b1100101101010 .
1!
#343750
0!
#350000
b10100101100101 1
b1100001000010000 0
b10000 2
b1101000000000000000 "
b10111101000 /
b1100011001101 .
1!
#356250
0!
#362500
b10001100011111 1
b1011111001010010 0
b10000 2
b1101100000000000000 "
b10100101100 /
b1100001000010 .
1!
#368750
0!
#375000
b1110010001001 1
b1011101100101100 0
b10000 2
b1110000000000000000 "
b10001100011 /
b1011111001010 .
1!
#381250
0!
#387500
b1010110100011 1
b1011100010110111 0
b10000 2
b1110100000000000000 "
b1110010001 /
b1011101100101 .
1!
#393750
0!
#400000
b111010001010 1
b1011011011110001 0
b10000 2
b1111000000000000000 "
b1010110100 /
b1011100010110 .
1!
#406250
0!
#412500
b11101001010 1
b1011010111100011 0
b10000 2
b1111100000000000000 "
b111010001 /
b1011011011110 .
1!
#418750
0!
#425000
b11 1
b1011010101111111 0
b10000 2
b10000000000000000000 "
b11101001 /
b1011010111100 .
1!
#431250
0!
#437500
b1111100010111101 1
b1011010111010111 0
b10000 2
b10000100000000000000 "
b0 /
b1011010101111 .
1!
#443750
0!
#450000
b1111000101111101 1
b1011011011101110 0
b10000 2
b10001000000000000000 "
b1111100010111 /
b1011010111010 .
1!
#456250
0!
#462500
b1110101001100011 1
b1011100010110100 0
b10000 2
b10001100000000000000 "
b1111000101111 /
b1011011011101 .
1!
#468750
0!
#475000
b1110001101111110 1
b1011101100101111 0
b10000 2
b10010000000000000000 "
b1110101001100 /
b1011100010110 .
1!
#481250
0!
#487500
b1101110011101000 1
b1011111001001101 0
b10000 2
b10010100000000000000 "
b1110001101111 /
b1011101100101 .
1!
#493750
0!
#500000
b1101011010100010 1
b1100001000001111 0
b10000 2
b10011000000000000000 "
b1101110011101 /
b1011111001001 .
1!
#506250
0!
#512500
b1101000011000000 1
b1100011001101001 0
b10000 2
b10011100000000000000 "
b1101011010100 /
b1100001000001 .
1!
#518750
0!
#525000
b1100101101010101 1
b1100101101010011 0
b10000 2
b10100000000000000000 "
b1101000011000 /
b1100011001101 .
1!
#531250
0!
#537500
b1100011001101001 1
b1101000011000000 0
b10000 2
b10100100000000000000 "
b1100101101010 /
b1100101101010 .
1!
#543750
0!
#550000
b1100001000001111 1
b1101011010100010 0
b10000 2
b10101000000000000000 "
b1100011001101 /
b1101000011000 .
1!
#556250
0!
#562500
b1011111001001101 1
b1101110011101000 0
b10000 2
b10101100000000000000 "
b1100001000001 /
b1101011010100 .
1!
#568750
0!
#575000
b1011101100101111 1
b1110001101111110 0
b10000 2
b10110000000000000000 "
b1011111001001 /
b1101110011101 .
1!
#581250
0!
#587500
b1011100010110100 1
b1110101001100011 0
b10000 2
b10110100000000000000 "
b1011101100101 /
b1110001101111 .
1!
#593750
0!
#600000
b1011011011101110 1
b1111000101111101 0
b10000 2
b10111000000000000000 "
b1011100010110 /
b1110101001100 .
1!
#606250
0!
#612500
b1011010111010111 1
b1111100010111101 0
b10000 2
b10111100000000000000 "
b1011011011101 /
b1111000101111 .
1!
#618750
0!
#625000
b1011010110000001 1
b11 0
b10000 2
b11000000000000000000 "
b1011010111010 /
b1111100010111 .
1!
#631250
0!
#637500
b1011010111100011 1
b11101001010 0
b10000 2
b11000100000000000000 "
b1011010110000 /
b0 .
1!
#643750
0!
#650000
b1011011011110001 1
b111010001010 0
b10000 2
b11001000000000000000 "
b1011010111100 /
b11101001 .
1!
#656250
0!
#662500
b1011100010110111 1
b1010110100011 0
b10000 2
b11001100000000000000 "
b1011011011110 /
b111010001 .
1!
#668750
0!
#675000
b1011101100101100 1
b1110010001001 0
b10000 2
b11010000000000000000 "
b1011100010110 /
b1010110100 .
1!
#681250
0!
#687500
b1011111001010010 1
b10001100011111 0
b10000 2
b11010100000000000000 "
b1011101100101 /
b1110010001 .
1!
#693750
0!
#700000
b1100001000010000 1
b10100101100101 0
b10000 2
b11011000000000000000 "
b1011111001010 /
b10001100011 .
1!
#706250
0!
#712500
b1100011001101010 1
b10111101000111 0
b10000 2
b11011100000000000000 "
b1100001000010 /
b10100101100 .
1!
#718750
0!
#725000
b1100101101010101 1
b11010010110010 0
b10000 2
b11100000000000000000 "
b1100011001101 /
b10111101000 .
1!
#731250
0!
#737500
b1101000010111110 1
b11100110011110 0
b10000 2
b11100100000000000000 "
b1100101101010 /
b11010010110 .
1!
#743750
0!
#750000
b1101011010100001 1
b11110111111000 0
b10000 2
b11101000000000000000 "
b1101000010111 /
b11100110011 .
1!
#756250
0!
#762500
b1101110011100011 1
b100000110111010 0
b10000 2
b11101100000000000000 "
b1101011010100 /
b11110111111 .
1!
#768750
0!
#775000
b1110001110000010 1
b100010011011000 0
b10000 2
b11110000000000000000 "
b1101110011100 /
b100000110111 .
1!
#781250
0!
#787500
b1110101001100010 1
b100011101010011 0
b10000 2
b11110100000000000000 "
b1110001110000 /
b100010011011 .
1!
#793750
0!
#800000
b1111000101111010 1
b100100100011001 0
b10000 2
b11111000000000000000 "
b1110101001100 /
b100011101010 .
1!
#806250
0!
#812500
b1111100010110011 1
b100101000110000 0
b10000 2
b11111100000000000000 "
b1111000101111 /
b100100100011 .
1!
#818750
0!
#825000
b11 1
b100101010001000 0
b10000 2
b0 "
b1111100010110 /
b100101000110 .
1!
#831250
0!
#837500
b11101010100 1
b100101000100011 0
b10000 2
b100000000000000 "
b0 /
b100101010001 .
1!
#843750
0!
#850000
b111010001101 1
b100100100010101 0
b10000 2
b1000000000000000 "
b11101010 /
b100101000100 .
1!
#856250
0!
#862500
b1010110100101 1
b100011101010000 0
b10000 2
b1100000000000000 "
b111010001 /
b100100100010 .
1!
#868750
0!
#875000
b1110010000101 1
b100010011011100 0
b10000 2
b10000000000000000 "
b1010110100 /
b100011101010 .
1!
#881250
0!
#887500
b10001100100100 1
b100000110110101 0
b10000 2
b10100000000000000 "
b1110010000 /
b100010011011 .
1!
#893750
0!
#900000
b10100101100111 1
b11110111110111 0
b10000 2
b11000000000000000 "
b10001100100 /
b100000110110 .
1!
#906250
0!
#912500
b10111101001001 1
b11100110011101 0
b10000 2
b11100000000000000 "
b10100101100 /
b11110111110 .
1!
#918750
0!
#925000
b11010010110100 1
b11010010110010 0
b10000 2
b100000000000000000 "
b10111101001 /
b11100110011 .
1!
#931250
0!
#937500
b11100110011101 1
b10111101001001 0
b10000 2
b100100000000000000 "
b11010010110 /
b11010010110 .
1!
#943750
0!
#950000
b11110111110111 1
b10100101100111 0
b10000 2
b101000000000000000 "
b11100110011 /
b10111101001 .
1!
#956250
0!
#962500
b100000110110101 1
b10001100100100 0
b10000 2
b101100000000000000 "
b11110111110 /
b10100101100 .
1!
#968750
0!
#975000
b100010011011100 1
b1110010000101 0
b10000 2
b110000000000000000 "
b100000110110 /
b10001100100 .
1!
#981250
0!
#987500
b100011101010000 1
b1010110100101 0
b10000 2
b110100000000000000 "
b100010011011 /
b1110010000 .
1!
#993750
0!
#1000000
b100100100010101 1
b111010001101 0
b10000 2
b111000000000000000 "
b100011101010 /
b1010110100 .
1!
#1006250
0!
#1012500
b100101000100011 1
b11101010100 0
b10000 2
b111100000000000000 "
b100100100010 /
b111010001 .
1!
#1018750
0!
#1025000
b100101010001000 1
b11 0
b10000 2
b1000000000000000000 "
b100101000100 /
b11101010 .
1!
#1031250
0!
#1037500
b100101000110000 1
b1111100010110011 0
b10000 2
b1000100000000000000 "
b100101010001 /
b0 .
1!
#1043750
0!
#1050000
b100100100011001 1
b1111000101111010 0
b10000 2
b1001000000000000000 "
b100101000110 /
b1111100010110 .
1!
#1056250
0!
#1062500
b100011101010011 1
b1110101001100010 0
b10000 2
b1001100000000000000 "
b100100100011 /
b1111000101111 .
1!
#1068750
0!
#1075000
b100010011011000 1
b1110001110000010 0
b10000 2
b1010000000000000000 "
b100011101010 /
b1110101001100 .
1!
#1081250
0!
#1087500
b100000110111010 1
b1101110011100011 0
b10000 2
b1010100000000000000 "
b100010011011 /
b1110001110000 .
1!
#1093750
0!
#1100000
b11110111111000 1
b1101011010100001 0
b10000 2
b1011000000000000000 "
b100000110111 /
b1101110011100 .
1!
#1106250
0!
#1112500
b11100110011110 1
b1101000010111110 0
b10000 2
b1011100000000000000 "
b11110111111 /
b1101011010100 .
1!
#1118750
0!
#1125000
b11010010110011 1
b1100101101010011 0
b10000 2
b1100000000000000000 "
b11100110011 /
b1101000010111 .
1!
#1131250
0!
#1137500
b10111101000111 1
b1100011001101010 0
b10000 2
b1100100000000000000 "
b11010010110 /
b1100101101010 .
1!
#1143750
0!
#1150000
b10100101100101 1
b1100001000010000 0
b10000 2
b1101000000000000000 "
b10111101000 /
b1100011001101 .
1!
#1156250
0!
#1162500
b10001100011111 1
b1011111001010010 0
b10000 2
b1101100000000000000 "
b10100101100 /
b1100001000010 .
1!
#1168750
0!
#1175000
b1110010001001 1
b1011101100101100 0
b10000 2
b1110000000000000000 "
b10001100011 /
b1011111001010 .
1!
#1181250
0!
#1187500
b1010110100011 1
b1011100010110111 0
b10000 2
b1110100000000000000 "
b1110010001 /
b1011101100101 .
1!
#1193750
0!
#1200000
b111010001010 1
b1011011011110001 0
b10000 2
b1111000000000000000 "
b1010110100 /
b1011100010110 .
1!
#1206250
0!
#1212500
b11101001010 1
b1011010111100011 0
b10000 2
b1111100000000000000 "
b111010001 /
b1011011011110 .
1!
#1218750
0!
#1225000
b11 1
b1011010101111111 0
b10000 2
b10000000000000000000 "
b11101001 /
b1011010111100 .
1!
#1231250
0!
#1237500
b1111100010111101 1
b1011010111010111 0
b10000 2
b10000100000000000000 "
b0 /
b1011010101111 .
1!
#1243750
0!
#1250000
b1111000101111101 1
b1011011011101110 0
b10000 2
b10001000000000000000 "
b1111100010111 /
b1011010111010 .
1!
#1256250
0!
#1262500
b1110101001100011 1
b1011100010110100 0
b10000 2
b10001100000000000000 "
b1111000101111 /
b1011011011101 .
1!
#1268750
0!
#1275000
b1110001101111110 1
b1011101100101111 0
b10000 2
b10010000000000000000 "
b1110101001100 /
b1011100010110 .
1!
#1281250
0!
#1287500
b1101110011101000 1
b1011111001001101 0
b10000 2
b10010100000000000000 "
b1110001101111 /
b1011101100101 .
1!
#1293750
0!
#1300000
b1101011010100010 1
b1100001000001111 0
b10000 2
b10011000000000000000 "
b1101110011101 /
b1011111001001 .
1!
#1306250
0!
#1312500
b1101000011000000 1
b1100011001101001 0
b10000 2
b10011100000000000000 "
b1101011010100 /
b1100001000001 .
1!
#1318750
0!
#1325000
b1100101101010101 1
b1100101101010011 0
b10000 2
b10100000000000000000 "
b1101000011000 /
b1100011001101 .
1!
#1331250
0!
#1337500
b1100011001101001 1
b1101000011000000 0
b10000 2
b10100100000000000000 "
b1100101101010 /
b1100101101010 .
1!
#1343750
0!
#1350000
b1100001000001111 1
b1101011010100010 0
b10000 2
b10101000000000000000 "
b1100011001101 /
b1101000011000 .
1!
#1356250
0!
#1362500
b1011111001001101 1
b1101110011101000 0
b10000 2
b10101100000000000000 "
b1100001000001 /
b1101011010100 .
1!
#1368750
0!
#1375000
b1011101100101111 1
b1110001101111110 0
b10000 2
b10110000000000000000 "
b1011111001001 /
b1101110011101 .
1!
#1381250
0!
#1387500
b1011100010110100 1
b1110101001100011 0
b10000 2
b10110100000000000000 "
b1011101100101 /
b1110001101111 .
1!
#1393750
0!
#1400000
b1011011011101110 1
b1111000101111101 0
b10000 2
b10111000000000000000 "
b1011100010110 /
b1110101001100 .
1!
#1406250
0!
#1412500
b1011010111010111 1
b1111100010111101 0
b10000 2
b10111100000000000000 "
b1011011011101 /
b1111000101111 .
1!
#1418750
0!
#1425000
b1011010110000001 1
b11 0
b10000 2
b11000000000000000000 "
b1011010111010 /
b1111100010111 .
1!
#1431250
0!
#1437500
b1011010111100011 1
b11101001010 0
b10000 2
b11000100000000000000 "
b1011010110000 /
b0 .
1!
#1443750
0!
#1450000
b1011011011110001 1
b111010001010 0
b10000 2
b11001000000000000000 "
b1011010111100 /
b11101001 .
1!
#1456250
0!
#1462500
b1011100010110111 1
b1010110100011 0
b10000 2
b11001100000000000000 "
b1011011011110 /
b111010001 .
1!
#1468750
0!
#1475000
b1011101100101100 1
b1110010001001 0
b10000 2
b11010000000000000000 "
b1011100010110 /
b1010110100 .
1!
#1481250
0!
#1487500
b1011111001010010 1
b10001100011111 0
b10000 2
b11010100000000000000 "
b1011101100101 /
b1110010001 .
1!
#1493750
0!
#1500000
b1100001000010000 1
b10100101100101 0
b10000 2
b11011000000000000000 "
b1011111001010 /
b10001100011 .
1!
#1506250
0!
#1512500
b1100011001101010 1
b10111101000111 0
b10000 2
b11011100000000000000 "
b1100001000010 /
b10100101100 .
1!
#1518750
0!
#1525000
b1100101101010101 1
b11010010110010 0
b10000 2
b11100000000000000000 "
b1100011001101 /
b10111101000 .
1!
#1531250
0!
#1537500
b1101000010111110 1
b11100110011110 0
b10000 2
b11100100000000000000 "
b1100101101010 /
b11010010110 .
1!
#1543750
0!
#1550000
b1101011010100001 1
b11110111111000 0
b10000 2
b11101000000000000000 "
b1101000010111 /
b11100110011 .
1!
#1556250
0!
#1562500
b1101110011100011 1
b100000110111010 0
b10000 2
b11101100000000000000 "
b1101011010100 /
b11110111111 .
1!
#1568750
0!
#1575000
b1110001110000010 1
b100010011011000 0
b10000 2
b11110000000000000000 "
b1101110011100 /
b100000110111 .
1!
#1581250
0!
#1587500
b1110101001100010 1
b100011101010011 0
b10000 2
b11110100000000000000 "
b1110001110000 /
b100010011011 .
1!
#1593750
0!
#1600000
b1111000101111010 1
b100100100011001 0
b10000 2
b11111000000000000000 "
b1110101001100 /
b100011101010 .
1!
#1606250
0!
#1612500
b1111100010110011 1
b100101000110000 0
b10000 2
b11111100000000000000 "
b1111000101111 /
b100100100011 .
1!
#1618750
0!
#1625000
b11 1
b100101010001000 0
b10000 2
b0 "
b1111100010110 /
b100101000110 .
1!
#1631250
0!
#1637500
b11101010100 1
b100101000100011 0
b10000 2
b100000000000000 "
b0 /
b100101010001 .
1!
#1643750
0!
#1650000
b111010001101 1
b100100100010101 0
b10000 2
b1000000000000000 "
b11101010 /
b100101000100 .
1!
#1656250
0!
#1662500
b1010110100101 1
b100011101010000 0
b10000 2
b1100000000000000 "
b111010001 /
b100100100010 .
1!
#1668750
0!
#1675000
b1110010000101 1
b100010011011100 0
b10000 2
b10000000000000000 "
b1010110100 /
b100011101010 .
1!
#1681250
0!
#1687500
b10001100100100 1
b100000110110101 0
b10000 2
b10100000000000000 "
b1110010000 /
b100010011011 .
1!
#1693750
0!
#1700000
b10100101100111 1
b11110111110111 0
b10000 2
b11000000000000000 "
b10001100100 /
b100000110110 .
1!
#1706250
0!
#1712500
b10111101001001 1
b11100110011101 0
b10000 2
b11100000000000000 "
b10100101100 /
b11110111110 .
1!
#1718750
0!
#1725000
b11010010110100 1
b11010010110010 0
b10000 2
b100000000000000000 "
b10111101001 /
b11100110011 .
1!
#1731250
0!
#1737500
b11100110011101 1
b10111101001001 0
b10000 2
b100100000000000000 "
b11010010110 /
b11010010110 .
1!
#1743750
0!
#1750000
b11110111110111 1
b10100101100111 0
b10000 2
b101000000000000000 "
b11100110011 /
b10111101001 .
1!
#1756250
0!
#1762500
b100000110110101 1
b10001100100100 0
b10000 2
b101100000000000000 "
b11110111110 /
b10100101100 .
1!
#1768750
0!
#1775000
b100010011011100 1
b1110010000101 0
b10000 2
b110000000000000000 "
b100000110110 /
b10001100100 .
1!
#1781250
0!
#1787500
b100011101010000 1
b1010110100101 0
b10000 2
b110100000000000000 "
b100010011011 /
b1110010000 .
1!
#1793750
0!
#1800000
b100100100010101 1
b111010001101 0
b10000 2
b111000000000000000 "
b100011101010 /
b1010110100 .
1!
#1806250
0!
#1812500
b100101000100011 1
b11101010100 0
b10000 2
b111100000000000000 "
b100100100010 /
b111010001 .
1!
#1818750
0!
#1825000
b100101010001000 1
b11 0
b10000 2
b1000000000000000000 "
b100101000100 /
b11101010 .
1!
#1831250
0!
#1837500
b100101000110000 1
b1111100010110011 0
b10000 2
b1000100000000000000 "
b100101010001 /
b0 .
1!
#1843750
0!
#1850000
b100100100011001 1
b1111000101111010 0
b10000 2
b1001000000000000000 "
b100101000110 /
b1111100010110 .
1!
#1856250
0!
#1862500
b100011101010011 1
b1110101001100010 0
b10000 2
b1001100000000000000 "
b100100100011 /
b1111000101111 .
1!
#1868750
0!
#1875000
b100010011011000 1
b1110001110000010 0
b10000 2
b1010000000000000000 "
b100011101010 /
b1110101001100 .
1!
#1881250
0!
#1887500
b100000110111010 1
b1101110011100011 0
b10000 2
b1010100000000000000 "
b100010011011 /
b1110001110000 .
1!
#1893750
0!
#1900000
b11110111111000 1
b1101011010100001 0
b10000 2
b1011000000000000000 "
b100000110111 /
b1101110011100 .
1!
#1906250
0!
#1912500
b11100110011110 1
b1101000010111110 0
b10000 2
b1011100000000000000 "
b11110111111 /
b1101011010100 .
1!
#1918750
0!
#1925000
b11010010110011 1
b1100101101010011 0
b10000 2
b1100000000000000000 "
b11100110011 /
b1101000010111 .
1!
#1931250
0!
#1937500
b10111101000111 1
b1100011001101010 0
b10000 2
b1100100000000000000 "
b11010010110 /
b1100101101010 .
1!
#1943750
0!
#1950000
b10100101100101 1
b1100001000010000 0
b10000 2
b1101000000000000000 "
b10111101000 /
b1100011001101 .
1!
#1956250
0!
#1962500
b10001100011111 1
b1011111001010010 0
b10000 2
b1101100000000000000 "
b10100101100 /
b1100001000010 .
1!
#1968750
0!
#1975000
b1110010001001 1
b1011101100101100 0
b10000 2
b1110000000000000000 "
b10001100011 /
b1011111001010 .
1!
#1981250
0!
#1987500
b1010110100011 1
b1011100010110111 0
b10000 2
b1110100000000000000 "
b1110010001 /
b1011101100101 .
1!
#1993750
0!
#2000000
b111010001010 1
b1011011011110001 0
b10000 2
b1111000000000000000 "
b1010110100 /
b1011100010110 .
1!
#2006250
0!
#2012500
b11101001010 1
b1011010111100011 0
b10000 2
b1111100000000000000 "
b111010001 /
b1011011011110 .
1!
#2018750
0!
#2025000
b11 1
b1011010101111111 0
b10000 2
b10000000000000000000 "
b11101001 /
b1011010111100 .
1!
#2031250
0!
#2037500
b1111100010111101 1
b1011010111010111 0
b10000 2
b10000100000000000000 "
b0 /
b1011010101111 .
1!
#2043750
0!
#2050000
b1111000101111101 1
b1011011011101110 0
b10000 2
b10001000000000000000 "
b1111100010111 /
b1011010111010 .
1!
#2056250
0!
#2062500
b1110101001100011 1
b1011100010110100 0
b10000 2
b10001100000000000000 "
b1111000101111 /
b1011011011101 .
1!
#2068750
0!
#2075000
b1110001101111110 1
b1011101100101111 0
b10000 2
b10010000000000000000 "
b1110101001100 /
b1011100010110 .
1!
#2081250
0!
#2087500
b1101110011101000 1
b1011111001001101 0
b10000 2
b10010100000000000000 "
b1110001101111 /
b1011101100101 .
1!
#2093750
0!
#2100000
b1101011010100010 1
b1100001000001111 0
b10000 2
b10011000000000000000 "
b1101110011101 /
b1011111001001 .
1!
#2106250
0!
#2112500
b1101000011000000 1
b1100011001101001 0
b10000 2
b10011100000000000000 "
b1101011010100 /
b1100001000001 .
1!
#2118750
0!
#2125000
b1100101101010101 1
b1100101101010011 0
b10000 2
b10100000000000000000 "
b1101000011000 /
b1100011001101 .
1!
#2131250
0!
#2137500
b1100011001101001 1
b1101000011000000 0
b10000 2
b10100100000000000000 "
b1100101101010 /
b1100101101010 .
1!
#2143750
0!
#2150000
b1100001000001111 1
b1101011010100010 0
b10000 2
b10101000000000000000 "
b1100011001101 /
b1101000011000 .
1!
