New Modules/SineGenerator/Testbench/simpleSine_gen.v
module simpleSine(
    clk,
    rst,
    sample_clock_ce,
    phase_inc_carrGen,
    sinewave
);

parameter SB = 12, // SINE_BITS
          LB = 8, // LUT_BITS
          PB = 64; // PHASE_BITS
input clk;
input wire rst;
input wire sample_clock_ce;
input reg signed[PB-1:0] phase_inc_carrGen;
output reg signed[SB-1:0] sinewave;

reg [PB-1:0] phase = 0;

always @(posedge clk or posedge rst) begin
    if (rst)
        phase <= 0;
    else if (sample_clock_ce)
        phase <= phase + phase_inc_carrGen;
end

always @(posedge clk) begin
    if(sample_clock_ce) begin
        case(phase[(PB-1):(PB-LB)])
        8'h00: sinewave <= 12'h000;
        8'h01: sinewave <= 12'h032;
        8'h02: sinewave <= 12'h064;
        8'h03: sinewave <= 12'h096;
        8'h04: sinewave <= 12'h0C8;
        8'h05: sinewave <= 12'h0FA;
        8'h06: sinewave <= 12'h12C;
        8'h07: sinewave <= 12'h15D;
        8'h08: sinewave <= 12'h18F;
        8'h09: sinewave <= 12'h1C0;
        8'h0A: sinewave <= 12'h1F1;
        8'h0B: sinewave <= 12'h221;
        8'h0C: sinewave <= 12'h252;
        8'h0D: sinewave <= 12'h282;
        8'h0E: sinewave <= 12'h2B1;
        8'h0F: sinewave <= 12'h2E0;
        8'h10: sinewave <= 12'h30F;
        8'h11: sinewave <= 12'h33D;
        8'h12: sinewave <= 12'h36B;
        8'h13: sinewave <= 12'h398;
        8'h14: sinewave <= 12'h3C4;
        8'h15: sinewave <= 12'h3F0;
        8'h16: sinewave <= 12'h41C;
        8'h17: sinewave <= 12'h447;
        8'h18: sinewave <= 12'h471;
        8'h19: sinewave <= 12'h49A;
        8'h1A: sinewave <= 12'h4C3;
        8'h1B: sinewave <= 12'h4EB;
        8'h1C: sinewave <= 12'h512;
        8'h1D: sinewave <= 12'h539;
        8'h1E: sinewave <= 12'h55E;
        8'h1F: sinewave <= 12'h583;
        8'h20: sinewave <= 12'h5A7;
        8'h21: sinewave <= 12'h5CA;
        8'h22: sinewave <= 12'h5EC;
        8'h23: sinewave <= 12'h60E;
        8'h24: sinewave <= 12'h62E;
        8'h25: sinewave <= 12'h64D;
        8'h26: sinewave <= 12'h66C;
        8'h27: sinewave <= 12'h689;
        8'h28: sinewave <= 12'h6A6;
        8'h29: sinewave <= 12'h6C1;
        8'h2A: sinewave <= 12'h6DB;
        8'h2B: sinewave <= 12'h6F5;
        8'h2C: sinewave <= 12'h70D;
        8'h2D: sinewave <= 12'h724;
        8'h2E: sinewave <= 12'h73A;
        8'h2F: sinewave <= 12'h74F;
        8'h30: sinewave <= 12'h763;
        8'h31: sinewave <= 12'h775;
        8'h32: sinewave <= 12'h787;
        8'h33: sinewave <= 12'h797;
        8'h34: sinewave <= 12'h7A6;
        8'h35: sinewave <= 12'h7B4;
        8'h36: sinewave <= 12'h7C1;
        8'h37: sinewave <= 12'h7CD;
        8'h38: sinewave <= 12'h7D7;
        8'h39: sinewave <= 12'h7E0;
        8'h3A: sinewave <= 12'h7E8;
        8'h3B: sinewave <= 12'h7EF;
        8'h3C: sinewave <= 12'h7F5;
        8'h3D: sinewave <= 12'h7F9;
        8'h3E: sinewave <= 12'h7FC;
        8'h3F: sinewave <= 12'h7FE;
        8'h40: sinewave <= 12'h7FF;
        8'h41: sinewave <= 12'h7FE;
        8'h42: sinewave <= 12'h7FC;
        8'h43: sinewave <= 12'h7F9;
        8'h44: sinewave <= 12'h7F5;
        8'h45: sinewave <= 12'h7EF;
        8'h46: sinewave <= 12'h7E8;
        8'h47: sinewave <= 12'h7E0;
        8'h48: sinewave <= 12'h7D7;
        8'h49: sinewave <= 12'h7CD;
        8'h4A: sinewave <= 12'h7C1;
        8'h4B: sinewave <= 12'h7B4;
        8'h4C: sinewave <= 12'h7A6;
        8'h4D: sinewave <= 12'h797;
        8'h4E: sinewave <= 12'h787;
        8'h4F: sinewave <= 12'h775;
        8'h50: sinewave <= 12'h763;
        8'h51: sinewave <= 12'h74F;
        8'h52: sinewave <= 12'h73A;
        8'h53: sinewave <= 12'h724;
        8'h54: sinewave <= 12'h70D;
        8'h55: sinewave <= 12'h6F5;
        8'h56: sinewave <= 12'h6DB;
        8'h57: sinewave <= 12'h6C1;
        8'h58: sinewave <= 12'h6A6;
        8'h59: sinewave <= 12'h689;
        8'h5A: sinewave <= 12'h66C;
        8'h5B: sinewave <= 12'h64D;
        8'h5C: sinewave <= 12'h62E;
        8'h5D: sinewave <= 12'h60E;
        8'h5E: sinewave <= 12'h5EC;
        8'h5F: sinewave <= 12'h5CA;
        8'h60: sinewave <= 12'h5A7;
        8'h61: sinewave <= 12'h583;
        8'h62: sinewave <= 12'h55E;
        8'h63: sinewave <= 12'h539;
        8'h64: sinewave <= 12'h512;
        8'h65: sinewave <= 12'h4EB;
        8'h66: sinewave <= 12'h4C3;
        8'h67: sinewave <= 12'h49A;
        8'h68: sinewave <= 12'h471;
        8'h69: sinewave <= 12'h447;
        8'h6A: sinewave <= 12'h41C;
        8'h6B: sinewave <= 12'h3F0;
        8'h6C: sinewave <= 12'h3C4;
        8'h6D: sinewave <= 12'h398;
        8'h6E: sinewave <= 12'h36B;
        8'h6F: sinewave <= 12'h33D;
        8'h70: sinewave <= 12'h30F;
        8'h71: sinewave <= 12'h2E0;
        8'h72: sinewave <= 12'h2B1;
        8'h73: sinewave <= 12'h282;
        8'h74: sinewave <= 12'h252;
        8'h75: sinewave <= 12'h221;
        8'h76: sinewave <= 12'h1F1;
        8'h77: sinewave <= 12'h1C0;
        8'h78: sinewave <= 12'h18F;
        8'h79: sinewave <= 12'h15D;
        8'h7A: sinewave <= 12'h12C;
        8'h7B: sinewave <= 12'h0FA;
        8'h7C: sinewave <= 12'h0C8;
        8'h7D: sinewave <= 12'h096;
        8'h7E: sinewave <= 12'h064;
        8'h7F: sinewave <= 12'h032;
        8'h80: sinewave <= 12'h000;
        8'h81: sinewave <= 12'hFCE;
        8'h82: sinewave <= 12'hF9C;
        8'h83: sinewave <= 12'hF6A;
        8'h84: sinewave <= 12'hF38;
        8'h85: sinewave <= 12'hF06;
        8'h86: sinewave <= 12'hED4;
        8'h87: sinewave <= 12'hEA3;
        8'h88: sinewave <= 12'hE71;
        8'h89: sinewave <= 12'hE40;
        8'h8A: sinewave <= 12'hE0F;
        8'h8B: sinewave <= 12'hDDF;
        8'h8C: sinewave <= 12'hDAE;
        8'h8D: sinewave <= 12'hD7E;
        8'h8E: sinewave <= 12'hD4F;
        8'h8F: sinewave <= 12'hD20;
        8'h90: sinewave <= 12'hCF1;
        8'h91: sinewave <= 12'hCC3;
        8'h92: sinewave <= 12'hC95;
        8'h93: sinewave <= 12'hC68;
        8'h94: sinewave <= 12'hC3C;
        8'h95: sinewave <= 12'hC10;
        8'h96: sinewave <= 12'hBE4;
        8'h97: sinewave <= 12'hBB9;
        8'h98: sinewave <= 12'hB8F;
        8'h99: sinewave <= 12'hB66;
        8'h9A: sinewave <= 12'hB3D;
        8'h9B: sinewave <= 12'hB15;
        8'h9C: sinewave <= 12'hAEE;
        8'h9D: sinewave <= 12'hAC7;
        8'h9E: sinewave <= 12'hAA2;
        8'h9F: sinewave <= 12'hA7D;
        8'hA0: sinewave <= 12'hA59;
        8'hA1: sinewave <= 12'hA36;
        8'hA2: sinewave <= 12'hA14;
        8'hA3: sinewave <= 12'h9F2;
        8'hA4: sinewave <= 12'h9D2;
        8'hA5: sinewave <= 12'h9B3;
        8'hA6: sinewave <= 12'h994;
        8'hA7: sinewave <= 12'h977;
        8'hA8: sinewave <= 12'h95A;
        8'hA9: sinewave <= 12'h93F;
        8'hAA: sinewave <= 12'h925;
        8'hAB: sinewave <= 12'h90B;
        8'hAC: sinewave <= 12'h8F3;
        8'hAD: sinewave <= 12'h8DC;
        8'hAE: sinewave <= 12'h8C6;
        8'hAF: sinewave <= 12'h8B1;
        8'hB0: sinewave <= 12'h89D;
        8'hB1: sinewave <= 12'h88B;
        8'hB2: sinewave <= 12'h879;
        8'hB3: sinewave <= 12'h869;
        8'hB4: sinewave <= 12'h85A;
        8'hB5: sinewave <= 12'h84C;
        8'hB6: sinewave <= 12'h83F;
        8'hB7: sinewave <= 12'h833;
        8'hB8: sinewave <= 12'h829;
        8'hB9: sinewave <= 12'h820;
        8'hBA: sinewave <= 12'h818;
        8'hBB: sinewave <= 12'h811;
        8'hBC: sinewave <= 12'h80B;
        8'hBD: sinewave <= 12'h807;
        8'hBE: sinewave <= 12'h804;
        8'hBF: sinewave <= 12'h802;
        8'hC0: sinewave <= 12'h801;
        8'hC1: sinewave <= 12'h802;
        8'hC2: sinewave <= 12'h804;
        8'hC3: sinewave <= 12'h807;
        8'hC4: sinewave <= 12'h80B;
        8'hC5: sinewave <= 12'h811;
        8'hC6: sinewave <= 12'h818;
        8'hC7: sinewave <= 12'h820;
        8'hC8: sinewave <= 12'h829;
        8'hC9: sinewave <= 12'h833;
        8'hCA: sinewave <= 12'h83F;
        8'hCB: sinewave <= 12'h84C;
        8'hCC: sinewave <= 12'h85A;
        8'hCD: sinewave <= 12'h869;
        8'hCE: sinewave <= 12'h879;
        8'hCF: sinewave <= 12'h88B;
        8'hD0: sinewave <= 12'h89D;
        8'hD1: sinewave <= 12'h8B1;
        8'hD2: sinewave <= 12'h8C6;
        8'hD3: sinewave <= 12'h8DC;
        8'hD4: sinewave <= 12'h8F3;
        8'hD5: sinewave <= 12'h90B;
        8'hD6: sinewave <= 12'h925;
        8'hD7: sinewave <= 12'h93F;
        8'hD8: sinewave <= 12'h95A;
        8'hD9: sinewave <= 12'h977;
        8'hDA: sinewave <= 12'h994;
        8'hDB: sinewave <= 12'h9B3;
        8'hDC: sinewave <= 12'h9D2;
        8'hDD: sinewave <= 12'h9F2;
        8'hDE: sinewave <= 12'hA14;
        8'hDF: sinewave <= 12'hA36;
        8'hE0: sinewave <= 12'hA59;
        8'hE1: sinewave <= 12'hA7D;
        8'hE2: sinewave <= 12'hAA2;
        8'hE3: sinewave <= 12'hAC7;
        8'hE4: sinewave <= 12'hAEE;
        8'hE5: sinewave <= 12'hB15;
        8'hE6: sinewave <= 12'hB3D;
        8'hE7: sinewave <= 12'hB66;
        8'hE8: sinewave <= 12'hB8F;
        8'hE9: sinewave <= 12'hBB9;
        8'hEA: sinewave <= 12'hBE4;
        8'hEB: sinewave <= 12'hC10;
        8'hEC: sinewave <= 12'hC3C;
        8'hED: sinewave <= 12'hC68;
        8'hEE: sinewave <= 12'hC95;
        8'hEF: sinewave <= 12'hCC3;
        8'hF0: sinewave <= 12'hCF1;
        8'hF1: sinewave <= 12'hD20;
        8'hF2: sinewave <= 12'hD4F;
        8'hF3: sinewave <= 12'hD7E;
        8'hF4: sinewave <= 12'hDAE;
        8'hF5: sinewave <= 12'hDDF;
        8'hF6: sinewave <= 12'hE0F;
        8'hF7: sinewave <= 12'hE40;
        8'hF8: sinewave <= 12'hE71;
        8'hF9: sinewave <= 12'hEA3;
        8'hFA: sinewave <= 12'hED4;
        8'hFB: sinewave <= 12'hF06;
        8'hFC: sinewave <= 12'hF38;
        8'hFD: sinewave <= 12'hF6A;
        8'hFE: sinewave <= 12'hF9C;
        8'hFF: sinewave <= 12'hFCE;
        endcase
    end
end

initial begin
    $dumpfile("simpleSine_waves.vcd");
    $dumpvars;
end

endmodule

New Modules/SineGenerator/Testbench/simpleSine_waves.vcd
$date
	Sat Apr 13 11:54:02 2024
$end
$version
	Icarus Verilog
$end
$timescale
	1ps
$end
$scope module simpleSine $end
$var wire 1 ! clk $end
$var wire 64 " phase_inc_carrGen [63:0] $end
$var wire 1 # rst $end
$var wire 1 $ sample_clock_ce $end
$var parameter 32 % LB $end
$var parameter 32 & PB $end
$var parameter 32 ' SB $end
$var reg 64 ( phase [63:0] $end
$var reg 12 ) sinewave [11:0] $end
$upscope $end
$enddefinitions $end
$comment Show the parameter values. $end
$dumpall
b1100 '
b1000000 &
b1000 %
$end
#0
$dumpvars
b0 )
b10011001100110011001100110011001100110011001100110011001100 (
1$
z#
b10011001100110011001100110011001100110011001100110011001100 "
1!
$end
#6250
0!
#12500
b11001000 )
b100110011001100110011001100110011001100110011001100110011000 (
1!
#18750
0!
#25000
b111000000 )
b111001100110011001100110011001100110011001100110011001100100 (
1!
#31250
0!
#37500
b1010110001 )
b1001100110011001100110011001100110011001100110011001100110000 (
1!
#43750
0!
#50000
b1110011000 )
b1011111111111111111111111111111111111111111111111111111111100 (
1!
#56250
0!
#62500
b10001000111 )
b1110011001100110011001100110011001100110011001100110011001000 (
1!
#68750
0!
#75000
b10100010010 )
b10000110011001100110011001100110011001100110011001100110010100 (
1!
#81250
0!
#87500
b10111001010 )
b10011001100110011001100110011001100110011001100110011001100000 (
1!
#93750
0!
#100000
b11001101100 )
b10101100110011001100110011001100110011001100110011001100101100 (
1!
#106250
0!
#112500
b11011110101 )
b10111111111111111111111111111111111111111111111111111111111000 (
1!
#118750
0!
#125000
b11101001111 )
b11010011001100110011001100110011001100110011001100110011000100 (
1!
#131250
0!
#137500
b11110100110 )
b11100110011001100110011001100110011001100110011001100110010000 (
1!
#143750
0!
#150000
b11111100000 )
b11111001100110011001100110011001100110011001100110011001011100 (
1!
#156250
0!
#162500
b11111111100 )
b100001100110011001100110011001100110011001100110011001100101000 (
1!
#168750
0!
#175000
b11111111001 )
b100011111111111111111111111111111111111111111111111111111110100 (
1!
#181250
0!
#187500
b11111100000 )
b100110011001100110011001100110011001100110011001100110011000000 (
1!
#193750
0!
#200000
b11110100110 )
b101000110011001100110011001100110011001100110011001100110001100 (
1!
#206250
0!
#212500
b11101001111 )
b101011001100110011001100110011001100110011001100110011001011000 (
1!
#218750
0!
#225000
b11011011011 )
b101101100110011001100110011001100110011001100110011001100100100 (
1!
#231250
0!
#237500
b11001001101 )
b101111111111111111111111111111111111111111111111111111111110000 (
1!
#243750
0!
#250000
b10111001010 )
b110010011001100110011001100110011001100110011001100110010111100 (
1!
#256250
0!
#262500
b10100010010 )
b110100110011001100110011001100110011001100110011001100110001000 (
1!
#268750
0!
#275000
b10001000111 )
b110111001100110011001100110011001100110011001100110011001010100 (
1!
#281250
0!
#287500
b1101101011 )
b111001100110011001100110011001100110011001100110011001100100000 (
1!
#293750
0!
#300000
b1010000010 )
b111011111111111111111111111111111111111111111111111111111101100 (
1!
#306250
0!
#312500
b111000000 )
b111110011001100110011001100110011001100110011001100110010111000 (
1!
#318750
0!
#325000
b11001000 )
b1000000110011001100110011001100110011001100110011001100110000100 (
1!
#331250
0!
#337500
b111111001110 )
b1000011001100110011001100110011001100110011001100110011001010000 (
1!
#343750
0!
#350000
b111011010100 )
b1000101100110011001100110011001100110011001100110011001100011100 (
1!
#356250
0!
#362500
b110111011111 )
b1000111111111111111111111111111111111111111111111111111111101000 (
1!
#368750
0!
#375000
b110100100000 )
b1001010011001100110011001100110011001100110011001100110010110100 (
1!
#381250
0!
#387500
b110000111100 )
b1001100110011001100110011001100110011001100110011001100110000000 (
1!
#393750
0!
#400000
b101101100110 )
b1001111001100110011001100110011001100110011001100110011001001100 (
1!
#406250
0!
#412500
b101010100010 )
b1010001100110011001100110011001100110011001100110011001100011000 (
1!
#418750
0!
#425000
b100111110010 )
b1010011111111111111111111111111111111111111111111111111111100100 (
1!
#431250
0!
#437500
b100101110111 )
b1010110011001100110011001100110011001100110011001100110010110000 (
1!
#443750
0!
#450000
b100011110011 )
b1011000110011001100110011001100110011001100110011001100101111100 (
1!
#456250
0!
#462500
b100010001011 )
b1011011001100110011001100110011001100110011001100110011001001000 (
1!
#468750
0!
#475000
b100000111111 )
b1011101100110011001100110011001100110011001100110011001100010100 (
1!
#481250
0!
#487500
b100000010001 )
b1011111111111111111111111111111111111111111111111111111111100000 (
1!
#493750
0!
#500000
b100000000010 )
b1100010011001100110011001100110011001100110011001100110010101100 (
1!
#506250
0!
#512500
b100000001011 )
b1100100110011001100110011001100110011001100110011001100101111000 (
1!
#518750
0!
#525000
b100000110011 )
b1100111001100110011001100110011001100110011001100110011001000100 (
1!
#531250
0!
#537500
b100001111001 )
b1101001100110011001100110011001100110011001100110011001100010000 (
1!
#543750
0!
#550000
b100011011100 )
b1101011111111111111111111111111111111111111111111111111111011100 (
1!
#556250
0!
#562500
b100100111111 )
b1101110011001100110011001100110011001100110011001100110010101000 (
1!
#568750
0!
#575000
b100111010010 )
b1110000110011001100110011001100110011001100110011001100101110100 (
1!
#581250
0!
#587500
b101001111101 )
b1110011001100110011001100110011001100110011001100110011001000000 (
1!
#593750
0!
#600000
b101100111101 )
b1110101100110011001100110011001100110011001100110011001100001100 (
1!
#606250
0!
#612500
b110000010000 )
b1110111111111111111111111111111111111111111111111111111111011000 (
1!
#618750
0!
#625000
b110011000011 )
b1111010011001100110011001100110011001100110011001100110010100100 (
1!
#631250
0!
#637500
b110110101110 )
b1111100110011001100110011001100110011001100110011001100101110000 (
1!
#643750
0!
#650000
b111010100011 )
b1111111001100110011001100110011001100110011001100110011000111100 (
1!
#656250
0!
#662500
b111110011100 )
b1100110011001100110011001100110011001100110011001100001000 (
1!
#668750
0!
#675000
b10010110 )
b11111111111111111111111111111111111111111111111111111010100 (
1!
#681250
0!
#687500
b101011101 )
b110011001100110011001100110011001100110011001100110010100000 (
1!
#693750
0!
#700000
b1001010010 )
b1000110011001100110011001100110011001100110011001100101101100 (
1!
#706250
0!
#712500
b1100111101 )
b1011001100110011001100110011001100110011001100110011000111000 (
1!
#718750
0!
#725000
b10000011100 )
b1101100110011001100110011001100110011001100110011001100000100 (
1!
#731250
0!
#737500
b10011101011 )
b1111111111111111111111111111111111111111111111111111111010000 (
1!
#743750
0!
#750000
b10110000011 )
b10010011001100110011001100110011001100110011001100110010011100 (
1!
#756250
0!
#762500
b11000101110 )
b10100110011001100110011001100110011001100110011001100101101000 (
1!
#768750
0!
#775000
b11011000001 )
b10111001100110011001100110011001100110011001100110011000110100 (
1!
#781250
0!
#787500
b11100111010 )
b11001100110011001100110011001100110011001100110011001100000000 (
1!
#793750
0!
#800000
b11110010111 )
b11011111111111111111111111111111111111111111111111111111001100 (
1!
#806250
0!
#812500
b11111001101 )
b11110011001100110011001100110011001100110011001100110010011000 (
1!
#818750
0!
#825000
b11111110101 )
b100000110011001100110011001100110011001100110011001100101100100 (
1!
#831250
0!
#837500
b11111111110 )
b100011001100110011001100110011001100110011001100110011000110000 (
1!
#843750
0!
#850000
b11111101000 )
b100101100110011001100110011001100110011001100110011001011111100 (
1!
#856250
0!
#862500
b11110110100 )
b100111111111111111111111111111111111111111111111111111111001000 (
1!
#868750
0!
#875000
b11101110101 )
b101010011001100110011001100110011001100110011001100110010010100 (
1!
#881250
0!
#887500
b11100001101 )
b101100110011001100110011001100110011001100110011001100101100000 (
1!
#893750
0!
#900000
b11010001001 )
b101111001100110011001100110011001100110011001100110011000101100 (
1!
#906250
0!
#912500
b10111101100 )
b110001100110011001100110011001100110011001100110011001011111000 (
1!
#918750
0!
#925000
b10100111001 )
b110011111111111111111111111111111111111111111111111111111000100 (
1!
#931250
0!
#937500
b10010011010 )
b110110011001100110011001100110011001100110011001100110010010000 (
1!
#943750
0!
#950000
b1111000100 )
b111000110011001100110011001100110011001100110011001100101011100 (
1!
#956250
0!
#962500
b1011100000 )
b111011001100110011001100110011001100110011001100110011000101000 (
1!
#968750
0!
#975000
b111110001 )
b111101100110011001100110011001100110011001100110011001011110100 (
1!
#981250
0!
#987500
b11111010 )
b111111111111111111111111111111111111111111111111111111111000000 (
1!
#993750
0!
#1000000
b110010 )
b1000010011001100110011001100110011001100110011001100110010001100 (
1!
#1006250
0!
#1012500
b111100111000 )
b1000100110011001100110011001100110011001100110011001100101011000 (
1!
#1018750
0!
#1025000
b111001000000 )
b1000111001100110011001100110011001100110011001100110011000100100 (
1!
#1031250
0!
#1037500
b110101001111 )
b1001001100110011001100110011001100110011001100110011001011110000 (
1!
#1043750
0!
#1050000
b110001101000 )
b1001011111111111111111111111111111111111111111111111111110111100 (
1!
#1056250
0!
#1062500
b101110111001 )
b1001110011001100110011001100110011001100110011001100110010001000 (
1!
#1068750
0!
#1075000
b101011101110 )
b1010000110011001100110011001100110011001100110011001100101010100 (
1!
#1081250
0!
#1087500
b101000110110 )
b1010011001100110011001100110011001100110011001100110011000100000 (
1!
#1093750
0!
#1100000
b100110010100 )
b1010101100110011001100110011001100110011001100110011001011101100 (
1!
#1106250
0!
#1112500
b100100001011 )
b1010111111111111111111111111111111111111111111111111111110111000 (
1!
#1118750
0!
#1125000
b100010110001 )
b1011010011001100110011001100110011001100110011001100110010000100 (
1!
#1131250
0!
#1137500
b100001011010 )
b1011100110011001100110011001100110011001100110011001100101010000 (
1!
#1143750
0!
#1150000
b100000100000 )
b1011111001100110011001100110011001100110011001100110011000011100 (
1!
#1156250
0!
#1162500
b100000000100 )
b1100001100110011001100110011001100110011001100110011001011101000 (
1!
#1168750
0!
#1175000
b100000000111 )
b1100011111111111111111111111111111111111111111111111111110110100 (
1!
#1181250
0!
#1187500
b100000100000 )
b1100110011001100110011001100110011001100110011001100110010000000 (
1!
#1193750
0!
#1200000
b100001011010 )
b1101000110011001100110011001100110011001100110011001100101001100 (
1!
#1206250
0!
#1212500
b100010110001 )
b1101011001100110011001100110011001100110011001100110011000011000 (
1!
#1218750
0!
#1225000
b100100100101 )
b1101101100110011001100110011001100110011001100110011001011100100 (
1!
#1231250
0!
#1237500
b100110110011 )
b1101111111111111111111111111111111111111111111111111111110110000 (
1!
#1243750
0!
#1250000
b101000110110 )
b1110010011001100110011001100110011001100110011001100110001111100 (
1!
#1256250
0!
#1262500
b101011101110 )
b1110100110011001100110011001100110011001100110011001100101001000 (
1!
#1268750
0!
#1275000
b101110111001 )
b1110111001100110011001100110011001100110011001100110011000010100 (
1!
#1281250
0!
#1287500
b110010010101 )
b1111001100110011001100110011001100110011001100110011001011100000 (
1!
#1293750
0!
#1300000
b110101111110 )
b1111011111111111111111111111111111111111111111111111111110101100 (
1!
#1306250
0!
#1312500
b111001000000 )
b1111110011001100110011001100110011001100110011001100110001111000 (
1!
#1318750
0!
#1325000
b111100111000 )
b110011001100110011001100110011001100110011001100101000100 (
1!
#1331250
0!
#1337500
b110010 )
b11001100110011001100110011001100110011001100110011000010000 (
1!
#1343750
0!
#1350000
b100101100 )
b101100110011001100110011001100110011001100110011001011011100 (
1!
#1356250
0!
#1362500
b1000100001 )
b111111111111111111111111111111111111111111111111111110101000 (
1!
#1368750
0!
#1375000
b1011100000 )
b1010011001100110011001100110011001100110011001100110001110100 (
1!
#1381250
0!
#1387500
b1111000100 )
b1100110011001100110011001100110011001100110011001100101000000 (
1!
#1393750
0!
#1400000
b10010011010 )
b1111001100110011001100110011001100110011001100110011000001100 (
1!
#1406250
0!
#1412500
b10101011110 )
b10001100110011001100110011001100110011001100110011001011011000 (
1!
#1418750
0!
#1425000
b11000001110 )
b10011111111111111111111111111111111111111111111111111110100100 (
1!
#1431250
0!
#1437500
b11010001001 )
b10110011001100110011001100110011001100110011001100110001110000 (
1!
#1443750
0!
#1450000
b11100001101 )
b11000110011001100110011001100110011001100110011001100100111100 (
1!
#1456250
0!
#1462500
b11101110101 )
b11011001100110011001100110011001100110011001100110011000001000 (
1!
#1468750
0!
#1475000
b11111000001 )
b11101100110011001100110011001100110011001100110011001011010100 (
1!
#1481250
0!
#1487500
b11111101111 )
b11111111111111111111111111111111111111111111111111111110100000 (
1!
#1493750
0!
#1500000
b11111111110 )
b100010011001100110011001100110011001100110011001100110001101100 (
1!
#1506250
0!
#1512500
b11111110101 )
b100100110011001100110011001100110011001100110011001100100111000 (
1!
#1518750
0!
#1525000
b11111001101 )
b100111001100110011001100110011001100110011001100110011000000100 (
1!
#1531250
0!
#1537500
b11110000111 )
b101001100110011001100110011001100110011001100110011001011010000 (
1!
#1543750
0!
#1550000
b11100100100 )
b101011111111111111111111111111111111111111111111111111110011100 (
1!
#1556250
0!
#1562500
b11011000001 )
b101110011001100110011001100110011001100110011001100110001101000 (
1!
#1568750
0!
#1575000
b11000101110 )
b110000110011001100110011001100110011001100110011001100100110100 (
1!
#1581250
0!
#1587500
b10110000011 )
b110011001100110011001100110011001100110011001100110011000000000 (
1!
#1593750
0!
#1600000
b10011000011 )
b110101100110011001100110011001100110011001100110011001011001100 (
1!
#1606250
0!
#1612500
b1111110000 )
b110111111111111111111111111111111111111111111111111111110011000 (
1!
#1618750
0!
#1625000
b1100111101 )
b111010011001100110011001100110011001100110011001100110001100100 (
1!
#1631250
0!
#1637500
b1001010010 )
b111100110011001100110011001100110011001100110011001100100110000 (
1!
#1643750
0!
#1650000
b101011101 )
b111111001100110011001100110011001100110011001100110010111111100 (
1!
#1656250
0!
#1662500
b1100100 )
b1000001100110011001100110011001100110011001100110011001011001000 (
1!
#1668750
0!
#1675000
b111101101010 )
b1000011111111111111111111111111111111111111111111111111110010100 (
1!
#1681250
0!
#1687500
b111010100011 )
b1000110011001100110011001100110011001100110011001100110001100000 (
1!
#1693750
0!
#1700000
b110110101110 )
b1001000110011001100110011001100110011001100110011001100100101100 (
1!
#1706250
0!
#1712500
b110011000011 )
b1001011001100110011001100110011001100110011001100110010111111000 (
1!
#1718750
0!
#1725000
b101111100100 )
b1001101100110011001100110011001100110011001100110011001011000100 (
1!
#1731250
0!
#1737500
b101100010101 )
b1001111111111111111111111111111111111111111111111111111110010000 (
1!
#1743750
0!
#1750000
b101001111101 )
b1010010011001100110011001100110011001100110011001100110001011100 (
1!
#1756250
0!
#1762500
b100111010010 )
b1010100110011001100110011001100110011001100110011001100100101000 (
1!
#1768750
0!
#1775000
b100100111111 )
b1010111001100110011001100110011001100110011001100110010111110100 (
1!
#1781250
0!
#1787500
b100011000110 )
b1011001100110011001100110011001100110011001100110011001011000000 (
1!
#1793750
0!
#1800000
b100001101001 )
b1011011111111111111111111111111111111111111111111111111110001100 (
1!
#1806250
0!
#1812500
b100000110011 )
b1011110011001100110011001100110011001100110011001100110001011000 (
1!
#1818750
0!
#1825000
b100000001011 )
b1100000110011001100110011001100110011001100110011001100100100100 (
1!
#1831250
0!
#1837500
b100000000010 )
b1100011001100110011001100110011001100110011001100110010111110000 (
1!
#1843750
0!
#1850000
b100000011000 )
b1100101100110011001100110011001100110011001100110011001010111100 (
1!
#1856250
0!
#1862500
b100001001100 )
b1100111111111111111111111111111111111111111111111111111110001000 (
1!
#1868750
0!
#1875000
b100010001011 )
b1101010011001100110011001100110011001100110011001100110001010100 (
1!
#1881250
0!
#1887500
b100011110011 )
b1101100110011001100110011001100110011001100110011001100100100000 (
1!
#1893750
0!
#1900000
b100101110111 )
b1101111001100110011001100110011001100110011001100110010111101100 (
1!
#1906250
0!
#1912500
b101000010100 )
b1110001100110011001100110011001100110011001100110011001010111000 (
1!
#1918750
0!
#1925000
b101011000111 )
b1110011111111111111111111111111111111111111111111111111110000100 (
1!
#1931250
0!
#1937500
b101101100110 )
b1110110011001100110011001100110011001100110011001100110001010000 (
1!
#1943750
0!
#1950000
b110000111100 )
b1111000110011001100110011001100110011001100110011001100100011100 (
1!
#1956250
0!
#1962500
b110100100000 )
b1111011001100110011001100110011001100110011001100110010111101000 (
1!
#1968750
0!
#1975000
b111000001111 )
b1111101100110011001100110011001100110011001100110011001010110100 (
1!
#1981250
0!
#1987500
b111100000110 )
b1111111111111111111111111111111111111111111111111111111110000000 (
1!
#1993750
0!
#2000000
b111111001110 )
b10011001100110011001100110011001100110011001100110001001100 (
1!
#2006250
0!
#2012500
b11001000 )
b100110011001100110011001100110011001100110011001100100011000 (
1!
#2018750
0!
#2025000
b111000000 )
b111001100110011001100110011001100110011001100110010111100100 (
1!
#2031250
0!
#2037500
b1010110001 )
b1001100110011001100110011001100110011001100110011001010110000 (
1!
#2043750
0!
#2050000
b1110011000 )
b1011111111111111111111111111111111111111111111111111101111100 (
1!
#2056250
0!
#2062500
b10001000111 )
b1110011001100110011001100110011001100110011001100110001001000 (
1!
#2068750
0!
#2075000
b10100010010 )
b10000110011001100110011001100110011001100110011001100100010100 (
1!
#2081250
0!
#2087500
b10111001010 )
b10011001100110011001100110011001100110011001100110010111100000 (
1!
#2093750
0!
#2100000
b11001101100 )
b10101100110011001100110011001100110011001100110011001010101100 (
1!
#2106250
0!
#2112500
b11011110101 )
b10111111111111111111111111111111111111111111111111111101111000 (
1!
#2118750
0!
#2125000
b11101001111 )
b11010011001100110011001100110011001100110011001100110001000100 (
1!
#2131250
0!
#2137500
b11110100110 )
b11100110011001100110011001100110011001100110011001100100010000 (
1!
#2143750
0!
#2150000
b11111100000 )
b11111001100110011001100110011001100110011001100110010111011100 (
1!
#2156250
0!
#2162500
b11111111100 )
b100001100110011001100110011001100110011001100110011001010101000 (
1!
#2168750
0!
#2175000
b11111111001 )
b100011111111111111111111111111111111111111111111111111101110100 (
1!
#2181250
0!
#2187500
b11111100000 )
b100110011001100110011001100110011001100110011001100110001000000 (
1!
#2193750
0!
#2200000
b11110100110 )
b101000110011001100110011001100110011001100110011001100100001100 (
1!
#2206250
0!
#2212500
b11101001111 )
b101011001100110011001100110011001100110011001100110010111011000 (
1!
#2218750
0!
#2225000
b11011011011 )
b101101100110011001100110011001100110011001100110011001010100100 (
1!
#2231250
0!
#2237500
b11001001101 )
b101111111111111111111111111111111111111111111111111111101110000 (
1!
#2243750
0!
#2250000
b10111001010 )
b110010011001100110011001100110011001100110011001100110000111100 (
1!
#2256250
0!
#2262500
b10100010010 )
b110100110011001100110011001100110011001100110011001100100001000 (
1!
#2268750
0!
#2275000
b10001000111 )
b110111001100110011001100110011001100110011001100110010111010100 (
1!
#2281250
0!
#2287500
b1101101011 )
b111001100110011001100110011001100110011001100110011001010100000 (
1!
#2293750
0!
