Testbenches/PWM/PWM.v
module PWM
(input clk,
input [11:0] DataIn,
output reg PWMOut
);

reg [9:0] counter;
reg [11:0] SimIn;
reg [11:0] DataInNoSign;
reg [11:0] DataInReg;
/*

always @(posedge clk)
	begin
		if (counter == 255)
			SimIn <= SimIn +1;
		else
			SimIn <= SimIn;
	end;

*/

always @(posedge clk)
	begin
		counter <= counter + 1'b 1;
		if (counter == 0)
			DataInReg <= DataIn +  10'd 512;
//			DataInNoSign <= DataIn +  12'd 2048;
	
//		if (counter > (DataInNoSign))  //DataIn is signed
		if (counter > (DataInReg[9:0])) 
			PWMOut <= 1'b 0;
		else
			PWMOut <= 1'b 1;
	end

initial begin
	$dumpfile("PWM_waves.vcd");
	$dumpvars;
end

endmodule

Testbenches/PWM/PWM_waves.vcd
$date
	Thu Apr 18 18:17:10 2024
$end
$version
	Icarus Verilog
$end
$timescale
	1ps
$end
$scope module PWM $end
$var wire 12 ! DataIn [11:0] $end
$var wire 1 " clk $end
$var reg 12 # DataInReg [11:0] $end
$var reg 1 $ PWMOut $end
$var reg 10 % counter [9:0] $end
$upscope $end
$enddefinitions $end
$comment Show the parameter values. $end
$dumpall
$end
#0
$dumpvars
b1 %
1$
b0 #
1"
b111000000000 !
$end
#6250
0"
#12500
0$
b10 %
1"
#18750
0"
#25000
b11 %
1"
#31250
0"
#37500
b100 %
1"
#43750
0"
#50000
b101 %
1"
#56250
0"
#62500
b110 %
1"
#68750
0"
#75000
b111 %
1"
#81250
0"
#87500
b1000 %
1"
#93750
0"
#100000
b1001 %
1"
#106250
0"
#112500
b1010 %
1"
#118750
0"
#125000
b1011 %
1"
#131250
0"
#137500
b1100 %
1"
#143750
0"
#150000
b1101 %
1"
#156250
0"
#162500
b1110 %
1"
#168750
0"
#175000
b1111 %
1"
#181250
0"
#187500
b10000 %
1"
#193750
0"
#200000
b10001 %
1"
#206250
0"
#212500
b10010 %
1"
#218750
0"
#225000
b10011 %
1"
#231250
0"
#237500
b10100 %
1"
#243750
0"
#250000
b10101 %
1"
#256250
0"
#262500
b10110 %
1"
#268750
0"
#275000
b10111 %
1"
#281250
0"
#287500
b11000 %
1"
#293750
0"
#300000
b11001 %
1"
#306250
0"
#312500
b11010 %
1"
#318750
0"
#325000
b11011 %
1"
#331250
0"
#337500
b11100 %
1"
#343750
0"
#350000
b11101 %
1"
#356250
0"
#362500
b11110 %
1"
#368750
0"
#375000
b11111 %
1"
#381250
0"
#387500
b100000 %
1"
#393750
0"
#400000
b100001 %
1"
#406250
0"
#412500
b100010 %
1"
#418750
0"
#425000
b100011 %
1"
#431250
0"
#437500
b100100 %
1"
#443750
0"
#450000
b100101 %
1"
#456250
0"
#462500
b100110 %
1"
#468750
0"
#475000
b100111 %
1"
#481250
0"
#487500
b101000 %
1"
#493750
0"
#500000
b101001 %
1"
#506250
0"
#512500
b101010 %
1"
#518750
0"
#525000
b101011 %
1"
#531250
0"
#537500
b101100 %
1"
#543750
0"
#550000
b101101 %
1"
#556250
0"
#562500
b101110 %
1"
#568750
0"
#575000
b101111 %
1"
#581250
0"
#587500
b110000 %
1"
#593750
0"
#600000
b110001 %
1"
#606250
0"
#612500
b110010 %
1"
#618750
0"
#625000
b110011 %
1"
#631250
0"
#637500
b110100 %
1"
#643750
0"
#650000
b110101 %
1"
#656250
0"
#662500
b110110 %
1"
#668750
0"
#675000
b110111 %
1"
#681250
0"
#687500
b111000 %
1"
#693750
0"
#700000
b111001 %
1"
#706250
0"
#712500
b111010 %
1"
#718750
0"
#725000
b111011 %
1"
#731250
0"
#737500
b111100 %
1"
#743750
0"
#750000
b111101 %
1"
#756250
0"
#762500
b111110 %
1"
#768750
0"
#775000
b111111 %
1"
#781250
0"
#787500
b1000000 %
1"
#793750
0"
#800000
b1000001 %
1"
#806250
0"
#812500
b1000010 %
1"
#818750
0"
#825000
b1000011 %
1"
#831250
0"
#837500
b1000100 %
1"
#843750
0"
#850000
b1000101 %
1"
#856250
0"
#862500
b1000110 %
1"
#868750
0"
#875000
b1000111 %
1"
#881250
0"
#887500
b1001000 %
1"
#893750
0"
#900000
b1001001 %
1"
#906250
0"
#912500
b1001010 %
1"
#918750
0"
#925000
b1001011 %
1"
#931250
0"
#937500
b1001100 %
1"
#943750
0"
#950000
b1001101 %
1"
#956250
0"
#962500
b1001110 %
1"
#968750
0"
#975000
b1001111 %
1"
#981250
0"
#987500
b1010000 %
1"
#993750
0"
#1000000
b1010001 %
1"
#1006250
0"
#1012500
b1010010 %
1"
#1018750
0"
#1025000
b1010011 %
1"
#1031250
0"
#1037500
b1010100 %
1"
#1043750
0"
#1050000
b1010101 %
1"
#1056250
0"
#1062500
b1010110 %
1"
#1068750
0"
#1075000
b1010111 %
1"
#1081250
0"
#1087500
b1011000 %
1"
#1093750
0"
#1100000
b1011001 %
1"
#1106250
0"
#1112500
b1011010 %
1"
#1118750
0"
#1125000
b1011011 %
1"
#1131250
0"
#1137500
b1011100 %
1"
#1143750
0"
#1150000
b1011101 %
1"
#1156250
0"
#1162500
b1011110 %
1"
#1168750
0"
#1175000
b1011111 %
1"
#1181250
0"
#1187500
b1100000 %
1"
#1193750
0"
#1200000
b1100001 %
1"
#1206250
0"
#1212500
b1100010 %
1"
#1218750
0"
#1225000
b1100011 %
1"
#1231250
0"
#1237500
b1100100 %
1"
#1243750
0"
#1250000
b1100101 %
1"
#1256250
0"
#1262500
b1100110 %
1"
#1268750
0"
#1275000
b1100111 %
1"
#1281250
0"
#1287500
b1101000 %
1"
#1293750
0"
#1300000
b1101001 %
1"
#1306250
0"
#1312500
b1101010 %
1"
#1318750
0"
#1325000
b1101011 %
1"
#1331250
0"
#1337500
b1101100 %
1"
#1343750
0"
#1350000
b1101101 %
1"
#1356250
0"
#1362500
b1101110 %
1"
#1368750
0"
#1375000
b1101111 %
1"
#1381250
0"
#1387500
b1110000 %
1"
#1393750
0"
#1400000
b1110001 %
1"
#1406250
0"
#1412500
b1110010 %
1"
#1418750
0"
#1425000
b1110011 %
1"
#1431250
0"
#1437500
b1110100 %
1"
#1443750
0"
#1450000
b1110101 %
1"
#1456250
0"
#1462500
b1110110 %
1"
#1468750
0"
#1475000
b1110111 %
1"
#1481250
0"
#1487500
b1111000 %
1"
#1493750
0"
#1500000
b1111001 %
1"
#1506250
0"
#1512500
b1111010 %
1"
#1518750
0"
#1525000
b1111011 %
1"
#1531250
0"
#1537500
b1111100 %
1"
#1543750
0"
#1550000
b1111101 %
1"
#1556250
0"
#1562500
b1111110 %
1"
#1568750
0"
#1575000
b1111111 %
1"
#1581250
0"
#1587500
b10000000 %
1"
#1593750
0"
#1600000
b10000001 %
1"
#1606250
0"
#1612500
b10000010 %
1"
#1618750
0"
#1625000
b10000011 %
1"
#1631250
0"
#1637500
b10000100 %
1"
#1643750
0"
#1650000
b10000101 %
1"
#1656250
0"
#1662500
b10000110 %
1"
#1668750
0"
#1675000
b10000111 %
1"
#1681250
0"
#1687500
b10001000 %
1"
#1693750
0"
#1700000
b10001001 %
1"
#1706250
0"
#1712500
b10001010 %
1"
#1718750
0"
#1725000
b10001011 %
1"
#1731250
0"
#1737500
b10001100 %
1"
#1743750
0"
#1750000
b10001101 %
1"
#1756250
0"
#1762500
b10001110 %
1"
#1768750
0"
#1775000
b10001111 %
1"
#1781250
0"
#1787500
b10010000 %
1"
#1793750
0"
#1800000
b10010001 %
1"
#1806250
0"
#1812500
b10010010 %
1"
#1818750
0"
#1825000
b10010011 %
1"
#1831250
0"
#1837500
b10010100 %
1"
#1843750
0"
#1850000
b10010101 %
1"
#1856250
0"
#1862500
b10010110 %
1"
#1868750
0"
#1875000
b10010111 %
1"
#1881250
0"
#1887500
b10011000 %
1"
#1893750
0"
#1900000
b10011001 %
1"
#1906250
0"
#1912500
b10011010 %
1"
#1918750
0"
#1925000
b10011011 %
1"
#1931250
0"
#1937500
b10011100 %
1"
#1943750
0"
#1950000
b10011101 %
1"
#1956250
0"
#1962500
b10011110 %
1"
#1968750
0"
#1975000
b10011111 %
1"
#1981250
0"
#1987500
b10100000 %
1"
#1993750
0"
#2000000
b10100001 %
1"
#2006250
0"
#2012500
b10100010 %
1"
#2018750
0"
#2025000
b10100011 %
1"
#2031250
0"
#2037500
b10100100 %
1"
#2043750
0"
#2050000
b10100101 %
1"
#2056250
0"
#2062500
b10100110 %
1"
#2068750
0"
#2075000
b10100111 %
1"
#2081250
0"
#2087500
b10101000 %
1"
#2093750
0"
#2100000
b10101001 %
1"
#2106250
0"
#2112500
b10101010 %
1"
#2118750
0"
#2125000
b10101011 %
1"
#2131250
0"
#2137500
b10101100 %
1"
#2143750
0"
#2150000
b10101101 %
1"
#2156250
0"
#2162500
b10101110 %
1"
#2168750
0"
#2175000
b10101111 %
1"
#2181250
0"
#2187500
b10110000 %
1"
#2193750
0"
#2200000
b10110001 %
1"
#2206250
0"
#2212500
b10110010 %
1"
#2218750
0"
#2225000
b10110011 %
1"
#2231250
0"
#2237500
b10110100 %
1"
#2243750
0"
#2250000
b10110101 %
1"
#2256250
0"
#2262500
b10110110 %
1"
#2268750
0"
#2275000
b10110111 %
1"
#2281250
0"
#2287500
b10111000 %
1"
#2293750
0"
#2300000
b10111001 %
1"
#2306250
0"
#2312500
b10111010 %
1"
#2318750
0"
#2325000
b10111011 %
1"
#2331250
0"
#2337500
b10111100 %
1"
#2343750
0"
#2350000
b10111101 %
1"
#2356250
0"
#2362500
b10111110 %
1"
#2368750
0"
#2375000
b10111111 %
1"
#2381250
0"
#2387500
b11000000 %
1"
#2393750
0"
#2400000
b11000001 %
1"
#2406250
0"
#2412500
b11000010 %
1"
#2418750
0"
#2425000
b11000011 %
1"
#2431250
0"
#2437500
b11000100 %
1"
#2443750
0"
#2450000
b11000101 %
1"
#2456250
0"
#2462500
b11000110 %
1"
#2468750
0"
#2475000
b11000111 %
1"
#2481250
0"
#2487500
b11001000 %
1"
#2493750
0"
#2500000
b11001001 %
1"
#2506250
0"
#2512500
b11001010 %
1"
#2518750
0"
#2525000
b11001011 %
1"
#2531250
0"
#2537500
b11001100 %
1"
#2543750
0"
#2550000
b11001101 %
1"
#2556250
0"
#2562500
b11001110 %
1"
#2568750
0"
#2575000
b11001111 %
1"
#2581250
0"
#2587500
b11010000 %
1"
#2593750
0"
#2600000
b11010001 %
1"
#2606250
0"
#2612500
b11010010 %
1"
#2618750
0"
#2625000
b11010011 %
1"
#2631250
0"
#2637500
b11010100 %
1"
#2643750
0"
#2650000
b11010101 %
1"
#2656250
0"
#2662500
b11010110 %
1"
#2668750
0"
#2675000
b11010111 %
1"
#2681250
0"
#2687500
b11011000 %
1"
#2693750
0"
#2700000
b11011001 %
1"
#2706250
0"
#2712500
b11011010 %
1"
#2718750
0"
#2725000
b11011011 %
1"
#2731250
0"
#2737500
b11011100 %
1"
#2743750
0"
#2750000
b11011101 %
1"
#2756250
0"
#2762500
b11011110 %
1"
#2768750
0"
#2775000
b11011111 %
1"
#2781250
0"
#2787500
b11100000 %
1"
#2793750
0"
#2800000
b11100001 %
1"
#2806250
0"
#2812500
b11100010 %
1"
#2818750
0"
#2825000
b11100011 %
1"
#2831250
0"
#2837500
b11100100 %
1"
#2843750
0"
#2850000
b11100101 %
1"
#2856250
0"
#2862500
b11100110 %
1"
#2868750
0"
#2875000
b11100111 %
1"
#2881250
0"
#2887500
b11101000 %
1"
#2893750
0"
#2900000
b11101001 %
1"
#2906250
0"
#2912500
b11101010 %
1"
#2918750
0"
#2925000
b11101011 %
1"
#2931250
0"
#2937500
b11101100 %
1"
#2943750
0"
#2950000
b11101101 %
1"
#2956250
0"
#2962500
b11101110 %
1"
#2968750
0"
#2975000
b11101111 %
1"
#2981250
0"
#2987500
b11110000 %
1"
#2993750
0"
#3000000
b11110001 %
1"
#3006250
0"
#3012500
b11110010 %
1"
#3018750
0"
#3025000
b11110011 %
1"
#3031250
0"
#3037500
b11110100 %
1"
#3043750
0"
#3050000
b11110101 %
1"
#3056250
0"
#3062500
b11110110 %
1"
#3068750
0"
#3075000
b11110111 %
1"
#3081250
0"
#3087500
b11111000 %
1"
#3093750
0"
#3100000
b11111001 %
1"
#3106250
0"
#3112500
b11111010 %
1"
#3118750
0"
#3125000
b11111011 %
1"
#3131250
0"
#3137500
b11111100 %
1"
#3143750
0"
#3150000
b11111101 %
1"
#3156250
0"
#3162500
b11111110 %
1"
#3168750
0"
#3175000
b11111111 %
1"
#3181250
0"
#3187500
b100000000 %
1"
#3193750
0"
#3200000
b100000001 %
1"
#3206250
0"
#3212500
b100000010 %
1"
#3218750
0"
#3225000
b100000011 %
1"
#3231250
0"
#3237500
b100000100 %
1"
#3243750
0"
#3250000
b100000101 %
1"
#3256250
0"
#3262500
b100000110 %
1"
#3268750
0"
#3275000
b100000111 %
1"
#3281250
0"
#3287500
b100001000 %
1"
#3293750
0"
#3300000
b100001001 %
1"
#3306250
0"
#3312500
b100001010 %
1"
#3318750
0"
#3325000
b100001011 %
1"
#3331250
0"
#3337500
b100001100 %
1"
#3343750
0"
#3350000
b100001101 %
1"
#3356250
0"
#3362500
b100001110 %
1"
#3368750
0"
#3375000
b100001111 %
1"
#3381250
0"
#3387500
b100010000 %
1"
#3393750
0"
#3400000
b100010001 %
1"
#3406250
0"
#3412500
b100010010 %
1"
#3418750
0"
#3425000
b100010011 %
1"
#3431250
0"
#3437500
b100010100 %
1"
#3443750
0"
#3450000
b100010101 %
1"
#3456250
0"
#3462500
b100010110 %
1"
#3468750
0"
#3475000
b100010111 %
1"
#3481250
0"
#3487500
b100011000 %
1"
#3493750
0"
#3500000
b100011001 %
1"
#3506250
0"
#3512500
b100011010 %
1"
#3518750
0"
#3525000
b100011011 %
1"
#3531250
0"
#3537500
b100011100 %
1"
#3543750
0"
#3550000
b100011101 %
1"
#3556250
0"
#3562500
b100011110 %
1"
#3568750
0"
#3575000
b100011111 %
1"
#3581250
0"
#3587500
b100100000 %
1"
#3593750
0"
#3600000
b100100001 %
1"
#3606250
0"
#3612500
b100100010 %
1"
#3618750
0"
#3625000
b100100011 %
1"
#3631250
0"
#3637500
b100100100 %
1"
#3643750
0"
#3650000
b100100101 %
1"
#3656250
0"
#3662500
b100100110 %
1"
#3668750
0"
#3675000
b100100111 %
1"
#3681250
0"
#3687500
b100101000 %
1"
#3693750
0"
#3700000
b100101001 %
1"
#3706250
0"
#3712500
b100101010 %
1"
#3718750
0"
#3725000
b100101011 %
1"
#3731250
0"
#3737500
b100101100 %
1"
#3743750
0"
#3750000
b100101101 %
1"
#3756250
0"
#3762500
b100101110 %
1"
#3768750
0"
#3775000
b100101111 %
1"
#3781250
0"
#3787500
b100110000 %
1"
#3793750
0"
#3800000
b100110001 %
1"
#3806250
0"
#3812500
b100110010 %
1"
#3818750
0"
#3825000
b100110011 %
1"
#3831250
0"
#3837500
b100110100 %
1"
#3843750
0"
#3850000
b100110101 %
1"
#3856250
0"
#3862500
b100110110 %
1"
#3868750
0"
#3875000
b100110111 %
1"
#3881250
0"
#3887500
b100111000 %
1"
#3893750
0"
#3900000
b100111001 %
1"
#3906250
0"
#3912500
b100111010 %
1"
#3918750
0"
#3925000
b100111011 %
1"
#3931250
0"
#3937500
b100111100 %
1"
#3943750
0"
#3950000
b100111101 %
1"
#3956250
0"
#3962500
b100111110 %
1"
#3968750
0"
#3975000
b100111111 %
1"
#3981250
0"
#3987500
b101000000 %
1"
#3993750
0"
#4000000
b101000001 %
1"
#4006250
0"
#4012500
b101000010 %
1"
#4018750
0"
#4025000
b101000011 %
1"
#4031250
0"
#4037500
b101000100 %
1"
#4043750
0"
#4050000
b101000101 %
1"
#4056250
0"
#4062500
b101000110 %
1"
#4068750
0"
#4075000
b101000111 %
1"
#4081250
0"
#4087500
b101001000 %
1"
#4093750
0"
#4100000
b101001001 %
1"
#4106250
0"
#4112500
b101001010 %
1"
#4118750
0"
#4125000
b101001011 %
1"
#4131250
0"
#4137500
b101001100 %
1"
#4143750
0"
#4150000
b101001101 %
1"
#4156250
0"
#4162500
b101001110 %
1"
#4168750
0"
#4175000
b101001111 %
1"
#4181250
0"
#4187500
b101010000 %
1"
#4193750
0"
#4200000
b101010001 %
1"
#4206250
0"
#4212500
b101010010 %
1"
#4218750
0"
#4225000
b101010011 %
1"
#4231250
0"
#4237500
b101010100 %
1"
#4243750
0"
#4250000
b101010101 %
1"
#4256250
0"
#4262500
b101010110 %
1"
#4268750
0"
#4275000
b101010111 %
1"
#4281250
0"
#4287500
b101011000 %
1"
#4293750
0"
#4300000
b101011001 %
1"
#4306250
0"
#4312500
b101011010 %
1"
#4318750
0"
#4325000
b101011011 %
1"
#4331250
0"
#4337500
b101011100 %
1"
#4343750
0"
#4350000
b101011101 %
1"
#4356250
0"
#4362500
b101011110 %
1"
#4368750
0"
#4375000
b101011111 %
1"
#4381250
0"
#4387500
b101100000 %
1"
#4393750
0"
#4400000
b101100001 %
1"
#4406250
0"
#4412500
b101100010 %
1"
#4418750
0"
#4425000
b101100011 %
1"
#4431250
0"
#4437500
b101100100 %
1"
#4443750
0"
#4450000
b101100101 %
1"
#4456250
0"
#4462500
b101100110 %
1"
#4468750
0"
#4475000
b101100111 %
1"
#4481250
0"
#4487500
b101101000 %
1"
#4493750
0"
#4500000
b101101001 %
1"
#4506250
0"
#4512500
b101101010 %
1"
#4518750
0"
#4525000
b101101011 %
1"
#4531250
0"
#4537500
b101101100 %
1"
#4543750
0"
#4550000
b101101101 %
1"
#4556250
0"
#4562500
b101101110 %
1"
#4568750
0"
#4575000
b101101111 %
1"
#4581250
0"
#4587500
b101110000 %
1"
#4593750
0"
#4600000
b101110001 %
1"
#4606250
0"
#4612500
b101110010 %
1"
#4618750
0"
#4625000
b101110011 %
1"
#4631250
0"
#4637500
b101110100 %
1"
#4643750
0"
#4650000
b101110101 %
1"
#4656250
0"
#4662500
b101110110 %
1"
#4668750
0"
#4675000
b101110111 %
1"
#4681250
0"
#4687500
b101111000 %
1"
#4693750
0"
#4700000
b101111001 %
1"
#4706250
0"
#4712500
b101111010 %
1"
#4718750
0"
#4725000
b101111011 %
1"
#4731250
0"
#4737500
b101111100 %
1"
#4743750
0"
#4750000
b101111101 %
1"
#4756250
0"
#4762500
b101111110 %
1"
#4768750
0"
#4775000
b101111111 %
1"
#4781250
0"
#4787500
b110000000 %
1"
#4793750
0"
#4800000
b110000001 %
1"
#4806250
0"
#4812500
b110000010 %
1"
#4818750
0"
#4825000
b110000011 %
1"
#4831250
0"
#4837500
b110000100 %
1"
#4843750
0"
#4850000
b110000101 %
1"
#4856250
0"
#4862500
b110000110 %
1"
#4868750
0"
#4875000
b110000111 %
1"
#4881250
0"
#4887500
b110001000 %
1"
#4893750
0"
#4900000
b110001001 %
1"
#4906250
0"
#4912500
b110001010 %
1"
#4918750
0"
#4925000
b110001011 %
1"
#4931250
0"
#4937500
b110001100 %
1"
#4943750
0"
#4950000
b110001101 %
1"
#4956250
0"
#4962500
b110001110 %
1"
#4968750
0"
#4975000
b110001111 %
1"
#4981250
0"
#4987500
b110010000 %
1"
#4993750
0"
#5000000
b110010001 %
1"
#5006250
0"
#5012500
b110010010 %
1"
#5018750
0"
#5025000
b110010011 %
1"
#5031250
0"
#5037500
b110010100 %
1"
#5043750
0"
#5050000
b110010101 %
1"
#5056250
0"
#5062500
b110010110 %
1"
#5068750
0"
#5075000
b110010111 %
1"
#5081250
0"
#5087500
b110011000 %
1"
#5093750
0"
#5100000
b110011001 %
1"
#5106250
0"
#5112500
b110011010 %
1"
#5118750
0"
#5125000
b110011011 %
1"
#5131250
0"
#5137500
b110011100 %
1"
#5143750
0"
#5150000
b110011101 %
1"
#5156250
0"
#5162500
b110011110 %
1"
#5168750
0"
#5175000
b110011111 %
1"
#5181250
0"
#5187500
b110100000 %
1"
#5193750
0"
#5200000
b110100001 %
1"
#5206250
0"
#5212500
b110100010 %
1"
#5218750
0"
#5225000
b110100011 %
1"
#5231250
0"
#5237500
b110100100 %
1"
#5243750
0"
#5250000
b110100101 %
1"
#5256250
0"
#5262500
b110100110 %
1"
#5268750
0"
#5275000
b110100111 %
1"
#5281250
0"
#5287500
b110101000 %
1"
#5293750
0"
#5300000
b110101001 %
1"
#5306250
0"
#5312500
b110101010 %
1"
#5318750
0"
#5325000
b110101011 %
1"
#5331250
0"
#5337500
b110101100 %
1"
#5343750
0"
#5350000
b110101101 %
1"
#5356250
0"
#5362500
b110101110 %
1"
#5368750
0"
#5375000
b110101111 %
1"
#5381250
0"
#5387500
b110110000 %
1"
#5393750
0"
#5400000
b110110001 %
1"
#5406250
0"
#5412500
b110110010 %
1"
#5418750
0"
#5425000
b110110011 %
1"
#5431250
0"
#5437500
b110110100 %
1"
#5443750
0"
#5450000
b110110101 %
1"
#5456250
0"
#5462500
b110110110 %
1"
#5468750
0"
#5475000
b110110111 %
1"
#5481250
0"
#5487500
b110111000 %
1"
#5493750
0"
#5500000
b110111001 %
1"
#5506250
0"
#5512500
b110111010 %
1"
#5518750
0"
#5525000
b110111011 %
1"
#5531250
0"
#5537500
b110111100 %
1"
#5543750
0"
#5550000
b110111101 %
1"
#5556250
0"
#5562500
b110111110 %
1"
#5568750
0"
#5575000
b110111111 %
1"
#5581250
0"
#5587500
b111000000 %
1"
#5593750
0"
#5600000
b111000001 %
1"
#5606250
0"
#5612500
b111000010 %
1"
#5618750
0"
#5625000
b111000011 %
1"
#5631250
0"
#5637500
b111000100 %
1"
#5643750
0"
#5650000
b111000101 %
1"
#5656250
0"
#5662500
b111000110 %
1"
#5668750
0"
#5675000
b111000111 %
1"
#5681250
0"
#5687500
b111001000 %
1"
#5693750
0"
#5700000
b111001001 %
1"
#5706250
0"
#5712500
b111001010 %
1"
#5718750
0"
#5725000
b111001011 %
1"
#5731250
0"
#5737500
b111001100 %
1"
#5743750
0"
#5750000
b111001101 %
1"
#5756250
0"
#5762500
b111001110 %
1"
#5768750
0"
#5775000
b111001111 %
1"
#5781250
0"
#5787500
b111010000 %
1"
#5793750
0"
#5800000
b111010001 %
1"
#5806250
0"
#5812500
b111010010 %
1"
#5818750
0"
#5825000
b111010011 %
1"
#5831250
0"
#5837500
b111010100 %
1"
#5843750
0"
#5850000
b111010101 %
1"
#5856250
0"
#5862500
b111010110 %
1"
#5868750
0"
#5875000
b111010111 %
1"
#5881250
0"
#5887500
b111011000 %
1"
#5893750
0"
#5900000
b111011001 %
1"
#5906250
0"
#5912500
b111011010 %
1"
#5918750
0"
#5925000
b111011011 %
1"
#5931250
0"
#5937500
b111011100 %
1"
#5943750
0"
#5950000
b111011101 %
1"
#5956250
0"
#5962500
b111011110 %
1"
#5968750
0"
#5975000
b111011111 %
1"
#5981250
0"
#5987500
b111100000 %
1"
#5993750
0"
#6000000
b111100001 %
1"
#6006250
0"
#6012500
b111100010 %
1"
#6018750
0"
#6025000
b111100011 %
1"
#6031250
0"
#6037500
b111100100 %
1"
#6043750
0"
#6050000
b111100101 %
1"
#6056250
0"
#6062500
b111100110 %
1"
#6068750
0"
#6075000
b111100111 %
1"
#6081250
0"
#6087500
b111101000 %
1"
#6093750
0"
#6100000
b111101001 %
1"
#6106250
0"
#6112500
b111101010 %
1"
#6118750
0"
#6125000
b111101011 %
1"
#6131250
0"
#6137500
b111101100 %
1"
#6143750
0"
#6150000
b111101101 %
1"
#6156250
0"
#6162500
b111101110 %
1"
#6168750
0"
#6175000
b111101111 %
1"
#6181250
0"
#6187500
b111110000 %
1"
#6193750
0"
#6200000
b111110001 %
1"
#6206250
0"
#6212500
b111110010 %
1"
#6218750
0"
#6225000
b111110011 %
1"
#6231250
0"
#6237500
b111110100 %
1"
#6243750
0"
#6250000
b111110101 %
1"
#6256250
0"
#6262500
b111110110 %
1"
#6268750
0"
#6275000
b111110111 %
1"
#6281250
0"
#6287500
b111111000 %
1"
#6293750
0"
#6300000
b111111001 %
1"
#6306250
0"
#6312500
b111111010 %
1"
#6318750
0"
#6325000
b111111011 %
1"
#6331250
0"
#6337500
b111111100 %
1"
#6343750
0"
#6350000
b111111101 %
1"
#6356250
0"
#6362500
b111111110 %
1"
#6368750
0"
#6375000
b111111111 %
1"
#6381250
0"
#6387500
b1000000000 %
1"
#6393750
0"
#6400000
b1000000001 %
1"
#6406250
0"
#6412500
b1000000010 %
1"
#6418750
0"
#6425000
b1000000011 %
1"
#6431250
0"
#6437500
b1000000100 %
1"
#6443750
0"
#6450000
b1000000101 %
1"
#6456250
0"
#6462500
b1000000110 %
1"
#6468750
0"
#6475000
b1000000111 %
1"
#6481250
0"
#6487500
b1000001000 %
1"
#6493750
0"
#6500000
b1000001001 %
1"
#6506250
0"
#6512500
b1000001010 %
1"
#6518750
0"
#6525000
b1000001011 %
1"
#6531250
0"
#6537500
b1000001100 %
1"
#6543750
0"
#6550000
b1000001101 %
1"
#6556250
0"
#6562500
b1000001110 %
1"
#6568750
0"
#6575000
b1000001111 %
1"
#6581250
0"
#6587500
b1000010000 %
1"
#6593750
0"
#6600000
b1000010001 %
1"
#6606250
0"
#6612500
b1000010010 %
1"
#6618750
0"
#6625000
b1000010011 %
1"
#6631250
0"
#6637500
b1000010100 %
1"
#6643750
0"
#6650000
b1000010101 %
1"
#6656250
0"
#6662500
b1000010110 %
1"
#6668750
0"
#6675000
b1000010111 %
1"
#6681250
0"
#6687500
b1000011000 %
1"
#6693750
0"
#6700000
b1000011001 %
1"
#6706250
0"
#6712500
b1000011010 %
1"
#6718750
0"
#6725000
b1000011011 %
1"
#6731250
0"
#6737500
b1000011100 %
1"
#6743750
0"
#6750000
b1000011101 %
1"
#6756250
0"
#6762500
b1000011110 %
1"
#6768750
0"
#6775000
b1000011111 %
1"
#6781250
0"
#6787500
b1000100000 %
1"
#6793750
0"
#6800000
b1000100001 %
1"
#6806250
0"
#6812500
b1000100010 %
1"
#6818750
0"
#6825000
b1000100011 %
1"
#6831250
0"
#6837500
b1000100100 %
1"
#6843750
0"
#6850000
b1000100101 %
1"
#6856250
0"
#6862500
b1000100110 %
1"
#6868750
0"
#6875000
b1000100111 %
1"
#6881250
0"
#6887500
b1000101000 %
1"
#6893750
0"
#6900000
b1000101001 %
1"
#6906250
0"
#6912500
b1000101010 %
1"
#6918750
0"
#6925000
b1000101011 %
1"
#6931250
0"
#6937500
b1000101100 %
1"
#6943750
0"
#6950000
b1000101101 %
1"
#6956250
0"
#6962500
b1000101110 %
1"
#6968750
0"
#6975000
b1000101111 %
1"
#6981250
0"
#6987500
b1000110000 %
1"
#6993750
0"
#7000000
b1000110001 %
1"
#7006250
0"
#7012500
b1000110010 %
1"
#7018750
0"
#7025000
b1000110011 %
1"
#7031250
0"
#7037500
b1000110100 %
1"
#7043750
0"
#7050000
b1000110101 %
1"
#7056250
0"
#7062500
b1000110110 %
1"
#7068750
0"
#7075000
b1000110111 %
1"
#7081250
0"
#7087500
b1000111000 %
1"
#7093750
0"
#7100000
b1000111001 %
1"
#7106250
0"
#7112500
b1000111010 %
1"
#7118750
0"
#7125000
b1000111011 %
1"
#7131250
0"
#7137500
b1000111100 %
1"
#7143750
0"
#7150000
b1000111101 %
1"
#7156250
0"
#7162500
b1000111110 %
1"
#7168750
0"
#7175000
b1000111111 %
1"
#7181250
0"
#7187500
b1001000000 %
1"
#7193750
0"
#7200000
b1001000001 %
1"
#7206250
0"
#7212500
b1001000010 %
1"
#7218750
0"
#7225000
b1001000011 %
1"
#7231250
0"
#7237500
b1001000100 %
1"
#7243750
0"
#7250000
b1001000101 %
1"
#7256250
0"
#7262500
b1001000110 %
1"
#7268750
0"
#7275000
b1001000111 %
1"
#7281250
0"
#7287500
b1001001000 %
1"
#7293750
0"
#7300000
b1001001001 %
1"
#7306250
0"
#7312500
b1001001010 %
1"
#7318750
0"
#7325000
b1001001011 %
1"
#7331250
0"
#7337500
b1001001100 %
1"
#7343750
0"
#7350000
b1001001101 %
1"
#7356250
0"
#7362500
b1001001110 %
1"
#7368750
0"
#7375000
b1001001111 %
1"
#7381250
0"
#7387500
b1001010000 %
1"
#7393750
0"
#7400000
b1001010001 %
1"
#7406250
0"
#7412500
b1001010010 %
1"
#7418750
0"
#7425000
b1001010011 %
1"
#7431250
0"
#7437500
b1001010100 %
1"
#7443750
0"
#7450000
b1001010101 %
1"
#7456250
0"
#7462500
b1001010110 %
1"
#7468750
0"
#7475000
b1001010111 %
1"
#7481250
0"
#7487500
b1001011000 %
1"
#7493750
0"
#7500000
b1001011001 %
1"
#7506250
0"
#7512500
b1001011010 %
1"
#7518750
0"
#7525000
b1001011011 %
1"
#7531250
0"
#7537500
b1001011100 %
1"
#7543750
0"
#7550000
b1001011101 %
1"
#7556250
0"
#7562500
b1001011110 %
1"
#7568750
0"
#7575000
b1001011111 %
1"
#7581250
0"
#7587500
b1001100000 %
1"
#7593750
0"
#7600000
b1001100001 %
1"
#7606250
0"
#7612500
b1001100010 %
1"
#7618750
0"
#7625000
b1001100011 %
1"
#7631250
0"
#7637500
b1001100100 %
1"
#7643750
0"
#7650000
b1001100101 %
1"
#7656250
0"
#7662500
b1001100110 %
1"
#7668750
0"
#7675000
b1001100111 %
1"
#7681250
0"
#7687500
b1001101000 %
1"
#7693750
0"
#7700000
b1001101001 %
1"
#7706250
0"
#7712500
b1001101010 %
1"
#7718750
0"
#7725000
b1001101011 %
1"
#7731250
0"
#7737500
b1001101100 %
1"
#7743750
0"
#7750000
b1001101101 %
1"
#7756250
0"
#7762500
b1001101110 %
1"
#7768750
0"
#7775000
b1001101111 %
1"
#7781250
0"
#7787500
b1001110000 %
1"
#7793750
0"
#7800000
b1001110001 %
1"
#7806250
0"
#7812500
b1001110010 %
1"
#7818750
0"
#7825000
b1001110011 %
1"
#7831250
0"
#7837500
b1001110100 %
1"
#7843750
0"
#7850000
b1001110101 %
1"
#7856250
0"
#7862500
b1001110110 %
1"
