Testbenches/PWM/PWM.v
module PWM
(input clk,
input [11:0] DataIn,
output reg PWMOut
);

reg [9:0] counter;
reg [11:0] SimIn;
reg [11:0] DataInNoSign;
reg [11:0] DataInReg;
/*

always @(posedge clk)
	begin
		if (counter == 255)
			SimIn <= SimIn +1;
		else
			SimIn <= SimIn;
	end;

*/

always @(posedge clk)
	begin
		counter <= counter + 1'b 1;
		if (counter == 0)
			DataInReg <= DataIn+  10'd 512;
//			DataInNoSign <= DataIn +  12'd 2048;
	
//		if (counter > (DataInNoSign))  //DataIn is signed
		if (counter > (DataInReg[9:0])) 
			PWMOut <= 1'b 0;
		else
			PWMOut <= 1'b 1;
	end

initial begin
	$dumpfile("PWM_waves.vcd");
	$dumpvars;
end

endmodule

Testbenches/PWM/PWM_waves.vcd
$date
	Sat Mar 30 22:02:49 2024
$end
$version
	Icarus Verilog
$end
$timescale
	1ps
$end
$scope module PWM $end
$var wire 12 ! DataIn [11:0] $end
$var wire 1 " clk $end
$var reg 12 # DataInReg [11:0] $end
$var reg 1 $ PWMOut $end
$var reg 10 % counter [9:0] $end
$upscope $end
$enddefinitions $end
$comment Show the parameter values. $end
$dumpall
$end
#0
$dumpvars
b0 %
1$
bx #
1"
b111000000000 !
$end
#2500
0"
#5000
b0 #
b1 %
1"
#7500
0"
#10000
0$
b10 %
1"
#12500
0"
#15000
b11 %
1"
#17500
0"
#20000
b100 %
1"
#22500
0"
#25000
b101 %
1"
#27500
0"
#30000
b110 %
1"
#32500
0"
#35000
b111 %
1"
#37500
0"
#40000
b1000 %
1"
#42500
0"
#45000
b1001 %
1"
#47500
0"
#50000
b1010 %
1"
#52500
0"
#55000
b1011 %
1"
#57500
0"
#60000
b1100 %
1"
#62500
0"
#65000
b1101 %
1"
#67500
0"
#70000
b1110 %
1"
#72500
0"
#75000
b1111 %
1"
#77500
0"
#80000
b10000 %
1"
#82500
0"
#85000
b10001 %
1"
#87500
0"
#90000
b10010 %
1"
#92500
0"
#95000
b10011 %
1"
#97500
0"
#100000
b10100 %
1"
#102500
0"
#105000
b10101 %
1"
#107500
0"
#110000
b10110 %
1"
#112500
0"
#115000
b10111 %
1"
#117500
0"
#120000
b11000 %
1"
#122500
0"
#125000
b11001 %
1"
#127500
0"
#130000
b11010 %
1"
#132500
0"
#135000
b11011 %
1"
#137500
0"
#140000
b11100 %
1"
#142500
0"
#145000
b11101 %
1"
#147500
0"
#150000
b11110 %
1"
#152500
0"
#155000
b11111 %
1"
#157500
0"
#160000
b100000 %
1"
#162500
0"
#165000
b100001 %
1"
#167500
0"
#170000
b100010 %
1"
#172500
0"
#175000
b100011 %
1"
#177500
0"
#180000
b100100 %
1"
#182500
0"
#185000
b100101 %
1"
#187500
0"
#190000
b100110 %
1"
#192500
0"
#195000
b100111 %
1"
#197500
0"
#200000
b101000 %
1"
#202500
0"
#205000
b101001 %
1"
#207500
0"
#210000
b101010 %
1"
#212500
0"
#215000
b101011 %
1"
#217500
0"
#220000
b101100 %
1"
#222500
0"
#225000
b101101 %
1"
#227500
0"
#230000
b101110 %
1"
#232500
0"
#235000
b101111 %
1"
#237500
0"
#240000
b110000 %
1"
#242500
0"
#245000
b110001 %
1"
#247500
0"
#250000
b110010 %
1"
#252500
0"
#255000
b110011 %
1"
#257500
0"
#260000
b110100 %
1"
#262500
0"
#265000
b110101 %
1"
#267500
0"
#270000
b110110 %
1"
#272500
0"
#275000
b110111 %
1"
#277500
0"
#280000
b111000 %
1"
#282500
0"
#285000
b111001 %
1"
#287500
0"
#290000
b111010 %
1"
#292500
0"
#295000
b111011 %
1"
#297500
0"
#300000
b111100 %
1"
#302500
0"
#305000
b111101 %
1"
#307500
0"
#310000
b111110 %
1"
#312500
0"
#315000
b111111 %
1"
#317500
0"
#320000
b1000000 %
1"
#322500
0"
#325000
b1000001 %
1"
#327500
0"
#330000
b1000010 %
1"
#332500
0"
#335000
b1000011 %
1"
#337500
0"
#340000
b1000100 %
1"
#342500
0"
#345000
b1000101 %
1"
#347500
0"
#350000
b1000110 %
1"
#352500
0"
#355000
b1000111 %
1"
#357500
0"
#360000
b1001000 %
1"
#362500
0"
#365000
b1001001 %
1"
#367500
0"
#370000
b1001010 %
1"
#372500
0"
#375000
b1001011 %
1"
#377500
0"
#380000
b1001100 %
1"
#382500
0"
#385000
b1001101 %
1"
#387500
0"
#390000
b1001110 %
1"
#392500
0"
#395000
b1001111 %
1"
#397500
0"
#400000
b1010000 %
1"
#402500
0"
#405000
b1010001 %
1"
#407500
0"
#410000
b1010010 %
1"
#412500
0"
#415000
b1010011 %
1"
#417500
0"
#420000
b1010100 %
1"
#422500
0"
#425000
b1010101 %
1"
#427500
0"
#430000
b1010110 %
1"
#432500
0"
#435000
b1010111 %
1"
#437500
0"
#440000
b1011000 %
1"
#442500
0"
#445000
b1011001 %
1"
#447500
0"
#450000
b1011010 %
1"
#452500
0"
#455000
b1011011 %
1"
#457500
0"
#460000
b1011100 %
1"
#462500
0"
#465000
b1011101 %
1"
#467500
0"
#470000
b1011110 %
1"
#472500
0"
#475000
b1011111 %
1"
#477500
0"
#480000
b1100000 %
1"
#482500
0"
#485000
b1100001 %
1"
#487500
0"
#490000
b1100010 %
1"
#492500
0"
#495000
b1100011 %
1"
#497500
0"
#500000
b1100100 %
1"
#502500
0"
#505000
b1100101 %
1"
#507500
0"
#510000
b1100110 %
1"
#512500
0"
#515000
b1100111 %
1"
#517500
0"
#520000
b1101000 %
1"
#522500
0"
#525000
b1101001 %
1"
#527500
0"
#530000
b1101010 %
1"
#532500
0"
#535000
b1101011 %
1"
#537500
0"
#540000
b1101100 %
1"
#542500
0"
#545000
b1101101 %
1"
#547500
0"
#550000
b1101110 %
1"
#552500
0"
#555000
b1101111 %
1"
#557500
0"
#560000
b1110000 %
1"
#562500
0"
#565000
b1110001 %
1"
#567500
0"
#570000
b1110010 %
1"
#572500
0"
#575000
b1110011 %
1"
#577500
0"
#580000
b1110100 %
1"
#582500
0"
#585000
b1110101 %
1"
#587500
0"
#590000
b1110110 %
1"
#592500
0"
#595000
b1110111 %
1"
#597500
0"
#600000
b1111000 %
1"
#602500
0"
#605000
b1111001 %
1"
#607500
0"
#610000
b1111010 %
1"
#612500
0"
#615000
b1111011 %
1"
#617500
0"
#620000
b1111100 %
1"
#622500
0"
#625000
b1111101 %
1"
#627500
0"
#630000
b1111110 %
1"
#632500
0"
#635000
b1111111 %
1"
#637500
0"
#640000
b10000000 %
1"
#642500
0"
#645000
b10000001 %
1"
#647500
0"
#650000
b10000010 %
1"
#652500
0"
#655000
b10000011 %
1"
#657500
0"
#660000
b10000100 %
1"
#662500
0"
#665000
b10000101 %
1"
#667500
0"
#670000
b10000110 %
1"
#672500
0"
#675000
b10000111 %
1"
#677500
0"
#680000
b10001000 %
1"
#682500
0"
#685000
b10001001 %
1"
#687500
0"
#690000
b10001010 %
1"
#692500
0"
#695000
b10001011 %
1"
#697500
0"
#700000
b10001100 %
1"
#702500
0"
#705000
b10001101 %
1"
#707500
0"
#710000
b10001110 %
1"
#712500
0"
#715000
b10001111 %
1"
#717500
0"
#720000
b10010000 %
1"
#722500
0"
#725000
b10010001 %
1"
#727500
0"
#730000
b10010010 %
1"
#732500
0"
#735000
b10010011 %
1"
#737500
0"
#740000
b10010100 %
1"
#742500
0"
#745000
b10010101 %
1"
#747500
0"
#750000
b10010110 %
1"
#752500
0"
#755000
b10010111 %
1"
#757500
0"
#760000
b10011000 %
1"
#762500
0"
#765000
b10011001 %
1"
#767500
0"
#770000
b10011010 %
1"
#772500
0"
#775000
b10011011 %
1"
#777500
0"
#780000
b10011100 %
1"
#782500
0"
#785000
b10011101 %
1"
#787500
0"
#790000
b10011110 %
1"
#792500
0"
#795000
b10011111 %
1"
#797500
0"
#800000
b10100000 %
1"
#802500
0"
#805000
b10100001 %
1"
#807500
0"
#810000
b10100010 %
1"
#812500
0"
#815000
b10100011 %
1"
#817500
0"
#820000
b10100100 %
1"
#822500
0"
#825000
b10100101 %
1"
#827500
0"
#830000
b10100110 %
1"
#832500
0"
#835000
b10100111 %
1"
#837500
0"
#840000
b10101000 %
1"
#842500
0"
#845000
b10101001 %
1"
#847500
0"
#850000
b10101010 %
1"
#852500
0"
#855000
b10101011 %
1"
#857500
0"
#860000
b10101100 %
1"
#862500
0"
#865000
b10101101 %
1"
#867500
0"
#870000
b10101110 %
1"
#872500
0"
#875000
b10101111 %
1"
#877500
0"
#880000
b10110000 %
1"
#882500
0"
#885000
b10110001 %
1"
#887500
0"
#890000
b10110010 %
1"
#892500
0"
#895000
b10110011 %
1"
#897500
0"
#900000
b10110100 %
1"
#902500
0"
#905000
b10110101 %
1"
#907500
0"
#910000
b10110110 %
1"
#912500
0"
#915000
b10110111 %
1"
#917500
0"
#920000
b10111000 %
1"
#922500
0"
#925000
b10111001 %
1"
#927500
0"
#930000
b10111010 %
1"
#932500
0"
#935000
b10111011 %
1"
#937500
0"
#940000
b10111100 %
1"
#942500
0"
#945000
b10111101 %
1"
#947500
0"
#950000
b10111110 %
1"
#952500
0"
#955000
b10111111 %
1"
#957500
0"
#960000
b11000000 %
1"
#962500
0"
#965000
b11000001 %
1"
#967500
0"
#970000
b11000010 %
1"
#972500
0"
#975000
b11000011 %
1"
#977500
0"
#980000
b11000100 %
1"
#982500
0"
#985000
b11000101 %
1"
#987500
0"
#990000
b11000110 %
1"
#992500
0"
#995000
b11000111 %
1"
#997500
0"
#1000000
b11001000 %
1"
#1002500
0"
#1005000
b11001001 %
1"
#1007500
0"
#1010000
b11001010 %
1"
#1012500
0"
#1015000
b11001011 %
1"
#1017500
0"
#1020000
b11001100 %
1"
#1022500
0"
#1025000
b11001101 %
1"
#1027500
0"
#1030000
b11001110 %
1"
#1032500
0"
#1035000
b11001111 %
1"
#1037500
0"
#1040000
b11010000 %
1"
#1042500
0"
#1045000
b11010001 %
1"
#1047500
0"
#1050000
b11010010 %
1"
#1052500
0"
#1055000
b11010011 %
1"
#1057500
0"
#1060000
b11010100 %
1"
#1062500
0"
#1065000
b11010101 %
1"
#1067500
0"
#1070000
b11010110 %
1"
#1072500
0"
#1075000
b11010111 %
1"
#1077500
0"
#1080000
b11011000 %
1"
#1082500
0"
#1085000
b11011001 %
1"
#1087500
0"
#1090000
b11011010 %
1"
#1092500
0"
#1095000
b11011011 %
1"
#1097500
0"
#1100000
b11011100 %
1"
#1102500
0"
#1105000
b11011101 %
1"
#1107500
0"
#1110000
b11011110 %
1"
#1112500
0"
#1115000
b11011111 %
1"
#1117500
0"
#1120000
b11100000 %
1"
#1122500
0"
#1125000
b11100001 %
1"
#1127500
0"
#1130000
b11100010 %
1"
#1132500
0"
#1135000
b11100011 %
1"
#1137500
0"
#1140000
b11100100 %
1"
#1142500
0"
#1145000
b11100101 %
1"
#1147500
0"
#1150000
b11100110 %
1"
#1152500
0"
#1155000
b11100111 %
1"
#1157500
0"
#1160000
b11101000 %
1"
#1162500
0"
#1165000
b11101001 %
1"
#1167500
0"
#1170000
b11101010 %
1"
#1172500
0"
#1175000
b11101011 %
1"
#1177500
0"
#1180000
b11101100 %
1"
#1182500
0"
#1185000
b11101101 %
1"
#1187500
0"
#1190000
b11101110 %
1"
#1192500
0"
#1195000
b11101111 %
1"
#1197500
0"
#1200000
b11110000 %
1"
#1202500
0"
#1205000
b11110001 %
1"
#1207500
0"
#1210000
b11110010 %
1"
#1212500
0"
#1215000
b11110011 %
1"
#1217500
0"
#1220000
b11110100 %
1"
#1222500
0"
#1225000
b11110101 %
1"
#1227500
0"
#1230000
b11110110 %
1"
#1232500
0"
#1235000
b11110111 %
1"
#1237500
0"
#1240000
b11111000 %
1"
#1242500
0"
#1245000
b11111001 %
1"
#1247500
0"
#1250000
b11111010 %
1"
#1252500
0"
#1255000
b11111011 %
1"
#1257500
0"
#1260000
b11111100 %
1"
#1262500
0"
#1265000
b11111101 %
1"
#1267500
0"
#1270000
b11111110 %
1"
#1272500
0"
#1275000
b11111111 %
1"
#1277500
0"
#1280000
b100000000 %
1"
#1282500
0"
#1285000
b100000001 %
1"
#1287500
0"
#1290000
b100000010 %
1"
#1292500
0"
#1295000
b100000011 %
1"
#1297500
0"
#1300000
b100000100 %
1"
#1302500
0"
#1305000
b100000101 %
1"
#1307500
0"
#1310000
b100000110 %
1"
#1312500
0"
#1315000
b100000111 %
1"
#1317500
0"
#1320000
b100001000 %
1"
#1322500
0"
#1325000
b100001001 %
1"
#1327500
0"
#1330000
b100001010 %
1"
#1332500
0"
#1335000
b100001011 %
1"
#1337500
0"
#1340000
b100001100 %
1"
#1342500
0"
#1345000
b100001101 %
1"
#1347500
0"
#1350000
b100001110 %
1"
#1352500
0"
#1355000
b100001111 %
1"
#1357500
0"
#1360000
b100010000 %
1"
#1362500
0"
#1365000
b100010001 %
1"
#1367500
0"
#1370000
b100010010 %
1"
#1372500
0"
#1375000
b100010011 %
1"
#1377500
0"
#1380000
b100010100 %
1"
#1382500
0"
#1385000
b100010101 %
1"
#1387500
0"
#1390000
b100010110 %
1"
#1392500
0"
#1395000
b100010111 %
1"
#1397500
0"
#1400000
b100011000 %
1"
#1402500
0"
#1405000
b100011001 %
1"
#1407500
0"
#1410000
b100011010 %
1"
#1412500
0"
#1415000
b100011011 %
1"
#1417500
0"
#1420000
b100011100 %
1"
#1422500
0"
#1425000
b100011101 %
1"
#1427500
0"
#1430000
b100011110 %
1"
#1432500
0"
#1435000
b100011111 %
1"
#1437500
0"
#1440000
b100100000 %
1"
#1442500
0"
#1445000
b100100001 %
1"
#1447500
0"
#1450000
b100100010 %
1"
#1452500
0"
#1455000
b100100011 %
1"
#1457500
0"
#1460000
b100100100 %
1"
#1462500
0"
#1465000
b100100101 %
1"
#1467500
0"
#1470000
b100100110 %
1"
#1472500
0"
#1475000
b100100111 %
1"
#1477500
0"
#1480000
b100101000 %
1"
#1482500
0"
#1485000
b100101001 %
1"
#1487500
0"
#1490000
b100101010 %
1"
#1492500
0"
#1495000
b100101011 %
1"
#1497500
0"
#1500000
b100101100 %
1"
#1502500
0"
#1505000
b100101101 %
1"
#1507500
0"
#1510000
b100101110 %
1"
#1512500
0"
#1515000
b100101111 %
1"
#1517500
0"
#1520000
b100110000 %
1"
#1522500
0"
#1525000
b100110001 %
1"
#1527500
0"
#1530000
b100110010 %
1"
#1532500
0"
#1535000
b100110011 %
1"
#1537500
0"
#1540000
b100110100 %
1"
#1542500
0"
#1545000
b100110101 %
1"
#1547500
0"
#1550000
b100110110 %
1"
#1552500
0"
#1555000
b100110111 %
1"
#1557500
0"
#1560000
b100111000 %
1"
#1562500
0"
#1565000
b100111001 %
1"
#1567500
0"
#1570000
b100111010 %
1"
#1572500
0"
#1575000
b100111011 %
1"
#1577500
0"
#1580000
b100111100 %
1"
#1582500
0"
#1585000
b100111101 %
1"
#1587500
0"
#1590000
b100111110 %
1"
#1592500
0"
#1595000
b100111111 %
1"
#1597500
0"
#1600000
b101000000 %
1"
#1602500
0"
#1605000
b101000001 %
1"
#1607500
0"
#1610000
b101000010 %
1"
#1612500
0"
#1615000
b101000011 %
1"
#1617500
0"
#1620000
b101000100 %
1"
#1622500
0"
#1625000
b101000101 %
1"
#1627500
0"
#1630000
b101000110 %
1"
#1632500
0"
#1635000
b101000111 %
1"
#1637500
0"
#1640000
b101001000 %
1"
#1642500
0"
#1645000
b101001001 %
1"
#1647500
0"
#1650000
b101001010 %
1"
#1652500
0"
#1655000
b101001011 %
1"
#1657500
0"
#1660000
b101001100 %
1"
#1662500
0"
#1665000
b101001101 %
1"
#1667500
0"
#1670000
b101001110 %
1"
#1672500
0"
#1675000
b101001111 %
1"
#1677500
0"
#1680000
b101010000 %
1"
#1682500
0"
#1685000
b101010001 %
1"
#1687500
0"
#1690000
b101010010 %
1"
#1692500
0"
#1695000
b101010011 %
1"
#1697500
0"
#1700000
b101010100 %
1"
#1702500
0"
#1705000
b101010101 %
1"
#1707500
0"
#1710000
b101010110 %
1"
#1712500
0"
#1715000
b101010111 %
1"
#1717500
0"
#1720000
b101011000 %
1"
#1722500
0"
#1725000
b101011001 %
1"
#1727500
0"
#1730000
b101011010 %
1"
#1732500
0"
#1735000
b101011011 %
1"
#1737500
0"
#1740000
b101011100 %
1"
#1742500
0"
#1745000
b101011101 %
1"
#1747500
0"
#1750000
b101011110 %
1"
#1752500
0"
#1755000
b101011111 %
1"
#1757500
0"
#1760000
b101100000 %
1"
#1762500
0"
#1765000
b101100001 %
1"
#1767500
0"
#1770000
b101100010 %
1"
#1772500
0"
#1775000
b101100011 %
1"
#1777500
0"
#1780000
b101100100 %
1"
#1782500
0"
#1785000
b101100101 %
1"
#1787500
0"
#1790000
b101100110 %
1"
#1792500
0"
#1795000
b101100111 %
1"
#1797500
0"
#1800000
b101101000 %
1"
#1802500
0"
#1805000
b101101001 %
1"
#1807500
0"
#1810000
b101101010 %
1"
#1812500
0"
#1815000
b101101011 %
1"
#1817500
0"
#1820000
b101101100 %
1"
#1822500
0"
#1825000
b101101101 %
1"
#1827500
0"
#1830000
b101101110 %
1"
#1832500
0"
#1835000
b101101111 %
1"
#1837500
0"
#1840000
b101110000 %
1"
#1842500
0"
#1845000
b101110001 %
1"
#1847500
0"
#1850000
b101110010 %
1"
#1852500
0"
#1855000
b101110011 %
1"
#1857500
0"
#1860000
b101110100 %
1"
#1862500
0"
#1865000
b101110101 %
1"
#1867500
0"
#1870000
b101110110 %
1"
#1872500
0"
#1875000
b101110111 %
1"
#1877500
0"
#1880000
b101111000 %
1"
#1882500
0"
#1885000
b101111001 %
1"
#1887500
0"
#1890000
b101111010 %
1"
#1892500
0"
#1895000
b101111011 %
1"
#1897500
0"
#1900000
b101111100 %
1"
#1902500
0"
#1905000
b101111101 %
1"
#1907500
0"
#1910000
b101111110 %
1"
#1912500
0"
#1915000
b101111111 %
1"
#1917500
0"
#1920000
b110000000 %
1"
#1922500
0"
#1925000
b110000001 %
1"
#1927500
0"
#1930000
b110000010 %
1"
#1932500
0"
#1935000
b110000011 %
1"
#1937500
0"
#1940000
b110000100 %
1"
#1942500
0"
#1945000
b110000101 %
1"
#1947500
0"
#1950000
b110000110 %
1"
#1952500
0"
#1955000
b110000111 %
1"
#1957500
0"
#1960000
b110001000 %
1"
#1962500
0"
#1965000
b110001001 %
1"
#1967500
0"
#1970000
b110001010 %
1"
#1972500
0"
#1975000
b110001011 %
1"
#1977500
0"
#1980000
b110001100 %
1"
#1982500
0"
#1985000
b110001101 %
1"
#1987500
0"
#1990000
b110001110 %
1"
#1992500
0"
#1995000
b110001111 %
1"
#1997500
0"
#2000000
b110010000 %
1"
#2002500
0"
#2005000
b110010001 %
1"
#2007500
0"
#2010000
b110010010 %
1"
#2012500
0"
#2015000
b110010011 %
1"
#2017500
0"
#2020000
b110010100 %
1"
#2022500
0"
#2025000
b110010101 %
1"
#2027500
0"
#2030000
b110010110 %
1"
#2032500
0"
#2035000
b110010111 %
1"
#2037500
0"
#2040000
b110011000 %
1"
#2042500
0"
#2045000
b110011001 %
1"
#2047500
0"
#2050000
b110011010 %
1"
#2052500
0"
#2055000
b110011011 %
1"
#2057500
0"
#2060000
b110011100 %
1"
#2062500
0"
#2065000
b110011101 %
1"
#2067500
0"
#2070000
b110011110 %
1"
#2072500
0"
#2075000
b110011111 %
1"
#2077500
0"
#2080000
b110100000 %
1"
#2082500
0"
#2085000
b110100001 %
1"
#2087500
0"
#2090000
b110100010 %
1"
#2092500
0"
#2095000
b110100011 %
1"
#2097500
0"
#2100000
b110100100 %
1"
#2102500
0"
#2105000
b110100101 %
1"
#2107500
0"
#2110000
b110100110 %
1"
#2112500
0"
#2115000
b110100111 %
1"
#2117500
0"
#2120000
b110101000 %
1"
#2122500
0"
#2125000
b110101001 %
1"
#2127500
0"
#2130000
b110101010 %
1"
#2132500
0"
#2135000
b110101011 %
1"
#2137500
0"
#2140000
b110101100 %
1"
#2142500
0"
#2145000
b110101101 %
1"
#2147500
0"
#2150000
b110101110 %
1"
#2152500
0"
#2155000
b110101111 %
1"
#2157500
0"
#2160000
b110110000 %
1"
#2162500
0"
#2165000
b110110001 %
1"
#2167500
0"
#2170000
b110110010 %
1"
#2172500
0"
#2175000
b110110011 %
1"
#2177500
0"
#2180000
b110110100 %
1"
#2182500
0"
#2185000
b110110101 %
1"
#2187500
0"
#2190000
b110110110 %
1"
#2192500
0"
#2195000
b110110111 %
1"
#2197500
0"
#2200000
b110111000 %
1"
#2202500
0"
#2205000
b110111001 %
1"
#2207500
0"
#2210000
b110111010 %
1"
#2212500
0"
#2215000
b110111011 %
1"
#2217500
0"
#2220000
b110111100 %
1"
#2222500
0"
#2225000
b110111101 %
1"
#2227500
0"
#2230000
b110111110 %
1"
#2232500
0"
#2235000
b110111111 %
1"
#2237500
0"
#2240000
b111000000 %
1"
#2242500
0"
#2245000
b111000001 %
1"
#2247500
0"
#2250000
b111000010 %
1"
#2252500
0"
#2255000
b111000011 %
1"
#2257500
0"
#2260000
b111000100 %
1"
#2262500
0"
#2265000
b111000101 %
1"
#2267500
0"
#2270000
b111000110 %
1"
#2272500
0"
#2275000
b111000111 %
1"
#2277500
0"
#2280000
b111001000 %
1"
#2282500
0"
#2285000
b111001001 %
1"
#2287500
0"
#2290000
b111001010 %
1"
#2292500
0"
#2295000
b111001011 %
1"
#2297500
0"
#2300000
b111001100 %
1"
#2302500
0"
#2305000
b111001101 %
1"
#2307500
0"
#2310000
b111001110 %
1"
#2312500
0"
#2315000
b111001111 %
1"
#2317500
0"
#2320000
b111010000 %
1"
#2322500
0"
#2325000
b111010001 %
1"
#2327500
0"
#2330000
b111010010 %
1"
#2332500
0"
#2335000
b111010011 %
1"
#2337500
0"
#2340000
b111010100 %
1"
#2342500
0"
#2345000
b111010101 %
1"
#2347500
0"
#2350000
b111010110 %
1"
#2352500
0"
#2355000
b111010111 %
1"
#2357500
0"
#2360000
b111011000 %
1"
#2362500
0"
#2365000
b111011001 %
1"
#2367500
0"
#2370000
b111011010 %
1"
#2372500
0"
#2375000
b111011011 %
1"
#2377500
0"
#2380000
b111011100 %
1"
#2382500
0"
#2385000
b111011101 %
1"
#2387500
0"
#2390000
b111011110 %
1"
#2392500
0"
#2395000
b111011111 %
1"
#2397500
0"
#2400000
b111100000 %
1"
#2402500
0"
#2405000
b111100001 %
1"
#2407500
0"
#2410000
b111100010 %
1"
#2412500
0"
#2415000
b111100011 %
1"
#2417500
0"
#2420000
b111100100 %
1"
#2422500
0"
#2425000
b111100101 %
1"
#2427500
0"
#2430000
b111100110 %
1"
#2432500
0"
#2435000
b111100111 %
1"
#2437500
0"
#2440000
b111101000 %
1"
#2442500
0"
#2445000
b111101001 %
1"
#2447500
0"
#2450000
b111101010 %
1"
#2452500
0"
#2455000
b111101011 %
1"
#2457500
0"
#2460000
b111101100 %
1"
#2462500
0"
#2465000
b111101101 %
1"
#2467500
0"
#2470000
b111101110 %
1"
#2472500
0"
#2475000
b111101111 %
1"
#2477500
0"
#2480000
b111110000 %
1"
#2482500
0"
#2485000
b111110001 %
1"
#2487500
0"
#2490000
b111110010 %
1"
#2492500
0"
#2495000
b111110011 %
1"
#2497500
0"
#2500000
b111110100 %
1"
#2502500
0"
#2505000
b111110101 %
1"
#2507500
0"
#2510000
b111110110 %
1"
#2512500
0"
#2515000
b111110111 %
1"
#2517500
0"
#2520000
b111111000 %
1"
#2522500
0"
#2525000
b111111001 %
1"
#2527500
0"
#2530000
b111111010 %
1"
#2532500
0"
#2535000
b111111011 %
1"
#2537500
0"
#2540000
b111111100 %
1"
#2542500
0"
#2545000
b111111101 %
1"
#2547500
0"
#2550000
b111111110 %
1"
#2552500
0"
#2555000
b111111111 %
1"
#2557500
0"
#2560000
b1000000000 %
1"
#2562500
0"
#2565000
b1000000001 %
1"
#2567500
0"
#2570000
b1000000010 %
1"
#2572500
0"
#2575000
b1000000011 %
1"
#2577500
0"
#2580000
b1000000100 %
1"
#2582500
0"
#2585000
b1000000101 %
1"
#2587500
0"
#2590000
b1000000110 %
1"
#2592500
0"
#2595000
b1000000111 %
1"
#2597500
0"
#2600000
b1000001000 %
1"
#2602500
0"
#2605000
b1000001001 %
1"
#2607500
0"
#2610000
b1000001010 %
1"
#2612500
0"
#2615000
b1000001011 %
1"
#2617500
0"
#2620000
b1000001100 %
1"
#2622500
0"
#2625000
b1000001101 %
1"
#2627500
0"
#2630000
b1000001110 %
1"
#2632500
0"
#2635000
b1000001111 %
1"
#2637500
0"
#2640000
b1000010000 %
1"
#2642500
0"
#2645000
b1000010001 %
1"
#2647500
0"
#2650000
b1000010010 %
1"
#2652500
0"
#2655000
b1000010011 %
1"
#2657500
0"
#2660000
b1000010100 %
1"
#2662500
0"
#2665000
b1000010101 %
1"
#2667500
0"
#2670000
b1000010110 %
1"
#2672500
0"
#2675000
b1000010111 %
1"
#2677500
0"
#2680000
b1000011000 %
1"
#2682500
0"
#2685000
b1000011001 %
1"
#2687500
0"
#2690000
b1000011010 %
1"
#2692500
0"
#2695000
b1000011011 %
1"
#2697500
0"
#2700000
b1000011100 %
1"
#2702500
0"
#2705000
b1000011101 %
1"
#2707500
0"
#2710000
b1000011110 %
1"
#2712500
0"
#2715000
b1000011111 %
1"
#2717500
0"
#2720000
b1000100000 %
1"
#2722500
0"
#2725000
b1000100001 %
1"
#2727500
0"
#2730000
b1000100010 %
1"
#2732500
0"
#2735000
b1000100011 %
1"
#2737500
0"
#2740000
b1000100100 %
1"
#2742500
0"
#2745000
b1000100101 %
1"
#2747500
0"
#2750000
b1000100110 %
1"
#2752500
0"
#2755000
b1000100111 %
1"
#2757500
0"
#2760000
b1000101000 %
1"
#2762500
0"
#2765000
b1000101001 %
1"
#2767500
0"
#2770000
b1000101010 %
1"
#2772500
0"
#2775000
b1000101011 %
1"
#2777500
0"
#2780000
b1000101100 %
1"
#2782500
0"
#2785000
b1000101101 %
1"
#2787500
0"
#2790000
b1000101110 %
1"
#2792500
0"
#2795000
b1000101111 %
1"
#2797500
0"
#2800000
b1000110000 %
1"
#2802500
0"
#2805000
b1000110001 %
1"
#2807500
0"
#2810000
b1000110010 %
1"
#2812500
0"
#2815000
b1000110011 %
1"
#2817500
0"
#2820000
b1000110100 %
1"
#2822500
0"
#2825000
b1000110101 %
1"
#2827500
0"
#2830000
b1000110110 %
1"
#2832500
0"
#2835000
b1000110111 %
1"
#2837500
0"
#2840000
b1000111000 %
1"
#2842500
0"
#2845000
b1000111001 %
1"
#2847500
0"
#2850000
b1000111010 %
1"
#2852500
0"
#2855000
b1000111011 %
1"
#2857500
0"
#2860000
b1000111100 %
1"
#2862500
0"
#2865000
b1000111101 %
1"
#2867500
0"
#2870000
b1000111110 %
1"
#2872500
0"
#2875000
b1000111111 %
1"
#2877500
0"
#2880000
b1001000000 %
1"
#2882500
0"
#2885000
b1001000001 %
1"
#2887500
0"
#2890000
b1001000010 %
1"
#2892500
0"
#2895000
b1001000011 %
1"
#2897500
0"
#2900000
b1001000100 %
1"
#2902500
0"
#2905000
b1001000101 %
1"
#2907500
0"
#2910000
b1001000110 %
1"
#2912500
0"
#2915000
b1001000111 %
1"
#2917500
0"
#2920000
b1001001000 %
1"
#2922500
0"
#2925000
b1001001001 %
1"
#2927500
0"
#2930000
b1001001010 %
1"
#2932500
0"
#2935000
b1001001011 %
1"
#2937500
0"
#2940000
b1001001100 %
1"
#2942500
0"
#2945000
b1001001101 %
1"
#2947500
0"
#2950000
b1001001110 %
1"
#2952500
0"
#2955000
b1001001111 %
1"
#2957500
0"
#2960000
b1001010000 %
1"
#2962500
0"
#2965000
b1001010001 %
1"
#2967500
0"
#2970000
b1001010010 %
1"
#2972500
0"
#2975000
b1001010011 %
1"
#2977500
0"
#2980000
b1001010100 %
1"
#2982500
0"
#2985000
b1001010101 %
1"
#2987500
0"
#2990000
b1001010110 %
1"
#2992500
0"
#2995000
b1001010111 %
1"
#2997500
0"
#3000000
b1001011000 %
1"
#3002500
0"
#3005000
b1001011001 %
1"
#3007500
0"
#3010000
b1001011010 %
1"
#3012500
0"
#3015000
b1001011011 %
1"
#3017500
0"
#3020000
b1001011100 %
1"
#3022500
0"
#3025000
b1001011101 %
1"
#3027500
0"
#3030000
b1001011110 %
1"
#3032500
0"
#3035000
b1001011111 %
1"
#3037500
0"
#3040000
b1001100000 %
1"
#3042500
0"
#3045000
b1001100001 %
1"
#3047500
0"
#3050000
b1001100010 %
1"
#3052500
0"
#3055000
b1001100011 %
1"
#3057500
0"
#3060000
b1001100100 %
1"
#3062500
0"
#3065000
b1001100101 %
1"
#3067500
0"
#3070000
b1001100110 %
1"
#3072500
0"
#3075000
b1001100111 %
1"
#3077500
0"
#3080000
b1001101000 %
1"
#3082500
0"
#3085000
b1001101001 %
1"
#3087500
0"
#3090000
b1001101010 %
1"
#3092500
0"
#3095000
b1001101011 %
1"
#3097500
0"
#3100000
b1001101100 %
1"
#3102500
0"
#3105000
b1001101101 %
1"
#3107500
0"
#3110000
b1001101110 %
1"
#3112500
0"
#3115000
b1001101111 %
1"
#3117500
0"
#3120000
b1001110000 %
1"
#3122500
0"
#3125000
b1001110001 %
1"
#3127500
0"
#3130000
b1001110010 %
1"
#3132500
0"
#3135000
b1001110011 %
1"
#3137500
0"
#3140000
b1001110100 %
1"
#3142500
0"
#3145000
b1001110101 %
1"
#3147500
0"
#3150000
b1001110110 %
1"
#3152500
0"
#3155000
b1001110111 %
1"
#3157500
0"
#3160000
b1001111000 %
1"
#3162500
0"
#3165000
b1001111001 %
1"
#3167500
0"
#3170000
b1001111010 %
1"
#3172500
0"
#3175000
b1001111011 %
1"
#3177500
0"
#3180000
b1001111100 %
1"
#3182500
0"
#3185000
b1001111101 %
1"
#3187500
0"
#3190000
b1001111110 %
1"
#3192500
0"
#3195000
b1001111111 %
1"
