New Modules/CORDIC/CORDIC-Comb/cordic.v
////////////////////////////////////////////////////////////////////////////////
//
// Filename: 	../rtl/cordic.v
// {{{
// Project:	A series of CORDIC related projects
//
// Purpose:	This file executes a vector rotation on the values
//		(i_xval, i_yval).  This vector is rotated left by
//	i_phase.  i_phase is given by the angle, in radians, multiplied by
//	2^32/(2pi).  In that fashion, a two pi value is zero just as a zero
//	angle is zero.
//
// This core was generated via a core generator using the following command
// line:
//
//  % ./gencordic -vca -f ../rtl/cordic.v -v -i 13 -o 13 -t p2r -x 2 -c
//
// Creator:	Dan Gisselquist, Ph.D.
//		Gisselquist Technology, LLC
//
////////////////////////////////////////////////////////////////////////////////
// }}}
// Copyright (C) 2017-2024, Gisselquist Technology, LLC
// {{{
// This file is part of the CORDIC related project set.
//
// The CORDIC related project set is free software (firmware): you can
// redistribute it and/or modify it under the terms of the GNU Lesser General
// Public License as published by the Free Software Foundation, either version
// 3 of the License, or (at your option) any later version.
//
// The CORDIC related project set is distributed in the hope that it will be
// useful, but WITHOUT ANY WARRANTY; without even the implied warranty of
// MERCHANTIBILITY or FITNESS FOR A PARTICULAR PURPOSE.  See the GNU Lesser
// General Public License for more details.
//
// You should have received a copy of the GNU Lesser General Public License
// along with this program.  (It's in the $(ROOT)/doc directory.  Run make
// with no target there if the PDF file isn't present.)  If not, see
// License:	LGPL, v3, as defined and found on www.gnu.org,
//		http://www.gnu.org/licenses/lgpl.html
//
////////////////////////////////////////////////////////////////////////////////
//
// }}}
`default_nettype	none
module	cordic#(
		// {{{
	localparam	IW=13,	// The number of bits in our inputs
			OW=13,	// The number of output bits to produce
			NSTAGES=16,
			// XTRA= 3,// Extra bits for internal precision
			WW=16,	// Our working bit-width
			PW=20	// Bits in our phase variables
		// }}}
	) (
		// {{{
	input	wire				i_clk, i_reset, i_ce,
	input	wire	signed	[(IW-1):0]		i_xval, i_yval,
	input	wire		[(PW-1):0]			i_phase,
	output	reg	signed	[(OW-1):0]	o_xval, o_yval,
	input	wire				i_aux,
	output	reg				o_aux
		// }}}
	);

	// Declare variables for all of the separate stages
	// {{{
	wire	signed [(WW-1):0]	e_xval, e_yval;
	reg	signed	[(WW-1):0]	xv	[0:(NSTAGES)];
	reg	signed	[(WW-1):0]	yv	[0:(NSTAGES)];
	reg		[(PW-1):0]	ph	[0:(NSTAGES)];
	reg		[(NSTAGES):0]	ax;
	// }}}

	// Sign extend our inputs
	// {{{
	// First step: expand our input to our working width.
	// This is going to involve extending our input by one
	// (or more) bits in addition to adding any xtra bits on
	// bits on the right.  The one bit extra on the left is to
	// allow for any accumulation due to the cordic gain
	// within the algorithm.
	// 
	assign	e_xval = { {i_xval[(IW-1)]}, i_xval, {(WW-IW-1){1'b0}} };
	assign	e_yval = { {i_yval[(IW-1)]}, i_yval, {(WW-IW-1){1'b0}} };

	// }}}
	//
	// Handle the auxilliary logic.
	// {{{
	// The auxilliary bit is designed so that you can place a valid bit into
	// the CORDIC function, and see when it comes out.  While the bit is
	// allowed to be anything, the requirement of this bit is that it *must*
	// be aligned with the output when done.  That is, if i_xval and i_yval
	// are input together with i_aux, then when o_xval and o_yval are set
	// to this value, o_aux *must* contain the value that was in i_aux.
	//

	initial	ax = 0;
	always @(posedge i_clk)
	if (i_reset)
		ax <= 0;
	else
		ax <= { ax[(NSTAGES-1):0], i_aux };
	// }}}

	// Pre-CORDIC rotation
	// {{{
	// First stage, get rid of all but 45 degrees
	//	The resulting phase needs to be between -45 and 45
	//		degrees but in units of normalized phase
	// Initialize arrays

	always @(posedge i_clk)
	if (i_reset)
	begin
		xv[0] = 0; yv[0] = 0; ph[0] = 0;
	end else
	begin
		// {{{
		// Walk through all possible quick phase shifts necessary
		// to constrain the input to within +/- 45 degrees.
		// This is a zero-gain operation, involving only sign
		// adjustments.
		case(i_phase[(PW-1):(PW-3)])
		3'b000: begin	// 0 .. 45, No change
		// {{{
			xv[0] <= e_xval;
			yv[0] <= e_yval;
			ph[0] <= i_phase;
			end
			// }}}
		3'b001: begin	// 45 .. 90
		// {{{
			xv[0] <= -e_yval;
			yv[0] <= e_xval;
			ph[0] <= i_phase - 20'h40000;
			end
			// }}}
		3'b010: begin	// 90 .. 135
		// {{{
			xv[0] <= -e_yval;
			yv[0] <= e_xval;
			ph[0] <= i_phase - 20'h40000;
			end
			// }}}
		3'b011: begin	// 135 .. 180
		// {{{
			xv[0] <= -e_xval;
			yv[0] <= -e_yval;
			ph[0] <= i_phase - 20'h80000;
			end
			// }}}
		3'b100: begin	// 180 .. 225
		// {{{
			xv[0] <= -e_xval;
			yv[0] <= -e_yval;
			ph[0] <= i_phase - 20'h80000;
			end
			// }}}
		3'b101: begin	// 225 .. 270
		// {{{
			xv[0] <= e_yval;
			yv[0] <= -e_xval;
			ph[0] <= i_phase - 20'hc0000;
			end
			// }}}
		3'b110: begin	// 270 .. 315
		// {{{
			xv[0] <= e_yval;
			yv[0] <= -e_xval;
			ph[0] <= i_phase - 20'hc0000;
			end
			// }}}
		3'b111: begin	// 315 .. 360, No change
		// {{{
			xv[0] <= e_xval;
			yv[0] <= e_yval;
			ph[0] <= i_phase;
			end
			// }}}
		endcase
		// }}}
	end
	// }}}
	// Cordic angle table
	// {{{
	// In many ways, the key to this whole algorithm lies in the angles
	// necessary to do this.  These angles are also our basic reason for
	// building this CORDIC in C++: Verilog just can't parameterize this
	// much.  Further, these angle's risk becoming unsupportable magic
	// numbers, hence we define these and set them in C++, based upon
	// the needs of our problem, specifically the number of stages and
	// the number of bits required in our phase accumulator
	//
	wire	[19:0]	cordic_angle [0:(NSTAGES-1)];

	assign	cordic_angle[ 0] = 20'h1_2e40; //  26.565051 deg
	assign	cordic_angle[ 1] = 20'h0_9fb3; //  14.036243 deg
	assign	cordic_angle[ 2] = 20'h0_5111; //   7.125016 deg
	assign	cordic_angle[ 3] = 20'h0_28b0; //   3.576334 deg
	assign	cordic_angle[ 4] = 20'h0_145d; //   1.789911 deg
	assign	cordic_angle[ 5] = 20'h0_0a2f; //   0.895174 deg
	assign	cordic_angle[ 6] = 20'h0_0517; //   0.447614 deg
	assign	cordic_angle[ 7] = 20'h0_028b; //   0.223811 deg
	assign	cordic_angle[ 8] = 20'h0_0145; //   0.111906 deg
	assign	cordic_angle[ 9] = 20'h0_00a2; //   0.055953 deg
	assign	cordic_angle[10] = 20'h0_0051; //   0.027976 deg
	assign	cordic_angle[11] = 20'h0_0028; //   0.013988 deg
	assign	cordic_angle[12] = 20'h0_0014; //   0.006994 deg
	assign	cordic_angle[13] = 20'h0_000a; //   0.003497 deg
	assign	cordic_angle[14] = 20'h0_0005; //   0.001749 deg
	assign	cordic_angle[15] = 20'h0_0002; //   0.000874 deg
	// {{{
	// Std-Dev    : 0.00 (Units)
	// Phase Quantization: 0.000015 (Radians)
	// Gain is 1.164435
	// You can annihilate this gain by multiplying by 32'hdbd95b16
	// and right shifting by 32 bits.
	// }}}
	// }}}

	// CORDIC rotations
	// {{{
	

    genvar i;
    generate
        for (i = 0; i < NSTAGES; i = i + 1) begin : CORDICops
            wire signed [(WW-1):0] next_xv, next_yv;
            wire [(PW-1):0] next_ph;

            assign next_xv = (ph[i][PW-1]) ?
                             (xv[i] + (yv[i] >>> (i+1))) :  // If phase is negative, rotate clockwise
                             (xv[i] - (yv[i] >>> (i+1)));   // If phase is positive, rotate counter-clockwise

            assign next_yv = (ph[i][PW-1]) ?
                             (yv[i] - (xv[i] >>> (i+1))) :
                             (yv[i] + (xv[i] >>> (i+1)));

            assign next_ph = (ph[i][PW-1]) ?
                             (ph[i] + cordic_angle[i]) :
                             (ph[i] - cordic_angle[i]);

            assign xv[i+1] = next_xv;
            assign yv[i+1] = next_yv;
            assign ph[i+1] = next_ph;
        end
    endgenerate

	// Round our result towards even
	// {{{
	wire	[(WW-1):0]	pre_xval, pre_yval;

	assign	pre_xval = xv[NSTAGES] + $signed({ {(OW){1'b0}},
				xv[NSTAGES][(WW-OW)],
				{(WW-OW-1){!xv[NSTAGES][WW-OW]}} });
	assign	pre_yval = yv[NSTAGES] + $signed({ {(OW){1'b0}},
				yv[NSTAGES][(WW-OW)],
				{(WW-OW-1){!yv[NSTAGES][WW-OW]}} });


	initial begin
		o_xval = 0;
		o_yval = 0;
		o_aux  = 0;
	end
	always @(posedge i_clk)
	if (i_reset)
	begin
		o_xval <= 0;
		o_yval <= 0;
		o_aux  <= 0;
	end else if (i_ce)
	begin
		o_xval <= pre_xval[(WW-1):(WW-OW)];
		o_yval <= pre_yval[(WW-1):(WW-OW)];
		o_aux <= ax[NSTAGES];
	end
	// }}}
	// Make Verilator happy with pre_.val
	// {{{
	// verilator lint_off UNUSED
	wire	unused_val;
	assign	unused_val = &{ 1'b0, 
		pre_xval[(WW-OW-1):0],
		pre_yval[(WW-OW-1):0]
		};
	// }}}
	// verilator lint_on UNUSED

    initial begin
        $dumpfile("cordic_waves.vcd");
        $dumpvars;
    end
endmodule

New Modules/CORDIC/cordic_waves.vcd
$date
	Sat Apr 13 10:16:53 2024
$end
$version
	Icarus Verilog
$end
$timescale
	1ps
$end
$scope module cordic $end
$var wire 1 ! i_aux $end
$var wire 1 " i_ce $end
$var wire 1 # i_clk $end
$var wire 20 $ i_phase [19:0] $end
$var wire 1 % i_reset $end
$var wire 13 & i_xval [12:0] $end
$var wire 13 ' i_yval [12:0] $end
$var wire 1 ( unused_val $end
$var wire 16 ) pre_yval [15:0] $end
$var wire 16 * pre_xval [15:0] $end
$var wire 16 + e_yval [15:0] $end
$var wire 16 , e_xval [15:0] $end
$var parameter 32 - IW $end
$var parameter 32 . NSTAGES $end
$var parameter 32 / OW $end
$var parameter 32 0 PW $end
$var parameter 32 1 WW $end
$var reg 17 2 ax [16:0] $end
$var reg 1 3 o_aux $end
$var reg 13 4 o_xval [12:0] $end
$var reg 13 5 o_yval [12:0] $end
$scope begin CORDICops[0] $end
$var parameter 2 6 i $end
$upscope $end
$scope begin CORDICops[1] $end
$var parameter 2 7 i $end
$upscope $end
$scope begin CORDICops[2] $end
$var parameter 3 8 i $end
$upscope $end
$scope begin CORDICops[3] $end
$var parameter 3 9 i $end
$upscope $end
$scope begin CORDICops[4] $end
$var parameter 4 : i $end
$upscope $end
$scope begin CORDICops[5] $end
$var parameter 4 ; i $end
$upscope $end
$scope begin CORDICops[6] $end
$var parameter 4 < i $end
$upscope $end
$scope begin CORDICops[7] $end
$var parameter 4 = i $end
$upscope $end
$scope begin CORDICops[8] $end
$var parameter 5 > i $end
$upscope $end
$scope begin CORDICops[9] $end
$var parameter 5 ? i $end
$upscope $end
$scope begin CORDICops[10] $end
$var parameter 5 @ i $end
$upscope $end
$scope begin CORDICops[11] $end
$var parameter 5 A i $end
$upscope $end
$scope begin CORDICops[12] $end
$var parameter 5 B i $end
$upscope $end
$scope begin CORDICops[13] $end
$var parameter 5 C i $end
$upscope $end
$scope begin CORDICops[14] $end
$var parameter 5 D i $end
$upscope $end
$scope begin CORDICops[15] $end
$var parameter 5 E i $end
$upscope $end
$upscope $end
$enddefinitions $end
$comment Show the parameter values. $end
$dumpall
b1111 E
b1110 D
b1101 C
b1100 B
b1011 A
b1010 @
b1001 ?
b1000 >
b111 =
b110 <
b101 ;
b100 :
b11 9
b10 8
b1 7
b0 6
b10000 1
b10100 0
b1101 /
b10000 .
b1101 -
$end
#0
$dumpvars
b0 5
b0 4
03
b0 2
bz00 ,
bz00 +
b11 *
b11 )
0(
bz '
bz &
0%
bz $
1#
z"
z!
$end
#6250
0#
#12500
b0 $
b0 +
b0 '
b11111111111100 ,
b111111111111 &
1"
1#
#18750
0#
#25000
b0z 2
1#
#31250
0#
#37500
b0zz 2
1#
#43750
0#
#50000
b0zzz 2
1#
#56250
0#
#62500
b0zzzz 2
1#
#68750
0#
#75000
b0zzzzz 2
1#
#81250
0#
#87500
b0zzzzzz 2
1#
#93750
0#
#100000
b0zzzzzzz 2
1#
#106250
0#
#112500
b0zzzzzzzz 2
1#
#118750
0#
#125000
b0zzzzzzzzz 2
1#
#131250
0#
#137500
b0zzzzzzzzzz 2
1#
#143750
0#
#150000
b0zzzzzzzzzzz 2
1#
#156250
0#
#162500
b0zzzzzzzzzzzz 2
1#
#168750
0#
#175000
b0zzzzzzzzzzzzz 2
1#
#181250
0#
#187500
b0zzzzzzzzzzzzzz 2
1#
#193750
0#
#200000
b0zzzzzzzzzzzzzzz 2
1#
#206250
0#
#212500
b0zzzzzzzzzzzzzzzz 2
1#
#218750
0#
#225000
b100101010001000 *
bz 2
1#
#231250
0#
#237500
z3
b100101010001 4
1#
#243750
0#
#250000
1#
#256250
0#
#262500
b100110011001101 $
1#
#268750
0#
#275000
1#
#281250
0#
#287500
1#
#293750
0#
#300000
1#
#306250
0#
#312500
1#
#318750
0#
#325000
1#
#331250
0#
#337500
1#
#343750
0#
#350000
1#
#356250
0#
#362500
1#
#368750
0#
#375000
1#
#381250
0#
#387500
1#
#393750
0#
#400000
1#
#406250
0#
#412500
1#
#418750
0#
#425000
1#
#431250
0#
#437500
1#
#443750
0#
#450000
1#
#456250
0#
#462500
1#
#468750
0#
#475000
b100011000110 )
b100100111111110 *
1#
#481250
0#
#487500
b100011000 5
b100100111111 4
1#
#493750
0#
#500000
b1001100110011010 $
1#
#506250
0#
#512500
1#
#518750
0#
#525000
1#
#531250
0#
#537500
1#
#543750
0#
#550000
1#
#556250
0#
#562500
1#
#568750
0#
#575000
1#
#581250
0#
#587500
1#
#593750
0#
#600000
1#
#606250
0#
#612500
1#
#618750
0#
#625000
1#
#631250
0#
#637500
1#
#643750
0#
#650000
1#
#656250
0#
#662500
1#
#668750
0#
#675000
1#
#681250
0#
#687500
1#
#693750
0#
#700000
1#
#706250
0#
#712500
b1000101101000 )
b100100001110011 *
1#
#718750
0#
#725000
b1000101101 5
b100100001110 4
1#
#731250
0#
#737500
b1110011001100111 $
1#
#743750
0#
#750000
1#
#756250
0#
#762500
1#
#768750
0#
#775000
1#
#781250
0#
#787500
1#
#793750
0#
#800000
1#
#806250
0#
#812500
1#
#818750
0#
#825000
1#
#831250
0#
#837500
1#
#843750
0#
#850000
1#
#856250
0#
#862500
1#
#868750
0#
#875000
1#
#881250
0#
#887500
1#
#893750
0#
#900000
1#
#906250
0#
#912500
1#
#918750
0#
#925000
1#
#931250
0#
#937500
1#
#943750
0#
#950000
b1100111001101 )
b100010111101001 *
1#
#956250
0#
#962500
b1100111001 5
b100010111101 4
1#
#968750
0#
#975000
b10011001100110100 $
1#
#981250
0#
#987500
1#
#993750
0#
#1000000
1#
#1006250
0#
#1012500
1#
#1018750
0#
#1025000
1#
#1031250
0#
#1037500
1#
#1043750
0#
#1050000
1#
#1056250
0#
#1062500
1#
#1068750
0#
#1075000
1#
#1081250
0#
#1087500
1#
#1093750
0#
#1100000
1#
#1106250
0#
#1112500
1#
#1118750
0#
#1125000
1#
#1131250
0#
#1137500
1#
#1143750
0#
#1150000
1#
#1156250
0#
#1162500
1#
#1168750
0#
#1175000
1#
#1181250
0#
#1187500
b10000111011010 )
b100001001100100 *
1#
#1193750
0#
#1200000
b10000111011 5
b100001001100 4
1#
#1206250
0#
#1212500
b11000000000000001 $
1#
#1218750
0#
#1225000
1#
#1231250
0#
#1237500
1#
#1243750
0#
#1250000
1#
#1256250
0#
#1262500
1#
#1268750
0#
#1275000
1#
#1281250
0#
#1287500
1#
#1293750
0#
#1300000
1#
#1306250
0#
#1312500
1#
#1318750
0#
#1325000
1#
#1331250
0#
#1337500
1#
#1343750
0#
#1350000
1#
#1356250
0#
#1362500
1#
#1368750
0#
#1375000
1#
#1381250
0#
#1387500
1#
#1393750
0#
#1400000
1#
#1406250
0#
#1412500
1#
#1418750
0#
#1425000
b10100101100111 )
b11110111110111 *
1#
#1431250
0#
#1437500
b10100101100 5
b11110111110 4
1#
#1443750
0#
#1450000
b11100110011001110 $
1#
#1456250
0#
#1462500
1#
#1468750
0#
#1475000
1#
#1481250
0#
#1487500
1#
#1493750
0#
#1500000
1#
#1506250
0#
#1512500
1#
#1518750
0#
#1525000
1#
#1531250
0#
#1537500
1#
#1543750
0#
#1550000
1#
#1556250
0#
#1562500
1#
#1568750
0#
#1575000
1#
#1581250
0#
#1587500
1#
#1593750
0#
#1600000
1#
#1606250
0#
#1612500
1#
#1618750
0#
#1625000
1#
#1631250
0#
#1637500
1#
#1643750
0#
#1650000
1#
#1656250
0#
#1662500
b11000001100100 )
b11100010101110 *
1#
#1668750
0#
#1675000
b11000001100 5
b11100010101 4
1#
#1681250
0#
#1687500
b100001100110011011 $
1#
#1693750
0#
#1700000
1#
#1706250
0#
#1712500
1#
#1718750
0#
#1725000
1#
#1731250
0#
#1737500
1#
#1743750
0#
#1750000
1#
#1756250
0#
#1762500
1#
#1768750
0#
#1775000
1#
#1781250
0#
#1787500
1#
#1793750
0#
#1800000
1#
#1806250
0#
#1812500
1#
#1818750
0#
#1825000
1#
#1831250
0#
#1837500
1#
#1843750
0#
#1850000
1#
#1856250
0#
#1862500
1#
#1868750
0#
#1875000
1#
#1881250
0#
#1887500
1#
#1893750
0#
#1900000
b11011010111100 )
b11001010010101 *
1#
#1906250
0#
#1912500
b11011010111 5
b11001010010 4
1#
#1918750
0#
#1925000
b100110011001101000 $
1#
#1931250
0#
#1937500
1#
#1943750
0#
#1950000
1#
#1956250
0#
#1962500
1#
#1968750
0#
#1975000
1#
#1981250
0#
#1987500
1#
#1993750
0#
#2000000
1#
#2006250
0#
#2012500
1#
#2018750
0#
#2025000
1#
#2031250
0#
#2037500
1#
#2043750
0#
#2050000
1#
#2056250
0#
#2062500
1#
#2068750
0#
#2075000
1#
#2081250
0#
#2087500
1#
#2093750
0#
#2100000
1#
#2106250
0#
#2112500
1#
#2118750
0#
#2125000
1#
#2131250
0#
#2137500
b11110001001001 )
b10101111001111 *
1#
#2143750
0#
#2150000
b11110001001 5
b10101111001 4
1#
#2156250
0#
#2162500
b101011001100110101 $
1#
#2168750
0#
#2175000
1#
#2181250
0#
#2187500
1#
#2193750
0#
#2200000
1#
#2206250
0#
#2212500
1#
#2218750
0#
#2225000
1#
#2231250
0#
#2237500
1#
#2243750
0#
#2250000
1#
#2256250
0#
#2262500
1#
#2268750
0#
#2275000
1#
#2281250
0#
#2287500
1#
#2293750
0#
#2300000
1#
#2306250
0#
#2312500
1#
#2318750
0#
#2325000
1#
#2331250
0#
#2337500
1#
#2343750
0#
#2350000
1#
#2356250
0#
#2362500
1#
#2368750
0#
#2375000
b100000100000011 )
b10010001101100 *
1#
#2381250
0#
#2387500
b100000100000 5
b10010001101 4
1#
#2393750
0#
#2400000
b110000000000000010 $
1#
#2406250
0#
#2412500
1#
#2418750
0#
#2425000
1#
#2431250
0#
#2437500
1#
#2443750
0#
#2450000
1#
#2456250
0#
#2462500
1#
#2468750
0#
#2475000
1#
#2481250
0#
#2487500
1#
#2493750
0#
#2500000
1#
#2506250
0#
#2512500
1#
#2518750
0#
#2525000
1#
#2531250
0#
#2537500
1#
#2543750
0#
#2550000
1#
#2556250
0#
#2562500
1#
#2568750
0#
#2575000
1#
#2581250
0#
#2587500
1#
#2593750
0#
#2600000
1#
#2606250
0#
#2612500
b100010011011100 )
b1110010000101 *
1#
#2618750
0#
#2625000
b100010011011 5
b1110010000 4
1#
#2631250
0#
#2637500
b110100110011001111 $
1#
#2643750
0#
#2650000
1#
#2656250
0#
#2662500
1#
#2668750
0#
#2675000
1#
#2681250
0#
#2687500
1#
#2693750
0#
#2700000
1#
#2706250
0#
#2712500
1#
#2718750
0#
#2725000
1#
#2731250
0#
#2737500
1#
#2743750
0#
#2750000
1#
#2756250
0#
#2762500
1#
#2768750
0#
#2775000
1#
#2781250
0#
#2787500
1#
#2793750
0#
#2800000
1#
#2806250
0#
#2812500
1#
#2818750
0#
#2825000
1#
#2831250
0#
#2837500
1#
#2843750
0#
#2850000
b100011110110110 )
b1010000111100 *
1#
#2856250
0#
#2862500
b100011110110 5
b1010000111 4
1#
#2868750
0#
#2875000
b111001100110011100 $
1#
#2881250
0#
#2887500
1#
#2893750
0#
#2900000
1#
#2906250
0#
#2912500
1#
#2918750
0#
#2925000
1#
#2931250
0#
#2937500
1#
#2943750
0#
#2950000
1#
#2956250
0#
#2962500
1#
#2968750
0#
#2975000
1#
#2981250
0#
#2987500
1#
#2993750
0#
#3000000
1#
#3006250
0#
#3012500
1#
#3018750
0#
#3025000
1#
#3031250
0#
#3037500
1#
#3043750
0#
#3050000
1#
#3056250
0#
#3062500
1#
#3068750
0#
#3075000
1#
#3081250
0#
#3087500
b100100110010101 )
b101110101110 *
1#
#3093750
0#
#3100000
b100100110010 5
b101110101 4
1#
#3106250
0#
#3112500
b111110011001101001 $
1#
#3118750
0#
#3125000
1#
#3131250
0#
#3137500
1#
#3143750
0#
#3150000
1#
#3156250
0#
#3162500
1#
#3168750
0#
#3175000
1#
#3181250
0#
#3187500
1#
#3193750
0#
#3200000
1#
#3206250
0#
#3212500
1#
#3218750
0#
#3225000
1#
#3231250
0#
#3237500
1#
#3243750
0#
#3250000
1#
#3256250
0#
#3262500
1#
#3268750
0#
#3275000
1#
#3281250
0#
#3287500
1#
#3293750
0#
#3300000
1#
#3306250
0#
#3312500
1#
#3318750
0#
#3325000
b100101001110100 )
b1011110010 *
1#
#3331250
0#
#3337500
b100101001110 5
b1011110 4
1#
#3343750
0#
#3350000
b1000011001100110110 $
1#
#3356250
0#
#3362500
1#
#3368750
0#
#3375000
1#
#3381250
0#
#3387500
1#
#3393750
0#
#3400000
1#
#3406250
0#
#3412500
1#
#3418750
0#
#3425000
1#
#3431250
0#
#3437500
1#
#3443750
0#
#3450000
1#
#3456250
0#
#3462500
1#
#3468750
0#
#3475000
1#
#3481250
0#
#3487500
1#
#3493750
0#
#3500000
1#
#3506250
0#
#3512500
1#
#3518750
0#
#3525000
1#
#3531250
0#
#3537500
1#
#3543750
0#
#3550000
1#
#3556250
0#
#3562500
b100101001000111 )
b1111101000101100 *
1#
#3568750
0#
#3575000
b100101001000 5
b1111101000101 4
1#
#3581250
0#
#3587500
b1001000000000000011 $
1#
#3593750
0#
#3600000
1#
#3606250
0#
#3612500
1#
#3618750
0#
#3625000
1#
#3631250
0#
#3637500
1#
#3643750
0#
#3650000
1#
#3656250
0#
#3662500
1#
#3668750
0#
#3675000
1#
#3681250
0#
#3687500
1#
#3693750
0#
#3700000
1#
#3706250
0#
#3712500
1#
#3718750
0#
#3725000
1#
#3731250
0#
#3737500
1#
#3743750
0#
#3750000
1#
#3756250
0#
#3762500
1#
#3768750
0#
#3775000
1#
#3781250
0#
#3787500
1#
#3793750
0#
#3800000
b100100100010111 )
b1111000101111010 *
1#
#3806250
0#
#3812500
b100100100010 5
b1111000101111 4
1#
#3818750
0#
#3825000
b1001100110011010000 $
1#
#3831250
0#
#3837500
1#
#3843750
0#
#3850000
1#
#3856250
0#
#3862500
1#
#3868750
0#
#3875000
1#
#3881250
0#
#3887500
1#
#3893750
0#
#3900000
1#
#3906250
0#
#3912500
1#
#3918750
0#
#3925000
1#
#3931250
0#
#3937500
1#
#3943750
0#
#3950000
1#
#3956250
0#
#3962500
1#
#3968750
0#
#3975000
1#
#3981250
0#
#3987500
1#
#3993750
0#
#4000000
1#
#4006250
0#
#4012500
1#
#4018750
0#
#4025000
1#
#4031250
0#
#4037500
b100011011100010 )
b1110100011111100 *
1#
#4043750
0#
#4050000
b100011011100 5
b1110100011111 4
1#
#4056250
0#
#4062500
b1010001100110011101 $
1#
#4068750
0#
#4075000
1#
#4081250
0#
#4087500
1#
#4093750
0#
#4100000
1#
#4106250
0#
#4112500
1#
#4118750
0#
#4125000
1#
#4131250
0#
#4137500
1#
#4143750
0#
#4150000
1#
#4156250
0#
#4162500
1#
#4168750
0#
#4175000
1#
#4181250
0#
#4187500
1#
#4193750
0#
#4200000
1#
#4206250
0#
#4212500
1#
#4218750
0#
#4225000
1#
#4231250
0#
#4237500
1#
#4243750
0#
#4250000
1#
#4256250
0#
#4262500
1#
#4268750
0#
#4275000
b100001110101101 )
b1110000011010101 *
1#
#4281250
0#
#4287500
b100001110101 5
b1110000011010 4
1#
#4293750
0#
#4300000
b1010110011001101010 $
1#
#4306250
0#
#4312500
1#
#4318750
0#
#4325000
1#
#4331250
0#
#4337500
1#
#4343750
0#
#4350000
1#
#4356250
0#
#4362500
1#
#4368750
0#
#4375000
1#
#4381250
0#
#4387500
1#
#4393750
0#
#4400000
1#
#4406250
0#
#4412500
1#
#4418750
0#
#4425000
1#
#4431250
0#
#4437500
1#
#4443750
0#
#4450000
1#
#4456250
0#
#4462500
1#
#4468750
0#
#4475000
1#
#4481250
0#
#4487500
1#
#4493750
0#
#4500000
1#
#4506250
0#
#4512500
b11111110001010 )
b1101100100010011 *
1#
#4518750
0#
#4525000
b11111110001 5
b1101100100010 4
1#
#4531250
0#
#4537500
b1011011001100110111 $
1#
#4543750
0#
#4550000
1#
#4556250
0#
#4562500
1#
#4568750
0#
#4575000
1#
#4581250
0#
#4587500
1#
#4593750
0#
#4600000
1#
#4606250
0#
#4612500
1#
#4618750
0#
#4625000
1#
#4631250
0#
#4637500
1#
#4643750
0#
#4650000
1#
#4656250
0#
#4662500
1#
#4668750
0#
#4675000
1#
#4681250
0#
#4687500
1#
#4693750
0#
#4700000
1#
#4706250
0#
#4712500
1#
#4718750
0#
#4725000
1#
#4731250
0#
#4737500
1#
#4743750
0#
#4750000
b11101010000100 )
b1101000111100100 *
1#
#4756250
0#
#4762500
b11101010000 5
b1101000111100 4
1#
#4768750
0#
#4775000
b1100000000000000100 $
1#
#4781250
0#
#4787500
1#
#4793750
0#
#4800000
1#
#4806250
0#
#4812500
1#
#4818750
0#
#4825000
1#
#4831250
0#
#4837500
1#
#4843750
0#
#4850000
1#
#4856250
0#
#4862500
1#
#4868750
0#
#4875000
1#
#4881250
0#
#4887500
1#
#4893750
0#
#4900000
1#
#4906250
0#
#4912500
1#
#4918750
0#
#4925000
1#
#4931250
0#
#4937500
1#
#4943750
0#
#4950000
1#
#4956250
0#
#4962500
1#
#4968750
0#
#4975000
1#
#4981250
0#
#4987500
b11010010110011 )
b1100101101010011 *
1#
#4993750
0#
#5000000
b11010010110 5
b1100101101010 4
1#
#5006250
0#
#5012500
b1100100110011010001 $
1#
#5018750
0#
#5025000
1#
#5031250
0#
#5037500
1#
#5043750
0#
#5050000
1#
#5056250
0#
#5062500
1#
#5068750
0#
#5075000
1#
#5081250
0#
#5087500
1#
#5093750
0#
#5100000
1#
#5106250
0#
#5112500
1#
#5118750
0#
#5125000
1#
#5131250
0#
#5137500
1#
#5143750
0#
#5150000
1#
#5156250
0#
#5162500
1#
#5168750
0#
#5175000
1#
#5181250
0#
#5187500
1#
#5193750
0#
#5200000
1#
#5206250
0#
#5212500
1#
#5218750
0#
#5225000
b10111000100011 )
b1100010110000000 *
1#
#5231250
0#
#5237500
b10111000100 5
b1100010110000 4
1#
#5243750
0#
#5250000
b1101001100110011110 $
1#
#5256250
0#
#5262500
1#
#5268750
0#
#5275000
1#
#5281250
0#
#5287500
1#
#5293750
0#
#5300000
1#
#5306250
0#
#5312500
1#
#5318750
0#
#5325000
1#
#5331250
0#
#5337500
1#
#5343750
0#
#5350000
1#
#5356250
0#
#5362500
1#
#5368750
0#
#5375000
1#
#5381250
0#
#5387500
1#
#5393750
0#
#5400000
1#
#5406250
0#
#5412500
1#
#5418750
0#
#5425000
1#
#5431250
0#
#5437500
1#
#5443750
0#
#5450000
1#
#5456250
0#
#5462500
b10011011110001 )
b1100000001111110 *
1#
#5468750
0#
#5475000
b10011011110 5
b1100000001111 4
1#
#5481250
0#
#5487500
b1101110011001101011 $
1#
#5493750
0#
#5500000
1#
#5506250
0#
#5512500
1#
#5518750
0#
#5525000
1#
#5531250
0#
#5537500
1#
#5543750
0#
#5550000
1#
#5556250
0#
#5562500
1#
#5568750
0#
#5575000
1#
#5581250
0#
#5587500
1#
#5593750
0#
#5600000
1#
#5606250
0#
#5612500
1#
#5618750
0#
#5625000
1#
#5631250
0#
#5637500
1#
#5643750
0#
#5650000
1#
#5656250
0#
#5662500
1#
#5668750
0#
#5675000
1#
#5681250
0#
#5687500
1#
#5693750
0#
#5700000
b1111100110100 )
b1011110001010110 *
1#
#5706250
0#
#5712500
b1111100110 5
b1011110001010 4
1#
#5718750
0#
#5725000
b1110011001100111000 $
1#
#5731250
0#
#5737500
1#
#5743750
0#
#5750000
1#
#5756250
0#
#5762500
1#
#5768750
0#
#5775000
1#
#5781250
0#
#5787500
1#
#5793750
0#
#5800000
1#
#5806250
0#
#5812500
1#
#5818750
0#
#5825000
1#
#5831250
0#
#5837500
1#
#5843750
0#
#5850000
1#
#5856250
0#
#5862500
1#
#5868750
0#
#5875000
1#
#5881250
0#
#5887500
1#
#5893750
0#
#5900000
1#
#5906250
0#
#5912500
1#
#5918750
0#
#5925000
1#
#5931250
0#
#5937500
b1011100000111 )
b1011100100101000 *
1#
#5943750
0#
#5950000
b1011100000 5
b1011100100101 4
1#
#5956250
0#
#5962500
b1111000000000000101 $
1#
#5968750
0#
#5975000
1#
#5981250
0#
#5987500
1#
#5993750
0#
#6000000
1#
#6006250
0#
#6012500
1#
#6018750
0#
#6025000
1#
#6031250
0#
#6037500
1#
#6043750
0#
#6050000
1#
#6056250
0#
#6062500
1#
#6068750
0#
#6075000
1#
#6081250
0#
#6087500
1#
#6093750
0#
#6100000
1#
#6106250
0#
#6112500
1#
#6118750
0#
#6125000
1#
#6131250
0#
#6137500
1#
#6143750
0#
#6150000
1#
#6156250
0#
#6162500
1#
#6168750
0#
#6175000
b111010001010 )
b1011011011110001 *
1#
#6181250
0#
#6187500
b111010001 5
b1011011011110 4
1#
#6193750
0#
#6200000
b1111100110011010010 $
1#
#6206250
0#
#6212500
1#
