1bitSDRLattice/First_Implementation/source/AMDemod.v

/*
Performs AM Demodulation: sqrt(I^2 + Q^2)
Square root code is taken from https://verilogcodes.blogspot.com/2017/11/a-verilog-function-for-finding-square-root.html

TODO: use only one multiplier with TDM
TODO: minimize rounding errors of sqrt, get fractional result by scaling input

Module Description:
This module performs AM demodulation by computing the square root of the sum of the squares of the I and Q input signals (i.e., sqrt(I^2 + Q^2)). It uses two multipliers to compute the squares of the I and Q signals and then sums these squares. The square root function is implemented as a Verilog function within the module.

Inputs:
- clk: Clock signal.
- I_in: Signed 12-bit input signal representing the I component.
- Q_in: Signed 12-bit input signal representing the Q component.

Output:
- d_out: 12-bit output signal representing the demodulated AM signal.
*/

module AMDemodulator #(
  parameter WIDTH = 12
)(
  input                     clk,  
  input  signed [WIDTH-1:0] I_in,
  input  signed [WIDTH-1:0] Q_in,
  output reg    [WIDTH-1:0] d_out
);

  reg signed [15:0]        d_out_d;
  reg        [1:0]         state;
  reg                      NewSample;
  reg        [31:0]        ISquare;
  reg        [15:0]        QSquare;
  reg        [15:0]        SquareSum;

  reg signed [WIDTH-1:0]   MultDataA;
  reg signed [WIDTH-1:0]   MultDataB;
  reg signed [2*WIDTH-1:0] MultResult1;

  reg signed [WIDTH:0]     MultDataC;
  reg signed [WIDTH:0]     MultDataD;
  reg signed [2*WIDTH-1:0] MultResult2;

  // Function to calculate the square root
  function [15:0] sqrt;
    input [31:0] num;  // Declare input
    // Intermediate signals
    reg [31:0] a;
    reg [15:0] q;
    reg [17:0] left, right, r;    
    integer i;
    begin
      // Initialize all the variables
      a = num;
      q = 0;
      i = 0;
      left = 0;   // Input to adder/subtractor
      right = 0;  // Input to adder/subtractor
      r = 0;  // Remainder

      // Run the calculations for 16 iterations
      for (i = 0; i < 16; i = i + 1) begin 
        right = {q, r[17], 1'b1};
        left = {r[15:0], a[31:30]};
        a = {a[29:0], 2'b00};  // Left shift by 2 bits
        if (r[17] == 1)  // Add if r is negative
          r = left + right;
        else  // Subtract if r is positive
          r = left - right;
        q = {q[14:0], !r[17]};       
      end
      sqrt = q;  // Final assignment of output
    end
  endfunction // End of Function


  // Main processing block
  always @(posedge clk) begin
    // Load inputs to multipliers
    MultDataA  <= I_in;
    MultDataB  <= I_in;
    MultDataC  <= Q_in;
    MultDataD  <= Q_in;

    MultResult1 <= MultDataA*MultDataB;
    MultResult2 <= MultDataC*MultDataD;

    // Calculate I^2 + Q^2
    ISquare     <= MultResult1 + MultResult2;

    // Compute the square root of the sum of squares
    d_out_d     <= sqrt(ISquare);

    // Assign the lower 12 bits to the output
    d_out       <= d_out_d[WIDTH-1:0];
  end

 //----------------------------- 
 // For sim only
 //----------------------------- 
  initial begin
      $dumpfile("AMDemod_waves.vcd");
      $dumpvars;
  end

endmodule

/*
-----------------------------------------------------------------------------
Version History:
-----------------------------------------------------------------------------
 2024/4/18 TH: initial creation    
 2024/5/26 TH: revision
*/

1bitSDRLattice/Testbenches/AMDemod/AMDemod_waves.vcd
$date
	Sun May 26 19:49:01 2024
$end
$version
	Icarus Verilog
$end
$timescale
	1ps
$end
$scope module AMDemodulator $end
$var wire 12 ! I_in [11:0] $end
$var wire 12 " Q_in [11:0] $end
$var wire 1 # clk $end
$var parameter 32 $ WIDTH $end
$var reg 32 % ISquare [31:0] $end
$var reg 12 & MultDataA [11:0] $end
$var reg 12 ' MultDataB [11:0] $end
$var reg 13 ( MultDataC [12:0] $end
$var reg 13 ) MultDataD [12:0] $end
$var reg 24 * MultResult1 [23:0] $end
$var reg 24 + MultResult2 [23:0] $end
$var reg 12 , d_out [11:0] $end
$var reg 16 - d_out_d [15:0] $end
$scope function sqrt $end
$var reg 32 . a [31:0] $end
$var reg 18 / left [17:0] $end
$var reg 32 0 num [31:0] $end
$var reg 16 1 q [15:0] $end
$var reg 18 2 r [17:0] $end
$var reg 18 3 right [17:0] $end
$var integer 32 4 i [31:0] $end
$upscope $end
$upscope $end
$enddefinitions $end
$comment Show the parameter values. $end
$dumpall
b1100 $
$end
#0
$dumpvars
b10000 4
b0xxxxxxxxxxxxxxxx1 3
bx 2
bx 1
bx 0
bx /
b0 .
bx -
bx ,
bx +
bx *
b0 )
b0 (
b0 '
b0 &
bx %
1#
b0 "
b0 !
$end
#6250
0#
#12500
b0 +
b0 *
bx 2
b0xxxxxxxxxxxxxxxx1 3
bx /
b10000 4
bx 1
b0 .
1#
#18750
0#
#25000
b0 %
bx 2
b0xxxxxxxxxxxxxxxx1 3
bx /
b10000 4
bx 1
b0 .
1#
#31250
0#
#37500
b0 -
b111111111111111111 2
b11 3
b111111111111111100 /
b10000 4
b0 1
b0 0
1#
#43750
0#
#50000
b0 ,
b111111111111111111 2
b11 3
b111111111111111100 /
b10000 4
1#
#56250
0#
#62500
b111111111111111111 2
b11 3
b111111111111111100 /
b10000 4
1#
#68750
0#
#75000
b11111111111 "
b11111111111 !
b111111111111111111 2
b11 3
b111111111111111100 /
b10000 4
1#
#81250
0#
#87500
b11111111111 )
b11111111111 (
b11111111111 '
b11111111111 &
b111111111111111111 2
b11 3
b111111111111111100 /
b10000 4
1#
#93750
0#
#100000
b1111111111000000000001 +
b1111111111000000000001 *
b111111111111111111 2
b11 3
b111111111111111100 /
b10000 4
1#
#106250
0#
#112500
b11111111110000000000010 %
b111111111111111111 2
b11 3
b111111111111111100 /
b10000 4
1#
#118750
0#
#125000
b101101001110 -
b101101001110 1
b111111110110100001 2
b1011010011101 3
b1010000111110 /
b10000 4
b0 .
b11111111110000000000010 0
1#
#131250
0#
#137500
b101101001110 ,
b111111110110100001 2
b1011010011101 3
b1010000111110 /
b10000 4
b101101001110 1
b0 .
1#
#143750
0#
#150000
b100000000000 "
b100000000000 !
b111111110110100001 2
b1011010011101 3
b1010000111110 /
b10000 4
b101101001110 1
b0 .
1#
#156250
0#
#162500
b1100000000000 )
b1100000000000 (
b100000000000 '
b100000000000 &
b111111110110100001 2
b1011010011101 3
b1010000111110 /
b10000 4
b101101001110 1
b0 .
1#
#168750
0#
#175000
b10000000000000000000000 +
b10000000000000000000000 *
b111111110110100001 2
b1011010011101 3
b1010000111110 /
b10000 4
b101101001110 1
b0 .
1#
#181250
0#
#187500
b100000000000000000000000 %
b111111110110100001 2
b1011010011101 3
b1010000111110 /
b10000 4
b101101001110 1
b0 .
1#
#193750
0#
#200000
b101101010000 -
b111111000001011111 2
b1011010100011 3
b111101100110111100 /
b10000 4
b101101010000 1
b0 .
b100000000000000000000000 0
1#
#206250
0#
#212500
b101101010000 ,
b111111000001011111 2
b1011010100011 3
b111101100110111100 /
b10000 4
b101101010000 1
b0 .
1#
#218750
0#
#225000
b10101 !
b111111000001011111 2
b1011010100011 3
b111101100110111100 /
b10000 4
b101101010000 1
b0 .
1#
#231250
0#
#237500
b10101 '
b10101 &
b111111000001011111 2
b1011010100011 3
b111101100110111100 /
b10000 4
b101101010000 1
b0 .
1#
#243750
0#
#250000
b110111001 *
b111111000001011111 2
b1011010100011 3
b111101100110111100 /
b10000 4
b101101010000 1
b0 .
1#
#256250
0#
#262500
b10000000000000110111001 %
b111111000001011111 2
b1011010100011 3
b111101100110111100 /
b10000 4
b101101010000 1
b0 .
1#
#268750
0#
#275000
b100000000000 -
b111111000110111000 2
b1000000000011 3
b111110000110110101 /
b10000 4
b100000000000 1
b0 .
b10000000000000110111001 0
1#
#281250
0#
#287500
b100000000000 ,
b111111000110111000 2
b1000000000011 3
b111110000110110101 /
b10000 4
b100000000000 1
b0 .
1#
#293750
0#
#300000
b11111111111 "
b100000000000 !
b111111000110111000 2
b1000000000011 3
b111110000110110101 /
b10000 4
b100000000000 1
b0 .
1#
#306250
0#
#312500
b11111111111 )
b11111111111 (
b100000000000 '
b100000000000 &
b111111000110111000 2
b1000000000011 3
b111110000110110101 /
b10000 4
b100000000000 1
b0 .
1#
#318750
0#
#325000
b1111111111000000000001 +
b10000000000000000000000 *
b111111000110111000 2
b1000000000011 3
b111110000110110101 /
b10000 4
b100000000000 1
b0 .
1#
#331250
0#
#337500
b11111111111000000000001 %
b111111000110111000 2
b1000000000011 3
b111110000110110101 /
b10000 4
b100000000000 1
b0 .
1#
#343750
0#
#350000
b101101001111 -
b110110100000 2
b1011010011101 3
b10010000111101 /
b10000 4
b101101001111 1
b0 .
b11111111111000000000001 0
1#
#356250
0#
#362500
b101101001111 ,
b110110100000 2
b1011010011101 3
b10010000111101 /
b10000 4
b101101001111 1
b0 .
1#
#368750
0#
#375000
b10010110010 "
b10111111011 !
b110110100000 2
b1011010011101 3
b10010000111101 /
b10000 4
b101101001111 1
b0 .
1#
#381250
0#
#387500
b10010110010 )
b10010110010 (
b10111111011 '
b10111111011 &
b110110100000 2
b1011010011101 3
b10010000111101 /
b10000 4
b101101001111 1
b0 .
1#
#393750
0#
#400000
b101100000101111000100 +
b1000111100010000011001 *
b110110100000 2
b1011010011101 3
b10010000111101 /
b10000 4
b101101001111 1
b0 .
1#
#406250
0#
#412500
b1110011100111111011101 %
b110110100000 2
b1011010011101 3
b10010000111101 /
b10000 4
b101101001111 1
b0 .
1#
#418750
0#
#425000
b11110011010 -
b111111100000000100 2
b111100110101 3
b11100111001 /
b10000 4
b11110011010 1
b0 .
b1110011100111111011101 0
1#
#431250
0#
#437500
b11110011010 ,
b111111100000000100 2
b111100110101 3
b11100111001 /
b10000 4
b11110011010 1
b0 .
1#
#443750
0#
#450000
b10110000000 "
b1010001111 !
b111111100000000100 2
b111100110101 3
b11100111001 /
b10000 4
b11110011010 1
b0 .
1#
#456250
0#
#462500
b10110000000 )
b10110000000 (
b1010001111 '
b1010001111 &
b111111100000000100 2
b111100110101 3
b11100111001 /
b10000 4
b11110011010 1
b0 .
1#
#468750
0#
#475000
b111100100000000000000 +
b1101000101111100001 *
b111111100000000100 2
b111100110101 3
b11100111001 /
b10000 4
b11110011010 1
b0 .
1#
#481250
0#
#487500
b1001001100101111100001 %
b111111100000000100 2
b111100110101 3
b11100111001 /
b10000 4
b11110011010 1
b0 .
1#
#493750
0#
#500000
b11000010000 -
b111111111011000000 2
b110000100011 3
b111111001010011101 /
b10000 4
b11000010000 1
b0 .
b1001001100101111100001 0
1#
#506250
0#
#512500
b11000010000 ,
b111111111011000000 2
b110000100011 3
b111111001010011101 /
b10000 4
b11000010000 1
b0 .
1#
#518750
0#
#525000
b10000110000 "
b110000001110 !
b111111111011000000 2
b110000100011 3
b111111001010011101 /
b10000 4
b11000010000 1
b0 .
1#
#531250
0#
#537500
b10000110000 )
b10000110000 (
b110000001110 '
b110000001110 &
b111111111011000000 2
b110000100011 3
b111111001010011101 /
b10000 4
b11000010000 1
b0 .
1#
#543750
0#
#550000
b100011000100100000000 +
b11111001000011000100 *
b111111111011000000 2
b110000100011 3
b111111001010011101 /
b10000 4
b11000010000 1
b0 .
1#
#556250
0#
#562500
b1000010001100111000100 %
b111111111011000000 2
b110000100011 3
b111111001010011101 /
b10000 4
b11000010000 1
b0 .
1#
#568750
0#
#575000
b10111000000 -
b111111111001000011 2
b101110000011 3
b111111001011000000 /
b10000 4
b10111000000 1
b0 .
b1000010001100111000100 0
1#
#581250
0#
#587500
b10111000000 ,
b111111111001000011 2
b101110000011 3
b111111001011000000 /
b10000 4
b10111000000 1
b0 .
1#
#593750
0#
#600000
b101000011000 "
b101001101 !
b111111111001000011 2
b101110000011 3
b111111001011000000 /
b10000 4
b10111000000 1
b0 .
1#
#606250
0#
#612500
b1101000011000 )
b1101000011000 (
b101001101 '
b101001101 &
b111111111001000011 2
b101110000011 3
b111111001011000000 /
b10000 4
b10111000000 1
b0 .
1#
#618750
0#
#625000
b1000101110001001000000 +
b11011000100101001 *
b111111111001000011 2
b101110000011 3
b111111001011000000 /
b10000 4
b10111000000 1
b0 .
1#
#631250
0#
#637500
b1001001001001101101001 %
b111111111001000011 2
b101110000011 3
b111111001011000000 /
b10000 4
b10111000000 1
b0 .
1#
#643750
0#
#650000
b11000001100 -
b111111011011000000 2
b110000011011 3
b111110101010100101 /
b10000 4
b11000001100 1
b0 .
b1001001001001101101001 0
1#
#656250
0#
#662500
b11000001100 ,
b111111011011000000 2
b110000011011 3
b111110101010100101 /
b10000 4
b11000001100 1
b0 .
1#
#668750
0#
#675000
b11111011111 "
b110100101001 !
b111111011011000000 2
b110000011011 3
b111110101010100101 /
b10000 4
b11000001100 1
b0 .
1#
#681250
0#
#687500
b11111011111 )
b11111011111 (
b110100101001 '
b110100101001 &
b111111011011000000 2
b110000011011 3
b111110101010100101 /
b10000 4
b11000001100 1
b0 .
1#
#693750
0#
#700000
b1111011111010001000001 +
b10000001000010010001 *
b111111011011000000 2
b110000011011 3
b111110101010100101 /
b10000 4
b11000001100 1
b0 .
1#
#706250
0#
#712500
b10001100000010011010010 %
b111111011011000000 2
b110000011011 3
b111110101010100101 /
b10000 4
b11000001100 1
b0 .
1#
#718750
0#
#725000
b100001011110 -
b111111000110010001 2
b1000010111101 3
b1001001110 /
b10000 4
b100001011110 1
b0 .
b10001100000010011010010 0
1#
#731250
0#
#737500
b100001011110 ,
b111111000110010001 2
b1000010111101 3
b1001001110 /
b10000 4
b100001011110 1
b0 .
1#
#743750
0#
#750000
b110100110001 "
b101011110111 !
b111111000110010001 2
b1000010111101 3
b1001001110 /
b10000 4
b100001011110 1
b0 .
1#
#756250
0#
#762500
b1110100110001 )
b1110100110001 (
b101011110111 '
b101011110111 &
b111111000110010001 2
b1000010111101 3
b1001001110 /
b10000 4
b100001011110 1
b0 .
1#
#768750
0#
#775000
b1111110001101100001 +
b110010101101001010001 *
b111111000110010001 2
b1000010111101 3
b1001001110 /
b10000 4
b100001011110 1
b0 .
1#
#781250
0#
#787500
b1000010011110110110010 %
b111111000110010001 2
b1000010111101 3
b1001001110 /
b10000 4
b100001011110 1
b0 .
1#
#793750
0#
#800000
b10111000011 -
b101100101001 2
b101110000101 3
b1011010101110 /
b10000 4
b10111000011 1
b0 .
b1000010011110110110010 0
1#
#806250
0#
#812500
b10111000011 ,
b101100101001 2
b101110000101 3
b1011010101110 /
b10000 4
b10111000011 1
b0 .
1#
#818750
0#
#825000
b101111000011 "
b10111010111 !
b101100101001 2
b101110000101 3
b1011010101110 /
b10000 4
b10111000011 1
b0 .
1#
#831250
0#
#837500
b1101111000011 )
b1101111000011 (
b10111010111 '
b10111010111 &
b101100101001 2
b101110000101 3
b1011010101110 /
b10000 4
b10111000011 1
b0 .
1#
#843750
0#
#850000
b100011111011010001001 +
b1000100001101010010001 *
b101100101001 2
b101110000101 3
b1011010101110 /
b10000 4
b10111000011 1
b0 .
1#
#856250
0#
#862500
b1101000001000100011010 %
b101100101001 2
b101110000101 3
b1011010101110 /
b10000 4
b10111000011 1
b0 .
1#
#868750
0#
#875000
b11100110111 -
b1101001001 2
b111001101101 3
b1000110110110 /
b10000 4
b11100110111 1
b0 .
b1101000001000100011010 0
1#
#881250
0#
#887500
b11100110111 ,
b1101001001 2
b111001101101 3
b1000110110110 /
b10000 4
b11100110111 1
b0 .
1#
#893750
0#
#900000
b10100011110 "
b1011110010 !
b1101001001 2
b111001101101 3
b1000110110110 /
b10000 4
b11100110111 1
b0 .
1#
#906250
0#
#912500
b10100011110 )
b10100011110 (
b1011110010 '
b1011110010 &
b1101001001 2
b111001101101 3
b1000110110110 /
b10000 4
b11100110111 1
b0 .
1#
#918750
0#
#925000
b110100010111110000100 +
b10001010110011000100 *
b1101001001 2
b111001101101 3
b1000110110110 /
b10000 4
b11100110111 1
b0 .
1#
#931250
0#
#937500
b1000101101110001001000 %
b1101001001 2
b111001101101 3
b1000110110110 /
b10000 4
b11100110111 1
b0 .
1#
#943750
0#
#950000
b10111100111 -
b10111010111 2
b101111001101 3
b1000110100100 /
b10000 4
b10111100111 1
b0 .
b1000101101110001001000 0
1#
#956250
0#
#962500
b10111100111 ,
b10111010111 2
b101111001101 3
b1000110100100 /
b10000 4
b10111100111 1
b0 .
1#
#968750
0#
#975000
b11111110101 "
b111001110001 !
b10111010111 2
b101111001101 3
b1000110100100 /
b10000 4
b10111100111 1
b0 .
1#
#981250
0#
#987500
b11111110101 )
b11111110101 (
b111001110001 '
b111001110001 &
b10111010111 2
b101111001101 3
b1000110100100 /
b10000 4
b10111100111 1
b0 .
1#
#993750
0#
#1000000
b1111110101000001111001 +
b100110110111100001 *
b10111010111 2
b101111001101 3
b1000110100100 /
b10000 4
b10111100111 1
b0 .
1#
#1006250
0#
#1012500
b10000011011111001011010 %
b10111010111 2
b101111001101 3
b1000110100100 /
b10000 4
b10111100111 1
b0 .
1#
#1018750
0#
#1025000
b100000011011 -
b101110000001 2
b1000000110101 3
b1101110110110 /
b10000 4
b100000011011 1
b0 .
b10000011011111001011010 0
1#
#1031250
0#
#1037500
b100000011011 ,
b101110000001 2
b1000000110101 3
b1101110110110 /
b10000 4
b100000011011 1
b0 .
1#
#1043750
0#
#1050000
b111101011111 "
b111011000111 !
b101110000001 2
b1000000110101 3
b1101110110110 /
b10000 4
b100000011011 1
b0 .
1#
#1056250
0#
#1062500
b1111101011111 )
b1111101011111 (
b111011000111 '
b111011000111 &
b101110000001 2
b1000000110101 3
b1101110110110 /
b10000 4
b100000011011 1
b0 .
1#
#1068750
0#
#1075000
b110010101000001 +
b10111111010110001 *
b101110000001 2
b1000000110101 3
b1101110110110 /
b10000 4
b100000011011 1
b0 .
1#
#1081250
0#
#1087500
b11110001111110010 %
b101110000001 2
b1000000110101 3
b1101110110110 /
b10000 4
b100000011011 1
b0 .
1#
#1093750
0#
#1100000
b101011111 -
b1010110001 2
b1010111101 3
b10101101110 /
b10000 4
b101011111 1
b0 .
b11110001111110010 0
1#
#1106250
0#
#1112500
b101011111 ,
b1010110001 2
b1010111101 3
b10101101110 /
b10000 4
b101011111 1
b0 .
1#
#1118750
0#
#1125000
b11011110101 "
b101111111011 !
b1010110001 2
b1010111101 3
b10101101110 /
b10000 4
b101011111 1
b0 .
1#
#1131250
0#
#1137500
b11011110101 )
b11011110101 (
b101111111011 '
b101111111011 &
b1010110001 2
b1010111101 3
b10101101110 /
b10000 4
b101011111 1
b0 .
1#
#1143750
0#
#1150000
b1100000110011001111001 +
b100000010100000011001 *
b1010110001 2
b1010111101 3
b10101101110 /
b10000 4
b101011111 1
b0 .
1#
#1156250
0#
#1162500
b10000001000111010010010 %
b1010110001 2
b1010111101 3
b10101101110 /
b10000 4
b101011111 1
b0 .
1#
#1168750
0#
#1175000
b100000001000 -
b111111111001000001 2
b1000000010011 3
b111110111000101110 /
b10000 4
b100000001000 1
b0 .
b10000001000111010010010 0
1#
#1181250
0#
#1187500
b100000001000 ,
b111111111001000001 2
b1000000010011 3
b111110111000101110 /
b10000 4
b100000001000 1
b0 .
1#
#1193750
0#
#1200000
b101001101011 "
b100101001010 !
b111111111001000001 2
b1000000010011 3
b111110111000101110 /
b10000 4
b100000001000 1
b0 .
1#
#1206250
0#
#1212500
b1101001101011 )
b1101001101011 (
b100101001010 '
b100101001010 &
b111111111001000001 2
b1000000010011 3
b111110111000101110 /
b10000 4
b100000001000 1
b0 .
1#
#1218750
0#
#1225000
b111110010100010111001 +
b1011010000100101100100 *
b111111111001000001 2
b1000000010011 3
b111110111000101110 /
b10000 4
b100000001000 1
b0 .
1#
#1231250
0#
#1237500
b10011000011001000011101 %
b111111111001000001 2
b1000000010011 3
b111110111000101110 /
b10000 4
b100000001000 1
b0 .
1#
#1243750
0#
#1250000
b100010111010 -
b111111100110000100 2
b1000101110101 3
b101011111001 /
b10000 4
b100010111010 1
b0 .
b10011000011001000011101 0
1#
#1256250
0#
#1262500
b100010111010 ,
b111111100110000100 2
b1000101110101 3
b101011111001 /
b10000 4
b100010111010 1
b0 .
1#
#1268750
0#
#1275000
b110110010111 "
b110100100 !
b111111100110000100 2
b1000101110101 3
b101011111001 /
b10000 4
b100010111010 1
b0 .
1#
#1281250
0#
#1287500
b1110110010111 )
b1110110010111 (
b110100100 '
b110100100 &
b111111100110000100 2
b1000101110101 3
b101011111001 /
b10000 4
b100010111010 1
b0 .
1#
#1293750
0#
#1300000
b1011100111100010001 +
b101011000100010000 *
b111111100110000100 2
b1000101110101 3
b101011111001 /
b10000 4
b100010111010 1
b0 .
1#
#1306250
0#
#1312500
b10001000000000100001 %
b111111100110000100 2
b1000101110101 3
b101011111001 /
b10000 4
b100010111010 1
b0 .
1#
#1318750
0#
#1325000
b1011101010 -
b111111110001101000 2
b10111010101 3
b1000111101 /
b10000 4
b1011101010 1
b0 .
b10001000000000100001 0
1#
#1331250
0#
#1337500
b1011101010 ,
b111111110001101000 2
b10111010101 3
b1000111101 /
b10000 4
b1011101010 1
b0 .
1#
#1343750
0#
#1350000
b111011101101 "
b101001100011 !
b111111110001101000 2
b10111010101 3
b1000111101 /
b10000 4
b1011101010 1
b0 .
1#
#1356250
0#
#1362500
b1111011101101 )
b1111011101101 (
b101001100011 '
b101001100011 &
b111111110001101000 2
b10111010101 3
b1000111101 /
b10000 4
b1011101010 1
b0 .
1#
#1368750
0#
#1375000
b10010011101101001 +
b111111000001001001001 *
b111111110001101000 2
b10111010101 3
b1000111101 /
b10000 4
b1011101010 1
b0 .
1#
#1381250
0#
#1387500
b1000001010100110110010 %
b111111110001101000 2
b10111010101 3
b1000111101 /
b10000 4
b1011101010 1
b0 .
1#
#1393750
0#
#1400000
b10110110111 -
b11100001 2
b101101101101 3
b110001001110 /
b10000 4
b10110110111 1
b0 .
b1000001010100110110010 0
1#
#1406250
0#
#1412500
b10110110111 ,
b11100001 2
b101101101101 3
b110001001110 /
b10000 4
b10110110111 1
b0 .
1#
#1418750
0#
#1425000
b111001110111 "
b101101111010 !
b11100001 2
b101101101101 3
b110001001110 /
b10000 4
b10110110111 1
b0 .
1#
#1431250
0#
#1437500
b1111001110111 )
b1111001110111 (
b101101111010 '
b101101111010 &
b11100001 2
b101101101101 3
b110001001110 /
b10000 4
b10110110111 1
b0 .
1#
#1443750
0#
#1450000
b100101101101010001 +
b101000111011000100100 *
b11100001 2
b101101101101 3
b110001001110 /
b10000 4
b10110110111 1
b0 .
1#
#1456250
0#
#1462500
b101101101000101110101 %
b11100001 2
b101101101101 3
b110001001110 /
b10000 4
b10110110111 1
b0 .
1#
#1468750
0#
#1475000
b10011000110 -
b111111111011000100 2
b100110001101 3
b100001010001 /
b10000 4
b10011000110 1
b0 .
b101101101000101110101 0
1#
#1481250
0#
#1487500
b10011000110 ,
b111111111011000100 2
b100110001101 3
b100001010001 /
b10000 4
b10011000110 1
b0 .
1#
#1493750
0#
#1500000
b101010000011 "
b110010000111 !
b111111111011000100 2
b100110001101 3
b100001010001 /
b10000 4
b10011000110 1
b0 .
1#
#1506250
0#
#1512500
b1101010000011 )
b1101010000011 (
b110010000111 '
b110010000111 &
b111111111011000100 2
b100110001101 3
b100001010001 /
b10000 4
b10011000110 1
b0 .
1#
#1518750
0#
#1525000
b111100001111100001001 +
b11000000111100110001 *
b111111111011000100 2
b100110001101 3
b100001010001 /
b10000 4
b10011000110 1
b0 .
1#
#1531250
0#
#1537500
b1010100010111000111010 %
b111111111011000100 2
b100110001101 3
b100001010001 /
b10000 4
b10011000110 1
b0 .
1#
#1543750
0#
#1550000
b11001111110 -
b111111101100111001 2
b110011111101 3
b100000110110 /
b10000 4
b11001111110 1
b0 .
b1010100010111000111010 0
1#
#1556250
0#
#1562500
b11001111110 ,
b111111101100111001 2
b110011111101 3
b100000110110 /
b10000 4
b11001111110 1
b0 .
1#
#1568750
0#
#1575000
b1011101001 "
b100011000000 !
b111111101100111001 2
b110011111101 3
b100000110110 /
b10000 4
b11001111110 1
b0 .
1#
#1581250
0#
#1587500
b1011101001 )
b1011101001 (
b100011000000 '
b100011000000 &
b111111101100111001 2
b110011111101 3
b100000110110 /
b10000 4
b11001111110 1
b0 .
1#
#1593750
0#
#1600000
b10000111100000010001 +
b1101001001000000000000 *
b111111101100111001 2
b110011111101 3
b100000110110 /
b10000 4
b11001111110 1
b0 .
1#
#1606250
0#
#1612500
b1111010000100000010001 %
b111111101100111001 2
b110011111101 3
b100000110110 /
b10000 4
b11001111110 1
b0 .
1#
#1618750
0#
#1625000
b11111001111 -
b111010110000 2
b111110011101 3
b1111001001101 /
b10000 4
b11111001111 1
b0 .
b1111010000100000010001 0
1#
#1631250
0#
#1637500
b11111001111 ,
b111010110000 2
b111110011101 3
b1111001001101 /
b10000 4
b11111001111 1
b0 .
1#
#1643750
0#
#1650000
b111101001000 "
b111111000100 !
b111010110000 2
b111110011101 3
b1111001001101 /
b10000 4
b11111001111 1
b0 .
1#
#1656250
0#
#1662500
b1111101001000 )
b1111101001000 (
b111111000100 '
b111111000100 &
b111010110000 2
b111110011101 3
b1111001001101 /
b10000 4
b11111001111 1
b0 .
1#
#1668750
0#
#1675000
b1000010001000000 +
b111000010000 *
b111010110000 2
b111110011101 3
b1111001001101 /
b10000 4
b11111001111 1
b0 .
1#
#1681250
0#
#1687500
b1001001001010000 %
b111010110000 2
b111110011101 3
b1111001001101 /
b10000 4
b11111001111 1
b0 .
1#
#1693750
0#
#1700000
b11000001 -
b11001111 2
b110000011 3
b111111111101001100 /
b10000 4
b11000001 1
b0 .
b1001001001010000 0
1#
#1706250
0#
#1712500
b11000001 ,
b11001111 2
b110000011 3
b111111111101001100 /
b10000 4
b11000001 1
b0 .
1#
#1718750
0#
#1725000
b100111001100 "
b11001001100 !
b11001111 2
b110000011 3
b111111111101001100 /
b10000 4
b11000001 1
b0 .
1#
#1731250
0#
#1737500
b1100111001100 )
b1100111001100 (
b11001001100 '
b11001001100 &
b11001111 2
b110000011 3
b111111111101001100 /
b10000 4
b11000001 1
b0 .
1#
#1743750
0#
#1750000
b1001100111101010010000 +
b1001111010011010010000 *
b11001111 2
b110000011 3
b111111111101001100 /
b10000 4
b11000001 1
b0 .
1#
#1756250
0#
#1762500
b10011100010000100100000 %
b11001111 2
b110000011 3
b111111111101001100 /
b10000 4
b11000001 1
b0 .
1#
#1768750
0#
#1775000
b100011010110 -
b111111110010001111 2
b1000110101101 3
b111000111100 /
b10000 4
b100011010110 1
b0 .
b10011100010000100100000 0
1#
#1781250
0#
#1787500
b100011010110 ,
b111111110010001111 2
b1000110101101 3
b111000111100 /
b10000 4
b100011010110 1
b0 .
1#
#1793750
0#
#1800000
b1110111011 "
b11000011011 !
b111111110010001111 2
b1000110101101 3
b111000111100 /
b10000 4
b100011010110 1
b0 .
1#
#1806250
0#
#1812500
b1110111011 )
b1110111011 (
b11000011011 '
b11000011011 &
b111111110010001111 2
b1000110101101 3
b111000111100 /
b10000 4
b100011010110 1
b0 .
1#
#1818750
0#
#1825000
b11011110101010011001 +
b1001010100011011011001 *
b111111110010001111 2
b1000110101101 3
b111000111100 /
b10000 4
b100011010110 1
b0 .
1#
#1831250
0#
#1837500
b1100110011000101110010 %
b111111110010001111 2
b1000110101101 3
b111000111100 /
b10000 4
b100011010110 1
b0 .
1#
#1843750
0#
#1850000
b11100100111 -
b100110000001 2
b111001001101 3
b1011111001110 /
b10000 4
b11100100111 1
b0 .
b1100110011000101110010 0
1#
#1856250
0#
#1862500
b11100100111 ,
b100110000001 2
b111001001101 3
b1011111001110 /
b10000 4
b11100100111 1
b0 .
1#
#1868750
0#
#1875000
b1111000101 "
b111001100010 !
b100110000001 2
b111001001101 3
b1011111001110 /
b10000 4
b11100100111 1
b0 .
1#
#1881250
0#
#1887500
b1111000101 )
b1111000101 (
b111001100010 '
b111001100010 &
b100110000001 2
b111001001101 3
b1011111001110 /
b10000 4
b11100100111 1
b0 .
1#
#1893750
0#
#1900000
b11100011010110011001 +
b101001110110000100 *
b100110000001 2
b111001001101 3
b1011111001110 /
b10000 4
b11100100111 1
b0 .
1#
#1906250
0#
#1912500
b100001101001100011101 %
b100110000001 2
b111001001101 3
b1011111001110 /
b10000 4
b11100100111 1
b0 .
1#
#1918750
0#
#1925000
b10000011010 -
b111111100001000100 2
b100000110101 3
b1111001 /
b10000 4
b10000011010 1
b0 .
b100001101001100011101 0
1#
#1931250
0#
#1937500
b10000011010 ,
b111111100001000100 2
b100000110101 3
b1111001 /
b10000 4
b10000011010 1
b0 .
1#
#1943750
0#
#1950000
b100000010000 "
b111111011000 !
b111111100001000100 2
b100000110101 3
b1111001 /
b10000 4
b10000011010 1
b0 .
1#
#1956250
0#
#1962500
b1100000010000 )
b1100000010000 (
b111111011000 '
b111111011000 &
b111111100001000100 2
b100000110101 3
b1111001 /
b10000 4
b10000011010 1
b0 .
1#
#1968750
0#
#1975000
b1111110000000100000000 +
b11001000000 *
b111111100001000100 2
b100000110101 3
b1111001 /
b10000 4
b10000011010 1
b0 .
1#
#1981250
0#
#1987500
b1111110000011101000000 %
b111111100001000100 2
b100000110101 3
b1111001 /
b10000 4
b10000011010 1
b0 .
1#
#1993750
0#
#2000000
b11111110000 -
b111111011001011111 2
b111111100011 3
b111110011001111100 /
b10000 4
b11111110000 1
b0 .
b1111110000011101000000 0
1#
#2006250
0#
#2012500
b11111110000 ,
b111111011001011111 2
b111111100011 3
b111110011001111100 /
b10000 4
b11111110000 1
b0 .
1#
#2018750
0#
#2025000
b11111010111 "
b100001011 !
b111111011001011111 2
b111111100011 3
b111110011001111100 /
b10000 4
b11111110000 1
b0 .
1#
#2031250
0#
#2037500
b11111010111 )
b11111010111 (
b100001011 '
b100001011 &
b111111011001011111 2
b111111100011 3
b111110011001111100 /
b10000 4
b11111110000 1
b0 .
1#
#2043750
0#
#2050000
b1111010111011010010001 +
b10001011001111001 *
b111111011001011111 2
b111111100011 3
b111110011001111100 /
b10000 4
b11111110000 1
b0 .
1#
#2056250
0#
#2062500
b1111101000110100001010 %
b111111011001011111 2
b111111100011 3
b111110011001111100 /
b10000 4
b11111110000 1
b0 .
1#
#2068750
0#
