1.RTLImplementation/2.sim/AMDemod/hdl/AMDemod.v

/*
Performs AM Demodulation: sqrt(I^2 + Q^2)
Square root code is taken from https://verilogcodes.blogspot.com/2017/11/a-verilog-function-for-finding-square-root.html

TODO: use only one multiplier with TDM
TODO: minimize rounding errors of sqrt, get fractional result by scaling input

Module Description:
This module performs AM demodulation by computing the square root of the sum of the squares of the I and Q input signals (i.e., sqrt(I^2 + Q^2)). It uses two multipliers to compute the squares of the I and Q signals and then sums these squares. The square root function is implemented as a Verilog function within the module.

Inputs:
- clk: Clock signal.
- I_in: Signed 12-bit input signal representing the I component.
- Q_in: Signed 12-bit input signal representing the Q component.

Output:
- d_out: 12-bit output signal representing the demodulated AM signal.
*/

module AMDemodulator #(
  parameter WIDTH = 12
)(
  input clk,  
  input signed [WIDTH-1:0] I_in,
  input signed [WIDTH-1:0] Q_in,
  output reg [WIDTH-1:0] d_out
);

  reg signed [15:0] d_out_d;
  reg [1:0] state;
  reg NewSample;
  reg [31:0] ISquare;
  reg [15:0] QSquare;
  reg [15:0] SquareSum;

  reg signed [WIDTH-1:0] MultDataA;
  reg signed [WIDTH-1:0] MultDataB;
  reg signed [2*WIDTH-1:0] MultResult1;

  reg signed [WIDTH:0] MultDataC;
  reg signed [WIDTH:0] MultDataD;
  reg signed [2*WIDTH-1:0] MultResult2;

  // Function to calculate the square root
  function [15:0] sqrt;
    input [31:0] num;  // Declare input
    // Intermediate signals
    reg [31:0] a;
    reg [15:0] q;
    reg [17:0] left, right, r;    
    integer i;
    begin
      // Initialize all the variables
      a = num;
      q = 0;
      i = 0;
      left = 0;   // Input to adder/subtractor
      right = 0;  // Input to adder/subtractor
      r = 0;  // Remainder

      // Run the calculations for 16 iterations
      for (i = 0; i < 16; i = i + 1) begin 
        right = {q, r[17], 1'b1};
        left = {r[15:0], a[31:30]};
        a = {a[29:0], 2'b00};  // Left shift by 2 bits
        if (r[17] == 1)  // Add if r is negative
          r = left + right;
        else  // Subtract if r is positive
          r = left - right;
        q = {q[14:0], !r[17]};       
      end
      sqrt = q;  // Final assignment of output
    end
  endfunction // End of Function


  // Main processing block
  always @(posedge clk) begin
    // Load inputs to multipliers
    MultDataA <= I_in;
    MultDataB <= I_in;
    MultDataC <= Q_in;
    MultDataD <= Q_in;

    MultResult1 <= MultDataA*MultDataB;
    MultResult2 <= MultDataC*MultDataD;

    // Calculate I^2 + Q^2
    ISquare <= MultResult1 + MultResult2;

    // Compute the square root of the sum of squares
    d_out_d <= sqrt(ISquare);

    // Assign the lower 12 bits to the output
    d_out <= d_out_d[WIDTH-1:0];
  end

 //----------------------------- 
 // For sim only
 //----------------------------- 
  initial begin
      $dumpfile("AMDemod_waves.vcd");
      $dumpvars;
  end

endmodule

/*
-----------------------------------------------------------------------------
Version History:
-----------------------------------------------------------------------------
 2024/4/18 TH: initial creation    
 2024/5/26 TH: revision
*/

1.RTLImplementation/2.sim/AMDemod/AMDemod_waves.vcd
$date
	Thu Jun 13 14:57:02 2024
$end
$version
	Icarus Verilog
$end
$timescale
	1ps
$end
$scope module AMDemodulator $end
$var wire 12 ! I_in [11:0] $end
$var wire 12 " Q_in [11:0] $end
$var wire 1 # clk $end
$var parameter 32 $ WIDTH $end
$var reg 32 % ISquare [31:0] $end
$var reg 12 & MultDataA [11:0] $end
$var reg 12 ' MultDataB [11:0] $end
$var reg 13 ( MultDataC [12:0] $end
$var reg 13 ) MultDataD [12:0] $end
$var reg 24 * MultResult1 [23:0] $end
$var reg 24 + MultResult2 [23:0] $end
$var reg 12 , d_out [11:0] $end
$var reg 16 - d_out_d [15:0] $end
$scope function sqrt $end
$var reg 32 . a [31:0] $end
$var reg 18 / left [17:0] $end
$var reg 32 0 num [31:0] $end
$var reg 16 1 q [15:0] $end
$var reg 18 2 r [17:0] $end
$var reg 18 3 right [17:0] $end
$var integer 32 4 i [31:0] $end
$upscope $end
$upscope $end
$enddefinitions $end
$comment Show the parameter values. $end
$dumpall
b1100 $
$end
#0
$dumpvars
b10000 4
b0xxxxxxxxxxxxxxxx1 3
bx 2
bx 1
bx 0
bx /
b0 .
bx -
bx ,
bx +
bx *
b0 )
b0 (
b0 '
b0 &
bx %
1#
b0 "
b0 !
$end
#6250
0#
#12500
b0 +
b0 *
bx 2
b0xxxxxxxxxxxxxxxx1 3
bx /
b10000 4
bx 1
b0 .
1#
#18750
0#
#25000
b0 %
bx 2
b0xxxxxxxxxxxxxxxx1 3
bx /
b10000 4
bx 1
b0 .
1#
#31250
0#
#37500
b0 -
b111111111111111111 2
b11 3
b111111111111111100 /
b10000 4
b0 1
b0 0
1#
#43750
0#
#50000
b0 ,
b111111111111111111 2
b11 3
b111111111111111100 /
b10000 4
1#
#56250
0#
#62500
b111111111111111111 2
b11 3
b111111111111111100 /
b10000 4
1#
#68750
0#
#75000
b11111111111 "
b11111111111 !
b111111111111111111 2
b11 3
b111111111111111100 /
b10000 4
1#
#81250
0#
#87500
b11111111111 )
b11111111111 (
b11111111111 '
b11111111111 &
b111111111111111111 2
b11 3
b111111111111111100 /
b10000 4
1#
#93750
0#
#100000
b1111111111000000000001 +
b1111111111000000000001 *
b111111111111111111 2
b11 3
b111111111111111100 /
b10000 4
1#
#106250
0#
#112500
b11111111110000000000010 %
b111111111111111111 2
b11 3
b111111111111111100 /
b10000 4
1#
#118750
0#
#125000
b101101001110 -
b101101001110 1
b111111110110100001 2
b1011010011101 3
b1010000111110 /
b10000 4
b0 .
b11111111110000000000010 0
1#
#131250
0#
#137500
b101101001110 ,
b111111110110100001 2
b1011010011101 3
b1010000111110 /
b10000 4
b101101001110 1
b0 .
1#
#143750
0#
#150000
b100000000000 "
b100000000000 !
b111111110110100001 2
b1011010011101 3
b1010000111110 /
b10000 4
b101101001110 1
b0 .
1#
#156250
0#
#162500
b1100000000000 )
b1100000000000 (
b100000000000 '
b100000000000 &
b111111110110100001 2
b1011010011101 3
b1010000111110 /
b10000 4
b101101001110 1
b0 .
1#
#168750
0#
#175000
b10000000000000000000000 +
b10000000000000000000000 *
b111111110110100001 2
b1011010011101 3
b1010000111110 /
b10000 4
b101101001110 1
b0 .
1#
#181250
0#
#187500
b100000000000000000000000 %
b111111110110100001 2
b1011010011101 3
b1010000111110 /
b10000 4
b101101001110 1
b0 .
1#
#193750
0#
#200000
b101101010000 -
b111111000001011111 2
b1011010100011 3
b111101100110111100 /
b10000 4
b101101010000 1
b0 .
b100000000000000000000000 0
1#
#206250
0#
#212500
b101101010000 ,
b111111000001011111 2
b1011010100011 3
b111101100110111100 /
b10000 4
b101101010000 1
b0 .
1#
#218750
0#
#225000
b10101 !
b111111000001011111 2
b1011010100011 3
b111101100110111100 /
b10000 4
b101101010000 1
b0 .
1#
#231250
0#
#237500
b10101 '
b10101 &
b111111000001011111 2
b1011010100011 3
b111101100110111100 /
b10000 4
b101101010000 1
b0 .
1#
#243750
0#
#250000
b110111001 *
b111111000001011111 2
b1011010100011 3
b111101100110111100 /
b10000 4
b101101010000 1
b0 .
1#
#256250
0#
#262500
b10000000000000110111001 %
b111111000001011111 2
b1011010100011 3
b111101100110111100 /
b10000 4
b101101010000 1
b0 .
1#
#268750
0#
#275000
b100000000000 -
b111111000110111000 2
b1000000000011 3
b111110000110110101 /
b10000 4
b100000000000 1
b0 .
b10000000000000110111001 0
1#
#281250
0#
#287500
b100000000000 ,
b111111000110111000 2
b1000000000011 3
b111110000110110101 /
b10000 4
b100000000000 1
b0 .
1#
#293750
0#
#300000
b11111111111 "
b100000000000 !
b111111000110111000 2
b1000000000011 3
b111110000110110101 /
b10000 4
b100000000000 1
b0 .
1#
#306250
0#
#312500
b11111111111 )
b11111111111 (
b100000000000 '
b100000000000 &
b111111000110111000 2
b1000000000011 3
b111110000110110101 /
b10000 4
b100000000000 1
b0 .
1#
#318750
0#
#325000
b1111111111000000000001 +
b10000000000000000000000 *
b111111000110111000 2
b1000000000011 3
b111110000110110101 /
b10000 4
b100000000000 1
b0 .
1#
#331250
0#
#337500
b11111111111000000000001 %
b111111000110111000 2
b1000000000011 3
b111110000110110101 /
b10000 4
b100000000000 1
b0 .
1#
#343750
0#
#350000
b101101001111 -
b110110100000 2
b1011010011101 3
b10010000111101 /
b10000 4
b101101001111 1
b0 .
b11111111111000000000001 0
1#
#356250
0#
#362500
b101101001111 ,
b110110100000 2
b1011010011101 3
b10010000111101 /
b10000 4
b101101001111 1
b0 .
1#
#368750
0#
#375000
b111011100101 "
b111001110000 !
b110110100000 2
b1011010011101 3
b10010000111101 /
b10000 4
b101101001111 1
b0 .
1#
#381250
0#
#387500
b1111011100101 )
b1111011100101 (
b111001110000 '
b111001110000 &
b110110100000 2
b1011010011101 3
b10010000111101 /
b10000 4
b101101001111 1
b0 .
1#
#393750
0#
#400000
b10011100011011001 +
b100111000100000000 *
b110110100000 2
b1011010011101 3
b10010000111101 /
b10000 4
b101101001111 1
b0 .
1#
#406250
0#
#412500
b111010100111011001 %
b110110100000 2
b1011010011101 3
b10010000111101 /
b10000 4
b101101001111 1
b0 .
1#
#418750
0#
#425000
b111101001 -
b1111001000 2
b1111010011 3
b111111111111110101 /
b10000 4
b111101001 1
b0 .
b111010100111011001 0
1#
#431250
0#
#437500
b111101001 ,
b1111001000 2
b1111010011 3
b111111111111110101 /
b10000 4
b111101001 1
b0 .
1#
#443750
0#
#450000
b1101000011 "
b11001111101 !
b1111001000 2
b1111010011 3
b111111111111110101 /
b10000 4
b111101001 1
b0 .
1#
#456250
0#
#462500
b1101000011 )
b1101000011 (
b11001111101 '
b11001111101 &
b1111001000 2
b1111010011 3
b111111111111110101 /
b10000 4
b111101001 1
b0 .
1#
#468750
0#
#475000
b10101010001110001001 +
b1010100001100100001001 *
b1111001000 2
b1111010011 3
b111111111111110101 /
b10000 4
b111101001 1
b0 .
1#
#481250
0#
#487500
b1101001011110010010010 %
b1111001000 2
b1111010011 3
b111111111111110101 /
b10000 4
b111101001 1
b0 .
1#
#493750
0#
#500000
b11101000011 -
b100001001 2
b111010000101 3
b111110001110 /
b10000 4
b11101000011 1
b0 .
b1101001011110010010010 0
1#
#506250
0#
#512500
b11101000011 ,
b100001001 2
b111010000101 3
b111110001110 /
b10000 4
b11101000011 1
b0 .
1#
#518750
0#
#525000
b111001001110 "
b111000010000 !
b100001001 2
b111010000101 3
b111110001110 /
b10000 4
b11101000011 1
b0 .
1#
#531250
0#
#537500
b1111001001110 )
b1111001001110 (
b111000010000 '
b111000010000 &
b100001001 2
b111010000101 3
b111110001110 /
b10000 4
b11101000011 1
b0 .
1#
#543750
0#
#550000
b101101111111000100 +
b111100000100000000 *
b100001001 2
b111010000101 3
b111110001110 /
b10000 4
b11101000011 1
b0 .
1#
#556250
0#
#562500
b1101010000011000100 %
b100001001 2
b111010000101 3
b111110001110 /
b10000 4
b11101000011 1
b0 .
1#
#568750
0#
#575000
b1010010011 -
b1011011 2
b10100100101 3
b10110000000 /
b10000 4
b1010010011 1
b0 .
b1101010000011000100 0
1#
#581250
0#
#587500
b1010010011 ,
b1011011 2
b10100100101 3
b10110000000 /
b10000 4
b1010010011 1
b0 .
1#
#593750
0#
#600000
b101111111011 "
b10000111001 !
b1011011 2
b10100100101 3
b10110000000 /
b10000 4
b1010010011 1
b0 .
1#
#606250
0#
#612500
b1101111111011 )
b1101111111011 (
b10000111001 '
b10000111001 &
b1011011 2
b10100100101 3
b10110000000 /
b10000 4
b1010010011 1
b0 .
1#
#618750
0#
#625000
b100000010100000011001 +
b100011101010010110001 *
b1011011 2
b10100100101 3
b10110000000 /
b10000 4
b1010010011 1
b0 .
1#
#631250
0#
#637500
b1000011111110011001010 %
b1011011 2
b10100100101 3
b10110000000 /
b10000 4
b1010010011 1
b0 .
1#
#643750
0#
#650000
b10111010100 -
b111111100110010001 2
b101110101011 3
b111110110111100110 /
b10000 4
b10111010100 1
b0 .
b1000011111110011001010 0
1#
#656250
0#
#662500
b10111010100 ,
b111111100110010001 2
b101110101011 3
b111110110111100110 /
b10000 4
b10111010100 1
b0 .
1#
#668750
0#
#675000
b100001000100 "
b100110000110 !
b111111100110010001 2
b101110101011 3
b111110110111100110 /
b10000 4
b10111010100 1
b0 .
1#
#681250
0#
#687500
b1100001000100 )
b1100001000100 (
b100110000110 '
b100110000110 &
b111111100110010001 2
b101110101011 3
b111110110111100110 /
b10000 4
b10111010100 1
b0 .
1#
#693750
0#
#700000
b1110111101001000010000 +
b1010011111001000100100 *
b111111100110010001 2
b101110101011 3
b111110110111100110 /
b10000 4
b10111010100 1
b0 .
1#
#706250
0#
#712500
b11001011100010000110100 %
b111111100110010001 2
b101110101011 3
b111110110111100110 /
b10000 4
b10111010100 1
b0 .
1#
#718750
0#
#725000
b101000010110 -
b111111011000100011 2
b1010000101101 3
b101001010000 /
b10000 4
b101000010110 1
b0 .
b11001011100010000110100 0
1#
#731250
0#
#737500
b101000010110 ,
b111111011000100011 2
b1010000101101 3
b101001010000 /
b10000 4
b101000010110 1
b0 .
1#
#743750
0#
#750000
b11100010011 "
b101101000000 !
b111111011000100011 2
b1010000101101 3
b101001010000 /
b10000 4
b101000010110 1
b0 .
1#
#756250
0#
#762500
b11100010011 )
b11100010011 (
b101101000000 '
b101101000000 &
b111111011000100011 2
b1010000101101 3
b101001010000 /
b10000 4
b101000010110 1
b0 .
1#
#768750
0#
#775000
b1100100000101101101001 +
b101101001000000000000 *
b111111011000100011 2
b1010000101101 3
b101001010000 /
b10000 4
b101000010110 1
b0 .
1#
#781250
0#
#787500
b10010001001101101101001 %
b111111011000100011 2
b1010000101101 3
b101001010000 /
b10000 4
b101000010110 1
b0 .
1#
#793750
0#
#800000
b100010000101 -
b11001010000 2
b1000100001011 3
b111111010101000101 /
b10000 4
b100010000101 1
b0 .
b10010001001101101101001 0
1#
#806250
0#
#812500
b100010000101 ,
b11001010000 2
b1000100001011 3
b111111010101000101 /
b10000 4
b100010000101 1
b0 .
1#
#818750
0#
#825000
b1001000110 "
b100111000010 !
b11001010000 2
b1000100001011 3
b111111010101000101 /
b10000 4
b100010000101 1
b0 .
1#
#831250
0#
#837500
b1001000110 )
b1001000110 (
b100111000010 '
b100111000010 &
b11001010000 2
b1000100001011 3
b111111010101000101 /
b10000 4
b100010000101 1
b0 .
1#
#843750
0#
#850000
b1010010101100100100 +
b1001101111011100000100 *
b11001010000 2
b1000100001011 3
b111111010101000101 /
b10000 4
b100010000101 1
b0 .
1#
#856250
0#
#862500
b1011000010001000101000 %
b11001010000 2
b1000100001011 3
b111111010101000101 /
b10000 4
b100010000101 1
b0 .
1#
#868750
0#
#875000
b11010100100 -
b111111101111001111 2
b110101001011 3
b111110111010000100 /
b10000 4
b11010100100 1
b0 .
b1011000010001000101000 0
1#
#881250
0#
#887500
b11010100100 ,
b111111101111001111 2
b110101001011 3
b111110111010000100 /
b10000 4
b11010100100 1
b0 .
1#
#893750
0#
#900000
b100000110110 "
b110101000101 !
b111111101111001111 2
b110101001011 3
b111110111010000100 /
b10000 4
b11010100100 1
b0 .
1#
#906250
0#
#912500
b1100000110110 )
b1100000110110 (
b110101000101 '
b110101000101 &
b111111101111001111 2
b110101001011 3
b111110111010000100 /
b10000 4
b11010100100 1
b0 .
1#
#918750
0#
#925000
b1111001010101101100100 +
b1110111010010011001 *
b111111101111001111 2
b110101001011 3
b111110111010000100 /
b10000 4
b11010100100 1
b0 .
1#
#931250
0#
#937500
b10001000001111111111101 %
b111111101111001111 2
b110101001011 3
b111110111010000100 /
b10000 4
b11010100100 1
b0 .
1#
#943750
0#
#950000
b100001000000 -
b111111111101111100 2
b1000010000011 3
b111110111011111001 /
b10000 4
b100001000000 1
b0 .
b10001000001111111111101 0
1#
#956250
0#
#962500
b100001000000 ,
b111111111101111100 2
b1000010000011 3
b111110111011111001 /
b10000 4
b100001000000 1
b0 .
1#
#968750
0#
#975000
b101010011101 "
b10101010 !
b111111111101111100 2
b1000010000011 3
b111110111011111001 /
b10000 4
b100001000000 1
b0 .
1#
#981250
0#
#987500
b1101010011101 )
b1101010011101 (
b10101010 '
b10101010 &
b111111111101111100 2
b1000010000011 3
b111110111011111001 /
b10000 4
b100001000000 1
b0 .
1#
#993750
0#
#1000000
b111010000010001001001 +
b111000011100100 *
b111111111101111100 2
b1000010000011 3
b111110111011111001 /
b10000 4
b100001000000 1
b0 .
1#
#1006250
0#
#1012500
b111010111010100101101 %
b111111111101111100 2
b1000010000011 3
b111110111011111001 /
b10000 4
b100001000000 1
b0 .
1#
#1018750
0#
#1025000
b10101101101 -
b10011000100 2
b101011011011 3
b111111100111101001 /
b10000 4
b10101101101 1
b0 .
b111010111010100101101 0
1#
#1031250
0#
#1037500
b10101101101 ,
b10011000100 2
b101011011011 3
b111111100111101001 /
b10000 4
b10101101101 1
b0 .
1#
#1043750
0#
#1050000
b111000001100 "
b1110001100 !
b10011000100 2
b101011011011 3
b111111100111101001 /
b10000 4
b10101101101 1
b0 .
1#
#1056250
0#
#1062500
b1111000001100 )
b1111000001100 (
b1110001100 '
b1110001100 &
b10011000100 2
b101011011011 3
b111111100111101001 /
b10000 4
b10101101101 1
b0 .
1#
#1068750
0#
#1075000
b111101000010010000 +
b11001001010010010000 *
b10011000100 2
b101011011011 3
b111111100111101001 /
b10000 4
b10101101101 1
b0 .
1#
#1081250
0#
#1087500
b100000110010100100000 %
b10011000100 2
b101011011011 3
b111111100111101001 /
b10000 4
b10101101101 1
b0 .
1#
#1093750
0#
#1100000
b10000001100 -
b111111110001110111 2
b100000011011 3
b111111010001011100 /
b10000 4
b10000001100 1
b0 .
b100000110010100100000 0
1#
#1106250
0#
#1112500
b10000001100 ,
b111111110001110111 2
b100000011011 3
b111111010001011100 /
b10000 4
b10000001100 1
b0 .
1#
#1118750
0#
#1125000
b111111111000 "
b110010011111 !
b111111110001110111 2
b100000011011 3
b111111010001011100 /
b10000 4
b10000001100 1
b0 .
1#
#1131250
0#
#1137500
b1111111111000 )
b1111111111000 (
b110010011111 '
b110010011111 &
b111111110001110111 2
b100000011011 3
b111111010001011100 /
b10000 4
b10000001100 1
b0 .
1#
#1143750
0#
#1150000
b1000000 +
b10110110101011000001 *
b111111110001110111 2
b100000011011 3
b111111010001011100 /
b10000 4
b10000001100 1
b0 .
1#
#1156250
0#
#1162500
b10110110101100000001 %
b111111110001110111 2
b100000011011 3
b111111010001011100 /
b10000 4
b10000001100 1
b0 .
1#
#1168750
0#
#1175000
b1101100001 -
b1000000 2
b11011000011 3
b111111100101111101 /
b10000 4
b1101100001 1
b0 .
b10110110101100000001 0
1#
#1181250
0#
#1187500
b1101100001 ,
b1000000 2
b11011000011 3
b111111100101111101 /
b10000 4
b1101100001 1
b0 .
1#
#1193750
0#
#1200000
b11010000001 "
b111100010000 !
b1000000 2
b11011000011 3
b111111100101111101 /
b10000 4
b1101100001 1
b0 .
1#
#1206250
0#
#1212500
b11010000001 )
b11010000001 (
b111100010000 '
b111100010000 &
b1000000 2
b11011000011 3
b111111100101111101 /
b10000 4
b1101100001 1
b0 .
1#
#1218750
0#
#1225000
b1010100100110100000001 +
b1110000100000000 *
b1000000 2
b11011000011 3
b111111100101111101 /
b10000 4
b1101100001 1
b0 .
1#
#1231250
0#
#1237500
b1010110010111000000001 %
b1000000 2
b11011000011 3
b111111100101111101 /
b10000 4
b1101100001 1
b0 .
1#
#1243750
0#
#1250000
b11010010010 -
b111111010110011000 2
b110100100101 3
b1010111101 /
b10000 4
b11010010010 1
b0 .
b1010110010111000000001 0
1#
#1256250
0#
#1262500
b11010010010 ,
b111111010110011000 2
b110100100101 3
b1010111101 /
b10000 4
b11010010010 1
b0 .
1#
#1268750
0#
#1275000
b10011111111 "
b11011010100 !
b111111010110011000 2
b110100100101 3
b1010111101 /
b10000 4
b11010010010 1
b0 .
1#
#1281250
0#
#1287500
b10011111111 )
b10011111111 (
b11011010100 '
b11011010100 &
b111111010110011000 2
b110100100101 3
b1010111101 /
b10000 4
b11010010010 1
b0 .
1#
#1293750
0#
#1300000
b110001111011000000001 +
b1011101001111110010000 *
b111111010110011000 2
b110100100101 3
b1010111101 /
b10000 4
b11010010010 1
b0 .
1#
#1306250
0#
#1312500
b10001111001010110010001 %
b111111010110011000 2
b110100100101 3
b1010111101 /
b10000 4
b11010010010 1
b0 .
1#
#1318750
0#
#1325000
b100001110101 -
b1000000011000 2
b1000011101011 3
b111111111100101101 /
b10000 4
b100001110101 1
b0 .
b10001111001010110010001 0
1#
#1331250
0#
#1337500
b100001110101 ,
b1000000011000 2
b1000011101011 3
b111111111100101101 /
b10000 4
b100001110101 1
b0 .
1#
#1343750
0#
#1350000
b101101111100 "
b110111110101 !
b1000000011000 2
b1000011101011 3
b111111111100101101 /
b10000 4
b100001110101 1
b0 .
1#
#1356250
0#
#1362500
b1101101111100 )
b1101101111100 (
b110111110101 '
b110111110101 &
b1000000011000 2
b1000011101011 3
b111111111100101101 /
b10000 4
b100001110101 1
b0 .
1#
#1368750
0#
#1375000
b101000110010000010000 +
b1000010110001111001 *
b1000000011000 2
b1000011101011 3
b111111111100101101 /
b10000 4
b100001110101 1
b0 .
1#
#1381250
0#
#1387500
b110001001000010001001 %
b1000000011000 2
b1000011101011 3
b111111111100101101 /
b10000 4
b100001110101 1
b0 .
1#
#1393750
0#
#1400000
b10011110100 -
b111111111000010000 2
b100111101011 3
b111111010000100101 /
b10000 4
b10011110100 1
b0 .
b110001001000010001001 0
1#
#1406250
0#
#1412500
b10011110100 ,
b111111111000010000 2
b100111101011 3
b111111010000100101 /
b10000 4
b10011110100 1
b0 .
1#
#1418750
0#
#1425000
b100010110101 "
b101100000101 !
b111111111000010000 2
b100111101011 3
b111111010000100101 /
b10000 4
b10011110100 1
b0 .
1#
#1431250
0#
#1437500
b1100010110101 )
b1100010110101 (
b101100000101 '
b101100000101 &
b111111111000010000 2
b100111101011 3
b111111010000100101 /
b10000 4
b10011110100 1
b0 .
1#
#1443750
0#
#1450000
b1101010010111111111001 +
b110001100111000011001 *
b111111111000010000 2
b100111101011 3
b111111010000100101 /
b10000 4
b10011110100 1
b0 .
1#
#1456250
0#
#1462500
b10011011111111000010010 %
b111111111000010000 2
b100111101011 3
b111111010000100101 /
b10000 4
b10011110100 1
b0 .
1#
#1468750
0#
#1475000
b100011010100 -
b111111110011011001 2
b1000110101011 3
b111110101100101110 /
b10000 4
b100011010100 1
b0 .
b10011011111111000010010 0
1#
#1481250
0#
#1487500
b100011010100 ,
b111111110011011001 2
b1000110101011 3
b111110101100101110 /
b10000 4
b100011010100 1
b0 .
1#
#1493750
0#
#1500000
b100001101000 "
b110010010 !
b111111110011011001 2
b1000110101011 3
b111110101100101110 /
b10000 4
b100011010100 1
b0 .
1#
#1506250
0#
#1512500
b1100001101000 )
b1100001101000 (
b110010010 '
b110010010 &
b111111110011011001 2
b1000110101011 3
b111110101100101110 /
b10000 4
b100011010100 1
b0 .
1#
#1518750
0#
#1525000
b1110011010101001000000 +
b100111011101000100 *
b111111110011011001 2
b1000110101011 3
b111110101100101110 /
b10000 4
b100011010100 1
b0 .
1#
#1531250
0#
#1537500
b1111000010000110000100 %
b111111110011011001 2
b1000110101011 3
b111110101100101110 /
b10000 4
b100011010100 1
b0 .
1#
#1543750
0#
#1550000
b11111000001 -
b1000000011 2
b111110000011 3
b111111001010000000 /
b10000 4
b11111000001 1
b0 .
b1111000010000110000100 0
1#
#1556250
0#
#1562500
b11111000001 ,
b1000000011 2
b111110000011 3
b111111001010000000 /
b10000 4
b11111000001 1
b0 .
1#
#1568750
0#
#1575000
b11000001 "
b100011100000 !
b1000000011 2
b111110000011 3
b111111001010000000 /
b10000 4
b11111000001 1
b0 .
1#
#1581250
0#
#1587500
b11000001 )
b11000001 (
b100011100000 '
b100011100000 &
b1000000011 2
b111110000011 3
b111111001010000000 /
b10000 4
b11111000001 1
b0 .
1#
#1593750
0#
#1600000
b1001000110000001 +
b1100101100010000000000 *
b1000000011 2
b111110000011 3
b111111001010000000 /
b10000 4
b11111000001 1
b0 .
1#
#1606250
0#
#1612500
b1100110101010110000001 %
b1000000011 2
b111110000011 3
b111111001010000000 /
b10000 4
b11111000001 1
b0 .
1#
#1618750
0#
#1625000
b11100101010 -
b111111010001001000 2
b111001010101 3
b1010011101 /
b10000 4
b11100101010 1
b0 .
b1100110101010110000001 0
1#
#1631250
0#
#1637500
b11100101010 ,
b111111010001001000 2
b111001010101 3
b1010011101 /
b10000 4
b11100101010 1
b0 .
1#
#1643750
0#
#1650000
b11101110000 "
b110010010110 !
b111111010001001000 2
b111001010101 3
b1010011101 /
b10000 4
b11100101010 1
b0 .
1#
#1656250
0#
#1662500
b11101110000 )
b11101110000 (
b110010010110 '
b110010010110 &
b111111010001001000 2
b111001010101 3
b1010011101 /
b10000 4
b11100101010 1
b0 .
1#
#1668750
0#
#1675000
b1101110101000100000000 +
b10111010011111100100 *
b111111010001001000 2
b111001010101 3
b1010011101 /
b10000 4
b11100101010 1
b0 .
1#
#1681250
0#
#1687500
b10000101111100011100100 %
b111111010001001000 2
b111001010101 3
b1010011101 /
b10000 4
b11100101010 1
b0 .
1#
#1693750
0#
#1700000
b100000101111 -
b1000011 2
b1000001011101 3
b1000010100000 /
b10000 4
b100000101111 1
b0 .
b10000101111100011100100 0
1#
#1706250
0#
#1712500
b100000101111 ,
b1000011 2
b1000001011101 3
b1000010100000 /
b10000 4
b100000101111 1
b0 .
1#
#1718750
0#
#1725000
b100010001100 "
b111100000110 !
b1000011 2
b1000001011101 3
b1000010100000 /
b10000 4
b100000101111 1
b0 .
1#
#1731250
0#
#1737500
b1100010001100 )
b1100010001100 (
b111100000110 '
b111100000110 &
b1000011 2
b1000001011101 3
b1000010100000 /
b10000 4
b100000101111 1
b0 .
1#
#1743750
0#
#1750000
b1101111000110010010000 +
b1111010000100100 *
b1000011 2
b1000001011101 3
b1000010100000 /
b10000 4
b100000101111 1
b0 .
1#
#1756250
0#
#1762500
b1110001000000010110100 %
b1000011 2
b1000001011101 3
b1000010100000 /
b10000 4
b100000101111 1
b0 .
1#
#1768750
0#
#1775000
b11110000100 -
b111111010110011011 2
b111100001011 3
b111110011010010000 /
b10000 4
b11110000100 1
b0 .
b1110001000000010110100 0
1#
#1781250
0#
#1787500
b11110000100 ,
b111111010110011011 2
b111100001011 3
b111110011010010000 /
b10000 4
b11110000100 1
b0 .
1#
#1793750
0#
#1800000
b10100001010 "
b101011001000 !
b111111010110011011 2
b111100001011 3
b111110011010010000 /
b10000 4
b11110000100 1
b0 .
1#
#1806250
0#
#1812500
b10100001010 )
b10100001010 (
b101011001000 '
b101011001000 &
b111111010110011011 2
b111100001011 3
b111110011010010000 /
b10000 4
b11110000100 1
b0 .
1#
#1818750
0#
#1825000
b110010110010001100100 +
b110110011110001000000 *
b111111010110011011 2
b111100001011 3
b111110011010010000 /
b10000 4
b11110000100 1
b0 .
1#
#1831250
0#
#1837500
b1101001010000010100100 %
b111111010110011011 2
b111100001011 3
b111110011010010000 /
b10000 4
b11110000100 1
b0 .
1#
#1843750
0#
#1850000
b11101000001 -
b1000100011 2
b111010000011 3
b111111001110100000 /
b10000 4
b11101000001 1
b0 .
b1101001010000010100100 0
1#
#1856250
0#
#1862500
b11101000001 ,
b1000100011 2
b111010000011 3
b111111001110100000 /
b10000 4
b11101000001 1
b0 .
1#
#1868750
0#
#1875000
b101111001111 "
b111110011111 !
b1000100011 2
b111010000011 3
b111111001110100000 /
b10000 4
b11101000001 1
b0 .
1#
#1881250
0#
#1887500
b1101111001111 )
b1101111001111 (
b111110011111 '
b111110011111 &
b1000100011 2
b111010000011 3
b111111001110100000 /
b10000 4
b11101000001 1
b0 .
1#
#1893750
0#
#1900000
b100011001000101100001 +
b10010011000001 *
b1000100011 2
b111010000011 3
b111111001110100000 /
b10000 4
b11101000001 1
b0 .
1#
#1906250
0#
#1912500
b100011011011000100010 %
b1000100011 2
b111010000011 3
b111111001110100000 /
b10000 4
b11101000001 1
b0 .
1#
#1918750
0#
#1925000
b10000110101 -
b1100101001 2
b100001101011 3
b111111101010111110 /
b10000 4
b10000110101 1
b0 .
b100011011011000100010 0
1#
#1931250
0#
#1937500
b10000110101 ,
b1100101001 2
b100001101011 3
b111111101010111110 /
b10000 4
b10000110101 1
b0 .
1#
#1943750
0#
#1950000
b11110111 "
b111110100101 !
b1100101001 2
b100001101011 3
b111111101010111110 /
b10000 4
b10000110101 1
b0 .
1#
#1956250
0#
#1962500
b11110111 )
b11110111 (
b111110100101 '
b111110100101 &
b1100101001 2
b100001101011 3
b111111101010111110 /
b10000 4
b10000110101 1
b0 .
1#
#1968750
0#
#1975000
b1110111001010001 +
b10000001011001 *
b1100101001 2
b100001101011 3
b111111101010111110 /
b10000 4
b10000110101 1
b0 .
1#
#1981250
0#
#1987500
b10000111010101010 %
b1100101001 2
b100001101011 3
b111111101010111110 /
b10000 4
b10000110101 1
b0 .
1#
#1993750
0#
#2000000
b100000111 -
b1111001 2
b1000001101 3
b1010000110 /
b10000 4
b100000111 1
b0 .
b10000111010101010 0
1#
#2006250
0#
#2012500
b100000111 ,
b1111001 2
b1000001101 3
b1010000110 /
b10000 4
b100000111 1
b0 .
1#
#2018750
0#
#2025000
b100101001010 "
b110100111111 !
b1111001 2
b1000001101 3
b1010000110 /
b10000 4
b100000111 1
b0 .
1#
#2031250
0#
#2037500
b1100101001010 )
b1100101001010 (
b110100111111 '
b110100111111 &
b1111001 2
b1000001101 3
b1010000110 /
b10000 4
b100000111 1
b0 .
1#
#2043750
0#
#2050000
b1011010000100101100100 +
b1111001010110000001 *
b1111001 2
b1000001101 3
b1010000110 /
b10000 4
b100000111 1
b0 .
1#
#2056250
0#
#2062500
b1101001001111011100101 %
b1111001 2
b1000001101 3
b1010000110 /
b10000 4
b100000111 1
b0 .
1#
#2068750
0#
