5.NewModules/MyCIC/Testbench/cic/hdl/verilog/comb.v
module comb(
    input wire i_clk,
    input wire i_reset,
    input wire i_ce, 
    input wire signed [IW-1:0]i_data,

    output reg signed [OW-1:0] o_data,
    output reg o_ready
);

parameter IW=4, OW=12, N=7;

integer i;

reg signed[IW-1:0] delay[N-1:0];

always @(posedge i_clk or i_reset) begin
    if(i_reset) begin
        o_data <= {OW{1'b0}};
        o_ready <= 1'b0;
    end else if(i_ce) begin
        delay[0] <= i_data;
        for(i = 1; i<N; i++)begin
            delay[i] <= delay[i-1];
        end
        o_data <= {{(OW-IW){i_data[IW-1]}}, i_data} - {{(OW-IW){delay[N-1][IW-1]}}, delay[N-1]};
        o_ready <= 1'b1;
    end else begin
        o_ready <= 1'b0;
    end
end

endmodule

5.NewModules/MyCIC/Testbench/cic/hdl/systemverilog/decimator.sv
module decimator #(
    parameter int W = 10,  // Width of the data
    parameter int R = 5,  // Decimation ratio
    parameter int RW = 5 // Width of the counter
)(
    input logic i_clk,
    input logic i_reset,
    input logic i_ce,
    input logic signed [W-1:0] i_data,

    output logic signed [W-1:0] o_data,
    output logic o_ready
);

    logic [RW-1:0] decimator_counter = 0; // Initializing counter to 0

    always_ff @(posedge i_clk or posedge i_reset) begin
        if (i_reset) begin
            o_data <= {W{1'b0}};
            o_ready <= 1'b0;
            decimator_counter <= 0;
        end else if (i_ce) begin
            decimator_counter <= decimator_counter + 1'b1;
            
            if (decimator_counter >= R) begin
                decimator_counter <= 0;
                o_data <= i_data;
                o_ready <= 1'b1;
            end else begin
                o_ready <= 1'b0;
            end
        end
    end
endmodule

5.NewModules/MyCIC/Testbench/cic/hdl/systemverilog/integrator.sv
module integrator #(
    parameter int IW = 10,   // Input width
    parameter int OW = 10    // Output width
)(
    input logic              i_clk,
    input logic              i_reset,
    input logic              i_ce,
    input logic signed [IW-1:0] i_data,
    
    output logic signed [OW-1:0] o_data,
    output logic             o_ready
);

logic signed [OW-1:0] accumulator = '0;  // Initial value with zero

always_ff @(posedge i_clk or posedge i_reset) begin
    if (i_reset) begin
        accumulator <= '0; // Reset accumulator to zero
        o_data <= '0;      // Reset output data to zero
        o_ready <= 1'b0;     // Reset auxiliary output to zero
    end else if (i_ce) begin
        accumulator <= accumulator + {{(OW-IW){i_data[IW-1]}}, i_data};  // Sign extend and accumulate
        o_data <= accumulator;  // Update output data
        o_ready <= 1'b1;          
    end else begin
        o_ready <= 1'b0;  
    end
end

endmodule

5.NewModules/MyCIC/Testbench/cic/hdl/systemverilog/cic.sv
module cic#(
    parameter int IW = 10,
    parameter int OW = 10,
    parameter int R = 100,
    parameter int M = 10
)(
    input logic i_clk,
    input logic i_reset,
    input logic i_ce,
    input logic signed [IW-1:0] i_data,

    output logic signed [OW-1:0] o_data,
    output logic o_ready

);

    //-----------------------------
    //
    //  INTEGRATOR
    //
    //-----------------------------
    logic signed[OW-1:0] integrator_data[M+1];
    logic integrator_ready[M+1];
    assign integrator_data[0] = {{(OW-IW){i_data[IW-1]}}, i_data};
    assign integrator_ready[0] = i_ce;

    genvar i;
    generate
        for(i = 1; i < M; i++) begin : gen_integrator
            integrator#(
                .IW(IW),
                .OW(OW) )
            integrator_inst(
                .i_clk(i_clk),
                .i_reset(i_reset),
                .i_ce(integrator_ready[i-1]),
                .i_data(integrator_data[i-1]),

                .o_data(integrator_data[i]),
                .o_ready(integrator_ready[i])
            );
        end
    endgenerate

    //-----------------------------
    //
    //  DECIMATOR
    //
    //-----------------------------
    logic decimator_ready;
    logic [OW-1:0] decimator_data;

    decimator#(
        .W(OW),
        .R(R))
    decimator_inst(
        .i_clk(i_clk),
        .i_reset(i_reset),
        .i_ce(i_ce),
        .i_data(integrator_data[M]),

        .o_data(decimator_data),
        .o_ready(decimator_ready)
    );

    //-----------------------------
    //
    //  COMB
    //
    //-----------------------------
     logic signed[OW-1:0] comb_data[M+1];
     logic comb_ready[M+1];
     assign comb_data[0] = decimator_data;
     assign comb_ready[0] = decimator_ready;

     genvar j;
     generate
         for(j = 1; j < M; j++) begin : gen_combo
              comb#(
                  .IW(OW),
                  .OW(OW),
                  .N(1)
              )comb_inst(
                  .i_clk(i_clk),
                  .i_reset(i_reset),
                  .i_ce(comb_ready[j-1]),
                  .i_data(comb_data[j-1]),

                  .o_data(comb_data[j]),
                  .o_ready(comb_ready[j])
              );
         end
     endgenerate

    assign o_data = comb_data[M];
    assign o_ready = comb_ready[M];

    //-----------------------------
    // For simulation only
    //-----------------------------
    initial begin
        $dumpfile("cic_waves.vcd");
        $dumpvars(0, cic);
    end

endmodule

5.NewModules/MyCIC/Testbench/cic/cic_waves.vcd
$date
	Sat Jul  6 16:01:17 2024
$end
$version
	Icarus Verilog
$end
$timescale
	1ps
$end
$scope module cic $end
$var wire 1 ! i_ce $end
$var wire 1 " i_clk $end
$var wire 10 # i_data [9:0] $end
$var wire 1 $ i_reset $end
$var wire 10 % o_data [9:0] $end
$var wire 1 & o_ready $end
$var wire 1 ' decimator_ready $end
$var wire 10 ( decimator_data [9:0] $end
$var parameter 32 ) IW $end
$var parameter 32 * M $end
$var parameter 32 + OW $end
$var parameter 32 , R $end
$scope begin gen_combo[1] $end
$var parameter 2 - j $end
$scope module comb_inst $end
$var wire 1 . i_ce $end
$var wire 1 " i_clk $end
$var wire 10 / i_data [9:0] $end
$var wire 1 $ i_reset $end
$var parameter 32 0 IW $end
$var parameter 32 1 N $end
$var parameter 32 2 OW $end
$var reg 10 3 o_data [9:0] $end
$var reg 1 4 o_ready $end
$var integer 32 5 i [31:0] $end
$upscope $end
$upscope $end
$scope begin gen_combo[2] $end
$var parameter 3 6 j $end
$scope module comb_inst $end
$var wire 1 4 i_ce $end
$var wire 1 " i_clk $end
$var wire 10 7 i_data [9:0] $end
$var wire 1 $ i_reset $end
$var parameter 32 8 IW $end
$var parameter 32 9 N $end
$var parameter 32 : OW $end
$var reg 10 ; o_data [9:0] $end
$var reg 1 < o_ready $end
$var integer 32 = i [31:0] $end
$upscope $end
$upscope $end
$scope begin gen_integrator[1] $end
$var parameter 2 > i $end
$scope module integrator_inst $end
$var wire 1 ? i_ce $end
$var wire 1 " i_clk $end
$var wire 10 @ i_data [9:0] $end
$var wire 1 $ i_reset $end
$var parameter 32 A IW $end
$var parameter 32 B OW $end
$var reg 10 C accumulator [9:0] $end
$var reg 10 D o_data [9:0] $end
$var reg 1 E o_ready $end
$upscope $end
$upscope $end
$scope begin gen_integrator[2] $end
$var parameter 3 F i $end
$scope module integrator_inst $end
$var wire 1 E i_ce $end
$var wire 1 " i_clk $end
$var wire 10 G i_data [9:0] $end
$var wire 1 $ i_reset $end
$var parameter 32 H IW $end
$var parameter 32 I OW $end
$var reg 10 J accumulator [9:0] $end
$var reg 10 K o_data [9:0] $end
$var reg 1 L o_ready $end
$upscope $end
$upscope $end
$scope module decimator_inst $end
$var wire 1 ! i_ce $end
$var wire 1 " i_clk $end
$var wire 10 M i_data [9:0] $end
$var wire 1 $ i_reset $end
$var parameter 32 N R $end
$var parameter 32 O RW $end
$var parameter 32 P W $end
$var reg 5 Q decimator_counter [4:0] $end
$var reg 10 R o_data [9:0] $end
$var reg 1 ' o_ready $end
$upscope $end
$upscope $end
$enddefinitions $end
$comment Show the parameter values. $end
$dumpall
b1010 P
b101 O
b1010 N
b1010 I
b1010 H
b10 F
b1010 B
b1010 A
b1 >
b1010 :
b1 9
b1010 8
b10 6
b1010 2
b1 1
b1010 0
b1 -
b1010 ,
b1010 +
b11 *
b1010 )
$end
#0
$dumpvars
b0 R
b0 Q
bz M
0L
b0 K
b0 J
b0 G
0E
b0 D
b0 C
b0 @
0?
b1 =
0<
b0 ;
b0 7
b1 5
04
b0 3
b0 /
0.
b0 (
0'
z&
bz %
1$
b0 #
1"
0!
$end
#6250
0"
#12500
1?
1!
0$
b1 =
b1 5
1"
#18750
0"
#25000
1E
b1 Q
1"
#31250
0"
#37500
b111111111 @
b111111111 #
b10 Q
1L
1"
#43750
0"
#50000
b1000000000 @
b1000000000 #
b111111111 C
b11 Q
1"
#56250
0"
#62500
b111111111 @
b111111111 #
b100 Q
b111111111 D
b111111111 G
b1111111111 C
1"
#68750
0"
#75000
b1000000000 @
b1000000000 #
b1111111111 D
b1111111111 G
b111111110 C
b111111111 J
b101 Q
1"
#81250
0"
#87500
b1110011100 @
b1110011100 #
b110 Q
b111111111 K
b111111110 J
b111111110 D
b111111110 G
b1111111110 C
1"
#93750
0"
#100000
b1011100000 @
b1011100000 #
b1111111110 D
b1111111110 G
b1110011010 C
b111111110 K
b1111111100 J
b111 Q
1"
#106250
0"
#112500
b110111001 @
b110111001 #
b1000 Q
b1111111100 K
b1111111010 J
b1110011010 D
b1110011010 G
b1001111010 C
1"
#118750
0"
#125000
b1100011110 @
b1100011110 #
b1001111010 D
b1001111010 G
b110011 C
b1111111010 K
b1110010100 J
b1001 Q
1"
#131250
0"
#137500
b1000011000 @
b1000011000 #
b1010 Q
b1110010100 K
b1000001110 J
b110011 D
b110011 G
b1101010001 C
1"
#143750
0"
#150000
b1000111110 @
b1000111110 #
b1101010001 D
b1101010001 G
b101101001 C
b1000001110 K
b1001000001 J
1.
1'
bz /
bz (
bz R
b0 Q
1"
#156250
0"
#162500
b100111 @
b100111 #
0.
0'
b1 Q
14
bx 3
bx 7
b1001000001 K
b110010010 J
b101101001 D
b101101001 G
b1110100111 C
1"
#168750
0"
#175000
b1101001 @
b1101001 #
b1110100111 D
b1110100111 G
b1111001110 C
b110010010 K
b1011111011 J
04
1<
bx ;
b10 Q
1"
#181250
0"
#187500
b10110111 @
b10110111 #
b11 Q
0<
b1011111011 K
b1010100010 J
b1111001110 D
b1111001110 G
b110111 C
1"
#193750
0"
#200000
b1010000101 @
b1010000101 #
b110111 D
b110111 G
b11101110 C
b1010100010 K
b1001110000 J
b100 Q
1"
#206250
0"
#212500
b101000111 @
b101000111 #
b101 Q
b1001110000 K
b1010100111 J
b11101110 D
b11101110 G
b1101110011 C
1"
#218750
0"
#225000
b10111001 @
b10111001 #
b1101110011 D
b1101110011 G
b10111010 C
b1010100111 K
b1110010101 J
b110 Q
1"
#231250
0"
#237500
b1101001101 @
b1101001101 #
b111 Q
b1110010101 K
b1100001000 J
b10111010 D
b10111010 G
b101110011 C
1"
#243750
0"
#250000
b1001101101 @
b1001101101 #
b101110011 D
b101110011 G
b11000000 C
b1100001000 K
b1111000010 J
b1000 Q
1"
#256250
0"
#262500
b100011110 @
b100011110 #
b1001 Q
b1111000010 K
b100110101 J
b11000000 D
b11000000 G
b1100101101 C
1"
#268750
0"
#275000
b1110001000 @
b1110001000 #
b1100101101 D
b1100101101 G
b1001011 C
b100110101 K
b111110101 J
b1010 Q
1"
#281250
0"
#287500
b111101101 @
b111101101 #
1.
1'
b0 Q
b111110101 K
b100100010 J
b1001011 D
b1001011 G
b1111010011 C
1"
#293750
0"
#300000
b1110100110 @
b1110100110 #
b1111010011 D
b1111010011 G
b111000000 C
b100100010 K
b101101101 J
14
0.
0'
b1 Q
1"
#306250
0"
#312500
b1000101111 @
b1000101111 #
b10 Q
1<
04
b101101101 K
b101000000 J
b111000000 D
b111000000 G
b101100110 C
1"
#318750
0"
#325000
b1011110101 @
b1011110101 #
b101100110 D
b101100110 G
b1110010101 C
b101000000 K
b1100000000 J
0<
b11 Q
1"
#331250
0"
#337500
b10101101 @
b10101101 #
b100 Q
b1100000000 K
b1100110 J
b1110010101 D
b1110010101 G
b1010001010 C
1"
#343750
0"
#350000
b1011101010 @
b1011101010 #
b1010001010 D
b1010001010 G
b1100110111 C
b1100110 K
b1111111011 J
b101 Q
1"
#356250
0"
#362500
b1111101001 @
b1111101001 #
b110 Q
b1111111011 K
b1010000101 J
b1100110111 D
b1100110111 G
b1000100001 C
1"
#368750
0"
#375000
b1000110010 @
b1000110010 #
b1000100001 D
b1000100001 G
b1000001010 C
b1010000101 K
b110111100 J
b111 Q
1"
#381250
0"
#387500
b1010011001 @
b1010011001 #
b1000 Q
b110111100 K
b1111011101 J
b1000001010 D
b1000001010 G
b111100 C
1"
#393750
0"
#400000
b1110110010 @
b1110110010 #
b111100 D
b111100 G
b1011010101 C
b1111011101 K
b111100111 J
b1001 Q
1"
#406250
0"
#412500
b1101001001 @
b1101001001 #
b1010 Q
b111100111 K
b1000100011 J
b1011010101 D
b1011010101 G
b1010000111 C
1"
#418750
0"
#425000
b1110100011 @
b1110100011 #
b1010000111 D
b1010000111 G
b111010000 C
b1000100011 K
b11111000 J
1.
1'
b0 Q
1"
#431250
0"
#437500
b1000111111 @
b1000111111 #
0.
0'
b1 Q
14
b11111000 K
b1101111111 J
b111010000 D
b111010000 G
b101110011 C
1"
#443750
0"
#450000
b1001110100 @
b1001110100 #
b101110011 D
b101110011 G
b1110110010 C
b1101111111 K
b101001111 J
04
1<
b10 Q
1"
#456250
0"
#462500
b1001010100 @
b1001010100 #
b11 Q
0<
b101001111 K
b1011000010 J
b1110110010 D
b1110110010 G
b1000100110 C
1"
#468750
0"
#475000
b111110100 @
b111110100 #
b1000100110 D
b1000100110 G
b1111010 C
b1011000010 K
b1001110100 J
b100 Q
1"
#481250
0"
#487500
b1111000001 @
b1111000001 #
b101 Q
b1001110100 K
b10011010 J
b1111010 D
b1111010 G
b1001101110 C
1"
#493750
0"
#500000
b1001111110 @
b1001111110 #
b1001101110 D
b1001101110 G
b1000101111 C
b10011010 K
b100010100 J
b110 Q
1"
#506250
0"
#512500
b1101110101 @
b1101110101 #
b111 Q
b100010100 K
b1110000010 J
b1000101111 D
b1000101111 G
b10101101 C
1"
#518750
0"
#525000
b1011101000 @
b1011101000 #
b10101101 D
b10101101 G
b100010 C
b1110000010 K
b110110001 J
b1000 Q
1"
#531250
0"
#537500
b110101001 @
b110101001 #
b1001 Q
b110110001 K
b1001011110 J
b100010 D
b100010 G
b1100001010 C
1"
#543750
0"
#550000
b1001110011 @
b1001110011 #
b1100001010 D
b1100001010 G
b10110011 C
b1001011110 K
b1010000000 J
b1010 Q
1"
#556250
0"
#562500
b1111000101 @
b1111000101 #
1.
1'
b0 Q
b1010000000 K
b110001010 J
b10110011 D
b10110011 G
b1100100110 C
1"
#568750
0"
#575000
b1010111010 @
b1010111010 #
b1100100110 D
b1100100110 G
b1011101011 C
b110001010 K
b1000111101 J
14
0.
0'
b1 Q
1"
#581250
0"
#587500
b100001111 @
b100001111 #
b10 Q
1<
04
b1000111101 K
b101100011 J
b1011101011 D
b1011101011 G
b110100101 C
1"
#593750
0"
#600000
b1100001000 @
b1100001000 #
b110100101 D
b110100101 G
b1010110100 C
b101100011 K
b1001110 J
0<
b11 Q
1"
#606250
0"
#612500
b1011010001 @
b1011010001 #
b100 Q
b1001110 K
b111110011 J
b1010110100 D
b1010110100 G
b110111100 C
1"
#618750
0"
#625000
b10100 @
b10100 #
b110111100 D
b110111100 G
b10001101 C
b111110011 K
b10100111 J
b101 Q
1"
#631250
0"
#637500
b111000100 @
b111000100 #
b110 Q
b10100111 K
b1001100011 J
b10001101 D
b10001101 G
b10100001 C
1"
#643750
0"
#650000
b100100110 @
b100100110 #
b10100001 D
b10100001 G
b1001100101 C
b1001100011 K
b1011110000 J
b111 Q
1"
#656250
0"
#662500
b1010101000 @
b1010101000 #
b1000 Q
b1011110000 K
b1110010001 J
b1001100101 D
b1001100101 G
b1110001011 C
1"
#668750
0"
#675000
b1110100101 @
b1110100101 #
b1110001011 D
b1110001011 G
b1000110011 C
b1110010001 K
b111110110 J
b1001 Q
1"
#681250
0"
#687500
b100101011 @
b100101011 #
b1010 Q
b111110110 K
b110000001 J
b1000110011 D
b1000110011 G
b111011000 C
1"
#693750
0"
#700000
b111110 @
b111110 #
b111011000 D
b111011000 G
b1100000011 C
b110000001 K
b1110110100 J
1.
1'
b0 Q
1"
#706250
0"
#712500
b1001011010 @
b1001011010 #
0.
0'
b1 Q
14
b1110110100 K
b110001100 J
b1100000011 D
b1100000011 G
b1101000001 C
1"
#718750
0"
#725000
b1111010100 @
b1111010100 #
b1101000001 D
b1101000001 G
b110011011 C
b110001100 K
b10001111 J
04
1<
b10 Q
1"
#731250
0"
#737500
b1100111111 @
b1100111111 #
b11 Q
0<
b10001111 K
b1111010000 J
b110011011 D
b110011011 G
b101101111 C
1"
#743750
0"
#750000
b100101101 @
b100101101 #
b101101111 D
b101101111 G
b10101110 C
b1111010000 K
b101101011 J
b100 Q
1"
#756250
0"
#762500
b1011001011 @
b1011001011 #
b101 Q
b101101011 K
b1011011010 J
b10101110 D
b10101110 G
b111011011 C
1"
#768750
0"
#775000
b1001010110 @
b1001010110 #
b111011011 D
b111011011 G
b10100110 C
b1011011010 K
b1110001000 J
b110 Q
1"
#781250
0"
#787500
b101110010 @
b101110010 #
b111 Q
b1110001000 K
b101100011 J
b10100110 D
b10100110 G
b1011111100 C
1"
#793750
0"
#800000
b101110110 @
b101110110 #
b1011111100 D
b1011111100 G
b1101110 C
b101100011 K
b1000001001 J
b1000 Q
1"
#806250
0"
#812500
b1100100111 @
b1100100111 #
b1001 Q
b1000001001 K
b100000101 J
b1101110 D
b1101110 G
b111100100 C
1"
#818750
0"
#825000
b1100011101 @
b1100011101 #
b111100100 D
b111100100 G
b100001011 C
b100000101 K
b101110011 J
b1010 Q
1"
#831250
0"
#837500
b1100001110 @
b1100001110 #
1.
1'
b0 Q
b101110011 K
b1101010111 J
b100001011 D
b100001011 G
b101000 C
1"
#843750
0"
#850000
b1010101110 @
b1010101110 #
b101000 D
b101000 G
b1100110110 C
b1101010111 K
b1100010 J
14
0.
0'
b1 Q
1"
#856250
0"
#862500
b1110111111 @
b1110111111 #
b10 Q
1<
04
b1100010 K
b10001010 J
b1100110110 D
b1100110110 G
b111100100 C
1"
#868750
0"
#875000
b1011000101 @
b1011000101 #
b111100100 D
b111100100 G
b110100011 C
b10001010 K
b1111000000 J
0<
b11 Q
1"
#881250
0"
#887500
b1111100100 @
b1111100100 #
b100 Q
b1111000000 K
b110100100 J
b110100011 D
b110100011 G
b1101000 C
1"
#893750
0"
#900000
b101000101 @
b101000101 #
b1101000 D
b1101000 G
b1001100 C
b110100100 K
b1101000111 J
b101 Q
1"
#906250
0"
#912500
b11000000 @
b11000000 #
b110 Q
b1101000111 K
b1110101111 J
b1001100 D
b1001100 G
b110010001 C
1"
#918750
0"
#925000
b1101000100 @
b1101000100 #
b110010001 D
b110010001 G
b1001010001 C
b1110101111 K
b1111111011 J
b111 Q
1"
#931250
0"
#937500
b100111 @
b100111 #
b1000 Q
b1111111011 K
b110001100 J
b1001010001 D
b1001010001 G
b110010101 C
1"
#943750
0"
#950000
b1010000000 @
b1010000000 #
b110010101 D
b110010101 G
b110111100 C
b110001100 K
b1111011101 J
b1001 Q
1"
#956250
0"
#962500
b101100110 @
b101100110 #
b1010 Q
b1111011101 K
b101110010 J
b110111100 D
b110111100 G
b111100 C
1"
#968750
0"
#975000
b1101111010 @
b1101111010 #
b111100 D
b111100 G
b110100010 C
b101110010 K
b1100101110 J
1.
1'
b0 Q
1"
#981250
0"
#987500
b1011010101 @
b1011010101 #
0.
0'
b1 Q
14
b1100101110 K
b1101101010 J
b110100010 D
b110100010 G
b100011100 C
1"
#993750
0"
#1000000
b100111111 @
b100111111 #
b100011100 D
b100011100 G
b1111110001 C
b1101101010 K
b100001100 J
04
1<
b10 Q
1"
#1006250
0"
#1012500
b1001000111 @
b1001000111 #
b11 Q
0<
b100001100 K
b1000101000 J
b1111110001 D
b1111110001 G
b100110000 C
1"
#1018750
0"
#1025000
b1000101100 @
b1000101100 #
b100110000 D
b100110000 G
b1101110111 C
b1000101000 K
b1000011001 J
b100 Q
1"
#1031250
0"
#1037500
b1101000 @
b1101000 #
b101 Q
b1000011001 K
b1101001001 J
b1101110111 D
b1101110111 G
b110100011 C
1"
#1043750
0"
#1050000
b11000101 @
b11000101 #
b110100011 D
b110100011 G
b1000001011 C
b1101001001 K
b1011000000 J
b110 Q
1"
#1056250
0"
#1062500
b1011000011 @
b1011000011 #
b111 Q
b1011000000 K
b1100011 J
b1000001011 D
b1000001011 G
b1011010000 C
1"
#1068750
0"
#1075000
b111000001 @
b111000001 #
b1011010000 D
b1011010000 G
b110010011 C
b1100011 K
b1001101110 J
b1000 Q
1"
#1081250
0"
#1087500
b10010010 @
b10010010 #
b1001 Q
b1001101110 K
b100111110 J
b110010011 D
b110010011 G
b1101010100 C
1"
#1093750
0"
#1100000
b11011010 @
b11011010 #
b1101010100 D
b1101010100 G
b1111100110 C
b100111110 K
b1011010001 J
b1010 Q
1"
#1106250
0"
#1112500
b1010100110 @
b1010100110 #
1.
1'
b0 Q
b1011010001 K
b1000100101 J
b1111100110 D
b1111100110 G
b11000000 C
1"
#1118750
0"
#1125000
b100010111 @
b100010111 #
b11000000 D
b11000000 G
b1101100110 C
b1000100101 K
b1000001011 J
14
0.
0'
b1 Q
1"
#1131250
0"
#1137500
b1111100010 @
b1111100010 #
b10 Q
1<
04
b1000001011 K
b1011001011 J
b1101100110 D
b1101100110 G
b1111101 C
1"
#1143750
0"
#1150000
b1010110000 @
b1010110000 #
b1111101 D
b1111101 G
b1011111 C
b1011001011 K
b1000110001 J
0<
b11 Q
1"
#1156250
0"
#1162500
b100111011 @
b100111011 #
b100 Q
b1000110001 K
b1010101110 J
b1011111 D
b1011111 G
b1100001111 C
1"
#1168750
0"
#1175000
b101110001 @
b101110001 #
b1100001111 D
b1100001111 G
b1001010 C
b1010101110 K
b1100001101 J
b101 Q
1"
#1181250
0"
#1187500
b1001011101 @
b1001011101 #
b110 Q
b1100001101 K
b1000011100 J
b1001010 D
b1001010 G
b110111011 C
1"
#1193750
0"
#1200000
b1100101111 @
b1100101111 #
b110111011 D
b110111011 G
b11000 C
b1000011100 K
b1001100110 J
b111 Q
1"
#1206250
0"
#1212500
b100000101 @
b100000101 #
b1000 Q
b1001100110 K
b100001 J
b11000 D
b11000 G
b1101000111 C
1"
#1218750
0"
#1225000
b1011101000 @
b1011101000 #
b1101000111 D
b1101000111 G
b1001100 C
b100001 K
b111001 J
b1001 Q
1"
#1231250
0"
#1237500
b1001111101 @
b1001111101 #
b1010 Q
b111001 K
b1110000000 J
b1001100 D
b1001100 G
b1100110100 C
1"
#1243750
0"
#1250000
b101000110 @
b101000110 #
b1100110100 D
b1100110100 G
b110110001 C
b1110000000 K
b1111001100 J
1.
1'
b0 Q
1"
#1256250
0"
#1262500
b10111 @
b10111 #
0.
0'
b1 Q
14
b1111001100 K
b1100000000 J
b110110001 D
b110110001 G
b1011110111 C
1"
#1268750
0"
#1275000
b101111000 @
b101111000 #
b1011110111 D
b1011110111 G
b1100001110 C
b1100000000 K
b10110001 J
04
1<
b10 Q
1"
#1281250
0"
#1287500
b1111010011 @
b1111010011 #
b11 Q
0<
b10110001 K
b1110101000 J
b1100001110 D
b1100001110 G
b10000110 C
1"
#1293750
0"
#1300000
b1001110000 @
b1001110000 #
b10000110 D
b10000110 G
b1011001 C
b1110101000 K
b1010110110 J
b100 Q
1"
#1306250
0"
#1312500
b1011000001 @
b1011000001 #
b101 Q
b1010110110 K
b1100111100 J
b1011001 D
b1011001 G
b1011001001 C
1"
#1318750
0"
#1325000
b110101000 @
b110101000 #
b1011001001 D
b1011001001 G
b110001010 C
b1100111100 K
b1110010101 J
b110 Q
1"
#1331250
0"
#1337500
b111 Q
b1110010101 K
b1001011110 J
b110001010 D
b110001010 G
b1100110010 C
1"
