5.NewModules/MyCIC/Testbench/cic/hdl/verilog/comb.v
module comb(
    input wire i_clk,
    input wire i_reset,
    input wire i_ce, 
    input wire signed [IW-1:0]i_data,

    output reg signed [OW-1:0] o_data,
    output reg o_ready
);

parameter IW=4, OW=12, N=7;

integer i;

reg signed[IW-1:0] delay[N-1:0];

always @(posedge i_clk or i_reset) begin
    if(i_reset) begin
        o_data <= {OW{1'b0}};
        o_ready <= 1'b0;
    end else if(i_ce) begin
        delay[0] <= i_data;
        for(i = 1; i<N; i++)begin
            delay[i] <= delay[i-1];
        end
        o_data <= {{(OW-IW){i_data[IW-1]}}, i_data} - {{(OW-IW){delay[N-1][IW-1]}}, delay[N-1]};
        o_ready <= 1'b1;
    end else begin
        o_ready <= 1'b0;
    end
end

endmodule

5.NewModules/MyCIC/Testbench/cic/hdl/systemverilog/decimator.sv
module decimator #(
    parameter int W = 10,  // Width of the data
    parameter int R = 5,  // Decimation ratio
    parameter int RW = 5 // Width of the counter
)(
    input logic i_clk,
    input logic i_reset,
    input logic i_ce,
    input logic signed [W-1:0] i_data,

    output logic signed [W-1:0] o_data,
    output logic o_ready
);

    logic [RW-1:0] decimator_counter = 0; // Initializing counter to 0

    always_ff @(posedge i_clk or posedge i_reset) begin
        if (i_reset) begin
            o_data <= {W{1'b0}};
            o_ready <= 1'b0;
            decimator_counter <= 0;
        end else if (i_ce) begin
            decimator_counter <= decimator_counter + 1'b1;
            
            if (decimator_counter >= R) begin
                decimator_counter <= 0;
                o_data <= i_data;
                o_ready <= 1'b1;
            end else begin
                o_ready <= 1'b0;
            end
        end
    end
endmodule

5.NewModules/MyCIC/Testbench/cic/hdl/systemverilog/integrator.sv
module integrator #(
    parameter int IW = 10,   // Input width
    parameter int OW = 10    // Output width
)(
    input logic              i_clk,
    input logic              i_reset,
    input logic              i_ce,
    input logic signed [IW-1:0] i_data,
    
    output logic signed [OW-1:0] o_data,
    output logic             o_ready
);

logic signed [OW-1:0] accumulator = '0;  // Initial value with zero

always_ff @(posedge i_clk or posedge i_reset) begin
    if (i_reset) begin
        accumulator <= '0; // Reset accumulator to zero
        o_data <= '0;      // Reset output data to zero
        o_ready <= 1'b0;     // Reset auxiliary output to zero
    end else if (i_ce) begin
        accumulator <= accumulator + {{(OW-IW){i_data[IW-1]}}, i_data};  // Sign extend and accumulate
        o_data <= accumulator;  // Update output data
        o_ready <= 1'b1;          
    end else begin
        o_ready <= 1'b0;  
    end
end

endmodule

5.NewModules/MyCIC/Testbench/cic/hdl/systemverilog/cic.sv
module cic#(
    parameter int IW = 10,
    parameter int OW = 10,
    parameter int R = 10,
    parameter int M = 3
)(
    input logic i_clk,
    input logic i_reset,
    input logic i_ce,
    input logic signed [IW-1:0] i_data,

    output logic signed [OW-1:0] o_data,
    output logic o_ready

);

    //-----------------------------
    //
    //  INTEGRATOR
    //
    //-----------------------------
    logic signed[OW-1:0] integrator_data[M+1];
    logic integrator_ready[M+1];
    assign integrator_data[0] = {{(OW-IW){i_data[IW-1]}}, i_data};
    assign integrator_ready[0] = i_ce;

    genvar i;
    generate
        for(i = 1; i < M; i++) begin : gen_integrator
            integrator#(
                .IW(IW),
                .OW(OW) )
            integrator_inst(
                .i_clk(i_clk),
                .i_reset(i_reset),
                .i_ce(integrator_ready[i-1]),
                .i_data(integrator_data[i-1]),

                .o_data(integrator_data[i]),
                .o_ready(integrator_ready[i])
            );
        end
    endgenerate

    //-----------------------------
    //
    //  DECIMATOR
    //
    //-----------------------------
    logic decimator_ready;
    logic [OW-1:0] decimator_data;

    decimator#(
        .W(OW),
        .R(R))
    decimator_inst(
        .i_clk(i_clk),
        .i_reset(i_reset),
        .i_ce(i_ce),
        .i_data(integrator_data[M]),

        .o_data(decimator_data),
        .o_ready(decimator_ready)
    );

    //-----------------------------
    //
    //  COMB
    //
    //-----------------------------
     logic signed[OW-1:0] comb_data[M+1];
     logic comb_ready[M+1];
     assign comb_data[0] = decimator_data;
     assign comb_ready[0] = decimator_ready;

     genvar j;
     generate
         for(j = 1; j < M; j++) begin : gen_combo
              comb#(
                  .IW(OW),
                  .OW(OW),
                  .N(1*R/R)
              )comb_inst(
                  .i_clk(i_clk),
                  .i_reset(i_reset),
                  .i_ce(comb_ready[j-1]),
                  .i_data(comb_data[j-1]),

                  .o_data(comb_data[j]),
                  .o_ready(comb_ready[j])
              );
         end
     endgenerate

    assign o_data = comb_data[M];
    assign o_ready = comb_ready[M];

    //-----------------------------
    // For simulation only
    //-----------------------------
    initial begin
        $dumpfile("cic_waves.vcd");
        $dumpvars(0, cic);
    end

endmodule

5.NewModules/MyCIC/Testbench/cic/cic_waves.vcd
$date
	Wed Jul  3 22:14:48 2024
$end
$version
	Icarus Verilog
$end
$timescale
	1ps
$end
$scope module cic $end
$var wire 1 ! i_ce $end
$var wire 1 " i_clk $end
$var wire 10 # i_data [9:0] $end
$var wire 1 $ i_reset $end
$var wire 10 % o_data [9:0] $end
$var wire 1 & o_ready $end
$var wire 1 ' decimator_ready $end
$var wire 10 ( decimator_data [9:0] $end
$var parameter 32 ) IW $end
$var parameter 32 * M $end
$var parameter 32 + OW $end
$var parameter 32 , R $end
$scope begin gen_combo[1] $end
$var parameter 2 - j $end
$scope module comb_inst $end
$var wire 1 . i_ce $end
$var wire 1 " i_clk $end
$var wire 10 / i_data [9:0] $end
$var wire 1 $ i_reset $end
$var parameter 32 0 IW $end
$var parameter 32 1 N $end
$var parameter 32 2 OW $end
$var reg 10 3 o_data [9:0] $end
$var reg 1 4 o_ready $end
$var integer 32 5 i [31:0] $end
$upscope $end
$upscope $end
$scope begin gen_combo[2] $end
$var parameter 3 6 j $end
$scope module comb_inst $end
$var wire 1 4 i_ce $end
$var wire 1 " i_clk $end
$var wire 10 7 i_data [9:0] $end
$var wire 1 $ i_reset $end
$var parameter 32 8 IW $end
$var parameter 32 9 N $end
$var parameter 32 : OW $end
$var reg 10 ; o_data [9:0] $end
$var reg 1 < o_ready $end
$var integer 32 = i [31:0] $end
$upscope $end
$upscope $end
$scope begin gen_combo[3] $end
$var parameter 3 > j $end
$scope module comb_inst $end
$var wire 1 < i_ce $end
$var wire 1 " i_clk $end
$var wire 10 ? i_data [9:0] $end
$var wire 1 $ i_reset $end
$var parameter 32 @ IW $end
$var parameter 32 A N $end
$var parameter 32 B OW $end
$var reg 10 C o_data [9:0] $end
$var reg 1 D o_ready $end
$var integer 32 E i [31:0] $end
$upscope $end
$upscope $end
$scope begin gen_combo[4] $end
$var parameter 4 F j $end
$scope module comb_inst $end
$var wire 1 D i_ce $end
$var wire 1 " i_clk $end
$var wire 10 G i_data [9:0] $end
$var wire 1 $ i_reset $end
$var parameter 32 H IW $end
$var parameter 32 I N $end
$var parameter 32 J OW $end
$var reg 10 K o_data [9:0] $end
$var reg 1 L o_ready $end
$var integer 32 M i [31:0] $end
$upscope $end
$upscope $end
$scope begin gen_combo[5] $end
$var parameter 4 N j $end
$scope module comb_inst $end
$var wire 1 L i_ce $end
$var wire 1 " i_clk $end
$var wire 10 O i_data [9:0] $end
$var wire 1 $ i_reset $end
$var parameter 32 P IW $end
$var parameter 32 Q N $end
$var parameter 32 R OW $end
$var reg 10 S o_data [9:0] $end
$var reg 1 T o_ready $end
$var integer 32 U i [31:0] $end
$upscope $end
$upscope $end
$scope begin gen_combo[6] $end
$var parameter 4 V j $end
$scope module comb_inst $end
$var wire 1 T i_ce $end
$var wire 1 " i_clk $end
$var wire 10 W i_data [9:0] $end
$var wire 1 $ i_reset $end
$var parameter 32 X IW $end
$var parameter 32 Y N $end
$var parameter 32 Z OW $end
$var reg 10 [ o_data [9:0] $end
$var reg 1 \ o_ready $end
$var integer 32 ] i [31:0] $end
$upscope $end
$upscope $end
$scope begin gen_combo[7] $end
$var parameter 4 ^ j $end
$scope module comb_inst $end
$var wire 1 \ i_ce $end
$var wire 1 " i_clk $end
$var wire 10 _ i_data [9:0] $end
$var wire 1 $ i_reset $end
$var parameter 32 ` IW $end
$var parameter 32 a N $end
$var parameter 32 b OW $end
$var reg 10 c o_data [9:0] $end
$var reg 1 d o_ready $end
$var integer 32 e i [31:0] $end
$upscope $end
$upscope $end
$scope begin gen_combo[8] $end
$var parameter 5 f j $end
$scope module comb_inst $end
$var wire 1 d i_ce $end
$var wire 1 " i_clk $end
$var wire 10 g i_data [9:0] $end
$var wire 1 $ i_reset $end
$var parameter 32 h IW $end
$var parameter 32 i N $end
$var parameter 32 j OW $end
$var reg 10 k o_data [9:0] $end
$var reg 1 l o_ready $end
$var integer 32 m i [31:0] $end
$upscope $end
$upscope $end
$scope begin gen_combo[9] $end
$var parameter 5 n j $end
$scope module comb_inst $end
$var wire 1 l i_ce $end
$var wire 1 " i_clk $end
$var wire 10 o i_data [9:0] $end
$var wire 1 $ i_reset $end
$var parameter 32 p IW $end
$var parameter 32 q N $end
$var parameter 32 r OW $end
$var reg 10 s o_data [9:0] $end
$var reg 1 t o_ready $end
$var integer 32 u i [31:0] $end
$upscope $end
$upscope $end
$scope begin gen_integrator[1] $end
$var parameter 2 v i $end
$scope module integrator_inst $end
$var wire 1 w i_ce $end
$var wire 1 " i_clk $end
$var wire 10 x i_data [9:0] $end
$var wire 1 $ i_reset $end
$var parameter 32 y IW $end
$var parameter 32 z OW $end
$var reg 10 { accumulator [9:0] $end
$var reg 10 | o_data [9:0] $end
$var reg 1 } o_ready $end
$upscope $end
$upscope $end
$scope begin gen_integrator[2] $end
$var parameter 3 ~ i $end
$scope module integrator_inst $end
$var wire 1 } i_ce $end
$var wire 1 " i_clk $end
$var wire 10 !" i_data [9:0] $end
$var wire 1 $ i_reset $end
$var parameter 32 "" IW $end
$var parameter 32 #" OW $end
$var reg 10 $" accumulator [9:0] $end
$var reg 10 %" o_data [9:0] $end
$var reg 1 &" o_ready $end
$upscope $end
$upscope $end
$scope begin gen_integrator[3] $end
$var parameter 3 '" i $end
$scope module integrator_inst $end
$var wire 1 &" i_ce $end
$var wire 1 " i_clk $end
$var wire 10 (" i_data [9:0] $end
$var wire 1 $ i_reset $end
$var parameter 32 )" IW $end
$var parameter 32 *" OW $end
$var reg 10 +" accumulator [9:0] $end
$var reg 10 ," o_data [9:0] $end
$var reg 1 -" o_ready $end
$upscope $end
$upscope $end
$scope begin gen_integrator[4] $end
$var parameter 4 ." i $end
$scope module integrator_inst $end
$var wire 1 -" i_ce $end
$var wire 1 " i_clk $end
$var wire 10 /" i_data [9:0] $end
$var wire 1 $ i_reset $end
$var parameter 32 0" IW $end
$var parameter 32 1" OW $end
$var reg 10 2" accumulator [9:0] $end
$var reg 10 3" o_data [9:0] $end
$var reg 1 4" o_ready $end
$upscope $end
$upscope $end
$scope begin gen_integrator[5] $end
$var parameter 4 5" i $end
$scope module integrator_inst $end
$var wire 1 4" i_ce $end
$var wire 1 " i_clk $end
$var wire 10 6" i_data [9:0] $end
$var wire 1 $ i_reset $end
$var parameter 32 7" IW $end
$var parameter 32 8" OW $end
$var reg 10 9" accumulator [9:0] $end
$var reg 10 :" o_data [9:0] $end
$var reg 1 ;" o_ready $end
$upscope $end
$upscope $end
$scope begin gen_integrator[6] $end
$var parameter 4 <" i $end
$scope module integrator_inst $end
$var wire 1 ;" i_ce $end
$var wire 1 " i_clk $end
$var wire 10 =" i_data [9:0] $end
$var wire 1 $ i_reset $end
$var parameter 32 >" IW $end
$var parameter 32 ?" OW $end
$var reg 10 @" accumulator [9:0] $end
$var reg 10 A" o_data [9:0] $end
$var reg 1 B" o_ready $end
$upscope $end
$upscope $end
$scope begin gen_integrator[7] $end
$var parameter 4 C" i $end
$scope module integrator_inst $end
$var wire 1 B" i_ce $end
$var wire 1 " i_clk $end
$var wire 10 D" i_data [9:0] $end
$var wire 1 $ i_reset $end
$var parameter 32 E" IW $end
$var parameter 32 F" OW $end
$var reg 10 G" accumulator [9:0] $end
$var reg 10 H" o_data [9:0] $end
$var reg 1 I" o_ready $end
$upscope $end
$upscope $end
$scope begin gen_integrator[8] $end
$var parameter 5 J" i $end
$scope module integrator_inst $end
$var wire 1 I" i_ce $end
$var wire 1 " i_clk $end
$var wire 10 K" i_data [9:0] $end
$var wire 1 $ i_reset $end
$var parameter 32 L" IW $end
$var parameter 32 M" OW $end
$var reg 10 N" accumulator [9:0] $end
$var reg 10 O" o_data [9:0] $end
$var reg 1 P" o_ready $end
$upscope $end
$upscope $end
$scope begin gen_integrator[9] $end
$var parameter 5 Q" i $end
$scope module integrator_inst $end
$var wire 1 P" i_ce $end
$var wire 1 " i_clk $end
$var wire 10 R" i_data [9:0] $end
$var wire 1 $ i_reset $end
$var parameter 32 S" IW $end
$var parameter 32 T" OW $end
$var reg 10 U" accumulator [9:0] $end
$var reg 10 V" o_data [9:0] $end
$var reg 1 W" o_ready $end
$upscope $end
$upscope $end
$scope module decimator_inst $end
$var wire 1 ! i_ce $end
$var wire 1 " i_clk $end
$var wire 10 X" i_data [9:0] $end
$var wire 1 $ i_reset $end
$var parameter 32 Y" R $end
$var parameter 32 Z" RW $end
$var parameter 32 [" W $end
$var reg 5 \" decimator_counter [4:0] $end
$var reg 10 ]" o_data [9:0] $end
$var reg 1 ' o_ready $end
$upscope $end
$upscope $end
$enddefinitions $end
$comment Show the parameter values. $end
$dumpall
b1010 ["
b101 Z"
b1100100 Y"
b1010 T"
b1010 S"
b1001 Q"
b1010 M"
b1010 L"
b1000 J"
b1010 F"
b1010 E"
b111 C"
b1010 ?"
b1010 >"
b110 <"
b1010 8"
b1010 7"
b101 5"
b1010 1"
b1010 0"
b100 ."
b1010 *"
b1010 )"
b11 '"
b1010 #"
b1010 ""
b10 ~
b1010 z
b1010 y
b1 v
b1010 r
b1 q
b1010 p
b1001 n
b1010 j
b1 i
b1010 h
b1000 f
b1010 b
b1 a
b1010 `
b111 ^
b1010 Z
b1 Y
b1010 X
b110 V
b1010 R
b1 Q
b1010 P
b101 N
b1010 J
b1 I
b1010 H
b100 F
b1010 B
b1 A
b1010 @
b11 >
b1010 :
b1 9
b1010 8
b10 6
b1010 2
b1 1
b1010 0
b1 -
b1100100 ,
b1010 +
b1010 *
b1010 )
$end
#0
$dumpvars
b0 ]"
b0 \"
bz X"
0W"
b0 V"
b0 U"
b0 R"
0P"
b0 O"
b0 N"
b0 K"
0I"
b0 H"
b0 G"
b0 D"
0B"
b0 A"
b0 @"
b0 ="
0;"
b0 :"
b0 9"
b0 6"
04"
b0 3"
b0 2"
b0 /"
0-"
b0 ,"
b0 +"
b0 ("
0&"
b0 %"
b0 $"
b0 !"
0}
b0 |
b0 {
b0 x
1w
b1 u
0t
b0 s
b0 o
b1 m
0l
b0 k
b0 g
b1 e
0d
b0 c
b0 _
b1 ]
0\
b0 [
b0 W
b1 U
0T
b0 S
b0 O
b1 M
0L
b0 K
b0 G
b1 E
0D
b0 C
b0 ?
b1 =
0<
b0 ;
b0 7
b1 5
04
b0 3
b0 /
0.
b0 (
0'
z&
bz %
0$
b0 #
1"
1!
$end
#6250
0"
#12500
b1 \"
1}
1"
#18750
0"
#25000
b111111111 x
b111111111 #
1&"
b10 \"
1"
#31250
0"
#37500
b1000000000 x
b1000000000 #
b11 \"
1-"
b111111111 {
1"
#43750
0"
#50000
b111111111 x
b111111111 #
b111111111 |
b111111111 !"
b1111111111 {
14"
b100 \"
1"
#56250
0"
#62500
b1000000000 x
b1000000000 #
b101 \"
1;"
b111111111 $"
b1111111111 |
b1111111111 !"
b111111110 {
1"
#68750
0"
#75000
b1011010100 x
b1011010100 #
b111111110 |
b111111110 !"
b1111111110 {
b111111111 %"
b111111111 ("
b111111110 $"
1B"
b110 \"
1"
#81250
0"
#87500
b110011010 x
b110011010 #
b111 \"
1I"
b111111111 +"
b111111110 %"
b111111110 ("
b1111111100 $"
b1111111110 |
b1111111110 !"
b1011010010 {
1"
#93750
0"
#100000
b101011110 x
b101011110 #
b1011010010 |
b1011010010 !"
b1101100 {
b1111111100 %"
b1111111100 ("
b1111111010 $"
b111111111 ,"
b111111111 /"
b1111111101 +"
1P"
b1000 \"
1"
#106250
0"
#112500
b1000101101 x
b1000101101 #
b1001 \"
1W"
b111111111 2"
b1111111101 ,"
b1111111101 /"
b1111111001 +"
b1111111010 %"
b1111111010 ("
b1011001100 $"
b1101100 |
b1101100 !"
b111001010 {
1"
#118750
0"
#125000
b1100111010 x
b1100111010 #
b111001010 |
b111001010 !"
b1111110111 {
b1011001100 %"
b1011001100 ("
b1100111000 $"
b1111111001 ,"
b1111111001 /"
b1111110011 +"
b111111111 3"
b111111111 6"
b111111100 2"
b1010 \"
1"
#131250
0"
#137500
b110100001 x
b110100001 #
b1011 \"
b111111111 9"
b111111100 3"
b111111100 6"
b111110101 2"
b1111110011 ,"
b1111110011 /"
b1010111111 +"
b1100111000 %"
b1100111000 ("
b100000010 $"
b1111110111 |
b1111110111 !"
b1100110001 {
1"
#143750
0"
#150000
b111110111 x
b111110111 #
b1100110001 |
b1100110001 !"
b11010010 {
b100000010 %"
b100000010 ("
b11111001 $"
b1010111111 ,"
b1010111111 /"
b111110111 +"
b111110101 3"
b111110101 6"
b111101000 2"
b111111111 :"
b111111111 ="
b1111111011 9"
b1100 \"
1"
#156250
0"
#162500
b1011101 x
b1011101 #
b1101 \"
b111111111 @"
b1111111011 :"
b1111111011 ="
b111110000 9"
b111101000 3"
b111101000 6"
b10100111 2"
b111110111 ,"
b111110111 /"
b1011111001 +"
b11111001 %"
b11111001 ("
b101010 $"
b11010010 |
b11010010 !"
b1011001001 {
1"
#168750
0"
#175000
b1100010101 x
b1100010101 #
b1011001001 |
b1011001001 !"
b1100100110 {
b101010 %"
b101010 ("
b11111100 $"
b1011111001 ,"
b1011111001 /"
b1111110010 +"
b10100111 3"
b10100111 6"
b1010011110 2"
b111110000 :"
b111110000 ="
b1111011000 9"
b111111111 A"
b111111111 D"
b111111010 @"
b1110 \"
1"
#181250
0"
#187500
b1000110011 x
b1000110011 #
b1111 \"
b111111111 G"
b111111010 A"
b111111010 D"
b1111101010 @"
b1111011000 :"
b1111011000 ="
b1111111 9"
b1010011110 3"
b1010011110 6"
b110010111 2"
b1111110010 ,"
b1111110010 /"
b11100 +"
b11111100 %"
b11111100 ("
b1111000101 $"
b1100100110 |
b1100100110 !"
b1000111011 {
1"
#193750
0"
#200000
b110001110 x
b110001110 #
b1000111011 |
b1000111011 !"
b1101110 {
b1111000101 %"
b1111000101 ("
b1011101011 $"
b11100 ,"
b11100 /"
b100011000 +"
b110010111 3"
b110010111 6"
b110001001 2"
b1111111 :"
b1111111 ="
b1100011101 9"
b1111101010 A"
b1111101010 D"
b1111000010 @"
b111111111 H"
b111111111 K"
b1111111001 G"
b10000 \"
1"
#206250
0"
#212500
b10111001 x
b10111001 #
b10001 \"
b111111111 N"
b1111111001 H"
b1111111001 K"
b1111100011 G"
b1111000010 A"
b1111000010 D"
b1000001 @"
b1100011101 :"
b1100011101 ="
b10110100 9"
b110001001 3"
b110001001 6"
b110100101 2"
b100011000 ,"
b100011000 /"
b11011101 +"
b1011101011 %"
b1011101011 ("
b100100110 $"
b1101110 |
b1101110 !"
b111111100 {
1"
#218750
0"
#225000
b100010010 x
b100010010 #
b111111100 |
b111111100 !"
b1010110101 {
b100100110 %"
b100100110 ("
b110010100 $"
b11011101 ,"
b11011101 /"
b1111001000 +"
b110100101 3"
b110100101 6"
b1010111101 2"
b10110100 :"
b10110100 ="
b1000111101 9"
b1000001 A"
b1000001 D"
b1101011110 @"
b1111100011 H"
b1111100011 K"
b1110100101 G"
b111111111 O"
b111111111 R"
b111111000 N"
b10010 \"
1"
#231250
0"
#237500
b101000110 x
b101000110 #
b10011 \"
b111111111 U"
b111111000 O"
b111111000 R"
b111011011 N"
b1110100101 H"
b1110100101 K"
b1111100110 G"
b1101011110 A"
b1101011110 D"
b10010 @"
b1000111101 :"
b1000111101 ="
b1111100010 9"
b1010111101 3"
b1010111101 6"
b1110011010 2"
b1111001000 ,"
b1111001000 /"
b11101110 +"
b110010100 %"
b110010100 ("
b1110010000 $"
b1010110101 |
b1010110101 !"
b1111000111 {
1"
#243750
0"
#250000
b11110110 x
b11110110 #
b1111000111 |
b1111000111 !"
b100001101 {
b1110010000 %"
b1110010000 ("
b1001000101 $"
b11101110 ,"
b11101110 /"
b1010000010 +"
b1110011010 3"
b1110011010 6"
b1101100010 2"
b1111100010 :"
b1111100010 ="
b1010011111 9"
b10010 A"
b10010 D"
b1001001111 @"
b1111100110 H"
b1111100110 K"
b1101000100 G"
b111011011 O"
b111011011 R"
b110000000 N"
b111111111 V"
b1111110111 U"
b10100 \"
1"
#256250
0"
#262500
b11101001 x
b11101001 #
b10101 \"
b1111110111 V"
b111010010 U"
b110000000 O"
b110000000 R"
b101100110 N"
b1101000100 H"
b1101000100 K"
b1101010110 G"
b1001001111 A"
b1001001111 D"
b1000110001 @"
b1010011111 :"
b1010011111 ="
b1000111001 9"
b1101100010 3"
b1101100010 6"
b1010000 2"
b1010000010 ,"
b1010000010 /"
b1000010010 +"
b1001000101 %"
b1001000101 ("
b1000001100 $"
b100001101 |
b100001101 !"
b1000000011 {
1"
#268750
0"
#275000
b1000001100 x
b1000001100 #
b1000000011 |
b1000000011 !"
b1011101100 {
b1000001100 %"
b1000001100 ("
b1100011001 $"
b1000010010 ,"
b1000010010 /"
b1010111 +"
b1010000 3"
b1010000 6"
b1011010010 2"
b1000111001 :"
b1000111001 ="
b110011011 9"
b1000110001 A"
b1000110001 D"
b11010000 @"
b1101010110 H"
b1101010110 K"
b110100101 G"
b101100110 O"
b101100110 R"
b10101010 N"
b111010010 V"
b1101010010 U"
b10110 \"
1"
#281250
0"
#287500
b1001001000 x
b1001001000 #
b10111 \"
b1101010010 V"
b10111000 U"
b10101010 O"
b10101010 R"
b0 N"
b110100101 H"
b110100101 K"
b1111010110 G"
b11010000 A"
b11010000 D"
b1100001001 @"
b110011011 :"
b110011011 ="
b111101011 9"
b1011010010 3"
b1011010010 6"
b11100100 2"
b1010111 ,"
b1010111 /"
b1001100011 +"
b1100011001 %"
b1100011001 ("
b100011100 $"
b1011101100 |
b1011101100 !"
b11111000 {
1"
#293750
0"
#300000
b1000111100 x
b1000111100 #
b11111000 |
b11111000 !"
b1101000000 {
b100011100 %"
b100011100 ("
b1000 $"
b1001100011 ,"
b1001100011 /"
b101111100 +"
b11100100 3"
b11100100 6"
b100111011 2"
b111101011 :"
b111101011 ="
b10111101 9"
b1100001001 A"
b1100001001 D"
b10100100 @"
b1111010110 H"
b1111010110 K"
b10100110 G"
b0 O"
b0 R"
b110100101 N"
b10111000 V"
b101100010 U"
b11000 \"
1"
#306250
0"
#312500
b1011010011 x
b1011010011 #
b11001 \"
b101100010 V"
b110100101 O"
b110100101 R"
b101111011 N"
b10100110 H"
b10100110 K"
b1110101111 G"
b10100100 A"
b10100100 D"
b1010001111 @"
b10111101 :"
b10111101 ="
b110100001 9"
b100111011 3"
b100111011 6"
b1110011110 2"
b101111100 ,"
b101111100 /"
b1010011000 +"
b1000 %"
b1000 ("
b100000000 $"
b1101000000 |
b1101000000 !"
b101111100 {
1"
#318750
0"
#325000
b1000010000 x
b1000010000 #
b101111100 |
b101111100 !"
b1001111 {
b100000000 %"
b100000000 ("
b1000000 $"
b1010011000 ,"
b1010011000 /"
b1010100000 +"
b1110011110 3"
b1110011110 6"
b100011010 2"
b110100001 :"
b110100001 ="
b1011011100 9"
b1010001111 A"
b1010001111 D"
b1101001100 @"
b1110101111 H"
b1110101111 K"
b1010011 G"
b101111011 O"
b101111011 R"
b1000100001 N"
b1100000111 U"
b11010 \"
1"
#331250
0"
#337500
b1010011111 x
b1010011111 #
b11011 \"
b1100000111 V"
b10000010 U"
b1000100001 O"
b1000100001 R"
b111010000 N"
b1010011 H"
b1010011 K"
b1011100010 G"
b1101001100 A"
b1101001100 D"
b11101101 @"
b1011011100 :"
b1011011100 ="
b1001111010 9"
b100011010 3"
b100011010 6"
b1110110010 2"
b1010100000 ,"
b1010100000 /"
b1110100000 +"
b1000000 %"
b1000000 ("
b110111100 $"
b1001111 |
b1001111 !"
b1001011111 {
1"
#343750
0"
#350000
b1100111 x
b1100111 #
b1001011111 |
b1001011111 !"
b11111110 {
b110111100 %"
b110111100 ("
b1000001011 $"
b1110100000 ,"
b1110100000 /"
b1111100000 +"
b1110110010 3"
b1110110010 6"
b1001010010 2"
b1001111010 :"
b1001111010 ="
b1110010100 9"
b11101101 A"
b11101101 D"
b1111001001 @"
b1011100010 H"
b1011100010 K"
b1000101110 G"
b111010000 O"
b111010000 R"
b1000100011 N"
b10000010 V"
b1010100011 U"
b11100 \"
1"
#356250
0"
#362500
b1000101100 x
b1000101100 #
b11101 \"
b1010100011 V"
b1110011 U"
b1000100011 O"
b1000100011 R"
b100000101 N"
b1000101110 H"
b1000101110 K"
b1100011011 G"
b1111001001 A"
b1111001001 D"
b1001000011 @"
b1110010100 :"
b1110010100 ="
b1101000110 9"
b1001010010 3"
b1001010010 6"
b111110010 2"
b1111100000 ,"
b1111100000 /"
b110011100 +"
b1000001011 %"
b1000001011 ("
b1101010 $"
b11111110 |
b11111110 !"
b101100101 {
1"
#368750
0"
#375000
b111000101 x
b111000101 #
b101100101 |
b101100101 !"
b1110010001 {
b1101010 %"
b1101010 ("
b101101000 $"
b110011100 ,"
b110011100 /"
b1110100111 +"
b111110010 3"
b111110010 6"
b111010010 2"
b1101000110 :"
b1101000110 ="
b110011000 9"
b1001000011 A"
b1001000011 D"
b111010111 @"
b1100011011 H"
b1100011011 K"
b1011100100 G"
b100000101 O"
b100000101 R"
b1100110011 N"
b1110011 V"
b1010010110 U"
b11110 \"
1"
#381250
0"
#387500
b101101010 x
b101101010 #
b11111 \"
b1010010110 V"
b1110011011 U"
b1100110011 O"
b1100110011 R"
b1001001110 N"
b1011100100 H"
b1011100100 K"
b100100111 G"
b111010111 A"
b111010111 D"
b100011101 @"
b110011000 :"
b110011000 ="
b1110001010 9"
b111010010 3"
b111010010 6"
b1101101110 2"
b1110100111 ,"
b1110100111 /"
b10001 +"
b101101000 %"
b101101000 ("
b1011001101 $"
b1110010001 |
b1110010001 !"
b101010110 {
1"
#393750
0"
#400000
b101001011 x
b101001011 #
b101010110 |
b101010110 !"
b1011000000 {
b1011001101 %"
b1011001101 ("
b1001011110 $"
b10001 ,"
b10001 /"
b101111001 +"
b1101101110 3"
b1101101110 6"
b1100010101 2"
b1110001010 :"
b1110001010 ="
b101011100 9"
b100011101 A"
b100011101 D"
b1010110101 @"
b100100111 H"
b100100111 K"
b1011111110 G"
b1001001110 O"
b1001001110 R"
b100110010 N"
b1110011011 V"
b1011001110 U"
b0 \"
1"
#406250
0"
#412500
b1101011000 x
b1101011000 #
b1 \"
b1011001110 V"
b100011100 U"
b100110010 O"
b100110010 R"
b1001011001 N"
b1011111110 H"
b1011111110 K"
b11011 G"
b1010110101 A"
b1010110101 D"
b1000111111 @"
b101011100 :"
b101011100 ="
b11001010 9"
b1100010101 3"
b1100010101 6"
b1100100110 2"
b101111001 ,"
b101111001 /"
b1000110 +"
b1001011110 %"
b1001011110 ("
b1110110100 $"
b1011000000 |
b1011000000 !"
b1011 {
1"
#418750
0"
#425000
b100011101 x
b100011101 #
b1011 |
b1011 !"
b1101100011 {
b1110110100 %"
b1110110100 ("
b1001110100 $"
b1000110 ,"
b1000110 /"
b1010100100 +"
b1100100110 3"
b1100100110 6"
b10011111 2"
b11001010 :"
b11001010 ="
b1111011111 9"
b1000111111 A"
b1000111111 D"
b1110011011 @"
b11011 H"
b11011 K"
b1011010000 G"
b1001011001 O"
b1001011001 R"
b101010111 N"
b100011100 V"
b1001001110 U"
b10 \"
1"
#431250
0"
#437500
b1010110011 x
b1010110011 #
b11 \"
b1001001110 V"
b10100111 U"
b101010111 O"
b101010111 R"
b101110010 N"
b1011010000 H"
b1011010000 K"
b100001111 G"
b1110011011 A"
b1110011011 D"
b1100101 @"
b1111011111 :"
b1111011111 ="
b1100000101 9"
b10011111 3"
b10011111 6"
b11100101 2"
b1010100100 ,"
b1010100100 /"
b1001011000 +"
b1001110100 %"
b1001110100 ("
b1001111111 $"
b1101100011 |
b1101100011 !"
b10000000 {
1"
#443750
0"
#450000
b1110010101 x
b1110010101 #
b10000000 |
b10000000 !"
b1100110011 {
b1001111111 %"
b1001111111 ("
b111100010 $"
b1001011000 ,"
b1001011000 /"
b11001100 +"
b11100101 3"
b11100101 6"
b1110001001 2"
b1100000101 :"
b1100000101 ="
b1110100100 9"
b1100101 A"
b1100101 D"
b1000100 @"
b100001111 H"
b100001111 K"
b10101010 G"
b101110010 O"
b101110010 R"
b1000010 N"
b10100111 V"
b111111110 U"
b100 \"
1"
#456250
0"
#462500
b111011001 x
b111011001 #
b101 \"
b111111110 V"
b1101110000 U"
b1000010 O"
b1000010 R"
b101010001 N"
b10101010 H"
b10101010 K"
b100001111 G"
b1000100 A"
b1000100 D"
b1101001001 @"
b1110100100 :"
b1110100100 ="
b10001001 9"
b1110001001 3"
b1110001001 6"
b111100001 2"
b11001100 ,"
b11001100 /"
b1101001011 +"
b111100010 %"
b111100010 ("
b1001100010 $"
b1100110011 |
b1100110011 !"
b1011001000 {
1"
#468750
0"
#475000
b1101011010 x
b1101011010 #
b1011001000 |
b1011001000 !"
b10100001 {
b1001100010 %"
b1001100010 ("
b110010101 $"
b1101001011 ,"
b1101001011 /"
b100101101 +"
b111100001 3"
b111100001 6"
b1010101101 2"
b10001001 :"
b10001001 ="
b10010 9"
b1101001001 A"
b1101001001 D"
b1011101101 @"
b100001111 H"
b100001111 K"
b101010011 G"
b101010001 O"
b101010001 R"
b111111011 N"
b1101110000 V"
b1110110010 U"
b110 \"
1"
#481250
0"
