New Modules/CORDIC/CORDIC-Comb/cordic.v
////////////////////////////////////////////////////////////////////////////////
//
// Filename: 	../rtl/cordic.v
// {{{
// Project:	A series of CORDIC related projects
//
// Purpose:	This file executes a vector rotation on the values
//		(i_xval, i_yval).  This vector is rotated left by
//	i_phase.  i_phase is given by the angle, in radians, multiplied by
//	2^32/(2pi).  In that fashion, a two pi value is zero just as a zero
//	angle is zero.
//
// This core was generated via a core generator using the following command
// line:
//
//  % ./gencordic -vca -f ../rtl/cordic.v -v -i 13 -o 13 -t p2r -x 2 -c
//
// Creator:	Dan Gisselquist, Ph.D.
//		Gisselquist Technology, LLC
//
////////////////////////////////////////////////////////////////////////////////
// }}}
// Copyright (C) 2017-2024, Gisselquist Technology, LLC
// {{{
// This file is part of the CORDIC related project set.
//
// The CORDIC related project set is free software (firmware): you can
// redistribute it and/or modify it under the terms of the GNU Lesser General
// Public License as published by the Free Software Foundation, either version
// 3 of the License, or (at your option) any later version.
//
// The CORDIC related project set is distributed in the hope that it will be
// useful, but WITHOUT ANY WARRANTY; without even the implied warranty of
// MERCHANTIBILITY or FITNESS FOR A PARTICULAR PURPOSE.  See the GNU Lesser
// General Public License for more details.
//
// You should have received a copy of the GNU Lesser General Public License
// along with this program.  (It's in the $(ROOT)/doc directory.  Run make
// with no target there if the PDF file isn't present.)  If not, see
// License:	LGPL, v3, as defined and found on www.gnu.org,
//		http://www.gnu.org/licenses/lgpl.html
//
////////////////////////////////////////////////////////////////////////////////
//
// }}}
`default_nettype	none
module	cordic#(
		// {{{
	localparam	IW=13,	// The number of bits in our inputs
			OW=13,	// The number of output bits to produce
			NSTAGES=16,
			// XTRA= 3,// Extra bits for internal precision
			WW=16,	// Our working bit-width
			PW=20	// Bits in our phase variables
		// }}}
	) (
		// {{{
	input	wire				i_clk, i_reset, i_ce,
	input	wire	signed	[(IW-1):0]		i_xval, i_yval,
	input	wire		[(PW-1):0]			i_phase,
	output	reg	signed	[(OW-1):0]	o_xval, o_yval,
	input	wire				i_aux,
	output	reg				o_aux
		// }}}
	);

	// Declare variables for all of the separate stages
	// {{{
	wire	signed [(WW-1):0]	e_xval, e_yval;
	reg	signed	[(WW-1):0]	xv	[0:(NSTAGES)];
	reg	signed	[(WW-1):0]	yv	[0:(NSTAGES)];
	reg		[(PW-1):0]	ph	[0:(NSTAGES)];
	reg		[(NSTAGES):0]	ax;
	// }}}

	// Sign extend our inputs
	// {{{
	// First step: expand our input to our working width.
	// This is going to involve extending our input by one
	// (or more) bits in addition to adding any xtra bits on
	// bits on the right.  The one bit extra on the left is to
	// allow for any accumulation due to the cordic gain
	// within the algorithm.
	// 
	assign	e_xval = { {i_xval[(IW-1)]}, i_xval, {(WW-IW-1){1'b0}} };
	assign	e_yval = { {i_yval[(IW-1)]}, i_yval, {(WW-IW-1){1'b0}} };

	// }}}
	//
	// Handle the auxilliary logic.
	// {{{
	// The auxilliary bit is designed so that you can place a valid bit into
	// the CORDIC function, and see when it comes out.  While the bit is
	// allowed to be anything, the requirement of this bit is that it *must*
	// be aligned with the output when done.  That is, if i_xval and i_yval
	// are input together with i_aux, then when o_xval and o_yval are set
	// to this value, o_aux *must* contain the value that was in i_aux.
	//

	initial	ax = 0;
	always @(posedge i_clk)
	if (i_reset)
		ax <= 0;
	else
		ax <= { ax[(NSTAGES-1):0], i_aux };
	// }}}

	// Pre-CORDIC rotation
	// {{{
	// First stage, get rid of all but 45 degrees
	//	The resulting phase needs to be between -45 and 45
	//		degrees but in units of normalized phase
	// Initialize arrays

	always @(posedge i_clk)
	if (i_reset)
	begin
		xv[0] = 0; yv[0] = 0; ph[0] = 0;
	end else
	begin
		// {{{
		// Walk through all possible quick phase shifts necessary
		// to constrain the input to within +/- 45 degrees.
		// This is a zero-gain operation, involving only sign
		// adjustments.
		case(i_phase[(PW-1):(PW-3)])
		3'b000: begin	// 0 .. 45, No change
		// {{{
			xv[0] <= e_xval;
			yv[0] <= e_yval;
			ph[0] <= i_phase;
			end
			// }}}
		3'b001: begin	// 45 .. 90
		// {{{
			xv[0] <= -e_yval;
			yv[0] <= e_xval;
			ph[0] <= i_phase - 20'h40000;
			end
			// }}}
		3'b010: begin	// 90 .. 135
		// {{{
			xv[0] <= -e_yval;
			yv[0] <= e_xval;
			ph[0] <= i_phase - 20'h40000;
			end
			// }}}
		3'b011: begin	// 135 .. 180
		// {{{
			xv[0] <= -e_xval;
			yv[0] <= -e_yval;
			ph[0] <= i_phase - 20'h80000;
			end
			// }}}
		3'b100: begin	// 180 .. 225
		// {{{
			xv[0] <= -e_xval;
			yv[0] <= -e_yval;
			ph[0] <= i_phase - 20'h80000;
			end
			// }}}
		3'b101: begin	// 225 .. 270
		// {{{
			xv[0] <= e_yval;
			yv[0] <= -e_xval;
			ph[0] <= i_phase - 20'hc0000;
			end
			// }}}
		3'b110: begin	// 270 .. 315
		// {{{
			xv[0] <= e_yval;
			yv[0] <= -e_xval;
			ph[0] <= i_phase - 20'hc0000;
			end
			// }}}
		3'b111: begin	// 315 .. 360, No change
		// {{{
			xv[0] <= e_xval;
			yv[0] <= e_yval;
			ph[0] <= i_phase;
			end
			// }}}
		endcase
		// }}}
	end
	// }}}
	// Cordic angle table
	// {{{
	// In many ways, the key to this whole algorithm lies in the angles
	// necessary to do this.  These angles are also our basic reason for
	// building this CORDIC in C++: Verilog just can't parameterize this
	// much.  Further, these angle's risk becoming unsupportable magic
	// numbers, hence we define these and set them in C++, based upon
	// the needs of our problem, specifically the number of stages and
	// the number of bits required in our phase accumulator
	//
	wire	[19:0]	cordic_angle [0:(NSTAGES-1)];

	assign	cordic_angle[ 0] = 20'h1_2e40; //  26.565051 deg
	assign	cordic_angle[ 1] = 20'h0_9fb3; //  14.036243 deg
	assign	cordic_angle[ 2] = 20'h0_5111; //   7.125016 deg
	assign	cordic_angle[ 3] = 20'h0_28b0; //   3.576334 deg
	assign	cordic_angle[ 4] = 20'h0_145d; //   1.789911 deg
	assign	cordic_angle[ 5] = 20'h0_0a2f; //   0.895174 deg
	assign	cordic_angle[ 6] = 20'h0_0517; //   0.447614 deg
	assign	cordic_angle[ 7] = 20'h0_028b; //   0.223811 deg
	assign	cordic_angle[ 8] = 20'h0_0145; //   0.111906 deg
	assign	cordic_angle[ 9] = 20'h0_00a2; //   0.055953 deg
	assign	cordic_angle[10] = 20'h0_0051; //   0.027976 deg
	assign	cordic_angle[11] = 20'h0_0028; //   0.013988 deg
	assign	cordic_angle[12] = 20'h0_0014; //   0.006994 deg
	assign	cordic_angle[13] = 20'h0_000a; //   0.003497 deg
	assign	cordic_angle[14] = 20'h0_0005; //   0.001749 deg
	assign	cordic_angle[15] = 20'h0_0002; //   0.000874 deg
	// {{{
	// Std-Dev    : 0.00 (Units)
	// Phase Quantization: 0.000015 (Radians)
	// Gain is 1.164435
	// You can annihilate this gain by multiplying by 32'hdbd95b16
	// and right shifting by 32 bits.
	// }}}
	// }}}

	// CORDIC rotations
	// {{{
	

    genvar i;
    generate
        for (i = 0; i < NSTAGES; i = i + 1) begin : CORDICops
            wire signed [(WW-1):0] next_xv, next_yv;
            wire [(PW-1):0] next_ph;

            assign next_xv = (ph[i][PW-1]) ?
                             (xv[i] + (yv[i] >>> (i+1))) :  // If phase is negative, rotate clockwise
                             (xv[i] - (yv[i] >>> (i+1)));   // If phase is positive, rotate counter-clockwise

            assign next_yv = (ph[i][PW-1]) ?
                             (yv[i] - (xv[i] >>> (i+1))) :
                             (yv[i] + (xv[i] >>> (i+1)));

            assign next_ph = (ph[i][PW-1]) ?
                             (ph[i] + cordic_angle[i]) :
                             (ph[i] - cordic_angle[i]);

            assign xv[i+1] = next_xv;
            assign yv[i+1] = next_yv;
            assign ph[i+1] = next_ph;
        end
    endgenerate

	// Round our result towards even
	// {{{
	wire	[(WW-1):0]	pre_xval, pre_yval;

	assign	pre_xval = xv[NSTAGES] + $signed({ {(OW){1'b0}},
				xv[NSTAGES][(WW-OW)],
				{(WW-OW-1){!xv[NSTAGES][WW-OW]}} });
	assign	pre_yval = yv[NSTAGES] + $signed({ {(OW){1'b0}},
				yv[NSTAGES][(WW-OW)],
				{(WW-OW-1){!yv[NSTAGES][WW-OW]}} });


	initial begin
		o_xval = 0;
		o_yval = 0;
		o_aux  = 0;
	end
	always @(posedge i_clk)
	if (i_reset)
	begin
		o_xval <= 0;
		o_yval <= 0;
		o_aux  <= 0;
	end else if (i_ce)
	begin
		o_xval <= pre_xval[(WW-1):(WW-OW)];
		o_yval <= pre_yval[(WW-1):(WW-OW)];
		o_aux <= ax[NSTAGES];
	end
	// }}}
	// Make Verilator happy with pre_.val
	// {{{
	// verilator lint_off UNUSED
	wire	unused_val;
	assign	unused_val = &{ 1'b0, 
		pre_xval[(WW-OW-1):0],
		pre_yval[(WW-OW-1):0]
		};
	// }}}
	// verilator lint_on UNUSED

    initial begin
        $dumpfile("cordic_waves.vcd");
        $dumpvars;
    end
endmodule

5.NewModules/CORDIC/CORDIC-Comb/cordic_waves.vcd
$date
	Sun Apr 14 22:18:16 2024
$end
$version
	Icarus Verilog
$end
$timescale
	1ps
$end
$scope module cordic $end
$var wire 1 ! i_aux $end
$var wire 1 " i_ce $end
$var wire 1 # i_clk $end
$var wire 20 $ i_phase [19:0] $end
$var wire 1 % i_reset $end
$var wire 13 & i_xval [12:0] $end
$var wire 13 ' i_yval [12:0] $end
$var wire 1 ( unused_val $end
$var wire 16 ) pre_yval [15:0] $end
$var wire 16 * pre_xval [15:0] $end
$var wire 16 + e_yval [15:0] $end
$var wire 16 , e_xval [15:0] $end
$var parameter 32 - IW $end
$var parameter 32 . NSTAGES $end
$var parameter 32 / OW $end
$var parameter 32 0 PW $end
$var parameter 32 1 WW $end
$var reg 17 2 ax [16:0] $end
$var reg 1 3 o_aux $end
$var reg 13 4 o_xval [12:0] $end
$var reg 13 5 o_yval [12:0] $end
$scope begin CORDICops[0] $end
$var wire 16 6 next_yv [15:0] $end
$var wire 16 7 next_xv [15:0] $end
$var wire 20 8 next_ph [19:0] $end
$var parameter 2 9 i $end
$upscope $end
$scope begin CORDICops[1] $end
$var wire 16 : next_yv [15:0] $end
$var wire 16 ; next_xv [15:0] $end
$var wire 20 < next_ph [19:0] $end
$var parameter 2 = i $end
$upscope $end
$scope begin CORDICops[2] $end
$var wire 16 > next_yv [15:0] $end
$var wire 16 ? next_xv [15:0] $end
$var wire 20 @ next_ph [19:0] $end
$var parameter 3 A i $end
$upscope $end
$scope begin CORDICops[3] $end
$var wire 16 B next_yv [15:0] $end
$var wire 16 C next_xv [15:0] $end
$var wire 20 D next_ph [19:0] $end
$var parameter 3 E i $end
$upscope $end
$scope begin CORDICops[4] $end
$var wire 16 F next_yv [15:0] $end
$var wire 16 G next_xv [15:0] $end
$var wire 20 H next_ph [19:0] $end
$var parameter 4 I i $end
$upscope $end
$scope begin CORDICops[5] $end
$var wire 16 J next_yv [15:0] $end
$var wire 16 K next_xv [15:0] $end
$var wire 20 L next_ph [19:0] $end
$var parameter 4 M i $end
$upscope $end
$scope begin CORDICops[6] $end
$var wire 16 N next_yv [15:0] $end
$var wire 16 O next_xv [15:0] $end
$var wire 20 P next_ph [19:0] $end
$var parameter 4 Q i $end
$upscope $end
$scope begin CORDICops[7] $end
$var wire 16 R next_yv [15:0] $end
$var wire 16 S next_xv [15:0] $end
$var wire 20 T next_ph [19:0] $end
$var parameter 4 U i $end
$upscope $end
$scope begin CORDICops[8] $end
$var wire 16 V next_yv [15:0] $end
$var wire 16 W next_xv [15:0] $end
$var wire 20 X next_ph [19:0] $end
$var parameter 5 Y i $end
$upscope $end
$scope begin CORDICops[9] $end
$var wire 16 Z next_yv [15:0] $end
$var wire 16 [ next_xv [15:0] $end
$var wire 20 \ next_ph [19:0] $end
$var parameter 5 ] i $end
$upscope $end
$scope begin CORDICops[10] $end
$var wire 16 ^ next_yv [15:0] $end
$var wire 16 _ next_xv [15:0] $end
$var wire 20 ` next_ph [19:0] $end
$var parameter 5 a i $end
$upscope $end
$scope begin CORDICops[11] $end
$var wire 16 b next_yv [15:0] $end
$var wire 16 c next_xv [15:0] $end
$var wire 20 d next_ph [19:0] $end
$var parameter 5 e i $end
$upscope $end
$scope begin CORDICops[12] $end
$var wire 16 f next_yv [15:0] $end
$var wire 16 g next_xv [15:0] $end
$var wire 20 h next_ph [19:0] $end
$var parameter 5 i i $end
$upscope $end
$scope begin CORDICops[13] $end
$var wire 16 j next_yv [15:0] $end
$var wire 16 k next_xv [15:0] $end
$var wire 20 l next_ph [19:0] $end
$var parameter 5 m i $end
$upscope $end
$scope begin CORDICops[14] $end
$var wire 16 n next_yv [15:0] $end
$var wire 16 o next_xv [15:0] $end
$var wire 20 p next_ph [19:0] $end
$var parameter 5 q i $end
$upscope $end
$scope begin CORDICops[15] $end
$var wire 16 r next_yv [15:0] $end
$var wire 16 s next_xv [15:0] $end
$var wire 20 t next_ph [19:0] $end
$var parameter 5 u i $end
$upscope $end
$upscope $end
$enddefinitions $end
$comment Show the parameter values. $end
$dumpall
b1111 u
b1110 q
b1101 m
b1100 i
b1011 e
b1010 a
b1001 ]
b1000 Y
b111 U
b110 Q
b101 M
b100 I
b11 E
b10 A
b1 =
b0 9
b10000 1
b10100 0
b1101 /
b10000 .
b1101 -
$end
#0
$dumpvars
b11111111111111111110 t
b0 s
b0 r
b11111111111111111011 p
b0 o
b0 n
b11111111111111110110 l
b0 k
b0 j
b11111111111111101100 h
b0 g
b0 f
b11111111111111011000 d
b0 c
b0 b
b11111111111110101111 `
b0 _
b0 ^
b11111111111101011110 \
b0 [
b0 Z
b11111111111010111011 X
b0 W
b0 V
b11111111110101110101 T
b0 S
b0 R
b11111111101011101001 P
b0 O
b0 N
b11111111010111010001 L
b0 K
b0 J
b11111110101110100011 H
b0 G
b0 F
b11111101011101010000 D
b0 C
b0 B
b11111010111011101111 @
b0 ?
b0 >
b11110110000001001101 <
b0 ;
b0 :
b11101101000111000000 8
b0 7
b0 6
b0 5
b0 4
03
b0 2
bz00 ,
bz00 +
b11 *
b11 )
0(
bz '
bz &
0%
bz $
1#
z"
z!
$end
#6250
0#
#12500
b0 $
b0 +
b0 '
b11111111111100 ,
b111111111111 &
1"
1#
#18750
0#
#25000
b1111111111110 6
b11110111000101110011 <
b11111011000101011110 @
b11111101011110011111 D
b11111110101110101101 H
b11111111010111010010 L
b11111111101011101000 P
b11111111110101110100 T
b11111111111010111010 X
b11111111111101011101 \
b11111111111110101111 `
b11111111111111010111 d
b11111111111111101100 h
b11111111111111110110 l
b11111111111111111011 p
b11111111111111111101 t
b11111111111100 7
b0z 2
1#
#31250
0#
#37500
b11111111111111101011 h
b11111111111110101110 `
b11111111111101011100 \
b11111111111010111001 X
b11111111110101110011 T
b11111111101011101001 P
b11111111010111011100 L
b11111110101111111100 H
b11111101101000001110 D
b11111100001010000100 @
b111111111111 :
b100011111111011 ;
b0zz 2
1#
#43750
0#
#50000
b11100000000 >
b100100111111010 ?
b11111110101100110100 D
b11111110111001101011 H
b11111111011000101011 L
b11111111101011110011 P
b11111111110101110100 T
b11111111111010111000 X
b11111111111101011011 \
b11111111111110101101 `
b11111111111111010110 d
b11111111111111110101 l
b0zzz 2
1#
#56250
0#
#62500
b11111111111111111010 p
b11111111111111101010 h
b11111111111111010101 d
b11111111111110101100 `
b11111111111101011010 \
b11111111111010111001 X
b11111111110101111110 T
b11111111101101000010 P
b11111111100010011010 L
b11111111111110010001 H
b1001100001 B
b100101001101010 C
b0zzzz 2
1#
#68750
0#
#75000
b1110 F
b100101001111101 G
b100111000000 L
b11111111110110110001 P
b11111111110111001101 T
b11111111111011000011 X
b11111111111101011011 \
b11111111111110101011 `
b11111111111111010100 d
b11111111111111101001 h
b11111111111111110100 l
b11111111111111111100 t
b0zzzzz 2
1#
#81250
0#
#87500
b11111111111111111001 p
b11111111111111110011 l
b11111111111111101000 h
b11111111111111010011 d
b11111111111110101100 `
b11111111111101100101 \
b11111111111100010010 X
b111100 T
b10010101001 P
b1111111011100101 J
b100101001111101 K
b0zzzzzz 2
1#
#93750
0#
#100000
b1111111101111001 N
b100101010000000 O
b1000011110 T
b11111111111011110111 X
b11111111111110110100 \
b11111111111110110110 `
b11111111111111010100 d
b11111111111111100111 h
b11111111111111110010 l
b11111111111111111000 p
b11111111111111111011 t
b0zzzzzzz 2
1#
#106250
0#
#112500
b11111111111111111010 t
b11111111111111110111 p
b11111111111111110001 l
b11111111111111101000 h
b11111111111111011110 d
b101 `
b11111111111110011001 \
b11011001 X
b1111111111000011 R
b100101010000001 S
b0zzzzzzzz 2
1#
#118750
0#
#125000
b1111111111101000 V
b100101010000010 W
b110111 \
b11111111111111101010 `
b11111111111111011101 d
b11111111111111110010 h
b11111111111111110010 l
b11111111111111110110 p
b11111111111111111001 t
b0zzzzzzzzz 2
1#
#131250
0#
#137500
b11111111111111111000 t
b11111111111111110111 p
b11111111111111111100 l
b11111111111111110001 h
b10010 d
b11111111111111100110 `
b1111111111111010 Z
b100101010000011 [
b0zzzzzzzzzz 2
1#
#143750
0#
#150000
b11 ^
b100101010000100 _
b1110 d
b11111111111111111110 h
b11111111111111111011 l
b1 p
b11111111111111111001 t
b0zzzzzzzzzzz 2
1#
#156250
0#
#162500
b11111111111111111111 t
b0 p
b1000 l
b11111111111111111010 h
b1111111111111111 b
b100101010000100 c
b0zzzzzzzzzzzz 2
1#
#168750
0#
#175000
b1 f
b100101010000101 g
b100 l
b11 p
b11111111111111111110 t
b0zzzzzzzzzzzzz 2
1#
#181250
0#
#187500
b1 t
b11111111111111111111 p
b100101010000101 k
b0zzzzzzzzzzzzzz 2
1#
#193750
0#
#200000
b100101010000101 o
b1 t
b0zzzzzzzzzzzzzzz 2
1#
#206250
0#
#212500
b100101010000101 s
b0zzzzzzzzzzzzzzzz 2
1#
#218750
0#
#225000
b100101010001000 *
bz 2
1#
#231250
0#
#237500
z3
b100101010001 4
1#
#243750
0#
#250000
1#
#256250
0#
#262500
b100110011001101 $
1#
#268750
0#
#275000
b11110001111010001101 8
1#
#281250
0#
#287500
b11111011111001000000 <
1#
#293750
0#
#300000
b111101010001 @
1#
#306250
0#
#312500
b100100110001010 C
b101110011111 B
b11111110011010100001 D
1#
#318750
0#
#325000
b11111111101011111110 H
b100101010011 F
b100100111100110 G
1#
#331250
0#
#337500
b10100101101 L
b100000101100 J
b100101000001011 K
1#
#343750
0#
#350000
b10110 P
b100011000000 N
b100100111111011 O
1#
#356250
0#
#362500
b11111111110110001011 T
b100100001001 R
b100100111110011 S
1#
#368750
0#
#375000
b11111111111011010000 X
b100011100101 V
b100100111110111 W
1#
#381250
0#
#387500
b11111111111101110010 \
b100011010011 Z
b100100111111001 [
1#
#393750
0#
#400000
b11111111111111000011 `
b100011001010 ^
b100100111111010 _
1#
#406250
0#
#412500
b11111111111111101011 d
b100011000110 b
b100100111111010 c
1#
#418750
0#
#425000
b11111111111111111111 h
b100011000100 f
b100100111111010 g
1#
#431250
0#
#437500
b1001 l
b100011000011 j
b100100111111010 k
1#
#443750
0#
#450000
b100 p
b100011000011 n
b100100111111010 o
1#
#456250
0#
#462500
b10 t
b100011000011 r
b100100111111010 s
1#
#468750
0#
#475000
b100011000110 )
b100100111111110 *
1#
#481250
0#
#487500
b100011000 5
b100100111111 4
1#
#493750
0#
#500000
b1001100110011010 $
1#
#506250
0#
#512500
b11110110101101011010 8
1#
#518750
0#
#525000
b101100001101 <
1#
#531250
0#
#537500
b100010111111100 ?
b1100011111110 >
b11111011100111111100 @
1#
#543750
0#
#550000
b11111110001010101100 D
b1010010011111 B
b100011110001011 C
1#
#556250
0#
#562500
b11111111011100001001 H
b1001001100011 F
b100100000101111 G
1#
#568750
0#
#575000
b100111000 L
b1000101000011 J
b100100001111000 K
1#
#581250
0#
#587500
b11111111110000100001 P
b1000111010011 N
b100100001010110 O
1#
#593750
0#
#600000
b11111111111010101100 T
b1000110001011 R
b100100001100111 S
1#
#606250
0#
#612500
b11111111111111110001 X
b1000101100111 V
b100100001101111 W
1#
#618750
0#
#625000
b10010011 \
b1000101010101 Z
b100100001110011 [
1#
#631250
0#
#637500
b1000010 `
b1000101011110 ^
b100100001110001 _
1#
#643750
0#
#650000
b11010 d
b1000101100010 b
b100100001110000 c
1#
#656250
0#
#662500
b110 h
b1000101100100 f
b100100001110000 g
1#
#668750
0#
#675000
b11111111111111111100 l
b1000101100101 j
b100100001110000 k
1#
#681250
0#
#687500
b1 p
b1000101100101 n
b100100001110000 o
1#
#693750
0#
#700000
b11111111111111111111 t
b1000101100101 r
b100100001110000 s
1#
#706250
0#
#712500
b1000101101000 )
b100100001110011 *
1#
#718750
0#
#725000
b1000101101 5
b100100001110 4
1#
#731250
0#
#737500
b1110011001100111 $
1#
#743750
0#
#750000
b11111011100000100111 8
1#
#756250
0#
#762500
b101011111011010 <
1#
#768750
0#
#775000
b11011001001 @
1#
#781250
0#
#787500
b100010001101101 C
b1110101011101 B
b11111101111000011001 D
1#
#793750
0#
#800000
b11111111001001110110 H
b1101100111010 F
b100010101010111 G
1#
#806250
0#
#812500
b11111111110010100101 L
b1101000100101 J
b100010111000011 K
1#
#818750
0#
#825000
b110111100 P
b1100110011010 N
b100010111110111 O
1#
#831250
0#
#837500
b11111111111100110001 T
b1100111011111 R
b100010111011110 S
1#
#843750
0#
#850000
b1110110 X
b1100110111101 V
b100010111101010 W
1#
#856250
0#
#862500
b11111111111111010100 \
b1100111001110 Z
b100010111100100 [
1#
#868750
0#
#875000
b100101 `
b1100111000110 ^
b100010111100111 _
1#
#881250
0#
#887500
b11111111111111111101 d
b1100111001010 b
b100010111100110 c
1#
#893750
0#
#900000
b10001 h
b1100111001000 f
b100010111100110 g
1#
#906250
0#
#912500
b111 l
b1100111001001 j
b100010111100110 k
1#
#918750
0#
#925000
b10 p
b1100111001001 n
b100010111100110 o
1#
#931250
0#
#937500
b0 t
b1100111001001 r
b100010111100110 s
1#
#943750
0#
#950000
b1100111001101 )
b100010111101001 *
1#
#956250
0#
#962500
b1100111001 5
b100010111101 4
1#
#968750
0#
#975000
b10011001100110100 $
1#
#981250
0#
#987500
b10011110100 8
1#
#993750
0#
#1000000
b11011111111101 ;
b10111111111101 :
b11110110010101000001 <
1#
#1006250
0#
#1012500
b11111011011001010010 @
b10100011111110 >
b11110111111100 ?
1#
#1018750
0#
#1025000
b11111101111100000010 D
b10010100011111 B
b100000010001011 C
1#
#1031250
0#
#1037500
b11111111001101011111 H
b10001100011011 F
b100000110110011 G
1#
#1043750
0#
#1050000
b11111111110110001110 L
b10001000010101 J
b100001000111111 K
1#
#1056250
0#
#1062500
b1010100101 P
b10000110010001 N
b100001010000011 O
1#
#1068750
0#
#1075000
b11010 T
b10000111010011 R
b100001001100010 S
1#
#1081250
0#
#1087500
b11111111111011010101 X
b10000111110100 V
b100001001010010 W
1#
#1093750
0#
#1100000
b11111111111101110111 \
b10000111100100 Z
b100001001011010 [
1#
#1106250
0#
#1112500
b11111111111111001000 `
b10000111011100 ^
b100001001011110 _
1#
#1118750
0#
#1125000
b11111111111111110000 d
b10000111011000 b
b100001001100000 c
1#
#1131250
0#
#1137500
b100 h
b10000111010110 f
b100001001100001 g
1#
#1143750
0#
#1150000
b11111111111111111010 l
b10000111010111 j
b100001001100001 k
1#
#1156250
0#
#1162500
b11111111111111111111 p
b10000111010111 n
b100001001100001 o
1#
#1168750
0#
#1175000
b1 t
b10000111010111 r
b100001001100001 s
1#
#1181250
0#
#1187500
b10000111011010 )
b100001001100100 *
1#
#1193750
0#
#1200000
b10000111011 5
b100001001100 4
1#
#1206250
0#
#1212500
b11000000000000001 $
1#
#1218750
0#
#1225000
b101000111000001 8
1#
#1231250
0#
#1237500
b11111011001000001110 <
1#
#1243750
0#
#1250000
b1100011111 @
1#
#1256250
0#
#1262500
b11101101101101 C
b10110011011101 B
b11111101101001101111 D
1#
#1268750
0#
#1275000
b11111110111011001100 H
b10101100000010 F
b11110011010011 G
1#
#1281250
0#
#1287500
b11111111100011111011 L
b10101000001111 J
b11110101111111 K
1#
#1293750
0#
#1300000
b11111111111000010010 P
b10100110010101 N
b11110111010011 O
1#
#1306250
0#
#1312500
b10011101 T
b10100101011000 R
b11110111111100 S
1#
#1318750
0#
#1325000
b11111111111101011000 X
b10100101110110 V
b11110111101000 W
1#
#1331250
0#
#1337500
b11111111111111111010 \
b10100101100111 Z
b11110111110010 [
1#
#1343750
0#
#1350000
b1001011 `
b10100101100000 ^
b11110111110111 _
1#
#1356250
0#
#1362500
b100011 d
b10100101100011 b
b11110111110101 c
1#
#1368750
0#
#1375000
b1111 h
b10100101100100 f
b11110111110100 g
1#
#1381250
0#
#1387500
b101 l
b10100101100100 j
b11110111110100 k
1#
#1393750
0#
#1400000
b0 p
b10100101100100 n
b11110111110100 o
1#
#1406250
0#
#1412500
b11111111111111111110 t
b10100101100100 r
b11110111110100 s
1#
#1418750
0#
#1425000
b10100101100111 )
b11110111110111 *
1#
#1431250
0#
#1437500
b10100101100 5
b11110111110 4
1#
#1443750
0#
#1450000
b11100110011001110 $
1#
#1456250
0#
#1462500
b1001111010001110 8
1#
#1468750
0#
#1475000
b11111111111011011011 <
1#
#1481250
0#
#1487500
b100111111101100 @
1#
#1493750
0#
#1500000
b10011100111100 D
1#
#1506250
0#
#1512500
b11101000000111 G
b10111010111000 F
b1001011011111 H
1#
#1518750
0#
#1525000
b100010110000 L
b10111110100000 J
b11100101001101 K
1#
#1531250
0#
#1537500
b1110011001 P
b11000000010010 N
b11100011101110 O
1#
#1543750
0#
#1550000
b100001110 T
b11000001001010 R
b11100010111110 S
1#
#1556250
0#
#1562500
b11111111111111001001 X
b11000001100110 V
b11100010100110 W
1#
#1568750
0#
#1575000
b1101011 \
b11000001011000 Z
b11100010110010 [
1#
#1581250
0#
#1587500
b11010 `
b11000001011111 ^
b11100010101100 _
1#
#1593750
0#
#1600000
b11111111111111110010 d
b11000001100010 b
b11100010101001 c
1#
#1606250
0#
#1612500
b110 h
b11000001100001 f
b11100010101010 g
1#
#1618750
0#
#1625000
b11111111111111111100 l
b11000001100001 j
b11100010101010 k
1#
#1631250
0#
#1637500
b1 p
b11000001100001 n
b11100010101010 o
1#
#1643750
0#
#1650000
b11111111111111111111 t
b11000001100001 r
b11100010101010 s
1#
#1656250
0#
#1662500
b11000001100100 )
b11100010101110 *
1#
#1668750
0#
#1675000
b11000001100 5
b11100010101 4
1#
#1681250
0#
#1687500
b100001100110011011 $
1#
#1693750
0#
#1700000
b11110100011111011011 8
b11111111111100 6
b1111111111110 7
1#
#1706250
0#
#1712500
b11111110011110001110 <
b11011111111101 :
b10111111111101 ;
1#
#1718750
0#
#1725000
b11100010011111 @
b11000111111110 >
b11011011111100 ?
1#
#1731250
0#
#1737500
b111111101111 D
b11010101101101 B
b11001111011101 C
1#
#1743750
0#
#1750000
b11111111101110010010 H
b11011100001011 F
b11001000110010 G
1#
#1756250
0#
#1762500
b10111000001 L
b11011001000011 J
b11001100001110 K
1#
#1768750
0#
#1775000
b10101010 P
b11011010101001 N
b11001010100010 O
1#
#1781250
0#
#1787500
b11111111111000011111 T
b11011011011011 R
b11001001101100 S
1#
#1793750
0#
#1800000
b11111111111101100100 X
b11011011000010 V
b11001010000111 W
1#
#1806250
0#
#1812500
b110 \
b11011010110110 Z
b11001010010100 [
1#
#1818750
0#
#1825000
b11111111111110110101 `
b11011010111100 ^
b11001010001110 _
1#
#1831250
0#
#1837500
b11111111111111011101 d
b11011010111001 b
b11001010010001 c
1#
#1843750
0#
#1850000
b11111111111111110001 h
b11011010111000 f
b11001010010010 g
1#
#1856250
0#
#1862500
b11111111111111111011 l
b11011010111000 j
b11001010010010 k
1#
#1868750
0#
#1875000
b0 p
b11011010111000 n
b11001010010010 o
1#
#1881250
0#
#1887500
b11111111111111111110 t
b11011010111000 r
b11001010010010 s
1#
#1893750
0#
#1900000
b11011010111100 )
b11001010010101 *
1#
#1906250
0#
#1912500
b11011010111 5
b11001010010 4
1#
#1918750
0#
#1925000
b100110011001101000 $
1#
#1931250
0#
#1937500
b11111001010010101000 8
1#
#1943750
0#
#1950000
b11010001011011 <
1#
#1956250
0#
#1962500
b10100011111110 ?
b11110111111100 >
b11111110001101001010 @
1#
#1968750
0#
#1975000
b101111111010 D
b11101101101101 B
b10110011011101 C
1#
#1981250
0#
#1987500
b11111111011110011101 H
b11110011010011 F
b10101100000010 G
1#
#1993750
0#
#2000000
b111001100 L
b11110000100111 J
b10101111110101 K
1#
#2006250
0#
#2012500
b11111111110010110101 P
b11110001111110 N
b10101101111101 O
1#
#2018750
0#
#2025000
b11111111111101000000 T
b11110001010011 R
b10101110111001 S
1#
#2031250
0#
#2037500
b10000101 X
b11110000111110 V
b10101111010111 W
1#
#2043750
0#
#2050000
b11111111111111100011 \
b11110001001000 Z
b10101111001000 [
1#
#2056250
0#
#2062500
b110100 `
b11110001000011 ^
b10101111001111 _
1#
#2068750
0#
#2075000
b1100 d
b11110001000101 b
b10101111001100 c
1#
#2081250
0#
#2087500
b11111111111111111000 h
b11110001000110 f
b10101111001011 g
1#
#2093750
0#
#2100000
b10 l
b11110001000110 j
b10101111001011 k
1#
#2106250
0#
#2112500
b11111111111111111101 p
b11110001000110 n
b10101111001011 o
1#
#2118750
0#
#2125000
b11111111111111111111 t
b11110001000110 r
b10101111001011 s
1#
#2131250
0#
#2137500
b11110001001001 )
b10101111001111 *
1#
#2143750
0#
#2150000
b11110001001 5
b10101111001 4
1#
#2156250
0#
#2162500
b101011001100110101 $
1#
#2168750
0#
#2175000
b11111110000101110101 8
1#
#2181250
0#
#2187500
b1000000100101000 <
1#
#2193750
0#
#2200000
b11000000010111 @
1#
#2206250
0#
#2212500
b10010100011111 C
b100000010001011 B
b11101100111 D
1#
