5.NewModules/MyCIC/Testbench/comb/hdl/systemverilog/comb.sv
module comb#(
    parameter int IW = 5,
    parameter int OW = 10,
    parameter int N = 7
)(
    input logic i_clk,
    input logic i_reset,
    input logic i_ce,
    input logic signed [IW-1:0] i_data,

    output logic signed [OW-1:0] o_data,
    output logic o_ready
);

integer i;

logic signed[IW-1:0] delay[N-1:0];

always@(posedge i_clk or i_reset) begin

    if(i_reset) begin
        o_data <= {OW{1'b0}};
        o_ready <= 1'b0;
    end else if(i_ce) begin
        delay[0] <= i_data;
        for(i = 1; i < N; i++) begin
            delay[i] <= delay[i-1];
        end
        o_data <= {{(OW-IW){i_data[IW-1]}}, i_data} - {{(OW-IW){delay[IW-1]}}, delay[N-1]};
        o_ready <= 1'b1;
    end else begin
        o_ready <= 1'b0;
    end

end

//-----------------------------
// For simulation only
//-----------------------------
initial begin
    $dumpfile("comb_waves.vcd");
    $dumpvars(0, comb);
end


endmodule

5.NewModules/MyCIC/Testbench/comb/comb_waves.vcd
$date
	Sat Apr 20 01:14:49 2024
$end
$version
	Icarus Verilog
$end
$timescale
	1ps
$end
$scope module comb $end
$var wire 1 ! i_ce $end
$var wire 1 " i_clk $end
$var wire 4 # i_data [3:0] $end
$var wire 1 $ i_reset $end
$var parameter 32 % IW $end
$var parameter 32 & N $end
$var parameter 32 ' OW $end
$var reg 12 ( o_data [11:0] $end
$var reg 1 ) o_ready $end
$var integer 32 * i [31:0] $end
$upscope $end
$enddefinitions $end
$comment Show the parameter values. $end
$dumpall
b1100 '
b111 &
b100 %
$end
#0
$dumpvars
bx *
x)
bx (
z$
bz #
z"
z!
$end
#5000
b111 *
b0 #
1)
bx (
1"
0$
1!
#11250
0"
#17500
b1110 #
b111 *
1"
#23750
0"
#30000
b1010 #
b111 *
1"
#36250
0"
#42500
b1100 #
b111 *
1"
#48750
0"
#55000
b1110 #
b111 *
1"
#61250
0"
#67500
b11 #
b111 *
1"
#73750
0"
#80000
b100 #
b111 *
1"
#86250
0"
#92500
b1110 #
b100 (
b111 *
1"
#98750
0"
#105000
b1 #
b111111111110 (
b111 *
1"
#111250
0"
#117500
b1010 #
b11 (
b111 *
1"
#123750
0"
#130000
b111 #
b0 (
b111 *
1"
#136250
0"
#142500
b1 #
b1011 (
b111 *
1"
#148750
0"
#155000
b111 #
b11 (
b111 *
1"
#161250
0"
#167500
b1101 #
b100 (
b111 *
1"
#173750
0"
#180000
b101 #
b111111111001 (
b111 *
1"
#186250
0"
#192500
b1111 #
b111 (
b111 *
1"
#198750
0"
#205000
b1101 #
b111111111110 (
b111 *
1"
#211250
0"
#217500
b110 #
b11 (
b111 *
1"
#223750
0"
#230000
b1000 #
b111111111111 (
b111 *
1"
#236250
0"
#242500
b1111 #
b111111110111 (
b111 *
1"
#248750
0"
#255000
b1101 #
b111111111000 (
b111 *
1"
#261250
0"
#267500
b1001 #
b0 (
b111 *
1"
#273750
0"
#280000
b101 #
b111111110100 (
b111 *
1"
#286250
0"
#292500
b1111 #
b110 (
b111 *
1"
#298750
0"
#305000
b0 #
b10 (
b111 *
1"
#311250
0"
#317500
b110 #
b111111111010 (
b111 *
1"
#323750
0"
#330000
b1111 #
b1110 (
b111 *
1"
#336250
0"
#342500
b110 #
b0 (
b111 *
1"
#348750
0"
#355000
b1000 #
b1001 (
b111 *
1"
#361250
0"
#367500
b1 #
b111111111111 (
b111 *
1"
#373750
0"
#380000
b110 #
b111111111100 (
b111 *
1"
#386250
0"
#392500
b1111 #
b111 (
b111 *
1"
#398750
0"
#405000
b11 #
b111111111111 (
b111 *
1"
#411250
0"
#417500
b100 #
b111111111101 (
b111 *
1"
#423750
0"
#430000
b1000 #
b101 (
b111 *
1"
#436250
0"
#442500
b0 #
b111111110010 (
b111 *
1"
#448750
0"
#455000
b1000 #
b1000 (
b111 *
1"
#461250
0"
#467500
b11 #
b111111110111 (
b111 *
1"
#473750
0"
#480000
b1111 #
b111111111101 (
b111 *
1"
#486250
0"
#492500
b101 #
b0 (
b111 *
1"
#498750
0"
#505000
b11 #
b10 (
b111 *
1"
#511250
0"
#517500
b1000 #
b111111111111 (
b111 *
1"
#523750
0"
#530000
b1011 #
b0 (
b111 *
1"
#536250
0"
#542500
b1100 #
b111111111011 (
b111 *
1"
#548750
0"
#555000
b1001 #
b100 (
b111 *
1"
#561250
0"
#567500
b111111110110 (
b111 *
1"
#573750
0"
#580000
b11 #
b111111111010 (
b111 *
1"
#586250
0"
#592500
b1010 #
b111111111110 (
b111 *
1"
#598750
0"
#605000
b1001 #
b111111110111 (
b111 *
1"
#611250
0"
#617500
b101 #
b1 (
b111 *
1"
#623750
0"
#630000
b1100 #
b1010 (
b111 *
1"
#636250
0"
#642500
b110 #
b0 (
b111 *
1"
#648750
0"
#655000
b11 #
b1101 (
b111 *
1"
#661250
0"
#667500
b1010 #
b1010 (
b111 *
1"
#673750
0"
#680000
b1100 #
b111111110111 (
b111 *
1"
#686250
0"
#692500
b10 #
b10 (
b111 *
1"
#698750
0"
#705000
b101 #
b1001 (
b111 *
1"
#711250
0"
#717500
b1111 #
b0 (
b111 *
1"
#723750
0"
#730000
b10 #
b11 (
b111 *
1"
#736250
0"
#742500
b110 #
b111111111100 (
b111 *
1"
#748750
0"
#755000
b1101 #
b11 (
b111 *
1"
#761250
0"
#767500
b1001 #
b111 *
1"
#773750
0"
#780000
b111111111101 (
b111 *
1"
#786250
0"
#792500
b1 #
b111111110111 (
b111 *
1"
#798750
0"
#805000
b1010 #
b111111111100 (
b111 *
1"
#811250
0"
#817500
b101 #
b111111111011 (
b111 *
1"
#823750
0"
#830000
b1011 #
b11 (
b111 *
1"
#836250
0"
#842500
b1 #
b111111110101 (
b111 *
1"
#848750
0"
#855000
b110 #
b100 (
b111 *
1"
#861250
0"
#867500
b100 #
b1101 (
b111 *
1"
#873750
0"
#880000
b101 #
b1011 (
b111 *
1"
#886250
0"
#892500
b1110 #
b100 (
b111 *
1"
#898750
0"
#905000
b10 #
b111 *
1"
#911250
0"
#917500
b0 #
b111111111101 (
b111 *
1"
#923750
0"
#930000
b10 #
b101 (
b111 *
1"
#936250
0"
#942500
b1111 #
b1 (
b111 *
1"
#948750
0"
#955000
b1 #
b111111111001 (
b111 *
1"
#961250
0"
#967500
b111 #
b111111111101 (
b111 *
1"
#973750
0"
#980000
b100 #
b10 (
b111 *
1"
#986250
0"
#992500
b111 #
b110 (
b111 *
1"
#998750
0"
#1005000
b110 #
b101 (
b111 *
1"
#1011250
0"
#1017500
b1001 #
b110 (
b111 *
1"
#1023750
0"
#1030000
b1111 #
b111111110111 (
b111 *
1"
#1036250
0"
#1042500
b101 #
b0 (
b111 *
1"
#1048750
0"
#1055000
b10 #
b100 (
b111 *
1"
#1061250
0"
#1067500
b111111111011 (
b111 *
1"
#1073750
0"
#1080000
b0 #
b111111111110 (
b111 *
1"
#1086250
0"
#1092500
b1100 #
b111111111001 (
b111 *
1"
#1098750
0"
#1105000
b111 #
b111111110110 (
b111 *
1"
#1111250
0"
#1117500
b0 #
b1110 (
b111 *
1"
#1123750
0"
#1130000
b1111 #
b1 (
b111 *
1"
#1136250
0"
#1142500
b11 #
b111111111010 (
b111 *
1"
#1148750
0"
#1155000
b10 #
b1 (
b111 *
1"
#1161250
0"
#1167500
b0 #
b0 (
b111 *
1"
#1173750
0"
#1180000
b1101 #
b111 *
1"
#1186250
0"
#1192500
b1 (
b111 *
1"
#1198750
0"
#1205000
b0 #
b111111110110 (
b111 *
1"
#1211250
0"
#1217500
b1 #
b0 (
b111 *
1"
#1223750
0"
#1230000
b1111 #
b10 (
b111 *
1"
#1236250
0"
#1242500
b1 #
b111111111100 (
b111 *
1"
#1248750
0"
#1255000
b101 #
b111111111111 (
b111 *
1"
#1261250
0"
#1267500
b101 (
b111 *
1"
